Workbook

Sheet Summary
A1: EPPIB Strategic Investment Plan
A2: Model status | B2: =Checks!B4 -> ALL CHECKS PASS | D2: Method | E2: =Methods!B2 -> Robust MVO
A4: 1. Strategic asset allocation | H4: 2. Brief compliance
A5: Asset class | B5: Current | C5: Benchmark | D5: Recommended | E5: Change vs current | F5: Trade (A$m) | H5: Requirement | I5: Limit | J5: Recommended | K5: Status
A6: Australian Equities | B6: =Portfolio!C6 -> 0.4 | C6: =Portfolio!D6 -> 0.25 | D6: =Portfolio!E6 -> 0.2738 | E6: =Portfolio!I6 -> -0.1262 | F6: =Portfolio!J6 -> -378.6 | H6: (a) Return: bond yield + 4% (compound) | I6: =Inputs!$B$25 -> 0.08988 | J6: =Risk!N58-Risk!M58^2/2 -> 0.066959679 | K6: =IF(J6>=I6,"MET",IF(Forecast!G18<I6,"MAX FEASIBLE","NOT MET")) -> MAX FEASIBLE
A7: World Equities | B7: =Portfolio!C7 -> 0.2 | C7: =Portfolio!D7 -> 0.24 | D7: =Portfolio!E7 -> 0.279 | E7: =Portfolio!I7 -> 0.079 | F7: =Portfolio!J7 -> 237 | H7: (b) Minimise risk: volatility vs current fund | I7: =Risk!M56 -> 0.083833964 | J7: =Risk!M58 -> 0.078389128 | K7: =IF(J7<=I7,"MET","NOT MET") -> MET
A8: Emerging Markets | B8: =Portfolio!C8 -> 0 | C8: =Portfolio!D8 -> 0.03 | D8: =Portfolio!E8 -> 0.0672 | E8: =Portfolio!I8 -> 0.0672 | F8: =Portfolio!J8 -> 201.6 | H8: (c) 5-year loss probability, bootstrap | I8: =Inputs!$B$28 -> 0.25 | J8: =Bootstrap!D6 -> 0.073 | K8: =IF(J8<=I8,"MET","NOT MET") -> MET
A9: Listed Property | B9: =Portfolio!C9 -> 0.1 | C9: =Portfolio!D9 -> 0.07 | D9: =Portfolio!E9 -> 0.0867 | E9: =Portfolio!I9 -> -0.0133 | F9: =Portfolio!J9 -> -39.9 | H9: (c) 5-year loss probability, normal | I9: =Inputs!$B$28 -> 0.25 | J9: =Bootstrap!D7 -> 0.028064013 | K9: =IF(J9<=I9,"MET","NOT MET") -> MET
A10: Commodities | B10: =Portfolio!C10 -> 0 | C10: =Portfolio!D10 -> 0.02 | D10: =Portfolio!E10 -> 0.0244 | E10: =Portfolio!I10 -> 0.0244 | F10: =Portfolio!J10 -> 73.2 | H10: (d) Tracking error, parametric | I10: =Inputs!$B$27 -> 0.015 | J10: =Risk!O58 -> 0.011002382 | K10: =IF(J10<=I10,"MET","NOT MET") -> MET
A11: Direct Property | B11: =Portfolio!C11 -> 0 | C11: =Portfolio!D11 -> 0.05 | D11: =Portfolio!E11 -> 0 | E11: =Portfolio!I11 -> 0 | F11: =Portfolio!J11 -> 0 | H11: (d) Tracking error, bootstrap | I11: =Inputs!$B$27 -> 0.015 | J11: =Bootstrap!D12 -> 0.011821602 | K11: =IF(J11<=I11,"MET","NOT MET") -> MET
A12: Hedge Funds | B12: =Portfolio!C12 -> 0 | C12: =Portfolio!D12 -> 0.03 | D12: =Portfolio!E12 -> 0 | E12: =Portfolio!I12 -> 0 | F12: =Portfolio!J12 -> 0 | H12: (e) Equity minimum | I12: =Inputs!$B$31 -> 0.42 | J12: =Portfolio!B34 -> 0.62 | K12: =IF(J12>=I12-0.000001,"MET","NOT MET") -> MET
A13: Private Equity | B13: =Portfolio!C13 -> 0 | C13: =Portfolio!D13 -> 0.03 | D13: =Portfolio!E13 -> 0 | E13: =Portfolio!I13 -> 0 | F13: =Portfolio!J13 -> 0 | H13: (e) Equity maximum | I13: =Inputs!$B$32 -> 0.62 | J13: =Portfolio!B34 -> 0.62 | K13: =IF(J13<=I13+0.000001,"MET","NOT MET") -> MET
A14: Australian Fixed Income | B14: =Portfolio!C14 -> 0.15 | C14: =Portfolio!D14 -> 0.14 | D14: =Portfolio!E14 -> 0.12 | E14: =Portfolio!I14 -> -0.03 | F14: =Portfolio!J14 -> -90 | H14: (e) Illiquid maximum | I14: =Inputs!$B$33 -> 0.3 | J14: =Portfolio!B35 -> 0 | K14: =IF(J14<=I14,"MET","NOT MET") -> MET
A15: World Fixed Income | B15: =Portfolio!C15 -> 0.08 | C15: =Portfolio!D15 -> 0.11 | D15: =Portfolio!E15 -> 0.1289 | E15: =Portfolio!I15 -> 0.0489 | F15: =Portfolio!J15 -> 146.7 | H15: (e) Cash minimum | I15: =Inputs!$B$34 -> 0.02 | J15: =Portfolio!B36 -> 0.02 | K15: =IF(J15>=I15,"MET","NOT MET") -> MET
A16: Cash | B16: =Portfolio!C16 -> 0.07 | C16: =Portfolio!D16 -> 0.03 | D16: =Portfolio!E16 -> 0.02 | E16: =Portfolio!I16 -> -0.05 | F16: =Portfolio!J16 -> -150 | H16: (e) No short sales or borrowing | I16: =0 -> 0 | J16: =MIN(Portfolio!E6:E16) -> 0 | K16: =IF(J16>=I16-0.000001,"MET","NOT MET") -> MET
A17: Total | B17: =SUM(B6:B16) -> 1 | C17: =SUM(C6:C16) -> 1 | D17: =SUM(D6:D16) -> 1 | E17: =SUM(E6:E16) -> 0 | F17: =SUM(F6:F16) -> 0
A18: One-way turnover | D18: =SUMPRODUCT(ABS(Portfolio!I6:I16))/2 -> 0.2195
A19: Change in fees (A$m p.a.) | D19: =(SUMPRODUCT(Portfolio!E6:E16,Inputs!$D$5:$D$15)-SUMPRODUCT(Portfolio!C6:C16,Inputs!$D$5:$D$15))*Inputs!$B$22 -> 0.6333
A22: 3. Expected outcomes (net of fees) | H22: 4. Stress tests (portfolio return)
A23: Metric | B23: Current | C23: Benchmark | D23: Recommended | E23: Change vs current | H23: Scenario | I23: Current | J23: Benchmark | K23: Recommended
A24: Expected return, compound (p.a.) | B24: =Risk!N56-Risk!M56^2/2 -> 0.066110548 | C24: =Risk!N57-Risk!M57^2/2 -> 0.063796067 | D24: =Risk!N58-Risk!M58^2/2 -> 0.066959679 | E24: =D24-B24 -> 0.00084913061 | H24: Global financial crisis | I24: =Stress!B26 -> -0.24167171 | J24: =Stress!B27 -> -0.19300089 | K24: =Stress!B28 -> -0.2350248
A25: Volatility (p.a.) | B25: =Risk!M56 -> 0.083833964 | C25: =Risk!M57 -> 0.070134112 | D25: =Risk!M58 -> 0.078389128 | E25: =D25-B25 -> -0.005444836 | H25: COVID shock | I25: =Stress!C26 -> -0.12092703 | J25: =Stress!C27 -> -0.091806485 | K25: =Stress!C28 -> -0.10748236
A26: Tracking error, parametric | B26: =Risk!O56 -> 0.021585026 | C26: =Risk!O57 -> 0 | D26: =Risk!O58 -> 0.011002382 | E26: =D26-B26 -> -0.010582644 | H26: Inflation sell-off (2022) | I26: =Stress!D26 -> -0.072754437 | J26: =Stress!D27 -> -0.072610798 | K26: =Stress!D28 -> -0.075405586
A27: Tracking error, bootstrap | B27: =Bootstrap!B12 -> 0.0156484 | C27: =Bootstrap!C12 -> 0 | D27: =Bootstrap!D12 -> 0.011821602 | E27: =D27-B27 -> -0.0038267977 | H27: US$150 oil (central case) | I27: =Stress!E26 -> -0.082609308 | J27: =Stress!E27 -> -0.073910247 | K27: =Stress!E28 -> -0.08363891
A28: 5-year loss probability, bootstrap | B28: =Bootstrap!B6 -> 0.077 | C28: =Bootstrap!C6 -> 0.062 | D28: =Bootstrap!D6 -> 0.073 | E28: =D28-B28 -> -0.004
A29: Median 5-year cumulative return | B29: =Bootstrap!B9 -> 0.39414359 | C29: =Bootstrap!C9 -> 0.3749255 | D29: =Bootstrap!D9 -> 0.39501952 | E29: =D29-B29 -> 0.00087593938 | H29: 5. Oil: 5-year regression on oil (log) change
A30: Management fee (p.a.) | B30: =SUMPRODUCT(Portfolio!C6:C16,Inputs!$D$5:$D$15) -> 0.00112 | C30: =SUMPRODUCT(Portfolio!D6:D16,Inputs!$D$5:$D$15) -> 0.00338 | D30: =SUMPRODUCT(Portfolio!E6:E16,Inputs!$D$5:$D$15) -> 0.0013311 | E30: =D30-B30 -> 0.0002111 | H30: Series | I30: Beta | J30: t-stat (adj.) | K30: R-squared
H31: US equities | I31: =Oil!C13 -> -0.22998127 | J31: =Oil!E13 -> -1.5542333 | K31: =Oil!F13 -> 0.1858332
H32: Australian equities | I32: =Oil!C16 -> 0.087571808 | J32: =Oil!E16 -> 0.57873507 | K32: =Oil!F16 -> 0.044450857
H33: AU 3-month rate (pp) | I33: =Oil!C19 -> 2.6117925 | J33: =Oil!E19 -> 1.4569815 | K33: =Oil!F19 -> 0.1670686
H34: Likelihood: 12-month rise of this size | K34: =Oil!B51 -> 0.10656934
H36: 6. Out-of-sample (2016-26) and sensitivity
H37: Measure | I37: Robust | J37: Naive MVO | K37: Current
H38: Realised return, annualised | I38: =Validation!B47 -> 0.087743665 | J38: =Validation!C47 -> 0.067680847 | K38: =Validation!D47 -> 0.077761951
H39: Realised volatility | I39: =Validation!B49 -> 0.081380343 | J39: =Validation!C49 -> 0.066488181 | K39: =Validation!D49 -> 0.085331791
H40: Return per unit of risk | I40: =Validation!B50 -> 1.0781924 | J40: =Validation!C50 -> 1.017938 | K40: =Validation!D50 -> 0.91128933
H41: Max weight move (sensitivity) | K41: =MAX(Validation!E58:E60) -> 0.0346
H43: 7. Track record: rolling 5-year windows since 2011
H44: Measure | I44: Current | J44: Benchmark | K44: Recommended
H45: Met return target | I45: ='Track record'!M13 -> 0.68852459 | J45: ='Track record'!N13 -> 0.68852459 | K45: ='Track record'!O13 -> 0.7704918
H46: Negative 5-year return | I46: ='Track record'!M14 -> 0.081967213 | J46: ='Track record'!N14 -> 0.032786885 | K46: ='Track record'!O14 -> 0.081967213
H47: Average realised TE | I47: ='Track record'!M16 -> 0.02026313 | J47: 0 | K47: ='Track record'!O16 -> 0.0108785
H49: 8. Methods and forecast risk
H50: Measure | I50: Value
H51: Methods meeting every brief constraint | K51: =COUNTIF(Methods!M22:M26,"MET")&" of 5" -> 5 of 5
H52: Robust vs resampled: largest weight gap | K52: =Methods!D33 -> 0.0274
H53: Return cost of the TE limit | K53: =Portfolio!D58 -> 0.0020994114
H54: Smallest forecast error that removes advantage | K54: =Validation!H79 -> 0.0067284518
H56: 9. Past performance (monthly rebalancing, net of fees)
H57: Measure | I57: Current | J57: Benchmark | K57: Difference
H58: Return, Mar-21 to Mar-26 | I58: =Performance!B17 -> 0.069191327 | J58: =Performance!C17 -> 0.07352858 | K58: =Performance!D17 -> -0.0043372531
H59: Return, 20 years | I59: =Performance!E17 -> 0.064916462 | J59: =Performance!F17 -> 0.065197281 | K59: =Performance!G17 -> -0.00028081973
H60: Sharpe ratio, 5 years | I60: =Performance!B20 -> 0.49280109 | J60: =Performance!C20 -> 0.66318202 | K60: =Performance!D20 -> -0.17038093
H61: Tracking error, 5 years | I61: =Performance!B21 -> 0.02049638
H62: Information ratio, 5 years | I62: =Performance!B22 -> -0.21161069
H63: Maximum drawdown, 20 years | I63: =Performance!E24 -> -0.28907364 | J63: =Performance!F24 -> -0.22841555 | K63: =Performance!G24 -> -0.060658095
H64: Down-market capture, 20 years | I64: =Performance!E27 -> 1.2521803 | J64: 1
H65: Active return, 2006-11 block | I65: =Performance!D35 -> 0.0011658878
H66: Active return, 2021-26 block | I66: =Performance!D38 -> -0.0043372531
H69: 10. Oil: robustness and mitigation
H70: Measure | K70: Value
H71: Australian equities: 12m oil beta since 1986 | K71: =Oil!E95 -> 0.10059841
A72: 11. Implementation and after-tax view | H72: AU 5-year yield: 12m oil beta since 1986 (pp) | K72: =Oil!E101 -> 1.4238999
A73: Measure | B73: Value | C73: Status | H73: Recommended: regression impact, 12 months | K73: =Oil!B124 -> 0.005810857
A74: Transition cost (A$m, one-way) | B74: =Portfolio!$D$75 -> 1.58265 | H74: Recommended: episode central case | K74: =Oil!F124 -> -0.08363891
A75: Transition cost (% of fund) | B75: =Portfolio!$D$76 -> 0.00052755 | H75: Recommended: severe case (2008 scaled) | K75: =Oil!E124 -> -0.13428639
A76: Amortised cost per year | B76: =Portfolio!$D$77 -> 0.00010551 | H76: Mitigation: commodities +2% from Aus equities, loss reduced | K76: =Oil!H153 -> 0.0074988283
A77: Expected return advantage after costs | B77: =Portfolio!$D$79 -> 0.00074362061 | C77: =Portfolio!$D$80 -> PASS | H77: Mitigation: same option, tracking error | K77: =Oil!D153 -> 0.011719693
A78: Franking uplift: recommended less current | B78: =Portfolio!$D$111 -> -0.001298598
A79: Return advantage including franking | B79: =Portfolio!$E$111 -> -0.00044946739 | C79: =Portfolio!$E$112 -> REVIEW
A80: Equity incl. listed property (recommended) | B80: =Portfolio!$D$119 -> 0.7067 | C80: =Portfolio!$D$122 -> REVIEW
A81: Transition phases meeting constraints | B81: =COUNTIF(Portfolio!C102:F102,"MET")&" of 4" -> 4 of 4
A82: Model checks flagged for disclosure | B82: =COUNTIF(Checks!D7:D49,"REVIEW") -> 2
A85: 12. Asset-class scope: portfolios with and without some asset classes (Portfolio section 9)
A86: Measure | B86: Recommended | C86: Alternatives fixed by scorecard | D86: No alternatives | E86: Alternatives at benchmark | F86: Core five only
A87: Expected return (compound) | B87: =Portfolio!B152 -> 0.066959679 | C87: =Portfolio!C152 -> 0.066235653 | D87: =Portfolio!D152 -> 0.066544076 | E87: =Portfolio!E152 -> 0.065443707 | F87: =Portfolio!F152 -> 0.065024548
A88: Volatility | B88: =Portfolio!B153 -> 0.078389128 | C88: =Portfolio!C153 -> 0.079350014 | D88: =Portfolio!D153 -> 0.076728986 | E88: =Portfolio!E153 -> 0.080170949 | F88: =Portfolio!F153 -> 0.073525791
A89: Tracking error (bootstrap) | B89: =Portfolio!B155 -> 0.011821602 | C89: =Portfolio!C155 -> 0.014189288 | D89: =Portfolio!D155 -> 0.011441138 | E89: =Portfolio!E155 -> 0.014702715 | F89: =Portfolio!F155 -> 0.011392985
A90: 5-year loss probability (bootstrap) | B90: =Portfolio!B156 -> 0.073 | C90: =Portfolio!C156 -> 0.077 | D90: =Portfolio!D156 -> 0.072 | E90: =Portfolio!E156 -> 0.08 | F90: =Portfolio!F156 -> 0.051
A91: Management fee (p.a.) | B91: =Portfolio!B159 -> 0.0013311 | C91: =Portfolio!C159 -> 0.00214125 | D91: =Portfolio!D159 -> 0.00130775 | E91: =Portfolio!E159 -> 0.0033851 | F91: =Portfolio!F159 -> 0.00123295
A92: Global financial crisis | B92: =Portfolio!B162 -> -0.2350248 | C92: =Portfolio!C162 -> -0.24431696 | D92: =Portfolio!D162 -> -0.22094255 | E92: =Portfolio!E162 -> -0.24201259 | F92: =Portfolio!F162 -> -0.17615063
A93: US$150 oil (central case) | B93: =Portfolio!B165 -> -0.08363891 | C93: =Portfolio!C165 -> -0.077412002 | D93: =Portfolio!D165 -> -0.091566214 | E93: =Portfolio!E165 -> -0.079928528 | F93: =Portfolio!F165 -> -0.083752154
A94: Transition cost (A$m) | B94: =Portfolio!B168 -> 1.58265 | C94: =Portfolio!C168 -> 3.81645 | D94: =Portfolio!D168 -> 1.6788 | E94: =Portfolio!E168 -> 4.66635 | F94: =Portfolio!F168 -> 1.7454
A95: Advantage vs current after costs | B95: =Portfolio!B169 -> 0.00074362061 | C95: =Portfolio!C169 -> -0.00012932454 | D95: =Portfolio!D169 -> 0.00032160764 | E95: =Portfolio!E169 -> -0.00097793078 | F95: =Portfolio!F169 -> -0.0012023603
A96: Brief constraints | B96: =Portfolio!B170 -> MET | C96: =Portfolio!C170 -> MET | D96: =Portfolio!D170 -> MET | E96: =Portfolio!E170 -> MET | F96: =Portfolio!F170 -> MET

Sheet Report figures
A1: Report figures
A3: Figure index
A4: Figure | B4: Title | F4: Source tab
A5: Figure 1 | B5: Risk-return opportunity set | F5: Validation, Methods
A6: Figure 2 | B6: Strategic asset allocation | F6: Portfolio
A7: Figure 3 | B7: Fund performance since 2006 | F7: Quarterly returns, RBA 5Y yield
A8: Figure 4 | B8: Annualised returns to March 2026 | F8: Track record
A9: Figure 5 | B9: Stress tests | F9: Stress
A10: Figure 6 | B10: Five-year outcomes (forecast-adjusted bootstrap) | F10: Bootstrap
A11: Figure 7 | B11: How far the return target is out of reach | F11: Portfolio
A12: Figure 8 | B12: US$150 oil: estimates by method | F12: Oil
A13: Figure 9 | B13: Oil and equity returns by horizon | F13: Oil
A14: Figure 10 | B14: Rolling 5-year return against the target | F14: Track record
A15: Figure 11 | B15: Portfolio construction methods | F15: Methods
... A19: Figure 15 | B19: Attribution of active return | F19: Performance
A20: Figure 1. Risk-return opportunity set | N20: Chart data, figure 1
N21: Point | O21: Vol (no TE limit) | P21: Return (no TE limit) | Q21: Vol (TE limit) | R21: Return (TE limit)
N22: Point 1 | O22: =Validation!B125 -> 0.046682076 | P22: =Validation!B124 -> 0.060410992 | Q22: =Validation!B143 -> 0.059513407 | R22: =Validation!B142 -> 0.063481367
N23: Point 2 | O23: =Validation!C125 -> 0.047504271 | P23: =Validation!C124 -> 0.061713833 | Q23: =Validation!C143 -> 0.059815896 | R23: =Validation!C142 -> 0.064209885
N24: Point 3 | O24: =Validation!D125 -> 0.050686493 | P24: =Validation!D124 -> 0.06301402 | Q24: =Validation!D143 -> 0.060560834 | R24: =Validation!D142 -> 0.064938609
N25: Point 4 | O25: =Validation!E125 -> 0.054921807 | P25: =Validation!E124 -> 0.064316815 | Q25: =Validation!E143 -> 0.061684335 | R25: =Validation!E142 -> 0.065664485
N26: Point 5 | O26: =Validation!F125 -> 0.059449541 | P26: =Validation!F124 -> 0.065618698 | Q26: =Validation!F143 -> 0.06326355 | R26: =Validation!F142 -> 0.066392561
N27: Point 6 | O27: =Validation!G125 -> 0.064206719 | P27: =Validation!G124 -> 0.066922303 | Q27: =Validation!G143 -> 0.065427375 | R27: =Validation!G142 -> 0.067119175
N28: Point 7 | O28: =Validation!H125 -> 0.069215546 | P28: =Validation!H124 -> 0.068223746 | Q28: =Validation!H143 -> 0.06800267 | R28: =Validation!H142 -> 0.067848386
N29: Point 8 | O29: =Validation!I125 -> 0.074801788 | P29: =Validation!I124 -> 0.069526202 | Q29: =Validation!I143 -> 0.070952573 | R29: =Validation!I142 -> 0.068574794
N30: Point 9 | O30: =Validation!J125 -> 0.080501525 | P30: =Validation!J124 -> 0.070829045 | Q30: =Validation!J143 -> 0.074195142 | R30: =Validation!J142 -> 0.06930514
N31: Point 10 | O31: =Validation!K125 -> 0.090059124 | P31: =Validation!K124 -> 0.072131518 | Q31: =Validation!K143 -> 0.078389128 | R31: =Validation!K142 -> 0.070032106
N32: Portfolio | O32: Volatility | P32: Expected return
N33: Current fund | O33: =Risk!M56 -> 0.083833964 | P33: =Risk!N56 -> 0.069624615
N34: Benchmark | O34: =Risk!M57 -> 0.070134112 | P34: =Risk!N57 -> 0.066255464
N35: Recommended | O35: =Risk!M58 -> 0.078389128 | P35: =Risk!N58 -> 0.070032106
N36: Sample MVO | O36: =Methods!C23 -> 0.078033813 | P36: =Methods!B23 -> 0.069911884
N37: Resampled MVO | O37: =Methods!C24 -> 0.074319311 | P37: =Methods!B24 -> 0.06807754
N38: Minimum variance | O38: =Methods!C25 -> 0.059513407 | P38: =Methods!B25 -> 0.063481367
N39: Risk parity | O39: =Methods!C26 -> 0.066508938 | P39: =Methods!B26 -> 0.066570324
A46: Figure 2. Strategic asset allocation | N46: Chart data, figure 2
N47: Asset class | O47: Current fund | P47: Benchmark | Q47: Recommended
N48: Australian Equities | O48: =Summary!B6 -> 0.4 | P48: =Summary!C6 -> 0.25 | Q48: =Summary!D6 -> 0.2738
N49: World Equities | O49: =Summary!B7 -> 0.2 | P49: =Summary!C7 -> 0.24 | Q49: =Summary!D7 -> 0.279
N50: Emerging Markets | O50: =Summary!B8 -> 0 | P50: =Summary!C8 -> 0.03 | Q50: =Summary!D8 -> 0.0672
N51: Listed Property | O51: =Summary!B9 -> 0.1 | P51: =Summary!C9 -> 0.07 | Q51: =Summary!D9 -> 0.0867
N52: Commodities | O52: =Summary!B10 -> 0 | P52: =Summary!C10 -> 0.02 | Q52: =Summary!D10 -> 0.0244
N53: Direct Property | O53: =Summary!B11 -> 0 | P53: =Summary!C11 -> 0.05 | Q53: =Summary!D11 -> 0
N54: Hedge Funds | O54: =Summary!B12 -> 0 | P54: =Summary!C12 -> 0.03 | Q54: =Summary!D12 -> 0
N55: Private Equity | O55: =Summary!B13 -> 0 | P55: =Summary!C13 -> 0.03 | Q55: =Summary!D13 -> 0
N56: Australian Fixed Income | O56: =Summary!B14 -> 0.15 | P56: =Summary!C14 -> 0.14 | Q56: =Summary!D14 -> 0.12
N57: World Fixed Income | O57: =Summary!B15 -> 0.08 | P57: =Summary!C15 -> 0.11 | Q57: =Summary!D15 -> 0.1289
N58: Cash | O58: =Summary!B16 -> 0.07 | P58: =Summary!C16 -> 0.03 | Q58: =Summary!D16 -> 0.02
A72: Figure 3. Fund performance since 2006 | V72: Chart data, figure 3
V73: Quarter end | W73: Current fund | X73: Benchmark | Y73: Recommended | Z73: Target: yield + 4%
V74: ='Quarterly returns'!A5 -> 38807 | W74: 1 | X74: 1 | Y74: 1 | Z74: 1
V75: ='Quarterly returns'!A6 -> 38898 | W75: =W74*(1+'Quarterly returns'!Z6) -> 0.98121065 | X75: =X74*(1+'Quarterly returns'!AA6) -> 0.98608295 | Y75: =Y74*(1+'Quarterly returns'!AB6) -> 0.97217655 | Z75: =Z74*(1+INDEX('RBA 5Y yield'!$B$5:$B$661,MATCH(V74,'RBA 5Y yield'!$A$5:$A$661,1))+Inputs!$B$24)^0.25 -> 1.0224749
V76: ='Quarterly returns'!A7 -> 38989 | W76: =W75*(1+'Quarterly returns'!Z7) -> 1.0175007 | X76: =X75*(1+'Quarterly returns'!AA7) -> 1.0166322 | Y76: =Y75*(1+'Quarterly returns'!AB7) -> 1.0067662 | Z76: =Z75*(1+INDEX('RBA 5Y yield'!$B$5:$B$661,MATCH(V75,'RBA 5Y yield'!$A$5:$A$661,1))+Inputs!$B$24)^0.25 -> 1.046531
V77: ='Quarterly returns'!A8 -> 39080 | W77: =W76*(1+'Quarterly returns'!Z8) -> 1.0737006 | X77: =X76*(1+'Quarterly returns'!AA8) -> 1.0587198 | Y77: =Y76*(1+'Quarterly returns'!AB8) -> 1.0515297 | Z77: =Z76*(1+INDEX('RBA 5Y yield'!$B$5:$B$661,MATCH(V76,'RBA 5Y yield'!$A$5:$A$661,1))+Inputs!$B$24)^0.25 -> 1.0713773
V78: ='Quarterly returns'!A9 -> 39171 | W78: =W77*(1+'Quarterly returns'!Z9) -> 1.1108351 | X78: =X77*(1+'Quarterly returns'!AA9) -> 1.0839818 | Y78: =Y77*(1+'Quarterly returns'!AB9) -> 1.077864 | Z78: =Z77*(1+INDEX('RBA 5Y yield'!$B$5:$B$661,MATCH(V77,'RBA 5Y yield'!$A$5:$A$661,1))+Inputs!$B$24)^0.25 -> 1.0967023
V79: ='Quarterly returns'!A10 -> 39262 | W79: =W78*(1+'Quarterly returns'!Z10) -> 1.1287517 | X79: =X78*(1+'Quarterly returns'!AA10) -> 1.1068027 | Y79: =Y78*(1+'Quarterly returns'!AB10) -> 1.0924334 | Z79: =Z78*(1+INDEX('RBA 5Y yield'!$B$5:$B$661,MATCH(V78,'RBA 5Y yield'!$A$5:$A$661,1))+Inputs!$B$24)^0.25 -> 1.1230585
V80: ='Quarterly returns'!A11 -> 39353 | W80: =W79*(1+'Quarterly returns'!Z11) -> 1.1454581 | X80: =X79*(1+'Quarterly returns'!AA11) -> 1.1180822 | Y80: =Y79*(1+'Quarterly returns'!AB11) -> 1.1057853 | Z80: =Z79*(1+INDEX('RBA 5Y yield'!$B$5:$B$661,MATCH(V79,'RBA 5Y yield'!$A$5:$A$661,1))+Inputs!$B$24)^0.25 -> 1.150327
V81: ='Quarterly returns'!A12 -> 39447 | W81: =W80*(1+'Quarterly returns'!Z12) -> 1.1235702 | X81: =X80*(1+'Quarterly returns'!AA12) -> 1.1111151 | Y81: =Y80*(1+'Quarterly returns'!AB12) -> 1.0932802 | Z81: =Z80*(1+INDEX('RBA 5Y yield'!$B$5:$B$661,MATCH(V80,'RBA 5Y yield'!$A$5:$A$661,1))+Inputs!$B$24)^0.25 -> 1.1784178
V82: ='Quarterly returns'!A13 -> 39538 | W82: =W81*(1+'Quarterly returns'!Z13) -> 1.0221682 | X82: =X81*(1+'Quarterly returns'!AA13) -> 1.0233949 | Y82: =Y81*(1+'Quarterly returns'!AB13) -> 0.99357799 | Z82: =Z81*(1+INDEX('RBA 5Y yield'!$B$5:$B$661,MATCH(V81,'RBA 5Y yield'!$A$5:$A$661,1))+Inputs!$B$24)^0.25 -> 1.2081036
V83: ='Quarterly returns'!A14 -> 39629 | W83: =W82*(1+'Quarterly returns'!Z14) -> 0.99550558 | X83: =X82*(1+'Quarterly returns'!AA14) -> 1.0000084 | Y83: =Y82*(1+'Quarterly returns'!AB14) -> 0.96560876 | Z83: =Z82*(1+INDEX('RBA 5Y yield'!$B$5:$B$661,MATCH(V82,'RBA 5Y yield'!$A$5:$A$661,1))+Inputs!$B$24)^0.25 -> 1.2375174
V84: ='Quarterly returns'!A15 -> 39721 | W84: =W83*(1+'Quarterly returns'!Z15) -> 0.99672819 | X84: =X83*(1+'Quarterly returns'!AA15) -> 1.0084066 | Y84: =Y83*(1+'Quarterly returns'!AB15) -> 0.97746841 | Z84: =Z83*(1+INDEX('RBA 5Y yield'!$B$5:$B$661,MATCH(V83,'RBA 5Y yield'!$A$5:$A$661,1))+Inputs!$B$24)^0.25 -> 1.2693422
V85: ='Quarterly returns'!A16 -> 39813 | W85: =W84*(1+'Quarterly returns'!Z16) -> 0.88528886 | X85: =X84*(1+'Quarterly returns'!AA16) -> 0.91587248 | Y85: =Y84*(1+'Quarterly returns'!AB16) -> 0.87091375 | Z85: =Z84*(1+INDEX('RBA 5Y yield'!$B$5:$B$661,MATCH(V84,'RBA 5Y yield'!$A$5:$A$661,1))+Inputs!$B$24)^0.25 -> 1.2985788
V86: ='Quarterly returns'!A17 -> 39903 | W86: =W85*(1+'Quarterly returns'!Z17) -> 0.84263511 | X86: =X85*(1+'Quarterly returns'!AA17) -> 0.87673509 | Y86: =Y85*(1+'Quarterly returns'!AB17) -> 0.82715948 | Z86: =Z85*(1+INDEX('RBA 5Y yield'!$B$5:$B$661,MATCH(V85,'RBA 5Y yield'!$A$5:$A$661,1))+Inputs!$B$24)^0.25 -> 1.3229533
... V97: ='Quarterly returns'!A28 -> 40907 | W97: =W96*(1+'Quarterly returns'!Z28) -> 1.0317395 | X97: =X96*(1+'Quarterly returns'!AA28) -> 1.0380812 | Y97: =Y96*(1+'Quarterly returns'!AB28) -> 0.97758952 | Z97: =Z96*(1+INDEX('RBA 5Y yield'!$B$5:$B$661,MATCH(V96,'RBA 5Y yield'!$A$5:$A$661,1))+Inputs!$B$24)^0.25 -> 1.6707357
A98: Figure 4. Annualised returns to March 2026 | N98: Chart data, figure 4 | V98: ='Quarterly returns'!A29 -> 40998 | W98: =W97*(1+'Quarterly returns'!Z29) -> 1.1032812 | X98: =X97*(1+'Quarterly returns'!AA29) -> 1.1036467 | Y98: =Y97*(1+'Quarterly returns'!AB29) -> 1.0485807 | Z98: =Z97*(1+INDEX('RBA 5Y yield'!$B$5:$B$661,MATCH(V97,'RBA 5Y yield'!$A$5:$A$661,1))+Inputs!$B$24)^0.25 -> 1.7015044
N99: Horizon | O99: Current fund | P99: Benchmark | Q99: Recommended | R99: Target: yield + 4% | V99: ='Quarterly returns'!A30 -> 41089 | W99: =W98*(1+'Quarterly returns'!Z30) -> 1.0876006 | X99: =X98*(1+'Quarterly returns'!AA30) -> 1.0899181 | Y99: =Y98*(1+'Quarterly returns'!AB30) -> 1.03137 | Z99: =Z98*(1+INDEX('RBA 5Y yield'!$B$5:$B$661,MATCH(V98,'RBA 5Y yield'!$A$5:$A$661,1))+Inputs!$B$24)^0.25 -> 1.7330309
N100: 5 years | O100: ='Track record'!M5 -> 0.06905946 | P100: ='Track record'!N5 -> 0.072194704 | Q100: ='Track record'!O5 -> 0.078536013 | R100: ='Track record'!P5 -> 0.04708 | V100: ='Quarterly returns'!A31 -> 41180 | W100: =W99*(1+'Quarterly returns'!Z31) -> 1.139956 | X100: =X99*(1+'Quarterly returns'!AA31) -> 1.1336733 | Y100: =Y99*(1+'Quarterly returns'!AB31) -> 1.0795528 | Z100: =Z99*(1+INDEX('RBA 5Y yield'!$B$5:$B$661,MATCH(V99,'RBA 5Y yield'!$A$5:$A$661,1))+Inputs!$B$24)^0.25 -> 1.7615634
N101: 10 years | O101: ='Track record'!M6 -> 0.077761951 | P101: ='Track record'!N6 -> 0.079036037 | Q101: ='Track record'!O6 -> 0.085520075 | R101: ='Track record'!P6 -> 0.06134 | V101: ='Quarterly returns'!A32 -> 41274 | W101: =W100*(1+'Quarterly returns'!Z32) -> 1.1859971 | X101: =X100*(1+'Quarterly returns'!AA32) -> 1.1721832 | Y101: =Y100*(1+'Quarterly returns'!AB32) -> 1.1194828 | Z101: =Z100*(1+INDEX('RBA 5Y yield'!$B$5:$B$661,MATCH(V100,'RBA 5Y yield'!$A$5:$A$661,1))+Inputs!$B$24)^0.25 -> 1.7908487
N102: 15 years | O102: ='Track record'!M7 -> 0.082327342 | P102: ='Track record'!N7 -> 0.083026852 | Q102: ='Track record'!O7 -> 0.089230278 | R102: ='Track record'!P7 -> 0.092075 | V102: ='Quarterly returns'!A33 -> 41362 | W102: =W101*(1+'Quarterly returns'!Z33) -> 1.2586919 | X102: =X101*(1+'Quarterly returns'!AA33) -> 1.2319599 | Y102: =Y101*(1+'Quarterly returns'!AB33) -> 1.1833811 | Z102: =Z101*(1+INDEX('RBA 5Y yield'!$B$5:$B$661,MATCH(V101,'RBA 5Y yield'!$A$5:$A$661,1))+Inputs!$B$24)^0.25 -> 1.8206527
N103: 20 years | O103: ='Track record'!M8 -> 0.065606512 | P103: ='Track record'!N8 -> 0.065617269 | Q103: ='Track record'!O8 -> 0.067760878 | R103: ='Track record'!P8 -> 0.092976 | V103: ='Quarterly returns'!A34 -> 41453 | W103: =W102*(1+'Quarterly returns'!Z34) -> 1.2967269 | X103: =X102*(1+'Quarterly returns'!AA34) -> 1.2885375 | Y103: =Y102*(1+'Quarterly returns'!AB34) -> 1.2452317 | Z103: =Z102*(1+INDEX('RBA 5Y yield'!$B$5:$B$661,MATCH(V102,'RBA 5Y yield'!$A$5:$A$661,1))+Inputs!$B$24)^0.25 -> 1.8517969
V104: ='Quarterly returns'!A35 -> 41547 | W104: =W103*(1+'Quarterly returns'!Z35) -> 1.3635995 | X104: =X103*(1+'Quarterly returns'!AA35) -> 1.342386 | Y104: =Y103*(1+'Quarterly returns'!AB35) -> 1.3009457 | Z104: =Z103*(1+INDEX('RBA 5Y yield'!$B$5:$B$661,MATCH(V103,'RBA 5Y yield'!$A$5:$A$661,1))+Inputs!$B$24)^0.25 -> 1.88245
V105: ='Quarterly returns'!A36 -> 41639 | W105: =W104*(1+'Quarterly returns'!Z36) -> 1.4271376 | X105: =X104*(1+'Quarterly returns'!AA36) -> 1.417442 | Y105: =Y104*(1+'Quarterly returns'!AB36) -> 1.3768434 | Z105: =Z104*(1+INDEX('RBA 5Y yield'!$B$5:$B$661,MATCH(V104,'RBA 5Y yield'!$A$5:$A$661,1))+Inputs!$B$24)^0.25 -> 1.9160408
V106: ='Quarterly returns'!A37 -> 41729 | W106: =W105*(1+'Quarterly returns'!Z37) -> 1.4438201 | X106: =X105*(1+'Quarterly returns'!AA37) -> 1.423793 | Y106: =Y105*(1+'Quarterly returns'!AB37) -> 1.3828116 | Z106: =Z105*(1+INDEX('RBA 5Y yield'!$B$5:$B$661,MATCH(V105,'RBA 5Y yield'!$A$5:$A$661,1))+Inputs!$B$24)^0.25 -> 1.9508212
V107: ='Quarterly returns'!A38 -> 41820 | W107: =W106*(1+'Quarterly returns'!Z38) -> 1.4728966 | X107: =X106*(1+'Quarterly returns'!AA38) -> 1.4565592 | Y107: =Y106*(1+'Quarterly returns'!AB38) -> 1.4151068 | Z107: =Z106*(1+INDEX('RBA 5Y yield'!$B$5:$B$661,MATCH(V106,'RBA 5Y yield'!$A$5:$A$661,1))+Inputs!$B$24)^0.25 -> 1.9860019
V108: ='Quarterly returns'!A39 -> 41912 | W108: =W107*(1+'Quarterly returns'!Z39) -> 1.5110171 | X108: =X107*(1+'Quarterly returns'!AA39) -> 1.5033572 | Y108: =Y107*(1+'Quarterly returns'!AB39) -> 1.467536 | Z108: =Z107*(1+INDEX('RBA 5Y yield'!$B$5:$B$661,MATCH(V107,'RBA 5Y yield'!$A$5:$A$661,1))+Inputs!$B$24)^0.25 -> 2.0204368
V109: ='Quarterly returns'!A40 -> 42004 | W109: =W108*(1+'Quarterly returns'!Z40) -> 1.6013117 | X109: =X108*(1+'Quarterly returns'!AA40) -> 1.5869674 | Y109: =Y108*(1+'Quarterly returns'!AB40) -> 1.5573312 | Z109: =Z108*(1+INDEX('RBA 5Y yield'!$B$5:$B$661,MATCH(V108,'RBA 5Y yield'!$A$5:$A$661,1))+Inputs!$B$24)^0.25 -> 2.0550993
V110: ='Quarterly returns'!A41 -> 42094 | W110: =W109*(1+'Quarterly returns'!Z41) -> 1.7381636 | X110: =X109*(1+'Quarterly returns'!AA41) -> 1.7093966 | Y110: =Y109*(1+'Quarterly returns'!AB41) -> 1.6953953 | Z110: =Z109*(1+INDEX('RBA 5Y yield'!$B$5:$B$661,MATCH(V109,'RBA 5Y yield'!$A$5:$A$661,1))+Inputs!$B$24)^0.25 -> 2.0873916
V111: ='Quarterly returns'!A42 -> 42185 | W111: =W110*(1+'Quarterly returns'!Z42) -> 1.6685187 | X111: =X110*(1+'Quarterly returns'!AA42) -> 1.6722152 | Y111: =Y110*(1+'Quarterly returns'!AB42) -> 1.6439285 | Z111: =Z110*(1+INDEX('RBA 5Y yield'!$B$5:$B$661,MATCH(V110,'RBA 5Y yield'!$A$5:$A$661,1))+Inputs!$B$24)^0.25 -> 2.1179117
V112: ='Quarterly returns'!A43 -> 42277 | W112: =W111*(1+'Quarterly returns'!Z43) -> 1.6595301 | X112: =X111*(1+'Quarterly returns'!AA43) -> 1.6668499 | Y112: =Y111*(1+'Quarterly returns'!AB43) -> 1.6373901 | Z112: =Z111*(1+INDEX('RBA 5Y yield'!$B$5:$B$661,MATCH(V111,'RBA 5Y yield'!$A$5:$A$661,1))+Inputs!$B$24)^0.25 -> 2.1504479
V113: ='Quarterly returns'!A44 -> 42369 | W113: =W112*(1+'Quarterly returns'!Z44) -> 1.7156178 | X113: =X112*(1+'Quarterly returns'!AA44) -> 1.7012204 | Y113: =Y112*(1+'Quarterly returns'!AB44) -> 1.6721798 | Z113: =Z112*(1+INDEX('RBA 5Y yield'!$B$5:$B$661,MATCH(V112,'RBA 5Y yield'!$A$5:$A$661,1))+Inputs!$B$24)^0.25 -> 2.1825228
V114: ='Quarterly returns'!A45 -> 42460 | W114: =W113*(1+'Quarterly returns'!Z45) -> 1.6854227 | X114: =X113*(1+'Quarterly returns'!AA45) -> 1.6659636 | Y114: =Y113*(1+'Quarterly returns'!AB45) -> 1.6334336 | Z114: =Z113*(1+INDEX('RBA 5Y yield'!$B$5:$B$661,MATCH(V113,'RBA 5Y yield'!$A$5:$A$661,1))+Inputs!$B$24)^0.25 -> 2.2160306
V115: ='Quarterly returns'!A46 -> 42551 | W115: =W114*(1+'Quarterly returns'!Z46) -> 1.7539023 | X115: =X114*(1+'Quarterly returns'!AA46) -> 1.7372537 | Y115: =Y114*(1+'Quarterly returns'!AB46) -> 1.7074903 | Z115: =Z114*(1+INDEX('RBA 5Y yield'!$B$5:$B$661,MATCH(V114,'RBA 5Y yield'!$A$5:$A$661,1))+Inputs!$B$24)^0.25 -> 2.2492586
... V123: ='Quarterly returns'!A54 -> 43280 | W123: =W122*(1+'Quarterly returns'!Z54) -> 2.0894232 | X123: =X122*(1+'Quarterly returns'!AA54) -> 2.0604735 | Y123: =Y122*(1+'Quarterly returns'!AB54) -> 2.0636797 | Z123: =Z122*(1+INDEX('RBA 5Y yield'!$B$5:$B$661,MATCH(V122,'RBA 5Y yield'!$A$5:$A$661,1))+Inputs!$B$24)^0.25 -> 2.5301516
A124: Figure 5. Stress tests | N124: Chart data, figure 5 | V124: ='Quarterly returns'!A55 -> 43371 | W124: =W123*(1+'Quarterly returns'!Z55) -> 2.1445313 | X124: =X123*(1+'Quarterly returns'!AA55) -> 2.113928 | Y124: =Y123*(1+'Quarterly returns'!AB55) -> 2.1287197 | Z124: =Z123*(1+INDEX('RBA 5Y yield'!$B$5:$B$661,MATCH(V123,'RBA 5Y yield'!$A$5:$A$661,1))+Inputs!$B$24)^0.25 -> 2.5697877
N125: Scenario | O125: Current fund | P125: Benchmark | Q125: Recommended | V125: ='Quarterly returns'!A56 -> 43465 | W125: =W124*(1+'Quarterly returns'!Z56) -> 2.0263008 | X125: =X124*(1+'Quarterly returns'!AA56) -> 2.0014175 | Y125: =Y124*(1+'Quarterly returns'!AB56) -> 2.00042 | Z125: =Z124*(1+INDEX('RBA 5Y yield'!$B$5:$B$661,MATCH(V124,'RBA 5Y yield'!$A$5:$A$661,1))+Inputs!$B$24)^0.25 -> 2.6089649
N126: GFC 2007-09 | O126: =Stress!B26 -> -0.24167171 | P126: =Stress!B27 -> -0.19300089 | Q126: =Stress!B28 -> -0.2350248 | V126: ='Quarterly returns'!A57 -> 43553 | W126: =W125*(1+'Quarterly returns'!Z57) -> 2.205747 | X126: =X125*(1+'Quarterly returns'!AA57) -> 2.1552217 | Y126: =Y125*(1+'Quarterly returns'!AB57) -> 2.1834855 | Z126: =Z125*(1+INDEX('RBA 5Y yield'!$B$5:$B$661,MATCH(V125,'RBA 5Y yield'!$A$5:$A$661,1))+Inputs!$B$24)^0.25 -> 2.6478539
N127: COVID 2020 | O127: =Stress!C26 -> -0.12092703 | P127: =Stress!C27 -> -0.091806485 | Q127: =Stress!C28 -> -0.10748236 | V127: ='Quarterly returns'!A58 -> 43644 | W127: =W126*(1+'Quarterly returns'!Z58) -> 2.317873 | X127: =X126*(1+'Quarterly returns'!AA58) -> 2.2497581 | Y127: =Y126*(1+'Quarterly returns'!AB58) -> 2.2833911 | Z127: =Z126*(1+INDEX('RBA 5Y yield'!$B$5:$B$661,MATCH(V126,'RBA 5Y yield'!$A$5:$A$661,1))+Inputs!$B$24)^0.25 -> 2.6850781
N128: Inflation 2022 | O128: =Stress!D26 -> -0.072754437 | P128: =Stress!D27 -> -0.072610798 | Q128: =Stress!D28 -> -0.075405586 | V128: ='Quarterly returns'!A59 -> 43738 | W128: =W127*(1+'Quarterly returns'!Z59) -> 2.4079446 | X128: =X127*(1+'Quarterly returns'!AA59) -> 2.3381935 | Y128: =Y127*(1+'Quarterly returns'!AB59) -> 2.37476 | Z128: =Z127*(1+INDEX('RBA 5Y yield'!$B$5:$B$661,MATCH(V127,'RBA 5Y yield'!$A$5:$A$661,1))+Inputs!$B$24)^0.25 -> 2.7199113
N129: US$150 oil | O129: =Stress!E26 -> -0.082609308 | P129: =Stress!E27 -> -0.073910247 | Q129: =Stress!E28 -> -0.08363891 | V129: ='Quarterly returns'!A60 -> 43830 | W129: =W128*(1+'Quarterly returns'!Z60) -> 2.4146922 | X129: =X128*(1+'Quarterly returns'!AA60) -> 2.3625342 | Y129: =Y128*(1+'Quarterly returns'!AB60) -> 2.3966875 | Z129: =Z128*(1+INDEX('RBA 5Y yield'!$B$5:$B$661,MATCH(V128,'RBA 5Y yield'!$A$5:$A$661,1))+Inputs!$B$24)^0.25 -> 2.7520443
V130: ='Quarterly returns'!A61 -> 43921 | W130: =W129*(1+'Quarterly returns'!Z61) -> 2.1220146 | X130: =X129*(1+'Quarterly returns'!AA61) -> 2.1436419 | Y130: =Y129*(1+'Quarterly returns'!AB61) -> 2.1382883 | Z130: =Z129*(1+INDEX('RBA 5Y yield'!$B$5:$B$661,MATCH(V129,'RBA 5Y yield'!$A$5:$A$661,1))+Inputs!$B$24)^0.25 -> 2.7849819
V131: ='Quarterly returns'!A62 -> 44012 | W131: =W130*(1+'Quarterly returns'!Z62) -> 2.2948598 | X131: =X130*(1+'Quarterly returns'!AA62) -> 2.2574573 | Y131: =Y130*(1+'Quarterly returns'!AB62) -> 2.2795043 | Z131: =Z130*(1+INDEX('RBA 5Y yield'!$B$5:$B$661,MATCH(V130,'RBA 5Y yield'!$A$5:$A$661,1))+Inputs!$B$24)^0.25 -> 2.8157977
V132: ='Quarterly returns'!A63 -> 44104 | W132: =W131*(1+'Quarterly returns'!Z63) -> 2.3155455 | X132: =X131*(1+'Quarterly returns'!AA63) -> 2.2961419 | Y132: =Y131*(1+'Quarterly returns'!AB63) -> 2.3090559 | Z132: =Z131*(1+INDEX('RBA 5Y yield'!$B$5:$B$661,MATCH(V131,'RBA 5Y yield'!$A$5:$A$661,1))+Inputs!$B$24)^0.25 -> 2.8462936
V133: ='Quarterly returns'!A64 -> 44196 | W133: =W132*(1+'Quarterly returns'!Z64) -> 2.4761973 | X133: =X132*(1+'Quarterly returns'!AA64) -> 2.4274432 | Y133: =Y132*(1+'Quarterly returns'!AB64) -> 2.4500079 | Z133: =Z132*(1+INDEX('RBA 5Y yield'!$B$5:$B$661,MATCH(V132,'RBA 5Y yield'!$A$5:$A$661,1))+Inputs!$B$24)^0.25 -> 2.8770509
V134: ='Quarterly returns'!A65 -> 44286 | W134: =W133*(1+'Quarterly returns'!Z65) -> 2.5522782 | X134: =X133*(1+'Quarterly returns'!AA65) -> 2.5156876 | Y134: =Y133*(1+'Quarterly returns'!AB65) -> 2.5427686 | Z134: =Z133*(1+INDEX('RBA 5Y yield'!$B$5:$B$661,MATCH(V133,'RBA 5Y yield'!$A$5:$A$661,1))+Inputs!$B$24)^0.25 -> 2.9077922
V135: ='Quarterly returns'!A66 -> 44377 | W135: =W134*(1+'Quarterly returns'!Z66) -> 2.7258284 | X135: =X134*(1+'Quarterly returns'!AA66) -> 2.6897276 | Y135: =Y134*(1+'Quarterly returns'!AB66) -> 2.7216263 | Z135: =Z134*(1+INDEX('RBA 5Y yield'!$B$5:$B$661,MATCH(V134,'RBA 5Y yield'!$A$5:$A$661,1))+Inputs!$B$24)^0.25 -> 2.9414288
V136: ='Quarterly returns'!A67 -> 44469 | W136: =W135*(1+'Quarterly returns'!Z67) -> 2.7870898 | X136: =X135*(1+'Quarterly returns'!AA67) -> 2.7599662 | Y136: =Y135*(1+'Quarterly returns'!AB67) -> 2.7848911 | Z136: =Z135*(1+INDEX('RBA 5Y yield'!$B$5:$B$661,MATCH(V135,'RBA 5Y yield'!$A$5:$A$661,1))+Inputs!$B$24)^0.25 -> 2.9756249
V137: ='Quarterly returns'!A68 -> 44561 | W137: =W136*(1+'Quarterly returns'!Z68) -> 2.8833239 | X137: =X136*(1+'Quarterly returns'!AA68) -> 2.8522073 | Y137: =Y136*(1+'Quarterly returns'!AB68) -> 2.8831105 | Z137: =Z136*(1+INDEX('RBA 5Y yield'!$B$5:$B$661,MATCH(V136,'RBA 5Y yield'!$A$5:$A$661,1))+Inputs!$B$24)^0.25 -> 3.0097298
V138: ='Quarterly returns'!A69 -> 44651 | W138: =W137*(1+'Quarterly returns'!Z69) -> 2.8003023 | X138: =X137*(1+'Quarterly returns'!AA69) -> 2.7603698 | Y138: =Y137*(1+'Quarterly returns'!AB69) -> 2.7806898 | Z138: =Z137*(1+INDEX('RBA 5Y yield'!$B$5:$B$661,MATCH(V137,'RBA 5Y yield'!$A$5:$A$661,1))+Inputs!$B$24)^0.25 -> 3.0490135
V139: ='Quarterly returns'!A70 -> 44742 | W139: =W138*(1+'Quarterly returns'!Z70) -> 2.5702161 | X139: =X138*(1+'Quarterly returns'!AA70) -> 2.5753309 | Y139: =Y138*(1+'Quarterly returns'!AB70) -> 2.5921827 | Z139: =Z138*(1+INDEX('RBA 5Y yield'!$B$5:$B$661,MATCH(V138,'RBA 5Y yield'!$A$5:$A$661,1))+Inputs!$B$24)^0.25 -> 3.0952854
V140: ='Quarterly returns'!A71 -> 44834 | W140: =W139*(1+'Quarterly returns'!Z71) -> 2.5731399 | X140: =X139*(1+'Quarterly returns'!AA71) -> 2.5607098 | Y140: =Y139*(1+'Quarterly returns'!AB71) -> 2.5883457 | Z140: =Z139*(1+INDEX('RBA 5Y yield'!$B$5:$B$661,MATCH(V139,'RBA 5Y yield'!$A$5:$A$661,1))+Inputs!$B$24)^0.25 -> 3.151721
...

Sheet Inputs
A1: Inputs
A3: 1. Asset classes (linked to Fund balance sheet and Fee schedule)
A4: Asset class | B4: Current fund | C4: Benchmark | D4: Fee (p.a.) | E4: Lower bound | F4: Upper bound | G4: Equity (1/0) | H4: Illiquid (1/0) | J4: Blue = input
A5: Australian Equities | B5: =N('Fund balance sheet'!C7) -> 0.4 | C5: =N('Fund balance sheet'!D7) -> 0.25 | D5: ='Fee schedule'!B6 -> 0.001 | E5: 0.15 | F5: 0.35 | G5: 1 | H5: 0 | J5: Black = formula
A6: World Equities | B6: =N('Fund balance sheet'!C8) -> 0.2 | C6: =N('Fund balance sheet'!D8) -> 0.24 | D6: ='Fee schedule'!B7 -> 0.0015 | E6: 0.15 | F6: 0.35 | G6: 1 | H6: 0 | J6: Yellow = Solver decision cell
A7: Emerging Markets | B7: =N('Fund balance sheet'!C9) -> 0 | C7: =N('Fund balance sheet'!D9) -> 0.03 | D7: ='Fee schedule'!B8 -> 0.002 | E7: 0 | F7: 0.08 | G7: 1 | H7: 0
A8: Listed Property | B8: =N('Fund balance sheet'!C19) -> 0.1 | C8: =N('Fund balance sheet'!D19) -> 0.07 | D8: ='Fee schedule'!B9 -> 0.0015 | E8: 0 | F8: 0.12 | G8: 0 | H8: 0
A9: Commodities | B9: =N('Fund balance sheet'!C26) -> 0 | C9: =N('Fund balance sheet'!D26) -> 0.02 | D9: ='Fee schedule'!B17 -> 0.0025 | E9: 0 | F9: 0.08 | G9: 0 | H9: 0
A10: Direct Property | B10: =N('Fund balance sheet'!C20) -> 0 | C10: =N('Fund balance sheet'!D20) -> 0.05 | D10: ='Fee schedule'!B14 -> 0.012 | E10: 0 | F10: 0.1 | G10: 0 | H10: 1
A11: Hedge Funds | B11: =N('Fund balance sheet'!C24) -> 0 | C11: =N('Fund balance sheet'!D24) -> 0.03 | D11: ='Fee schedule'!B15 -> 0.025 | E11: 0 | F11: 0.08 | G11: 0 | H11: 1
A12: Private Equity | B12: =N('Fund balance sheet'!C25) -> 0 | C12: =N('Fund balance sheet'!D25) -> 0.03 | D12: ='Fee schedule'!B16 -> 0.03 | E12: 0 | F12: 0.08 | G12: 0 | H12: 1
A13: Australian Fixed Income | B13: =N('Fund balance sheet'!C13) -> 0.15 | C13: =N('Fund balance sheet'!D13) -> 0.14 | D13: ='Fee schedule'!B10 -> 0.001 | E13: 0.12 | F13: 0.25 | G13: 0 | H13: 0
A14: World Fixed Income | B14: =N('Fund balance sheet'!C14) -> 0.08 | C14: =N('Fund balance sheet'!D14) -> 0.11 | D14: ='Fee schedule'!B11 -> 0.0015 | E14: 0.05 | F14: 0.2 | G14: 0 | H14: 0
A15: Cash | B15: =N('Fund balance sheet'!C15) -> 0.07 | C15: =N('Fund balance sheet'!D15) -> 0.03 | D15: ='Fee schedule'!B5 -> 0 | E15: 0.02 | F15: 0.1 | G15: 0 | H15: 0
A16: Total | B16: =SUM(B5:B15) -> 1 | C16: =SUM(C5:C15) -> 1
A18: Australian fixed income floor 12%: home-currency defensive anchor; keeps the bond split stable against resampling (Methods section 3).
A20: 2. Mandate and constraints
A21: Parameter | B21: Value | C21: Source
A22: Funds under management (A$m) | B22: ='Fund balance sheet'!B29 -> 3000 | C22: Fund balance sheet
A23: 5-year bond yield | B23: 0.04988 | C23: RBA F2, 22-Sep-26
A24: Target spread | B24: 0.04 | C24: Brief
A25: Required return (yield + spread) | B25: =B23+B24 -> 0.08988 | C25: Calc
A26: Australian cash rate | B26: 0.046 | C26: RBA, 29-Sep-26
A27: Tracking error limit | B27: 0.015 | C27: Brief
A28: 5-year loss probability limit | B28: 0.25 | C28: Brief
A29: Equity band (+/-) | B29: 0.1 | C29: Brief
A30: Benchmark equity weight | B30: =SUMPRODUCT(C5:C15,G5:G15) -> 0.52 | C30: Calc
A31: Equity minimum | B31: =B30-B29 -> 0.42 | C31: Calc
A32: Equity maximum | B32: =B30+B29 -> 0.62 | C32: Calc
A33: Illiquid maximum | B33: 0.3 | C33: Brief
A34: Cash minimum | B34: 0.02 | C34: Brief
A36: 3. Model settings
A37: Parameter | B37: Value | C37: Source
A38: Shrinkage intensity | B38: 0.35 | C38: Ledoit-Wolf (2004)
A39: Direct property smoothing | B39: 0.65 | C39: Lag-1 autocorrelation
A40: Private equity smoothing | B40: 0.24 | C40: Lag-1 autocorrelation
A41: Risk aversion (delta) | B41: 4 | C41: Black-Litterman
A42: Max confidence in building blocks | B42: 0.65 | C42: Judgement
A43: Min confidence in building blocks | B43: 0.2 | C43: Judgement
A44: Method dispersion at min confidence | B44: 0.04 | C44: Judgement
A45: TE limit in optimiser | B45: 0.011 | C45: Calibrated: bootstrap TE < 1.5%
A46: Equal Aus/world equity returns (1 = yes) | B46: 1 | C46: Lecture 5
A47: Stage 2 overweight cap | B47: 0.02 | C47: Judgement
A48: Bootstrap seed | B48: 20261016 | C48: Fixed seed
A49: Selected method (1 Robust, 2 Sample, 3 Resampled, 4 Min var, 5 Risk parity) | B49: 1 | C49: Methods tab
A52: 4. Implementation: one-way transaction costs (judgement, indicative)
A53: Asset class | B53: Cost (one-way) | C53: Basis
A54: Australian Equities | B54: 0.001 | C54: Brokerage + spread
A55: World Equities | B55: 0.001 | C55: Brokerage + spread
A56: Emerging Markets | B56: 0.0025 | C56: Wider spreads
A57: Listed Property | B57: 0.002 | C57: Spread
A58: Commodities | B58: 0.001 | C58: Futures roll + spread
A59: Direct Property | B59: 0.015 | C59: Unlisted fund buy spread
A60: Hedge Funds | B60: 0.005 | C60: Fund buy spread
A61: Private Equity | B61: 0.01 | C61: Secondary or commitment costs
A62: Australian Fixed Income | B62: 0.001 | C62: Spread
A63: World Fixed Income | B63: 0.0015 | C63: Spread (hedged)
A64: Cash | B64: 0 | C64: None
A67: 5. Transition and tax parameters
A68: Parameter | B68: Value | C68: Source
A69: Years to amortise transition costs | B69: 5 | C69: SIP horizon
A70: Direct property funded by end of year 1 | B70: 0.5 | C70: Judgement: unlisted fund queues
A71: Direct property funded by end of year 2 | B71: 1 | C71: Judgement
A72: Private equity funded by end of year 1 | B72: 0.33333333 | C72: Commitments drawn over 3 years
A73: Private equity funded by end of year 2 | B73: 0.66666667 | C73: Commitments drawn over 3 years
A74: Private equity funded by end of year 3 | B74: 1 | C74: Commitments drawn over 3 years
A75: Unfunded direct property: share held in listed property | B75: 0.8 | C75: Judgement: listed property is the closest liquid proxy
A76: Unfunded private equity held in | B76: Cash | C76: Liquid reserve for capital calls
A77: Australian equity dividend yield (trailing) | B77: =Forecast!B41 -> 0.0343 | C77: Forecast tab
A78: Share of dividends franked | B78: 0.7 | C78: Judgement: ASX franking level c.70%
A79: Company tax rate | B79: 0.3 | C79: Australian company tax rate
A80: Share of franking value the fund captures | B80: 1 | C80: Super fund taxed at 15% uses credits in full

Sheet Forecast
A1: Forecast
A3: 1. Summary
A5: Asset class | B5: Building-block composite (gross, arithmetic) | C5: Equilibrium prior | D5: Confidence | E5: Gross forecast | F5: Fee | G5: Net forecast | H5: Volatility | I5: View dispersion
A6: Australian Equities | B6: =G139 -> 0.078008816 | C6: =Inputs!$B$23+Inputs!$B$41*SUMPRODUCT(MMULT(Risk!$B$41:$L$41,Inputs!$C$5:$C$15)) -> 0.085434421 | D6: =Inputs!$B$42-(Inputs!$B$42-Inputs!$B$43)*MIN(1,I6/Inputs!$B$44) -> 0.4072028 | E6: =IF(Inputs!$B$46=1,AVERAGE((D6*B6+(1-D6)*C6),(D7*B7+(1-D7)*C7)),(D6*B6+(1-D6)*C6)) -> 0.078798125 | F6: =Inputs!D5 -> 0.001 | G6: =E6-F6 -> 0.077798125 | H6: =Risk!M41 -> 0.15381532 | I6: =I139 -> 0.021581973
A7: World Equities | B7: =G140 -> 0.069574729 | C7: =Inputs!$B$23+Inputs!$B$41*SUMPRODUCT(MMULT(Risk!$B$42:$L$42,Inputs!$C$5:$C$15)) -> 0.077973432 | D7: =Inputs!$B$42-(Inputs!$B$42-Inputs!$B$43)*MIN(1,I7/Inputs!$B$44) -> 0.33194119 | E7: =IF(Inputs!$B$46=1,AVERAGE((D6*B6+(1-D6)*C6),(D7*B7+(1-D7)*C7)),(D7*B7+(1-D7)*C7)) -> 0.078798125 | F7: =Inputs!D6 -> 0.0015 | G7: =E7-F7 -> 0.077298125 | H7: =Risk!M42 -> 0.12748315 | I7: =I140 -> 0.028271894
A8: Emerging Markets | B8: =G141 -> 0.079179468 | C8: =Inputs!$B$23+Inputs!$B$41*SUMPRODUCT(MMULT(Risk!$B$43:$L$43,Inputs!$C$5:$C$15)) -> 0.066679499 | D8: =Inputs!$B$42-(Inputs!$B$42-Inputs!$B$43)*MIN(1,I8/Inputs!$B$44) -> 0.48125 | E8: =(D8*B8+(1-D8)*C8) -> 0.072695109 | F8: =Inputs!D7 -> 0.002 | G8: =E8-F8 -> 0.070695109 | H8: =Risk!M43 -> 0.1049906 | I8: =I141 -> 0.015
A9: Listed Property | B9: =G142 -> 0.082782899 | C9: =Inputs!$B$23+Inputs!$B$41*SUMPRODUCT(MMULT(Risk!$B$44:$L$44,Inputs!$C$5:$C$15)) -> 0.07862403 | D9: =Inputs!$B$42-(Inputs!$B$42-Inputs!$B$43)*MIN(1,I9/Inputs!$B$44) -> 0.48125 | E9: =(D9*B9+(1-D9)*C9) -> 0.080625486 | F9: =Inputs!D8 -> 0.0015 | G9: =E9-F9 -> 0.079125486 | H9: =Risk!M44 -> 0.16766255 | I9: =I142 -> 0.015
A10: Commodities | B10: =G143 -> 0.086478574 | C10: =Inputs!$B$23+Inputs!$B$41*SUMPRODUCT(MMULT(Risk!$B$45:$L$45,Inputs!$C$5:$C$15)) -> 0.066007581 | D10: =Inputs!$B$42-(Inputs!$B$42-Inputs!$B$43)*MIN(1,I10/Inputs!$B$44) -> 0.3125 | E10: =(D10*B10+(1-D10)*C10) -> 0.072404767 | F10: =Inputs!D9 -> 0.0025 | G10: =E10-F10 -> 0.069904767 | H10: =Risk!M45 -> 0.24588035 | I10: =I143 -> 0.03
A11: Direct Property | B11: =G144 -> 0.054080974 | C11: =Inputs!$B$23+Inputs!$B$41*SUMPRODUCT(MMULT(Risk!$B$46:$L$46,Inputs!$C$5:$C$15)) -> 0.057809544 | D11: =Inputs!$B$42-(Inputs!$B$42-Inputs!$B$43)*MIN(1,I11/Inputs!$B$44) -> 0.425 | E11: =(D11*B11+(1-D11)*C11) -> 0.056224902 | F11: =Inputs!D10 -> 0.012 | G11: =E11-F11 -> 0.044224902 | H11: =Risk!M46 -> 0.095333549 | I11: =I144 -> 0.02
A12: Hedge Funds | B12: =G145 -> 0.079280702 | C12: =Inputs!$B$23+Inputs!$B$41*SUMPRODUCT(MMULT(Risk!$B$47:$L$47,Inputs!$C$5:$C$15)) -> 0.049701287 | D12: =Inputs!$B$42-(Inputs!$B$42-Inputs!$B$43)*MIN(1,I12/Inputs!$B$44) -> 0.425 | E12: =(D12*B12+(1-D12)*C12) -> 0.062272538 | F12: =Inputs!D11 -> 0.025 | G12: =E12-F12 -> 0.037272538 | H12: =Risk!M47 -> 0.071939397 | I12: =I145 -> 0.02
A13: Private Equity | B13: =G146 -> 0.11254628 | C13: =Inputs!$B$23+Inputs!$B$41*SUMPRODUCT(MMULT(Risk!$B$48:$L$48,Inputs!$C$5:$C$15)) -> 0.067396811 | D13: =Inputs!$B$42-(Inputs!$B$42-Inputs!$B$43)*MIN(1,I13/Inputs!$B$44) -> 0.3125 | E13: =(D13*B13+(1-D13)*C13) -> 0.081506021 | F13: =Inputs!D12 -> 0.03 | G13: =E13-F13 -> 0.051506021 | H13: =Risk!M48 -> 0.12724606 | I13: =I146 -> 0.03
A14: Australian Fixed Income | B14: =G147 -> 0.051402658 | C14: =Inputs!$B$23+Inputs!$B$41*SUMPRODUCT(MMULT(Risk!$B$49:$L$49,Inputs!$C$5:$C$15)) -> 0.050887359 | D14: =Inputs!$B$42-(Inputs!$B$42-Inputs!$B$43)*MIN(1,I14/Inputs!$B$44) -> 0.61625 | E14: =(D14*B14+(1-D14)*C14) -> 0.051204912 | F14: =Inputs!D13 -> 0.001 | G14: =E14-F14 -> 0.050204912 | H14: =Risk!M49 -> 0.042489011 | I14: =I147 -> 0.003
A15: World Fixed Income | B15: =G148 -> 0.057193023 | C15: =Inputs!$B$23+Inputs!$B$41*SUMPRODUCT(MMULT(Risk!$B$50:$L$50,Inputs!$C$5:$C$15)) -> 0.051289318 | D15: =Inputs!$B$42-(Inputs!$B$42-Inputs!$B$43)*MIN(1,I15/Inputs!$B$44) -> 0.59375 | E15: =(D15*B15+(1-D15)*C15) -> 0.054794643 | F15: =Inputs!D14 -> 0.0015 | G15: =E15-F15 -> 0.053294643 | H15: =Risk!M50 -> 0.040530808 | I15: =I148 -> 0.005
A16: Cash | B16: =G149 -> 0.046488137 | C16: =Inputs!$B$23+Inputs!$B$41*SUMPRODUCT(MMULT(Risk!$B$51:$L$51,Inputs!$C$5:$C$15)) -> 0.049641723 | D16: =Inputs!$B$42-(Inputs!$B$42-Inputs!$B$43)*MIN(1,I16/Inputs!$B$44) -> 0.61625 | E16: =(D16*B16+(1-D16)*C16) -> 0.047698326 | F16: =Inputs!D15 -> 0 | G16: =E16-F16 -> 0.047698326 | H16: =Risk!M51 -> 0.0098119767 | I16: =I149 -> 0.003
A18: Best single-asset forecast (compound) | G18: =MAX(M139:M149) -> 0.069172149
A19: Return target (bond yield + 4%) | G19: =Inputs!$B$25 -> 0.08988
A20: Target reachable? | G20: =IF(G18>=G19,"YES","NO") -> NO
A23: 2. Historical returns (adjusted quarterly data)
A24: Asset class | B24: 20-year CAGR | C24: 10-year CAGR | D24: 5-year CAGR | E24: Excess vs cash, 20y | F24: Excess vs cash, 10y | G24: Excess vs cash, 5y
A25: Australian Equities | B25: =EXP(SUMPRODUCT(LN(1+'Quarterly returns'!N$6:N$85))*4/80)-1 -> 0.06950125 | C25: =EXP(SUMPRODUCT(LN(1+'Quarterly returns'!N$46:N$85))*4/40)-1 -> 0.094599768 | D25: =EXP(SUMPRODUCT(LN(1+'Quarterly returns'!N$66:N$85))*4/20)-1 -> 0.0836422 | E25: =B25-B$35 -> 0.0364421 | F25: =C25-C$35 -> 0.072734217 | G25: =D25-D$35 -> 0.054730416
A26: World Equities | B26: =EXP(SUMPRODUCT(LN(1+'Quarterly returns'!O$6:O$85))*4/80)-1 -> 0.088450813 | C26: =EXP(SUMPRODUCT(LN(1+'Quarterly returns'!O$46:O$85))*4/40)-1 -> 0.14009824 | D26: =EXP(SUMPRODUCT(LN(1+'Quarterly returns'!O$66:O$85))*4/20)-1 -> 0.13819307 | E26: =B26-B$35 -> 0.055391663 | F26: =C26-C$35 -> 0.11823269 | G26: =D26-D$35 -> 0.10928129
A27: Emerging Markets | B27: =EXP(SUMPRODUCT(LN(1+'Quarterly returns'!P$6:P$85))*4/80)-1 -> 0.079988928 | C27: =EXP(SUMPRODUCT(LN(1+'Quarterly returns'!P$46:P$85))*4/40)-1 -> 0.11222714 | D27: =EXP(SUMPRODUCT(LN(1+'Quarterly returns'!P$66:P$85))*4/20)-1 -> 0.089739489 | E27: =B27-B$35 -> 0.046929778 | F27: =C27-C$35 -> 0.090361593 | G27: =D27-D$35 -> 0.060827705
A28: Listed Property | B28: =EXP(SUMPRODUCT(LN(1+'Quarterly returns'!Q$6:Q$85))*4/80)-1 -> 0.053753446 | C28: =EXP(SUMPRODUCT(LN(1+'Quarterly returns'!Q$46:Q$85))*4/40)-1 -> 0.059762085 | D28: =EXP(SUMPRODUCT(LN(1+'Quarterly returns'!Q$66:Q$85))*4/20)-1 -> 0.070428794 | E28: =B28-B$35 -> 0.020694296 | F28: =C28-C$35 -> 0.037896534 | G28: =D28-D$35 -> 0.04151701
A29: Commodities | B29: =EXP(SUMPRODUCT(LN(1+'Quarterly returns'!R$6:R$85))*4/80)-1 -> -0.0067382599 | C29: =EXP(SUMPRODUCT(LN(1+'Quarterly returns'!R$46:R$85))*4/40)-1 -> 0.1127272 | D29: =EXP(SUMPRODUCT(LN(1+'Quarterly returns'!R$66:R$85))*4/20)-1 -> 0.22123504 | E29: =B29-B$35 -> -0.039797409 | F29: =C29-C$35 -> 0.090861648 | G29: =D29-D$35 -> 0.19232325
A30: Direct Property | B30: =EXP(SUMPRODUCT(LN(1+'Quarterly returns'!S$6:S$85))*4/80)-1 -> 0.060608487 | C30: =EXP(SUMPRODUCT(LN(1+'Quarterly returns'!S$46:S$85))*4/40)-1 -> 0.056636213 | D30: =EXP(SUMPRODUCT(LN(1+'Quarterly returns'!S$66:S$85))*4/20)-1 -> 0.046465511 | E30: =B30-B$35 -> 0.027549338 | F30: =C30-C$35 -> 0.034770662 | G30: =D30-D$35 -> 0.017553727
A31: Hedge Funds | B31: =EXP(SUMPRODUCT(LN(1+'Quarterly returns'!T$6:T$85))*4/80)-1 -> 0.076551345 | C31: =EXP(SUMPRODUCT(LN(1+'Quarterly returns'!T$46:T$85))*4/40)-1 -> 0.075066369 | D31: =EXP(SUMPRODUCT(LN(1+'Quarterly returns'!T$66:T$85))*4/20)-1 -> 0.083698848 | E31: =B31-B$35 -> 0.043492196 | F31: =C31-C$35 -> 0.053200818 | G31: =D31-D$35 -> 0.054787063
A32: Private Equity | B32: =EXP(SUMPRODUCT(LN(1+'Quarterly returns'!U$6:U$85))*4/80)-1 -> 0.1068722 | C32: =EXP(SUMPRODUCT(LN(1+'Quarterly returns'!U$46:U$85))*4/40)-1 -> 0.10920514 | D32: =EXP(SUMPRODUCT(LN(1+'Quarterly returns'!U$66:U$85))*4/20)-1 -> 0.10226788 | E32: =B32-B$35 -> 0.073813048 | F32: =C32-C$35 -> 0.08733959 | G32: =D32-D$35 -> 0.073356092
A33: Australian Fixed Income | B33: =EXP(SUMPRODUCT(LN(1+'Quarterly returns'!V$6:V$85))*4/80)-1 -> 0.039606305 | C33: =EXP(SUMPRODUCT(LN(1+'Quarterly returns'!V$46:V$85))*4/40)-1 -> 0.016560819 | D33: =EXP(SUMPRODUCT(LN(1+'Quarterly returns'!V$66:V$85))*4/20)-1 -> -0.0008978244 | E33: =B33-B$35 -> 0.0065471554 | F33: =C33-C$35 -> -0.0053047319 | G33: =D33-D$35 -> -0.029809609
A34: World Fixed Income | B34: =EXP(SUMPRODUCT(LN(1+'Quarterly returns'!W$6:W$85))*4/80)-1 -> 0.043020943 | C34: =EXP(SUMPRODUCT(LN(1+'Quarterly returns'!W$46:W$85))*4/40)-1 -> 0.0093981374 | D34: =EXP(SUMPRODUCT(LN(1+'Quarterly returns'!W$66:W$85))*4/20)-1 -> -0.011384459 | E34: =B34-B$35 -> 0.0099617934 | F34: =C34-C$35 -> -0.012467414 | G34: =D34-D$35 -> -0.040296243
A35: Cash | B35: =EXP(SUMPRODUCT(LN(1+'Quarterly returns'!X$6:X$85))*4/80)-1 -> 0.033059149 | C35: =EXP(SUMPRODUCT(LN(1+'Quarterly returns'!X$46:X$85))*4/40)-1 -> 0.021865551 | D35: =EXP(SUMPRODUCT(LN(1+'Quarterly returns'!X$66:X$85))*4/20)-1 -> 0.028911784 | E35: =B35-B$35 -> 0 | F35: =C35-C$35 -> 0 | G35: =D35-D$35 -> 0
A38: 3. Implied equity returns
A39: Item | B39: Australian equities | C39: World equities | D39: Source
A40: As at | B40: 46265 | C40: 46265
A41: Dividend yield (trailing) | B41: 0.0343 | C41: 0.015 | D41: Market data
A42: P/E (trailing) | B42: 20.39 | C42: 23.2
A43: P/E (forward) | B43: 18.82 | C43: 18.55
A44: Expected inflation | B44: =$B$58 -> 0.0275 | C44: =$B$59 -> 0.025 | D44: Section 4
A45: Real growth | B45: =$B$65 -> 0.02 | C45: =$B$70 -> 0.018 | D45: Section 4
A46: Forward dividend yield | B46: =B41*B42/B43 -> 0.037161371 | C46: =C41*C42/C43 -> 0.018760108
A47: Nominal growth | B47: =B44+B45 -> 0.0475 | C47: =C44+C45 -> 0.043
A48: DDM: D1/P0 + g | B48: =B46+B47 -> 0.084661371 | C48: =C46+C47 -> 0.061760108
A49: Earnings yield + inflation | B49: =1/B43+B44 -> 0.080634963 | C49: =1/C43+C44 -> 0.078908356
A50: Implied return (average; cross-check on section 5b) | B50: =AVERAGE(B48:B49) -> 0.082648167 | C50: =AVERAGE(C48:C49) -> 0.070334232
A53: 4. Market and economic inputs, Sep-2026 (blue = sourced or judgement input)
A54: Input | B54: Value | C54: Source
A55: AU cash rate (RBA target) | B55: =Inputs!$B$26 -> 0.046 | C55: RBA, 29-Sep-26 (Inputs B26)
A56: AU 5-year government bond yield | B56: =Inputs!$B$23 -> 0.04988 | C56: RBA F2, 22-Sep-26 (Inputs B23)
A57: AU 5-year term premium | B57: 0.003 | C57: Judgement; Hambur & Finlay (2018), RBA RDP 2018-02, find small positive term premia
A58: Australian inflation, 5-year average | B58: 0.0275 | C58: RBA Statement on Monetary Policy, Aug-2026: inflation back to 2.5% by early 2028
A59: Foreign inflation, 5-year average | B59: 0.025 | C59: Judgement: above 2% targets near term (Fed, ECB and BoJ all raised rates in Sep-2026)
A60: Equity premium over bills (geometric, long run) | B60: 0.035 | C60: Dimson, Marsh & Staunton, UBS Global Investment Returns Yearbook 2026: c.3.5% p.a.
A61: Share of the P/E gap closed over 5 years | B61: 0.5 | C61: Judgement; Campbell & Shiller (1998): valuations mean-revert slowly
A62: Australian equities: forward dividend yield | B62: =$B$46 -> 0.037161371 | C62: Section 3 (market data, 31-Aug-26)
A63: Australian equities: forward P/E | B63: =$B$43 -> 18.82 | C63: Section 3 (market data, 31-Aug-26)
A64: Australian equities: long-run average forward P/E | B64: 14.8 | C64: Judgement: long-run average forward P/E (IG, ASX 200 outlook 2026: 14.8x)
A65: Australian equities: real earnings growth | B65: 0.02 | C65: Judgement: about potential GDP growth (RBA SMP Aug-2026)
A66: Australian equities: net dilution | B66: 0.01 | C66: Bernstein & Arnott (2003): c.2% p.a.; judgement 1% (DRPs offset by buybacks)
A67: World equities: forward dividend yield | B67: =$C$46 -> 0.018760108 | C67: Section 3 (market data, 31-Aug-26)
A68: World equities: forward P/E | B68: =$C$43 -> 18.55 | C68: Section 3 (market data, 31-Aug-26)
A69: World equities: long-run average forward P/E | B69: 15.5 | C69: Judgement: long-run average forward P/E for MSCI World
A70: World equities: real earnings growth | B70: 0.018 | C70: Judgement: developed-market potential growth
A71: World equities: net dilution | B71: 0.005 | C71: Judgement: US buybacks offset issuance elsewhere; Bernstein & Arnott (2003)
A72: Emerging markets: dividend yield | B72: 0.02 | C72: iShares MSCI EM ETF trailing 12-month yield, May-2026
A73: Emerging markets: forward P/E | B73: 11.6 | C73: Siblis Research, Jan-2026
A74: Emerging markets: long-run average forward P/E | B74: 12 | C74: Judgement: long-run average forward P/E for MSCI EM
A75: Emerging markets: real earnings growth | B75: 0.035 | C75: Judgement: EM potential growth
A76: Emerging markets: net dilution | B76: 0.02 | C76: Bernstein & Arnott (2003): c.2% p.a.
A77: Listed property: REIT dividend yield | B77: 0.0368 | C77: Nareit, FTSE Nareit All Equity REITs, Aug-2026
A78: Listed property: net issuance | B78: 0.01 | C78: Judgement: REITs fund growth with new equity
A79: Listed property: real rent growth | B79: 0.005 | C79: Judgement
A80: Direct property: gross rental yield | B80: 0.0379 | C80: Cotality, national dwellings, Aug-2026
... A97: World bonds: United Kingdom weight | B97: 0.061 | C97: Vanguard VIF fact sheet
A98: World bonds: euro area and other weight | B98: =1-$B$95-$B$96-$B$97 -> 0.387 | C98: Remainder, priced at Bund rates (conservative)
A99: World bonds: duration and basis adjustment | B99: -0.0025 | C99: Judgement: 10-year yields overstate a 6.7-year duration index (-0.15%); basis and costs (-0.10%)
A100: Commodities: excess return over collateral | B100: 0.015 | C100: Levine et al. (2018): 3.3% geometric for a diversified index; Erb & Harvey (2006): c.0% for the average commodity
A101: Hedge funds: equity beta | B101: 0.35 | C101: Judgement from factor-model literature (Fung & Hsieh 2004); data estimate in section 5c
A102: Hedge funds: net alpha | B102: 0 | C102: Dichev & Yu (2011): investors earn 3-7% less than fund returns
A103: Private equity: equity beta | B103: 1.2 | C103: Korteweg (2019) survey: 0.7 to 3.2; Axelson, Sorensen & Stromberg (2014); judgement
A104: Private equity: net premium over levered public equity | B104: 0.01 | C104: Harris, Jenkinson & Kaplan (2014): >3% p.a. (1984-2008 vintages); judgement 1% for recent vintages
A107: 5a. Yield, carry and factor builds (compound, p.a.)
A108: Asset class | B108: Starting yield or income | C108: Growth or carry | D108: Adjustments | E108: Currency or hedge | F108: View A | G108: View B | H108: Method
A109: Cash | B109: =$B$56 -> 0.04988 | D109: =-$B$57 -> -0.003 | F109: =SUM(B109:E109) -> 0.04688 | G109: =$B$55 -> 0.046 | H109: Expectations hypothesis
A110: Australian Fixed Income | B110: =$B$84 -> 0.051 | D110: =-$B$86 -> -0.0005 | F110: =SUM(B110:E110) -> 0.0505 | H110: Yield to maturity
A111: World Fixed Income | B111: =($B$95*$B$87+$B$96*$B$91+$B$97*$B$93+$B$98*$B$89) -> 0.0421554 | D111: =$B$99 -> -0.0025 | E111: =$B$55-($B$95*$B$88+$B$96*$B$92+$B$97*$B$94+$B$98*$B$90) -> 0.01671625 | F111: =SUM(B111:E111) -> 0.05637165 | H111: Covered interest parity
A112: Commodities | B112: =$B$88 -> 0.03875 | C112: =$B$100 -> 0.015 | E112: =$B$58-$B$59 -> 0.0025 | F112: =SUM(B112:E112) -> 0.05625 | H112: Collateral + excess + PPP
A113: Direct Property | B113: =$B$80-$B$81-$B$82 -> 0.0119 | C113: =$B$58+$B$83 -> 0.0325 | D113: 0 | F113: =SUM(B113:E113) -> 0.0444 | G113: =$D$149+$B$131*$B$60 -> 0.054673462 | H113: Cap-rate model; B: beta build-up
A114: Hedge Funds | B114: =$D$149 -> 0.04644 | C114: =$B$101*($D$140-$D$149) -> 0.0052530632 | D114: =$B$102 -> 0 | F114: =SUM(B114:E114) -> 0.051693063 | H114: Factor model (net of fees)
A115: Private Equity | B115: =$D$149 -> 0.04644 | C115: =$B$103*($D$140-$D$149) -> 0.018010502 | D115: =$B$104 -> 0.01 | F115: =SUM(B115:E115) -> 0.074450502 | H115: Levered equity (net of fees)
A119: 5b. Equities and listed property: Grinold-Kroner and risk-premium build-up (compound, p.a.; foreign returns in AUD via relative PPP)
A120: Asset class | B120: Dividend yield | C120: Net dilution | D120: Real earnings growth | E120: Inflation (AUD) | F120: Repricing | G120: View A: Grinold-Kroner | H120: Beta to equity premium | I120: View B: cash + beta x premium
A121: Australian Equities | B121: =$B$62 -> 0.037161371 | C121: =-$B$66 -> -0.01 | D121: =$B$65 -> 0.02 | E121: =$B$58 -> 0.0275 | F121: =($B$64/$B$63)^($B$61/5)-1 -> -0.02374289 | G121: =SUM(B121:F121) -> 0.05091848 | H121: =1 -> 1 | I121: =$D$149+H121*$B$60 -> 0.08144
A122: World Equities | B122: =$B$67 -> 0.018760108 | C122: =-$B$71 -> -0.005 | D122: =$B$70 -> 0.018 | E122: =$B$58 -> 0.0275 | F122: =($B$69/$B$68)^($B$61/5)-1 -> -0.017802604 | G122: =SUM(B122:F122) -> 0.041457504 | H122: =1 -> 1 | I122: =$D$149+H122*$B$60 -> 0.08144
A123: Emerging Markets | B123: =$B$72 -> 0.02 | C123: =-$B$76 -> -0.02 | D123: =$B$75 -> 0.035 | E123: =$B$58 -> 0.0275 | F123: =($B$74/$B$73)^($B$61/5)-1 -> 0.0033959082 | G123: =SUM(B123:F123) -> 0.065895908 | H123: =1 -> 1 | I123: =$D$149+H123*$B$60 -> 0.08144
A124: Listed Property | B124: =$B$77 -> 0.0368 | C124: =-$B$78 -> -0.01 | D124: =$B$79 -> 0.005 | E124: =$B$58 -> 0.0275 | F124: 0 | G124: =SUM(B124:F124) -> 0.0593 | H124: =$B$130 -> 0.90614483 | I124: =$D$149+H124*$B$60 -> 0.078155069
A128: 5c. Betas to world equities (quarterly excess returns since 2006)
A129: Asset class | B129: Beta | C129: R-squared | D129: Quarters | E129: Used? | F129: Literature value
A130: Listed Property | B130: =SLOPE('Quarterly returns'!$AG$6:$AG$85,'Quarterly returns'!$AF$6:$AF$85) -> 0.90614483 | C130: =RSQ('Quarterly returns'!$AG$6:$AG$85,'Quarterly returns'!$AF$6:$AF$85) -> 0.48507524 | D130: =COUNT('Quarterly returns'!$AG$6:$AG$85) -> 80 | E130: Yes
A131: Direct Property | B131: =SLOPE('Quarterly returns'!$AH$6:$AH$85,'Quarterly returns'!$AF$6:$AF$85) -> 0.23524179 | C131: =RSQ('Quarterly returns'!$AH$6:$AH$85,'Quarterly returns'!$AF$6:$AF$85) -> 0.099666111 | D131: =COUNT('Quarterly returns'!$AH$6:$AH$85) -> 80 | E131: Yes
A132: Private Equity | B132: =SLOPE('Quarterly returns'!$AI$6:$AI$85,'Quarterly returns'!$AF$6:$AF$85) -> 0.47194825 | C132: =RSQ('Quarterly returns'!$AI$6:$AI$85,'Quarterly returns'!$AF$6:$AF$85) -> 0.22878638 | D132: =COUNT('Quarterly returns'!$AI$6:$AI$85) -> 80 | E132: No: AUD index distorts beta | F132: =$B$103 -> 1.2
A133: Hedge Funds | B133: =SLOPE('Quarterly returns'!$AJ$6:$AJ$85,'Quarterly returns'!$AF$6:$AF$85) -> 0.0039350414 | C133: =RSQ('Quarterly returns'!$AJ$6:$AJ$85,'Quarterly returns'!$AF$6:$AF$85) -> 5.2020264e-05 | D133: =COUNT('Quarterly returns'!$AJ$6:$AJ$85) -> 80 | E133: No: AUD index distorts beta | F133: =$B$101 -> 0.35
...

Sheet Risk
A1: Risk
A3: 1. Sample covariance (annualised, adjusted quarterly returns)
A4: Asset class | B4: Australian Equities | C4: World Equities | D4: Emerging Markets | E4: Listed Property | F4: Commodities | G4: Direct Property | H4: Hedge Funds | I4: Private Equity | J4: Australian Fixed Income | K4: World Fixed Income | L4: Cash | M4: Sample vol
A5: Australian Equities | B5: =_xlfn.COVARIANCE.S('Quarterly returns'!$N$6:$N$85,'Quarterly returns'!$N$6:$N$85)*4 -> 0.023659152 | C5: =_xlfn.COVARIANCE.S('Quarterly returns'!$N$6:$N$85,'Quarterly returns'!$O$6:$O$85)*4 -> 0.010201113 | D5: =_xlfn.COVARIANCE.S('Quarterly returns'!$N$6:$N$85,'Quarterly returns'!$P$6:$P$85)*4 -> 0.0093962404 | E5: =_xlfn.COVARIANCE.S('Quarterly returns'!$N$6:$N$85,'Quarterly returns'!$Q$6:$Q$85)*4 -> 0.011218765 | F5: =_xlfn.COVARIANCE.S('Quarterly returns'!$N$6:$N$85,'Quarterly returns'!$R$6:$R$85)*4 -> 0.0093552336 | G5: =_xlfn.COVARIANCE.S('Quarterly returns'!$N$6:$N$85,'Quarterly returns'!$S$6:$S$85)*4 -> 0.003164105 | H5: =_xlfn.COVARIANCE.S('Quarterly returns'!$N$6:$N$85,'Quarterly returns'!$T$6:$T$85)*4 -> -0.0020963989 | I5: =_xlfn.COVARIANCE.S('Quarterly returns'!$N$6:$N$85,'Quarterly returns'!$U$6:$U$85)*4 -> 0.010511054 | J5: =_xlfn.COVARIANCE.S('Quarterly returns'!$N$6:$N$85,'Quarterly returns'!$V$6:$V$85)*4 -> -0.0010678114 | K5: =_xlfn.COVARIANCE.S('Quarterly returns'!$N$6:$N$85,'Quarterly returns'!$W$6:$W$85)*4 -> 0.00017412555 | L5: =_xlfn.COVARIANCE.S('Quarterly returns'!$N$6:$N$85,'Quarterly returns'!$X$6:$X$85)*4 -> -0.00028218901 | M5: =SQRT(B5) -> 0.15381532
A6: World Equities | B6: =_xlfn.COVARIANCE.S('Quarterly returns'!$O$6:$O$85,'Quarterly returns'!$N$6:$N$85)*4 -> 0.010201113 | C6: =_xlfn.COVARIANCE.S('Quarterly returns'!$O$6:$O$85,'Quarterly returns'!$O$6:$O$85)*4 -> 0.016251953 | D6: =_xlfn.COVARIANCE.S('Quarterly returns'!$O$6:$O$85,'Quarterly returns'!$P$6:$P$85)*4 -> 0.0091897284 | E6: =_xlfn.COVARIANCE.S('Quarterly returns'!$O$6:$O$85,'Quarterly returns'!$Q$6:$Q$85)*4 -> 0.014691055 | F6: =_xlfn.COVARIANCE.S('Quarterly returns'!$O$6:$O$85,'Quarterly returns'!$R$6:$R$85)*4 -> 0.0060217523 | G6: =_xlfn.COVARIANCE.S('Quarterly returns'!$O$6:$O$85,'Quarterly returns'!$S$6:$S$85)*4 -> 0.0034416564 | H6: =_xlfn.COVARIANCE.S('Quarterly returns'!$O$6:$O$85,'Quarterly returns'!$T$6:$T$85)*4 -> -0.00025929381 | I6: =_xlfn.COVARIANCE.S('Quarterly returns'!$O$6:$O$85,'Quarterly returns'!$U$6:$U$85)*4 -> 0.0074619821 | J6: =_xlfn.COVARIANCE.S('Quarterly returns'!$O$6:$O$85,'Quarterly returns'!$V$6:$V$85)*4 -> -0.00021924073 | K6: =_xlfn.COVARIANCE.S('Quarterly returns'!$O$6:$O$85,'Quarterly returns'!$W$6:$W$85)*4 -> -0.00063739192 | L6: =_xlfn.COVARIANCE.S('Quarterly returns'!$O$6:$O$85,'Quarterly returns'!$X$6:$X$85)*4 -> -0.00033337705 | M6: =SQRT(C6) -> 0.12748315
A7: Emerging Markets | B7: =_xlfn.COVARIANCE.S('Quarterly returns'!$P$6:$P$85,'Quarterly returns'!$N$6:$N$85)*4 -> 0.0093962404 | C7: =_xlfn.COVARIANCE.S('Quarterly returns'!$P$6:$P$85,'Quarterly returns'!$O$6:$O$85)*4 -> 0.0091897284 | D7: =_xlfn.COVARIANCE.S('Quarterly returns'!$P$6:$P$85,'Quarterly returns'!$P$6:$P$85)*4 -> 0.011023027 | E7: =_xlfn.COVARIANCE.S('Quarterly returns'!$P$6:$P$85,'Quarterly returns'!$Q$6:$Q$85)*4 -> 0.0067816259 | F7: =_xlfn.COVARIANCE.S('Quarterly returns'!$P$6:$P$85,'Quarterly returns'!$R$6:$R$85)*4 -> 0.0051228004 | G7: =_xlfn.COVARIANCE.S('Quarterly returns'!$P$6:$P$85,'Quarterly returns'!$S$6:$S$85)*4 -> 0.0041754167 | H7: =_xlfn.COVARIANCE.S('Quarterly returns'!$P$6:$P$85,'Quarterly returns'!$T$6:$T$85)*4 -> -6.2837013e-05 | I7: =_xlfn.COVARIANCE.S('Quarterly returns'!$P$6:$P$85,'Quarterly returns'!$U$6:$U$85)*4 -> 0.0040455748 | J7: =_xlfn.COVARIANCE.S('Quarterly returns'!$P$6:$P$85,'Quarterly returns'!$V$6:$V$85)*4 -> -0.00055660691 | K7: =_xlfn.COVARIANCE.S('Quarterly returns'!$P$6:$P$85,'Quarterly returns'!$W$6:$W$85)*4 -> -0.00032363921 | L7: =_xlfn.COVARIANCE.S('Quarterly returns'!$P$6:$P$85,'Quarterly returns'!$X$6:$X$85)*4 -> -0.00018014153 | M7: =SQRT(D7) -> 0.1049906
A8: Listed Property | B8: =_xlfn.COVARIANCE.S('Quarterly returns'!$Q$6:$Q$85,'Quarterly returns'!$N$6:$N$85)*4 -> 0.011218765 | C8: =_xlfn.COVARIANCE.S('Quarterly returns'!$Q$6:$Q$85,'Quarterly returns'!$O$6:$O$85)*4 -> 0.014691055 | D8: =_xlfn.COVARIANCE.S('Quarterly returns'!$Q$6:$Q$85,'Quarterly returns'!$P$6:$P$85)*4 -> 0.0067816259 | E8: =_xlfn.COVARIANCE.S('Quarterly returns'!$Q$6:$Q$85,'Quarterly returns'!$Q$6:$Q$85)*4 -> 0.028110729 | F8: =_xlfn.COVARIANCE.S('Quarterly returns'!$Q$6:$Q$85,'Quarterly returns'!$R$6:$R$85)*4 -> 0.0032896337 | G8: =_xlfn.COVARIANCE.S('Quarterly returns'!$Q$6:$Q$85,'Quarterly returns'!$S$6:$S$85)*4 -> 0.0016672375 | H8: =_xlfn.COVARIANCE.S('Quarterly returns'!$Q$6:$Q$85,'Quarterly returns'!$T$6:$T$85)*4 -> -0.0019657819 | I8: =_xlfn.COVARIANCE.S('Quarterly returns'!$Q$6:$Q$85,'Quarterly returns'!$U$6:$U$85)*4 -> 0.007622374 | J8: =_xlfn.COVARIANCE.S('Quarterly returns'!$Q$6:$Q$85,'Quarterly returns'!$V$6:$V$85)*4 -> 0.0011424276 | K8: =_xlfn.COVARIANCE.S('Quarterly returns'!$Q$6:$Q$85,'Quarterly returns'!$W$6:$W$85)*4 -> 0.0011450282 | L8: =_xlfn.COVARIANCE.S('Quarterly returns'!$Q$6:$Q$85,'Quarterly returns'!$X$6:$X$85)*4 -> -0.00029733142 | M8: =SQRT(E8) -> 0.16766255
A9: Commodities | B9: =_xlfn.COVARIANCE.S('Quarterly returns'!$R$6:$R$85,'Quarterly returns'!$N$6:$N$85)*4 -> 0.0093552336 | C9: =_xlfn.COVARIANCE.S('Quarterly returns'!$R$6:$R$85,'Quarterly returns'!$O$6:$O$85)*4 -> 0.0060217523 | D9: =_xlfn.COVARIANCE.S('Quarterly returns'!$R$6:$R$85,'Quarterly returns'!$P$6:$P$85)*4 -> 0.0051228004 | E9: =_xlfn.COVARIANCE.S('Quarterly returns'!$R$6:$R$85,'Quarterly returns'!$Q$6:$Q$85)*4 -> 0.0032896337 | F9: =_xlfn.COVARIANCE.S('Quarterly returns'!$R$6:$R$85,'Quarterly returns'!$R$6:$R$85)*4 -> 0.060457147 | G9: =_xlfn.COVARIANCE.S('Quarterly returns'!$R$6:$R$85,'Quarterly returns'!$S$6:$S$85)*4 -> 0.0048364771 | H9: =_xlfn.COVARIANCE.S('Quarterly returns'!$R$6:$R$85,'Quarterly returns'!$T$6:$T$85)*4 -> -0.0029536532 | I9: =_xlfn.COVARIANCE.S('Quarterly returns'!$R$6:$R$85,'Quarterly returns'!$U$6:$U$85)*4 -> -0.00028250152 | J9: =_xlfn.COVARIANCE.S('Quarterly returns'!$R$6:$R$85,'Quarterly returns'!$V$6:$V$85)*4 -> -0.0054720198 | K9: =_xlfn.COVARIANCE.S('Quarterly returns'!$R$6:$R$85,'Quarterly returns'!$W$6:$W$85)*4 -> -0.0054841287 | L9: =_xlfn.COVARIANCE.S('Quarterly returns'!$R$6:$R$85,'Quarterly returns'!$X$6:$X$85)*4 -> -0.0003053015 | M9: =SQRT(F9) -> 0.24588035
A10: Direct Property | B10: =_xlfn.COVARIANCE.S('Quarterly returns'!$S$6:$S$85,'Quarterly returns'!$N$6:$N$85)*4 -> 0.003164105 | C10: =_xlfn.COVARIANCE.S('Quarterly returns'!$S$6:$S$85,'Quarterly returns'!$O$6:$O$85)*4 -> 0.0034416564 | D10: =_xlfn.COVARIANCE.S('Quarterly returns'!$S$6:$S$85,'Quarterly returns'!$P$6:$P$85)*4 -> 0.0041754167 | E10: =_xlfn.COVARIANCE.S('Quarterly returns'!$S$6:$S$85,'Quarterly returns'!$Q$6:$Q$85)*4 -> 0.0016672375 | F10: =_xlfn.COVARIANCE.S('Quarterly returns'!$S$6:$S$85,'Quarterly returns'!$R$6:$R$85)*4 -> 0.0048364771 | G10: =_xlfn.COVARIANCE.S('Quarterly returns'!$S$6:$S$85,'Quarterly returns'!$S$6:$S$85)*4 -> 0.0090884856 | H10: =_xlfn.COVARIANCE.S('Quarterly returns'!$S$6:$S$85,'Quarterly returns'!$T$6:$T$85)*4 -> 0.0004080026 | I10: =_xlfn.COVARIANCE.S('Quarterly returns'!$S$6:$S$85,'Quarterly returns'!$U$6:$U$85)*4 -> 0.0023270627 | J10: =_xlfn.COVARIANCE.S('Quarterly returns'!$S$6:$S$85,'Quarterly returns'!$V$6:$V$85)*4 -> -0.0011143499 | K10: =_xlfn.COVARIANCE.S('Quarterly returns'!$S$6:$S$85,'Quarterly returns'!$W$6:$W$85)*4 -> -0.00067265871 | L10: =_xlfn.COVARIANCE.S('Quarterly returns'!$S$6:$S$85,'Quarterly returns'!$X$6:$X$85)*4 -> -0.00013132648 | M10: =SQRT(G10) -> 0.095333549
A11: Hedge Funds | B11: =_xlfn.COVARIANCE.S('Quarterly returns'!$T$6:$T$85,'Quarterly returns'!$N$6:$N$85)*4 -> -0.0020963989 | C11: =_xlfn.COVARIANCE.S('Quarterly returns'!$T$6:$T$85,'Quarterly returns'!$O$6:$O$85)*4 -> -0.00025929381 | D11: =_xlfn.COVARIANCE.S('Quarterly returns'!$T$6:$T$85,'Quarterly returns'!$P$6:$P$85)*4 -> -6.2837013e-05 | E11: =_xlfn.COVARIANCE.S('Quarterly returns'!$T$6:$T$85,'Quarterly returns'!$Q$6:$Q$85)*4 -> -0.0019657819 | F11: =_xlfn.COVARIANCE.S('Quarterly returns'!$T$6:$T$85,'Quarterly returns'!$R$6:$R$85)*4 -> -0.0029536532 | G11: =_xlfn.COVARIANCE.S('Quarterly returns'!$T$6:$T$85,'Quarterly returns'!$S$6:$S$85)*4 -> 0.0004080026 | H11: =_xlfn.COVARIANCE.S('Quarterly returns'!$T$6:$T$85,'Quarterly returns'!$T$6:$T$85)*4 -> 0.0051752768 | I11: =_xlfn.COVARIANCE.S('Quarterly returns'!$T$6:$T$85,'Quarterly returns'!$U$6:$U$85)*4 -> -0.00063140198 | J11: =_xlfn.COVARIANCE.S('Quarterly returns'!$T$6:$T$85,'Quarterly returns'!$V$6:$V$85)*4 -> 0.00035220021 | K11: =_xlfn.COVARIANCE.S('Quarterly returns'!$T$6:$T$85,'Quarterly returns'!$W$6:$W$85)*4 -> 5.021398e-06 | L11: =_xlfn.COVARIANCE.S('Quarterly returns'!$T$6:$T$85,'Quarterly returns'!$X$6:$X$85)*4 -> 0.00010340346 | M11: =SQRT(H11) -> 0.071939397
A12: Private Equity | B12: =_xlfn.COVARIANCE.S('Quarterly returns'!$U$6:$U$85,'Quarterly returns'!$N$6:$N$85)*4 -> 0.010511054 | C12: =_xlfn.COVARIANCE.S('Quarterly returns'!$U$6:$U$85,'Quarterly returns'!$O$6:$O$85)*4 -> 0.0074619821 | D12: =_xlfn.COVARIANCE.S('Quarterly returns'!$U$6:$U$85,'Quarterly returns'!$P$6:$P$85)*4 -> 0.0040455748 | E12: =_xlfn.COVARIANCE.S('Quarterly returns'!$U$6:$U$85,'Quarterly returns'!$Q$6:$Q$85)*4 -> 0.007622374 | F12: =_xlfn.COVARIANCE.S('Quarterly returns'!$U$6:$U$85,'Quarterly returns'!$R$6:$R$85)*4 -> -0.00028250152 | G12: =_xlfn.COVARIANCE.S('Quarterly returns'!$U$6:$U$85,'Quarterly returns'!$S$6:$S$85)*4 -> 0.0023270627 | H12: =_xlfn.COVARIANCE.S('Quarterly returns'!$U$6:$U$85,'Quarterly returns'!$T$6:$T$85)*4 -> -0.00063140198 | I12: =_xlfn.COVARIANCE.S('Quarterly returns'!$U$6:$U$85,'Quarterly returns'!$U$6:$U$85)*4 -> 0.01619156 | J12: =_xlfn.COVARIANCE.S('Quarterly returns'!$U$6:$U$85,'Quarterly returns'!$V$6:$V$85)*4 -> 0.00032821521 | K12: =_xlfn.COVARIANCE.S('Quarterly returns'!$U$6:$U$85,'Quarterly returns'!$W$6:$W$85)*4 -> 0.00042088405 | L12: =_xlfn.COVARIANCE.S('Quarterly returns'!$U$6:$U$85,'Quarterly returns'!$X$6:$X$85)*4 -> -0.00013855702 | M12: =SQRT(I12) -> 0.12724606
A13: Australian Fixed Income | B13: =_xlfn.COVARIANCE.S('Quarterly returns'!$V$6:$V$85,'Quarterly returns'!$N$6:$N$85)*4 -> -0.0010678114 | C13: =_xlfn.COVARIANCE.S('Quarterly returns'!$V$6:$V$85,'Quarterly returns'!$O$6:$O$85)*4 -> -0.00021924073 | D13: =_xlfn.COVARIANCE.S('Quarterly returns'!$V$6:$V$85,'Quarterly returns'!$P$6:$P$85)*4 -> -0.00055660691 | E13: =_xlfn.COVARIANCE.S('Quarterly returns'!$V$6:$V$85,'Quarterly returns'!$Q$6:$Q$85)*4 -> 0.0011424276 | F13: =_xlfn.COVARIANCE.S('Quarterly returns'!$V$6:$V$85,'Quarterly returns'!$R$6:$R$85)*4 -> -0.0054720198 | G13: =_xlfn.COVARIANCE.S('Quarterly returns'!$V$6:$V$85,'Quarterly returns'!$S$6:$S$85)*4 -> -0.0011143499 | H13: =_xlfn.COVARIANCE.S('Quarterly returns'!$V$6:$V$85,'Quarterly returns'!$T$6:$T$85)*4 -> 0.00035220021 | I13: =_xlfn.COVARIANCE.S('Quarterly returns'!$V$6:$V$85,'Quarterly returns'!$U$6:$U$85)*4 -> 0.00032821521 | J13: =_xlfn.COVARIANCE.S('Quarterly returns'!$V$6:$V$85,'Quarterly returns'!$V$6:$V$85)*4 -> 0.0018053161 | K13: =_xlfn.COVARIANCE.S('Quarterly returns'!$V$6:$V$85,'Quarterly returns'!$W$6:$W$85)*4 -> 0.0014020089 | L13: =_xlfn.COVARIANCE.S('Quarterly returns'!$V$6:$V$85,'Quarterly returns'!$X$6:$X$85)*4 -> 0.00014748733 | M13: =SQRT(J13) -> 0.042489011
A14: World Fixed Income | B14: =_xlfn.COVARIANCE.S('Quarterly returns'!$W$6:$W$85,'Quarterly returns'!$N$6:$N$85)*4 -> 0.00017412555 | C14: =_xlfn.COVARIANCE.S('Quarterly returns'!$W$6:$W$85,'Quarterly returns'!$O$6:$O$85)*4 -> -0.00063739192 | D14: =_xlfn.COVARIANCE.S('Quarterly returns'!$W$6:$W$85,'Quarterly returns'!$P$6:$P$85)*4 -> -0.00032363921 | E14: =_xlfn.COVARIANCE.S('Quarterly returns'!$W$6:$W$85,'Quarterly returns'!$Q$6:$Q$85)*4 -> 0.0011450282 | F14: =_xlfn.COVARIANCE.S('Quarterly returns'!$W$6:$W$85,'Quarterly returns'!$R$6:$R$85)*4 -> -0.0054841287 | G14: =_xlfn.COVARIANCE.S('Quarterly returns'!$W$6:$W$85,'Quarterly returns'!$S$6:$S$85)*4 -> -0.00067265871 | H14: =_xlfn.COVARIANCE.S('Quarterly returns'!$W$6:$W$85,'Quarterly returns'!$T$6:$T$85)*4 -> 5.021398e-06 | I14: =_xlfn.COVARIANCE.S('Quarterly returns'!$W$6:$W$85,'Quarterly returns'!$U$6:$U$85)*4 -> 0.00042088405 | J14: =_xlfn.COVARIANCE.S('Quarterly returns'!$W$6:$W$85,'Quarterly returns'!$V$6:$V$85)*4 -> 0.0014020089 | K14: =_xlfn.COVARIANCE.S('Quarterly returns'!$W$6:$W$85,'Quarterly returns'!$W$6:$W$85)*4 -> 0.0016427464 | L14: =_xlfn.COVARIANCE.S('Quarterly returns'!$W$6:$W$85,'Quarterly returns'!$X$6:$X$85)*4 -> 0.00013721798 | M14: =SQRT(K14) -> 0.040530808
A15: Cash | B15: =_xlfn.COVARIANCE.S('Quarterly returns'!$X$6:$X$85,'Quarterly returns'!$N$6:$N$85)*4 -> -0.00028218901 | C15: =_xlfn.COVARIANCE.S('Quarterly returns'!$X$6:$X$85,'Quarterly returns'!$O$6:$O$85)*4 -> -0.00033337705 | D15: =_xlfn.COVARIANCE.S('Quarterly returns'!$X$6:$X$85,'Quarterly returns'!$P$6:$P$85)*4 -> -0.00018014153 | E15: =_xlfn.COVARIANCE.S('Quarterly returns'!$X$6:$X$85,'Quarterly returns'!$Q$6:$Q$85)*4 -> -0.00029733142 | F15: =_xlfn.COVARIANCE.S('Quarterly returns'!$X$6:$X$85,'Quarterly returns'!$R$6:$R$85)*4 -> -0.0003053015 | G15: =_xlfn.COVARIANCE.S('Quarterly returns'!$X$6:$X$85,'Quarterly returns'!$S$6:$S$85)*4 -> -0.00013132648 | H15: =_xlfn.COVARIANCE.S('Quarterly returns'!$X$6:$X$85,'Quarterly returns'!$T$6:$T$85)*4 -> 0.00010340346 | I15: =_xlfn.COVARIANCE.S('Quarterly returns'!$X$6:$X$85,'Quarterly returns'!$U$6:$U$85)*4 -> -0.00013855702 | J15: =_xlfn.COVARIANCE.S('Quarterly returns'!$X$6:$X$85,'Quarterly returns'!$V$6:$V$85)*4 -> 0.00014748733 | K15: =_xlfn.COVARIANCE.S('Quarterly returns'!$X$6:$X$85,'Quarterly returns'!$W$6:$W$85)*4 -> 0.00013721798 | L15: =_xlfn.COVARIANCE.S('Quarterly returns'!$X$6:$X$85,'Quarterly returns'!$X$6:$X$85)*4 -> 9.6274886e-05 | M15: =SQRT(L15) -> 0.0098119767
A18: 2. Correlation
A19: Asset class | B19: Australian Equities | C19: World Equities | D19: Emerging Markets | E19: Listed Property | F19: Commodities | G19: Direct Property | H19: Hedge Funds | I19: Private Equity | J19: Australian Fixed Income | K19: World Fixed Income | L19: Cash
A20: Australian Equities | B20: =B5/($M5*$M$5) -> 1 | C20: =C5/($M5*$M$6) -> 0.52022975 | D20: =D5/($M5*$M$7) -> 0.5818407 | E20: =E5/($M5*$M$8) -> 0.43502018 | F20: =F5/($M5*$M$9) -> 0.247361 | G20: =G5/($M5*$M$10) -> 0.2157772 | H20: =H5/($M5*$M$11) -> -0.18945564 | I20: =I5/($M5*$M$12) -> 0.53703467 | J20: =J5/($M5*$M$13) -> -0.16338731 | K20: =K5/($M5*$M$14) -> 0.027930433 | L20: =L5/($M5*$M$15) -> -0.1869752
A21: World Equities | B21: =B6/($M6*$M$5) -> 0.52022975 | C21: =C6/($M6*$M$6) -> 1 | D21: =D6/($M6*$M$7) -> 0.68659313 | E21: =E6/($M6*$M$8) -> 0.68732817 | F21: =F6/($M6*$M$9) -> 0.19210837 | G21: =G6/($M6*$M$10) -> 0.28318416 | H21: =H6/($M6*$M$11) -> -0.028273044 | I21: =I6/($M6*$M$12) -> 0.45999921 | J21: =J6/($M6*$M$13) -> -0.040475463 | K21: =K6/($M6*$M$14) -> -0.12335834 | L21: =L6/($M6*$M$15) -> -0.26651791
A22: Emerging Markets | B22: =B7/($M7*$M$5) -> 0.5818407 | C22: =C7/($M7*$M$6) -> 0.68659313 | D22: =D7/($M7*$M$7) -> 1 | E22: =E7/($M7*$M$8) -> 0.38525416 | F22: =F7/($M7*$M$9) -> 0.19844181 | G22: =G7/($M7*$M$10) -> 0.41716093 | H22: =H7/($M7*$M$11) -> -0.0083195206 | I22: =I7/($M7*$M$12) -> 0.30282063 | J22: =J7/($M7*$M$13) -> -0.12477326 | K22: =K7/($M7*$M$14) -> -0.076054592 | L22: =L7/($M7*$M$15) -> -0.17486662
A23: Listed Property | B23: =B8/($M8*$M$5) -> 0.43502018 | C23: =C8/($M8*$M$6) -> 0.68732817 | D23: =D8/($M8*$M$7) -> 0.38525416 | E23: =E8/($M8*$M$8) -> 1 | F23: =F8/($M8*$M$9) -> 0.079797201 | G23: =G8/($M8*$M$10) -> 0.10430753 | H23: =H8/($M8*$M$11) -> -0.16297931 | I23: =I8/($M8*$M$12) -> 0.35728095 | J23: =J8/($M8*$M$13) -> 0.16036736 | K23: =K8/($M8*$M$14) -> 0.16849804 | L23: =L8/($M8*$M$15) -> -0.18073749
A24: Commodities | B24: =B9/($M9*$M$5) -> 0.247361 | C24: =C9/($M9*$M$6) -> 0.19210837 | D24: =D9/($M9*$M$7) -> 0.19844181 | E24: =E9/($M9*$M$8) -> 0.079797201 | F24: =F9/($M9*$M$9) -> 1 | G24: =G9/($M9*$M$10) -> 0.20632865 | H24: =H9/($M9*$M$11) -> -0.1669817 | I24: =I9/($M9*$M$12) -> -0.0090292696 | J24: =J9/($M9*$M$13) -> -0.52377795 | K24: =K9/($M9*$M$14) -> -0.55029878 | L24: =L9/($M9*$M$15) -> -0.12654605
A25: Direct Property | B25: =B10/($M10*$M$5) -> 0.2157772 | C25: =C10/($M10*$M$6) -> 0.28318416 | D25: =D10/($M10*$M$7) -> 0.41716093 | E25: =E10/($M10*$M$8) -> 0.10430753 | F25: =F10/($M10*$M$9) -> 0.20632865 | G25: =G10/($M10*$M$10) -> 1 | H25: =H10/($M10*$M$11) -> 0.059490877 | I25: =I10/($M10*$M$12) -> 0.19183064 | J25: =J10/($M10*$M$13) -> -0.27510544 | K25: =K10/($M10*$M$14) -> -0.17408596 | L25: =L10/($M10*$M$15) -> -0.14039448
A26: Hedge Funds | B26: =B11/($M11*$M$5) -> -0.18945564 | C26: =C11/($M11*$M$6) -> -0.028273044 | D26: =D11/($M11*$M$7) -> -0.0083195206 | E26: =E11/($M11*$M$8) -> -0.16297931 | F26: =F11/($M11*$M$9) -> -0.1669817 | G26: =G11/($M11*$M$10) -> 0.059490877 | H26: =H11/($M11*$M$11) -> 1 | I26: =I11/($M11*$M$12) -> -0.068975492 | J26: =J11/($M11*$M$13) -> 0.11522486 | K26: =K11/($M11*$M$14) -> 0.0017221564 | L26: =L11/($M11*$M$15) -> 0.14649128
A27: Private Equity | B27: =B12/($M12*$M$5) -> 0.53703467 | C27: =C12/($M12*$M$6) -> 0.45999921 | D27: =D12/($M12*$M$7) -> 0.30282063 | E27: =E12/($M12*$M$8) -> 0.35728095 | F27: =F12/($M12*$M$9) -> -0.0090292696 | G27: =G12/($M12*$M$10) -> 0.19183064 | H27: =H12/($M12*$M$11) -> -0.068975492 | I27: =I12/($M12*$M$12) -> 1 | J27: =J12/($M12*$M$13) -> 0.060706856 | K27: =K12/($M12*$M$14) -> 0.081608025 | L27: =L12/($M12*$M$15) -> -0.11097565
A28: Australian Fixed Income | B28: =B13/($M13*$M$5) -> -0.16338731 | C28: =C13/($M13*$M$6) -> -0.040475463 | D28: =D13/($M13*$M$7) -> -0.12477326 | E28: =E13/($M13*$M$8) -> 0.16036736 | F28: =F13/($M13*$M$9) -> -0.52377795 | G28: =G13/($M13*$M$10) -> -0.27510544 | H28: =H13/($M13*$M$11) -> 0.11522486 | I28: =I13/($M13*$M$12) -> 0.060706856 | J28: =J13/($M13*$M$13) -> 1 | K28: =K13/($M13*$M$14) -> 0.81412085 | L28: =L13/($M13*$M$15) -> 0.35377048
A29: World Fixed Income | B29: =B14/($M14*$M$5) -> 0.027930433 | C29: =C14/($M14*$M$6) -> -0.12335834 | D29: =D14/($M14*$M$7) -> -0.076054592 | E29: =E14/($M14*$M$8) -> 0.16849804 | F29: =F14/($M14*$M$9) -> -0.55029878 | G29: =G14/($M14*$M$10) -> -0.17408596 | H29: =H14/($M14*$M$11) -> 0.0017221564 | I29: =I14/($M14*$M$12) -> 0.081608025 | J29: =J14/($M14*$M$13) -> 0.81412085 | K29: =K14/($M14*$M$14) -> 1 | L29: =L14/($M14*$M$15) -> 0.34503985
A30: Cash | B30: =B15/($M15*$M$5) -> -0.1869752 | C30: =C15/($M15*$M$6) -> -0.26651791 | D30: =D15/($M15*$M$7) -> -0.17486662 | E30: =E15/($M15*$M$8) -> -0.18073749 | F30: =F15/($M15*$M$9) -> -0.12654605 | G30: =G15/($M15*$M$10) -> -0.14039448 | H30: =H15/($M15*$M$11) -> 0.14649128 | I30: =I15/($M15*$M$12) -> -0.11097565 | J30: =J15/($M15*$M$13) -> 0.35377048 | K30: =K15/($M15*$M$14) -> 0.34503985 | L30: =L15/($M15*$M$15) -> 1
A32: Average correlation (target) | B32: =(SUM(B20:L30)-11)/110 -> 0.10095138
A38: 3. Shrunk covariance
A40: Asset class | B40: Australian Equities | C40: World Equities | D40: Emerging Markets | E40: Listed Property | F40: Commodities | G40: Direct Property | H40: Hedge Funds | I40: Private Equity | J40: Australian Fixed Income | K40: World Fixed Income | L40: Cash | M40: Shrunk vol
A41: Australian Equities | B41: =B5 -> 0.023659152 | C41: =(1-Inputs!$B$38)*C5+Inputs!$B$38*$B$32*$M5*$M$6 -> 0.0073235629 | D41: =(1-Inputs!$B$38)*D5+Inputs!$B$38*$B$32*$M5*$M$7 -> 0.0066781543 | E41: =(1-Inputs!$B$38)*E5+Inputs!$B$38*$B$32*$M5*$M$8 -> 0.0082034018 | F41: =(1-Inputs!$B$38)*F5+Inputs!$B$38*$B$32*$M5*$M$9 -> 0.007417201 | G41: =(1-Inputs!$B$38)*G5+Inputs!$B$38*$B$32*$M5*$M$10 -> 0.0025747826 | H41: =(1-Inputs!$B$38)*H5+Inputs!$B$38*$B$32*$M5*$M$11 -> -0.00097168636 | I41: =(1-Inputs!$B$38)*I5+Inputs!$B$38*$B$32*$M5*$M$12 -> 0.0075237358 | J41: =(1-Inputs!$B$38)*J5+Inputs!$B$38*$B$32*$M5*$M$13 -> -0.00046316007 | K41: =(1-Inputs!$B$38)*K5+Inputs!$B$38*$B$32*$M5*$M$14 -> 0.00033345657 | L41: =(1-Inputs!$B$38)*L5+Inputs!$B$38*$B$32*$M5*$M$15 -> -0.00013009718 | M41: =SQRT(B41) -> 0.15381532
A42: World Equities | B42: =(1-Inputs!$B$38)*B6+Inputs!$B$38*$B$32*$M6*$M$5 -> 0.0073235629 | C42: =C6 -> 0.016251953 | D42: =(1-Inputs!$B$38)*D6+Inputs!$B$38*$B$32*$M6*$M$7 -> 0.0064462389 | E42: =(1-Inputs!$B$38)*E6+Inputs!$B$38*$B$32*$M6*$M$8 -> 0.010304398 | F42: =(1-Inputs!$B$38)*F6+Inputs!$B$38*$B$32*$M6*$M$9 -> 0.0050216726 | G42: =(1-Inputs!$B$38)*G6+Inputs!$B$38*$B$32*$M6*$M$10 -> 0.0026664933 | H42: =(1-Inputs!$B$38)*H6+Inputs!$B$38*$B$32*$M6*$M$11 -> 0.00015549994 | I42: =(1-Inputs!$B$38)*I6+Inputs!$B$38*$B$32*$M6*$M$12 -> 0.0054234504 | J42: =(1-Inputs!$B$38)*J6+Inputs!$B$38*$B$32*$M6*$M$13 -> 4.8879317e-05 | K42: =(1-Inputs!$B$38)*K6+Inputs!$B$38*$B$32*$M6*$M$14 -> -0.00023173941 | L42: =(1-Inputs!$B$38)*L6+Inputs!$B$38*$B$32*$M6*$M$15 -> -0.00017249841 | M42: =SQRT(C42) -> 0.12748315
A43: Emerging Markets | B43: =(1-Inputs!$B$38)*B7+Inputs!$B$38*$B$32*$M7*$M$5 -> 0.0066781543 | C43: =(1-Inputs!$B$38)*C7+Inputs!$B$38*$B$32*$M7*$M$6 -> 0.0064462389 | D43: =D7 -> 0.011023027 | E43: =(1-Inputs!$B$38)*E7+Inputs!$B$38*$B$32*$M7*$M$8 -> 0.0050300231 | F43: =(1-Inputs!$B$38)*F7+Inputs!$B$38*$B$32*$M7*$M$9 -> 0.0042419457 | G43: =(1-Inputs!$B$38)*G7+Inputs!$B$38*$B$32*$M7*$M$10 -> 0.0030676732 | H43: =(1-Inputs!$B$38)*H7+Inputs!$B$38*$B$32*$M7*$M$11 -> 0.00022602456 | I43: =(1-Inputs!$B$38)*I7+Inputs!$B$38*$B$32*$M7*$M$12 -> 0.0031016595 | J43: =(1-Inputs!$B$38)*J7+Inputs!$B$38*$B$32*$M7*$M$13 -> -0.00020417593 | K43: =(1-Inputs!$B$38)*K7+Inputs!$B$38*$B$32*$M7*$M$14 -> -6.0011145e-05 | L43: =(1-Inputs!$B$38)*L7+Inputs!$B$38*$B$32*$M7*$M$15 -> -8.0693182e-05 | M43: =SQRT(D43) -> 0.1049906
A44: Listed Property | B44: =(1-Inputs!$B$38)*B8+Inputs!$B$38*$B$32*$M8*$M$5 -> 0.0082034018 | C44: =(1-Inputs!$B$38)*C8+Inputs!$B$38*$B$32*$M8*$M$6 -> 0.010304398 | D44: =(1-Inputs!$B$38)*D8+Inputs!$B$38*$B$32*$M8*$M$7 -> 0.0050300231 | E44: =E8 -> 0.028110729 | F44: =(1-Inputs!$B$38)*F8+Inputs!$B$38*$B$32*$M8*$M$9 -> 0.0035948614 | G44: =(1-Inputs!$B$38)*G8+Inputs!$B$38*$B$32*$M8*$M$10 -> 0.001648462 | H44: =(1-Inputs!$B$38)*H8+Inputs!$B$38*$B$32*$M8*$M$11 -> -0.00085158795 | I44: =(1-Inputs!$B$38)*I8+Inputs!$B$38*$B$32*$M8*$M$12 -> 0.005708351 | J44: =(1-Inputs!$B$38)*J8+Inputs!$B$38*$B$32*$M8*$M$13 -> 0.00099428356 | K44: =(1-Inputs!$B$38)*K8+Inputs!$B$38*$B$32*$M8*$M$14 -> 0.00098437353 | L44: =(1-Inputs!$B$38)*L8+Inputs!$B$38*$B$32*$M8*$M$15 -> -0.0001351391 | M44: =SQRT(E44) -> 0.16766255
A45: Commodities | B45: =(1-Inputs!$B$38)*B9+Inputs!$B$38*$B$32*$M9*$M$5 -> 0.007417201 | C45: =(1-Inputs!$B$38)*C9+Inputs!$B$38*$B$32*$M9*$M$6 -> 0.0050216726 | D45: =(1-Inputs!$B$38)*D9+Inputs!$B$38*$B$32*$M9*$M$7 -> 0.0042419457 | E45: =(1-Inputs!$B$38)*E9+Inputs!$B$38*$B$32*$M9*$M$8 -> 0.0035948614 | F45: =F9 -> 0.060457147 | G45: =(1-Inputs!$B$38)*G9+Inputs!$B$38*$B$32*$M9*$M$10 -> 0.003971938 | H45: =(1-Inputs!$B$38)*H9+Inputs!$B$38*$B$32*$M9*$M$11 -> -0.0012948877 | I45: =(1-Inputs!$B$38)*I9+Inputs!$B$38*$B$32*$M9*$M$12 -> 0.0009218478 | J45: =(1-Inputs!$B$38)*J9+Inputs!$B$38*$B$32*$M9*$M$13 -> -0.0031876817 | K45: =(1-Inputs!$B$38)*K9+Inputs!$B$38*$B$32*$M9*$M$14 -> -0.0032125647 | L45: =(1-Inputs!$B$38)*L9+Inputs!$B$38*$B$32*$M9*$M$15 -> -0.0001132026 | M45: =SQRT(F45) -> 0.24588035
A46: Direct Property | B46: =(1-Inputs!$B$38)*B10+Inputs!$B$38*$B$32*$M10*$M$5 -> 0.0025747826 | C46: =(1-Inputs!$B$38)*C10+Inputs!$B$38*$B$32*$M10*$M$6 -> 0.0026664933 | D46: =(1-Inputs!$B$38)*D10+Inputs!$B$38*$B$32*$M10*$M$7 -> 0.0030676732 | E46: =(1-Inputs!$B$38)*E10+Inputs!$B$38*$B$32*$M10*$M$8 -> 0.001648462 | F46: =(1-Inputs!$B$38)*F10+Inputs!$B$38*$B$32*$M10*$M$9 -> 0.003971938 | G46: =G10 -> 0.0090884856 | H46: =(1-Inputs!$B$38)*H10+Inputs!$B$38*$B$32*$M10*$M$11 -> 0.00050752368 | I46: =(1-Inputs!$B$38)*I10+Inputs!$B$38*$B$32*$M10*$M$12 -> 0.0019412087 | J46: =(1-Inputs!$B$38)*J10+Inputs!$B$38*$B$32*$M10*$M$13 -> -0.00058120664 | K46: =(1-Inputs!$B$38)*K10+Inputs!$B$38*$B$32*$M10*$M$14 -> -0.00030070344 | L46: =(1-Inputs!$B$38)*L10+Inputs!$B$38*$B$32*$M10*$M$15 -> -5.2311367e-05 | M46: =SQRT(G46) -> 0.095333549
A47: Hedge Funds | B47: =(1-Inputs!$B$38)*B11+Inputs!$B$38*$B$32*$M11*$M$5 -> -0.00097168636 | C47: =(1-Inputs!$B$38)*C11+Inputs!$B$38*$B$32*$M11*$M$6 -> 0.00015549994 | D47: =(1-Inputs!$B$38)*D11+Inputs!$B$38*$B$32*$M11*$M$7 -> 0.00022602456 | E47: =(1-Inputs!$B$38)*E11+Inputs!$B$38*$B$32*$M11*$M$8 -> -0.00085158795 | F47: =(1-Inputs!$B$38)*F11+Inputs!$B$38*$B$32*$M11*$M$9 -> -0.0012948877 | G47: =(1-Inputs!$B$38)*G11+Inputs!$B$38*$B$32*$M11*$M$10 -> 0.00050752368 | H47: =H11 -> 0.0051752768 | I47: =(1-Inputs!$B$38)*I11+Inputs!$B$38*$B$32*$M11*$M$12 -> -8.6973008e-05 | J47: =(1-Inputs!$B$38)*J11+Inputs!$B$38*$B$32*$M11*$M$13 -> 0.00033693012 | K47: =(1-Inputs!$B$38)*K11+Inputs!$B$38*$B$32*$M11*$M$14 -> 0.00010628647 | L47: =(1-Inputs!$B$38)*L11+Inputs!$B$38*$B$32*$M11*$M$15 -> 9.215266e-05 | M47: =SQRT(H47) -> 0.071939397
A48: Private Equity | B48: =(1-Inputs!$B$38)*B12+Inputs!$B$38*$B$32*$M12*$M$5 -> 0.0075237358 | C48: =(1-Inputs!$B$38)*C12+Inputs!$B$38*$B$32*$M12*$M$6 -> 0.0054234504 | D48: =(1-Inputs!$B$38)*D12+Inputs!$B$38*$B$32*$M12*$M$7 -> 0.0031016595 | E48: =(1-Inputs!$B$38)*E12+Inputs!$B$38*$B$32*$M12*$M$8 -> 0.005708351 | F48: =(1-Inputs!$B$38)*F12+Inputs!$B$38*$B$32*$M12*$M$9 -> 0.0009218478 | G48: =(1-Inputs!$B$38)*G12+Inputs!$B$38*$B$32*$M12*$M$10 -> 0.0019412087 | H48: =(1-Inputs!$B$38)*H12+Inputs!$B$38*$B$32*$M12*$M$11 -> -8.6973008e-05 | I48: =I12 -> 0.01619156 | J48: =(1-Inputs!$B$38)*J12+Inputs!$B$38*$B$32*$M12*$M$13 -> 0.00040436974 | K48: =(1-Inputs!$B$38)*K12+Inputs!$B$38*$B$32*$M12*$M$14 -> 0.00045580044 | L48: =(1-Inputs!$B$38)*L12+Inputs!$B$38*$B$32*$M12*$M$15 -> -4.5947589e-05 | M48: =SQRT(I48) -> 0.12724606
A49: Australian Fixed Income | B49: =(1-Inputs!$B$38)*B13+Inputs!$B$38*$B$32*$M13*$M$5 -> -0.00046316007 | C49: =(1-Inputs!$B$38)*C13+Inputs!$B$38*$B$32*$M13*$M$6 -> 4.8879317e-05 | D49: =(1-Inputs!$B$38)*D13+Inputs!$B$38*$B$32*$M13*$M$7 -> -0.00020417593 | E49: =(1-Inputs!$B$38)*E13+Inputs!$B$38*$B$32*$M13*$M$8 -> 0.00099428356 | F49: =(1-Inputs!$B$38)*F13+Inputs!$B$38*$B$32*$M13*$M$9 -> -0.0031876817 | G49: =(1-Inputs!$B$38)*G13+Inputs!$B$38*$B$32*$M13*$M$10 -> -0.00058120664 | H49: =(1-Inputs!$B$38)*H13+Inputs!$B$38*$B$32*$M13*$M$11 -> 0.00033693012 | I49: =(1-Inputs!$B$38)*I13+Inputs!$B$38*$B$32*$M13*$M$12 -> 0.00040436974 | J49: =J13 -> 0.0018053161 | K49: =(1-Inputs!$B$38)*K13+Inputs!$B$38*$B$32*$M13*$M$14 -> 0.00097215318 | L49: =(1-Inputs!$B$38)*L13+Inputs!$B$38*$B$32*$M13*$M$15 -> 0.00011059713 | M49: =SQRT(J49) -> 0.042489011
A50: World Fixed Income | B50: =(1-Inputs!$B$38)*B14+Inputs!$B$38*$B$32*$M14*$M$5 -> 0.00033345657 | C50: =(1-Inputs!$B$38)*C14+Inputs!$B$38*$B$32*$M14*$M$6 -> -0.00023173941 | D50: =(1-Inputs!$B$38)*D14+Inputs!$B$38*$B$32*$M14*$M$7 -> -6.0011145e-05 | E50: =(1-Inputs!$B$38)*E14+Inputs!$B$38*$B$32*$M14*$M$8 -> 0.00098437353 | F50: =(1-Inputs!$B$38)*F14+Inputs!$B$38*$B$32*$M14*$M$9 -> -0.0032125647 | G50: =(1-Inputs!$B$38)*G14+Inputs!$B$38*$B$32*$M14*$M$10 -> -0.00030070344 | H50: =(1-Inputs!$B$38)*H14+Inputs!$B$38*$B$32*$M14*$M$11 -> 0.00010628647 | I50: =(1-Inputs!$B$38)*I14+Inputs!$B$38*$B$32*$M14*$M$12 -> 0.00045580044 | J50: =(1-Inputs!$B$38)*J14+Inputs!$B$38*$B$32*$M14*$M$13 -> 0.00097215318 | K50: =K14 -> 0.0016427464 | L50: =(1-Inputs!$B$38)*L14+Inputs!$B$38*$B$32*$M14*$M$15 -> 0.00010324317 | M50: =SQRT(K50) -> 0.040530808
A51: Cash | B51: =(1-Inputs!$B$38)*B15+Inputs!$B$38*$B$32*$M15*$M$5 -> -0.00013009718 | C51: =(1-Inputs!$B$38)*C15+Inputs!$B$38*$B$32*$M15*$M$6 -> -0.00017249841 | D51: =(1-Inputs!$B$38)*D15+Inputs!$B$38*$B$32*$M15*$M$7 -> -8.0693182e-05 | E51: =(1-Inputs!$B$38)*E15+Inputs!$B$38*$B$32*$M15*$M$8 -> -0.0001351391 | F51: =(1-Inputs!$B$38)*F15+Inputs!$B$38*$B$32*$M15*$M$9 -> -0.0001132026 | G51: =(1-Inputs!$B$38)*G15+Inputs!$B$38*$B$32*$M15*$M$10 -> -5.2311367e-05 | H51: =(1-Inputs!$B$38)*H15+Inputs!$B$38*$B$32*$M15*$M$11 -> 9.215266e-05 | I51: =(1-Inputs!$B$38)*I15+Inputs!$B$38*$B$32*$M15*$M$12 -> -4.5947589e-05 | J51: =(1-Inputs!$B$38)*J15+Inputs!$B$38*$B$32*$M15*$M$13 -> 0.00011059713 | K51: =(1-Inputs!$B$38)*K15+Inputs!$B$38*$B$32*$M15*$M$14 -> 0.00010324317 | L51: =L15 -> 9.6274886e-05 | M51: =SQRT(L51) -> 0.0098119767
A53: 4. Portfolio metrics
A54: Net forecast return | B54: =Forecast!$G$6 -> 0.077798125 | C54: =Forecast!$G$7 -> 0.077298125 | D54: =Forecast!$G$8 -> 0.070695109 | E54: =Forecast!$G$9 -> 0.079125486 | F54: =Forecast!$G$10 -> 0.069904767 | G54: =Forecast!$G$11 -> 0.044224902 | H54: =Forecast!$G$12 -> 0.037272538 | I54: =Forecast!$G$13 -> 0.051506021 | J54: =Forecast!$G$14 -> 0.050204912 | K54: =Forecast!$G$15 -> 0.053294643 | L54: =Forecast!$G$16 -> 0.047698326
A55: Portfolio | B55: Australian Equities | C55: World Equities | D55: Emerging Markets | E55: Listed Property | F55: Commodities | G55: Direct Property | H55: Hedge Funds | I55: Private Equity | J55: Australian Fixed Income | K55: World Fixed Income | L55: Cash | M55: Volatility | N55: Expected return (arithmetic) | O55: Tracking error | P55: Max weight gap vs recommended
A56: Current fund | B56: =Inputs!$B$5 -> 0.4 | C56: =Inputs!$B$6 -> 0.2 | D56: =Inputs!$B$7 -> 0 | E56: =Inputs!$B$8 -> 0.1 | F56: =Inputs!$B$9 -> 0 | G56: =Inputs!$B$10 -> 0 | H56: =Inputs!$B$11 -> 0 | I56: =Inputs!$B$12 -> 0 | J56: =Inputs!$B$13 -> 0.15 | K56: =Inputs!$B$14 -> 0.08 | L56: =Inputs!$B$15 -> 0.07 | M56: =SQRT(SUMPRODUCT(MMULT(B56:L56,$B$41:$L$51),B56:L56)) -> 0.083833964 | N56: =SUMPRODUCT($B$54:$L$54,B56:L56) -> 0.069624615 | O56: =SQRT(SUMPRODUCT(MMULT(B67:L67,$B$41:$L$51),B67:L67)) -> 0.021585026
A57: Benchmark | B57: =Inputs!$C$5 -> 0.25 | C57: =Inputs!$C$6 -> 0.24 | D57: =Inputs!$C$7 -> 0.03 | E57: =Inputs!$C$8 -> 0.07 | F57: =Inputs!$C$9 -> 0.02 | G57: =Inputs!$C$10 -> 0.05 | H57: =Inputs!$C$11 -> 0.03 | I57: =Inputs!$C$12 -> 0.03 | J57: =Inputs!$C$13 -> 0.14 | K57: =Inputs!$C$14 -> 0.11 | L57: =Inputs!$C$15 -> 0.03 | M57: =SQRT(SUMPRODUCT(MMULT(B57:L57,$B$41:$L$51),B57:L57)) -> 0.070134112 | N57: =SUMPRODUCT($B$54:$L$54,B57:L57) -> 0.066255464 | O57: 0
A58: Recommended | B58: =Portfolio!$E$6 -> 0.2738 | C58: =Portfolio!$E$7 -> 0.279 | D58: =Portfolio!$E$8 -> 0.0672 | E58: =Portfolio!$E$9 -> 0.0867 | F58: =Portfolio!$E$10 -> 0.0244 | G58: =Portfolio!$E$11 -> 0 | H58: =Portfolio!$E$12 -> 0 | I58: =Portfolio!$E$13 -> 0 | J58: =Portfolio!$E$14 -> 0.12 | K58: =Portfolio!$E$15 -> 0.1289 | L58: =Portfolio!$E$16 -> 0.02 | M58: =SQRT(SUMPRODUCT(MMULT(B58:L58,$B$41:$L$51),B58:L58)) -> 0.078389128 | N58: =SUMPRODUCT($B$54:$L$54,B58:L58) -> 0.070032106 | O58: =SQRT(SUMPRODUCT(MMULT(B68:L68,$B$41:$L$51),B68:L68)) -> 0.011002382
A59: Naive MVO | B59: =Validation!$B$30 -> 0.2149 | C59: =Validation!$B$31 -> 0.35 | D59: =Validation!$B$32 -> 0.0551 | E59: =Validation!$B$33 -> 0.0372 | F59: =Validation!$B$34 -> 0.03 | G59: =Validation!$B$35 -> 0.05 | H59: =Validation!$B$36 -> 0 | I59: =Validation!$B$37 -> 0.01 | J59: =Validation!$B$38 -> 0.05 | K59: =Validation!$B$39 -> 0.1828 | L59: =Validation!$B$40 -> 0.02 | M59: =SQRT(SUMPRODUCT(MMULT(B59:L59,$B$41:$L$51),B59:L59)) -> 0.075341501 | N59: =SUMPRODUCT($B$54:$L$54,B59:L59) -> 0.068641851 | O59: =SQRT(SUMPRODUCT(MMULT(B69:L69,$B$41:$L$51),B69:L69)) -> 0.013477683 | P59: =MAX(ABS(B59-$B$58),ABS(C59-$C$58),ABS(D59-$D$58),ABS(E59-$E$58),ABS(F59-$F$58),ABS(G59-$G$58),ABS(H59-$H$58),ABS(I59-$I$58),ABS(J59-$J$58),ABS(K59-$K$58),ABS(L59-$L$58)) -> 0.071
A60: Unshrunk covariance | B60: =Validation!$C$30 -> 0.2732 | C60: =Validation!$C$31 -> 0.2879 | D60: =Validation!$C$32 -> 0.0589 | E60: =Validation!$C$33 -> 0.08 | F60: =Validation!$C$34 -> 0.0243 | G60: =Validation!$C$35 -> 0 | H60: =Validation!$C$36 -> 0 | I60: =Validation!$C$37 -> 0 | J60: =Validation!$C$38 -> 0.12 | K60: =Validation!$C$39 -> 0.1357 | L60: =Validation!$C$40 -> 0.02 | M60: =SQRT(SUMPRODUCT(MMULT(B60:L60,$B$41:$L$51),B60:L60)) -> 0.078033813 | N60: =SUMPRODUCT($B$54:$L$54,B60:L60) -> 0.069911884 | O60: =SQRT(SUMPRODUCT(MMULT(B70:L70,$B$41:$L$51),B70:L70)) -> 0.010637134 | P60: =MAX(ABS(B60-$B$58),ABS(C60-$C$58),ABS(D60-$D$58),ABS(E60-$E$58),ABS(F60-$F$58),ABS(G60-$G$58),ABS(H60-$H$58),ABS(I60-$I$58),ABS(J60-$J$58),ABS(K60-$K$58),ABS(L60-$L$58)) -> 0.0089
A61: Tight TE (0.75%) | B61: =Validation!$D$30 -> 0.2638 | C61: =Validation!$D$31 -> 0.2667 | D61: =Validation!$D$32 -> 0.0569 | E61: =Validation!$D$33 -> 0.078 | F61: =Validation!$D$34 -> 0.0237 | G61: =Validation!$D$35 -> 0.0128 | H61: =Validation!$D$36 -> 0 | I61: =Validation!$D$37 -> 0.0097 | J61: =Validation!$D$38 -> 0.12 | K61: =Validation!$D$39 -> 0.1484 | L61: =Validation!$D$40 -> 0.02 | M61: =SQRT(SUMPRODUCT(MMULT(B61:L61,$B$41:$L$51),B61:L61)) -> 0.075244545 | N61: =SUMPRODUCT($B$54:$L$54,B61:L61) -> 0.068942806 | O61: =SQRT(SUMPRODUCT(MMULT(B71:L71,$B$41:$L$51),B71:L71)) -> 0.0074991601 | P61: =MAX(ABS(B61-$B$58),ABS(C61-$C$58),ABS(D61-$D$58),ABS(E61-$E$58),ABS(F61-$F$58),ABS(G61-$G$58),ABS(H61-$H$58),ABS(I61-$I$58),ABS(J61-$J$58),ABS(K61-$K$58),ABS(L61-$L$58)) -> 0.0195
A62: Loose TE (1.5%) | B62: =Validation!$E$30 -> 0.2803 | C62: =Validation!$E$31 -> 0.2809 | D62: =Validation!$E$32 -> 0.0588 | E62: =Validation!$E$33 -> 0.1165 | F62: =Validation!$E$34 -> 0.0292 | G62: =Validation!$E$35 -> 0 | H62: =Validation!$E$36 -> 0 | I62: =Validation!$E$37 -> 0 | J62: =Validation!$E$38 -> 0.12 | K62: =Validation!$E$39 -> 0.0943 | L62: =Validation!$E$40 -> 0.02 | M62: =SQRT(SUMPRODUCT(MMULT(B62:L62,$B$41:$L$51),B62:L62)) -> 0.082238715 | N62: =SUMPRODUCT($B$54:$L$54,B62:L62) -> 0.070940309 | O62: =SQRT(SUMPRODUCT(MMULT(B72:L72,$B$41:$L$51),B72:L72)) -> 0.015003647 | P62: =MAX(ABS(B62-$B$58),ABS(C62-$C$58),ABS(D62-$D$58),ABS(E62-$E$58),ABS(F62-$F$58),ABS(G62-$G$58),ABS(H62-$H$58),ABS(I62-$I$58),ABS(J62-$J$58),ABS(K62-$K$58),ABS(L62-$L$58)) -> 0.0346
A63: OOS robust, fit 2006-16 | B63: =Validation!$B$17 -> 0.2744 | C63: =Validation!$B$18 -> 0.2734 | D63: =Validation!$B$19 -> 0.0603 | E63: =Validation!$B$20 -> 0.0846 | F63: =Validation!$B$21 -> 0.03 | G63: =Validation!$B$22 -> 0.05 | H63: =Validation!$B$23 -> 0 | I63: =Validation!$B$24 -> 0.01 | J63: =Validation!$B$25 -> 0.1473 | K63: =Validation!$B$26 -> 0.05 | L63: =Validation!$B$27 -> 0.02 | M63: =SQRT(SUMPRODUCT(MMULT(B63:L63,$B$41:$L$51),B63:L63)) -> 0.079226287 | N63: =SUMPRODUCT($B$54:$L$54,B63:L63) -> 0.069275375
A64: OOS naive, fit 2006-16 | B64: =Validation!$C$17 -> 0.2332 | C64: =Validation!$C$18 -> 0.15 | D64: =Validation!$C$19 -> 0.0516 | E64: =Validation!$C$20 -> 0.0927 | F64: =Validation!$C$21 -> 0.03 | G64: =Validation!$C$22 -> 0.05 | H64: =Validation!$C$23 -> 0 | I64: =Validation!$C$24 -> 0.01 | J64: =Validation!$C$25 -> 0.1625 | K64: =Validation!$C$26 -> 0.2 | L64: =Validation!$C$27 -> 0.02 | M64: =SQRT(SUMPRODUCT(MMULT(B64:L64,$B$41:$L$51),B64:L64)) -> 0.063216364 | N64: =SUMPRODUCT($B$54:$L$54,B64:L64) -> 0.065314683
A66: Active weights vs benchmark
A67: Current fund | B67: =B56-B$57 -> 0.15 | C67: =C56-C$57 -> -0.04 | D67: =D56-D$57 -> -0.03 | E67: =E56-E$57 -> 0.03 | F67: =F56-F$57 -> -0.02 | G67: =G56-G$57 -> -0.05 | H67: =H56-H$57 -> -0.03 | I67: =I56-I$57 -> -0.03 | ... L67: =L56-L$57 -> 0.04
A68: Recommended | B68: =B58-B$57 -> 0.0238 | C68: =C58-C$57 -> 0.039 | D68: =D58-D$57 -> 0.0372 | E68: =E58-E$57 -> 0.0167 | F68: =F58-F$57 -> 0.0044 | G68: =G58-G$57 -> -0.05 | H68: =H58-H$57 -> -0.03 | I68: =I58-I$57 -> -0.03 | ... L68: =L58-L$57 -> -0.01
A69: Naive MVO | B69: =B59-B$57 -> -0.0351 | C69: =C59-C$57 -> 0.11 | D69: =D59-D$57 -> 0.0251 | E69: =E59-E$57 -> -0.0328 | F69: =F59-F$57 -> 0.01 | G69: =G59-G$57 -> 0 | H69: =H59-H$57 -> -0.03 | I69: =I59-I$57 -> -0.02 | ... L69: =L59-L$57 -> -0.01
A70: Unshrunk covariance | B70: =B60-B$57 -> 0.0232 | C70: =C60-C$57 -> 0.0479 | D70: =D60-D$57 -> 0.0289 | E70: =E60-E$57 -> 0.01 | F70: =F60-F$57 -> 0.0043 | G70: =G60-G$57 -> -0.05 | H70: =H60-H$57 -> -0.03 | I70: =I60-I$57 -> -0.03 | ... L70: =L60-L$57 -> -0.01
A71: Tight TE | B71: =B61-B$57 -> 0.0138 | C71: =C61-C$57 -> 0.0267 | D71: =D61-D$57 -> 0.0269 | E71: =E61-E$57 -> 0.008 | F71: =F61-F$57 -> 0.0037 | G71: =G61-G$57 -> -0.0372 | H71: =H61-H$57 -> -0.03 | I71: =I61-I$57 -> -0.0203 | ... L71: =L61-L$57 -> -0.01
A72: Loose TE | B72: =B62-B$57 -> 0.0303 | C72: =C62-C$57 -> 0.0409 | D72: =D62-D$57 -> 0.0288 | E72: =E62-E$57 -> 0.0465 | F72: =F62-F$57 -> 0.0092 | G72: =G62-G$57 -> -0.05 | H72: =H62-H$57 -> -0.03 | I72: =I62-I$57 -> -0.03 | ... L72: =L62-L$57 -> -0.01

Sheet Portfolio
A1: Portfolio
A3: 1. Stage 1 (optimised) and Stage 2 (judgement)
A5: Asset class | B5: Stage | C5: Current | D5: Benchmark | E5: Recommended | F5: Lower | G5: Upper | H5: Active vs benchmark | I5: Change vs current | J5: Trade (A$m) | K5: Net forecast (arithmetic) | L5: Return contribution
A6: Australian Equities | B6: 1: optimised | C6: =Inputs!B5 -> 0.4 | D6: =Inputs!C5 -> 0.25 | E6: =Methods!I6 -> 0.2738 | F6: =Inputs!E5 -> 0.15 | G6: =Inputs!F5 -> 0.35 | H6: =E6-D6 -> 0.0238 | I6: =E6-C6 -> -0.1262 | J6: =I6*Inputs!$B$22 -> -378.6 | K6: =Forecast!G6 -> 0.077798125 | L6: =E6*K6 -> 0.021301127
A7: World Equities | B7: 1: optimised | C7: =Inputs!B6 -> 0.2 | D7: =Inputs!C6 -> 0.24 | E7: =Methods!I7 -> 0.279 | F7: =Inputs!E6 -> 0.15 | G7: =Inputs!F6 -> 0.35 | H7: =E7-D7 -> 0.039 | I7: =E7-C7 -> 0.079 | J7: =I7*Inputs!$B$22 -> 237 | K7: =Forecast!G7 -> 0.077298125 | L7: =E7*K7 -> 0.021566177
A8: Emerging Markets | B8: 1: optimised | C8: =Inputs!B7 -> 0 | D8: =Inputs!C7 -> 0.03 | E8: =Methods!I8 -> 0.0672 | F8: =Inputs!E7 -> 0 | G8: =Inputs!F7 -> 0.08 | H8: =E8-D8 -> 0.0372 | I8: =E8-C8 -> 0.0672 | J8: =I8*Inputs!$B$22 -> 201.6 | K8: =Forecast!G8 -> 0.070695109 | L8: =E8*K8 -> 0.0047507113
A9: Listed Property | B9: 1: optimised | C9: =Inputs!B8 -> 0.1 | D9: =Inputs!C8 -> 0.07 | E9: =Methods!I9 -> 0.0867 | F9: =Inputs!E8 -> 0 | G9: =Inputs!F8 -> 0.12 | H9: =E9-D9 -> 0.0167 | I9: =E9-C9 -> -0.0133 | J9: =I9*Inputs!$B$22 -> -39.9 | K9: =Forecast!G9 -> 0.079125486 | L9: =E9*K9 -> 0.0068601796
A10: Commodities | B10: 2: optimised | C10: =Inputs!B9 -> 0 | D10: =Inputs!C9 -> 0.02 | E10: =Methods!I10 -> 0.0244 | F10: =Inputs!E9 -> 0 | G10: =Inputs!F9 -> 0.08 | H10: =E10-D10 -> 0.0044 | I10: =E10-C10 -> 0.0244 | J10: =I10*Inputs!$B$22 -> 73.2 | K10: =Forecast!G10 -> 0.069904767 | L10: =E10*K10 -> 0.0017056763
A11: Direct Property | B11: 2: optimised | C11: =Inputs!B10 -> 0 | D11: =Inputs!C10 -> 0.05 | E11: =Methods!I11 -> 0 | F11: =Inputs!E10 -> 0 | G11: =Inputs!F10 -> 0.1 | H11: =E11-D11 -> -0.05 | I11: =E11-C11 -> 0 | J11: =I11*Inputs!$B$22 -> 0 | K11: =Forecast!G11 -> 0.044224902 | L11: =E11*K11 -> 0
A12: Hedge Funds | B12: 2: optimised | C12: =Inputs!B11 -> 0 | D12: =Inputs!C11 -> 0.03 | E12: =Methods!I12 -> 0 | F12: =Inputs!E11 -> 0 | G12: =Inputs!F11 -> 0.08 | H12: =E12-D12 -> -0.03 | I12: =E12-C12 -> 0 | J12: =I12*Inputs!$B$22 -> 0 | K12: =Forecast!G12 -> 0.037272538 | L12: =E12*K12 -> 0
A13: Private Equity | B13: 2: optimised | C13: =Inputs!B12 -> 0 | D13: =Inputs!C12 -> 0.03 | E13: =Methods!I13 -> 0 | F13: =Inputs!E12 -> 0 | G13: =Inputs!F12 -> 0.08 | H13: =E13-D13 -> -0.03 | I13: =E13-C13 -> 0 | J13: =I13*Inputs!$B$22 -> 0 | K13: =Forecast!G13 -> 0.051506021 | L13: =E13*K13 -> 0
A14: Australian Fixed Income | B14: 1: optimised | C14: =Inputs!B13 -> 0.15 | D14: =Inputs!C13 -> 0.14 | E14: =Methods!I14 -> 0.12 | F14: =Inputs!E13 -> 0.12 | G14: =Inputs!F13 -> 0.25 | H14: =E14-D14 -> -0.02 | I14: =E14-C14 -> -0.03 | J14: =I14*Inputs!$B$22 -> -90 | K14: =Forecast!G14 -> 0.050204912 | L14: =E14*K14 -> 0.0060245894
A15: World Fixed Income | B15: 1: optimised | C15: =Inputs!B14 -> 0.08 | D15: =Inputs!C14 -> 0.11 | E15: =Methods!I15 -> 0.1289 | F15: =Inputs!E14 -> 0.05 | G15: =Inputs!F14 -> 0.2 | H15: =E15-D15 -> 0.0189 | I15: =E15-C15 -> 0.0489 | J15: =I15*Inputs!$B$22 -> 146.7 | K15: =Forecast!G15 -> 0.053294643 | L15: =E15*K15 -> 0.0068696795
A16: Cash | B16: 1: optimised | C16: =Inputs!B15 -> 0.07 | D16: =Inputs!C15 -> 0.03 | E16: =Methods!I16 -> 0.02 | F16: =Inputs!E15 -> 0.02 | G16: =Inputs!F15 -> 0.1 | H16: =E16-D16 -> -0.01 | I16: =E16-C16 -> -0.05 | J16: =I16*Inputs!$B$22 -> -150 | K16: =Forecast!G16 -> 0.047698326 | L16: =E16*K16 -> 0.00095396652
A17: Total | C17: =SUM(C6:C16) -> 1 | D17: =SUM(D6:D16) -> 1 | E17: =SUM(E6:E16) -> 1 | H17: =SUM(H6:H16) -> 0 | I17: =SUM(I6:I16) -> 0 | J17: =SUM(J6:J16) -> 0 | L17: =SUM(L6:L16) -> 0.070032106
A20: 2. Stage 2 scorecard (1 to 5): cross-check on the optimised alternatives weights
A22: Asset class | B22: Return | C22: Diversification | D22: Liquidity | E22: Data quality | F22: Implementation | G22: Average | H22: Optimised weight | I22: Benchmark
A23: Commodities | B23: 3 | C23: 5 | D23: 5 | E23: 3 | F23: 4 | G23: =AVERAGE(B23:F23) -> 4 | H23: =E10 -> 0.0244 | I23: =Inputs!C9 -> 0.02
A24: Direct Property | B24: 3 | C24: 4 | D24: 1 | E24: 2 | F24: 2 | G24: =AVERAGE(B24:F24) -> 2.4 | H24: =E11 -> 0 | I24: =Inputs!C10 -> 0.05
A25: Hedge Funds | B25: 2 | C25: 3 | D25: 2 | E25: 2 | F25: 2 | G25: =AVERAGE(B25:F25) -> 2.2 | H25: =E12 -> 0 | I25: =Inputs!C11 -> 0.03
A26: Private Equity | B26: 4 | C26: 3 | D26: 1 | E26: 2 | F26: 2 | G26: =AVERAGE(B26:F26) -> 2.4 | H26: =E13 -> 0 | I26: =Inputs!C12 -> 0.03
A27: Total Stage 2 | H27: =SUM(H23:H26) -> 0.0244 | I27: =SUM(I23:I26) -> 0.13
A30: 3. Solver constraints
A31: Metric | B31: Value | C31: Lower limit | D31: Upper limit | E31: Status
A32: Expected return, arithmetic (maximise) | B32: =SUMPRODUCT(E6:E16,K6:K16) -> 0.070032106 | E32: ="INFO" -> INFO
A33: Tracking error (parametric) | B33: =Risk!O58 -> 0.011002382 | D33: =Inputs!$B$45 -> 0.011 | E33: =IF(B33<=D33+0.00005,"MET","NOT MET") -> MET
A34: Equity allocation | B34: =SUMPRODUCT(E6:E16,Inputs!$G$5:$G$15) -> 0.62 | C34: =Inputs!$B$31 -> 0.42 | D34: =Inputs!$B$32 -> 0.62 | E34: =IF(AND(B34>=C34-0.000001,B34<=D34+0.000001),"MET","NOT MET") -> MET
A35: Illiquid allocation | B35: =SUMPRODUCT(E6:E16,Inputs!$H$5:$H$15) -> 0 | D35: =Inputs!$B$33 -> 0.3 | E35: =IF(B35<=D35,"MET","NOT MET") -> MET
A36: Cash allocation | B36: =E16 -> 0.02 | C36: =Inputs!$B$34 -> 0.02 | E36: =IF(B36>=C36,"MET","NOT MET") -> MET
A37: Weights sum to 100% | B37: =SUM(E6:E16) -> 1 | C37: 1 | D37: 1 | E37: =IF(ABS(B37-1)<0.000001,"MET","NOT MET") -> MET
A38: Share inside bounds | B38: =SUMPRODUCT((E6:E16>=F6:F16-0.000001)*(E6:E16<=G6:G16+0.000001))/11 -> 1 | C38: 1 | E38: =IF(B38>=C38,"MET","NOT MET") -> MET
A41: 4. What each constraint costs
A42: Asset class | B42: Base (recommended) | C42: TE limit 1.5% | D42: No TE limit | E42: Equity max 72% | F42: Alternatives fixed by scorecard | G42: Long-only only
A43: Australian Equities | B43: =E6 -> 0.2738 | C43: 0.2803 | D43: 0.35 | E43: 0.274 | F43: 0.2722 | G43: 0
A44: World Equities | B44: =E7 -> 0.279 | C44: 0.2809 | D44: 0.27 | E44: 0.2798 | F44: 0.2749 | G44: 0
A45: Emerging Markets | B45: =E8 -> 0.0672 | C45: 0.0588 | D45: 0 | E45: 0.0685 | F45: 0.0547 | G45: 0
A46: Listed Property | B46: =E9 -> 0.0867 | C46: 0.1165 | D46: 0.12 | E46: 0.0852 | F46: 0.09 | G46: 0.98
A47: Commodities | B47: =E10 -> 0.0244 | C47: 0.0292 | D47: 0.07 | E47: 0.024 | F47: 0.03 | G47: 0
A48: Direct Property | B48: =E11 -> 0 | C48: 0 | D48: 0 | E48: 0 | F48: 0.05 | G48: 0
A49: Hedge Funds | B49: =E12 -> 0 | C49: 0 | D49: 0 | E49: 0 | F49: 0 | G49: 0
A50: Private Equity | B50: =E13 -> 0 | C50: 0 | D50: 0 | E50: 0 | F50: 0.01 | G50: 0
A51: Australian Fixed Income | B51: =E14 -> 0.12 | C51: 0.12 | D51: 0.12 | E51: 0.12 | F51: 0.12 | G51: 0
A52: World Fixed Income | B52: =E15 -> 0.1289 | C52: 0.0943 | D52: 0.05 | E52: 0.1285 | F52: 0.0782 | G52: 0
A53: Cash | B53: =E16 -> 0.02 | C53: 0.02 | D53: 0.02 | E53: 0.02 | F53: 0.02 | G53: 0.02
A55: Expected return (arithmetic) | B55: =SUMPRODUCT(B43:B53,Forecast!$G$6:$G$16) -> 0.070032106 | C55: =SUMPRODUCT(C43:C53,Forecast!$G$6:$G$16) -> 0.070940309 | D55: =SUMPRODUCT(D43:D53,Forecast!$G$6:$G$16) -> 0.072131518 | E55: =SUMPRODUCT(E43:E53,Forecast!$G$6:$G$16) -> 0.07003344 | F55: =SUMPRODUCT(F43:F53,Forecast!$G$6:$G$16) -> 0.069383866 | G55: =SUMPRODUCT(G43:G53,Forecast!$G$6:$G$16) -> 0.078496943
A56: Volatility | B56: =SQRT(SUMPRODUCT(B43:B53,MMULT(Risk!$B$41:$L$51,B43:B53))) -> 0.078389128 | C56: =SQRT(SUMPRODUCT(C43:C53,MMULT(Risk!$B$41:$L$51,C43:C53))) -> 0.082238715 | D56: =SQRT(SUMPRODUCT(D43:D53,MMULT(Risk!$B$41:$L$51,D43:D53))) -> 0.090059124 | E56: =SQRT(SUMPRODUCT(E43:E53,MMULT(Risk!$B$41:$L$51,E43:E53))) -> 0.07839348 | F56: =SQRT(SUMPRODUCT(F43:F53,MMULT(Risk!$B$41:$L$51,F43:F53))) -> 0.079350014 | G56: =SQRT(SUMPRODUCT(G43:G53,MMULT(Risk!$B$41:$L$51,G43:G53))) -> 0.16429329
A57: Tracking error | B57: =SQRT(SUMPRODUCT(B43:B53-Inputs!$C$5:$C$15,MMULT(Risk!$B$41:$L$51,B43:B53-Inputs!$C$5:$C$15))) -> 0.011002382 | C57: =SQRT(SUMPRODUCT(C43:C53-Inputs!$C$5:$C$15,MMULT(Risk!$B$41:$L$51,C43:C53-Inputs!$C$5:$C$15))) -> 0.015003647 | D57: =SQRT(SUMPRODUCT(D43:D53-Inputs!$C$5:$C$15,MMULT(Risk!$B$41:$L$51,D43:D53-Inputs!$C$5:$C$15))) -> 0.025147636 | E57: =SQRT(SUMPRODUCT(E43:E53-Inputs!$C$5:$C$15,MMULT(Risk!$B$41:$L$51,E43:E53-Inputs!$C$5:$C$15))) -> 0.011003982 | F57: =SQRT(SUMPRODUCT(F43:F53-Inputs!$C$5:$C$15,MMULT(Risk!$B$41:$L$51,F43:F53-Inputs!$C$5:$C$15))) -> 0.010998745 | G57: =SQRT(SUMPRODUCT(G43:G53-Inputs!$C$5:$C$15,MMULT(Risk!$B$41:$L$51,G43:G53-Inputs!$C$5:$C$15))) -> 0.13352486
A58: Return gain vs base | B58: =B55-$B$55 -> 0 | C58: =C55-$B$55 -> 0.00090820305 | D58: =D55-$B$55 -> 0.0020994114 | E58: =E55-$B$55 -> 1.3337743e-06 | F58: =F55-$B$55 -> -0.00064824049 | G58: =G55-$B$55 -> 0.0084648364
A59: Reaches return target? (compound) | B59: =IF(B55-B56^2/2>=Inputs!$B$25,"YES","NO") -> NO | C59: =IF(C55-C56^2/2>=Inputs!$B$25,"YES","NO") -> NO | D59: =IF(D55-D56^2/2>=Inputs!$B$25,"YES","NO") -> NO | E59: =IF(E55-E56^2/2>=Inputs!$B$25,"YES","NO") -> NO | F59: =IF(F55-F56^2/2>=Inputs!$B$25,"YES","NO") -> NO | G59: =IF(G55-G56^2/2>=Inputs!$B$25,"YES","NO") -> NO
A62: 5. Transition costs (A$m; one-way costs from Inputs section 4)
A63: Asset class | B63: Trade (A$m) | C63: Cost rate | D63: Cost (A$m)
A64: Australian Equities | B64: =J6 -> -378.6 | C64: =Inputs!B54 -> 0.001 | D64: =ABS(B64)*C64 -> 0.3786
A65: World Equities | B65: =J7 -> 237 | C65: =Inputs!B55 -> 0.001 | D65: =ABS(B65)*C65 -> 0.237
A66: Emerging Markets | B66: =J8 -> 201.6 | C66: =Inputs!B56 -> 0.0025 | D66: =ABS(B66)*C66 -> 0.504
A67: Listed Property | B67: =J9 -> -39.9 | C67: =Inputs!B57 -> 0.002 | D67: =ABS(B67)*C67 -> 0.0798
A68: Commodities | B68: =J10 -> 73.2 | C68: =Inputs!B58 -> 0.001 | D68: =ABS(B68)*C68 -> 0.0732
A69: Direct Property | B69: =J11 -> 0 | C69: =Inputs!B59 -> 0.015 | D69: =ABS(B69)*C69 -> 0
A70: Hedge Funds | B70: =J12 -> 0 | C70: =Inputs!B60 -> 0.005 | D70: =ABS(B70)*C70 -> 0
A71: Private Equity | B71: =J13 -> 0 | C71: =Inputs!B61 -> 0.01 | D71: =ABS(B71)*C71 -> 0
A72: Australian Fixed Income | B72: =J14 -> -90 | C72: =Inputs!B62 -> 0.001 | D72: =ABS(B72)*C72 -> 0.09
A73: World Fixed Income | B73: =J15 -> 146.7 | C73: =Inputs!B63 -> 0.0015 | D73: =ABS(B73)*C73 -> 0.22005
A74: Cash | B74: =J16 -> -150 | C74: =Inputs!B64 -> 0 | D74: =ABS(B74)*C74 -> 0
A75: Total | B75: =SUMPRODUCT(ABS(B64:B74))/2 -> 658.5 | D75: =SUM(D64:D74) -> 1.58265
A76: Cost as % of fund | D76: =D75/Inputs!$B$22 -> 0.00052755
A77: Amortised cost per year | D77: =D76/Inputs!$B$69 -> 0.00010551
A78: Expected compound return advantage vs current (p.a.) | D78: =(Risk!$N$58-Risk!$M$58^2/2)-(Risk!$N$56-Risk!$M$56^2/2) -> 0.00084913061
A79: Advantage after amortised transition costs | D79: =D78-D77 -> 0.00074362061
A80: Status | D80: =IF(D79>=0,"PASS","REVIEW") -> PASS
A83: 6. Transition plan: liquid assets move now; direct property and private equity are built over 1 to 3 years (undrawn amounts parked in liquid proxies)
A84: Asset class | B84: Current | C84: Phase 1: liquid rebalance | D84: End of year 1 | E84: End of year 2 | F84: End of year 3 (target)
A85: Australian Equities | B85: =C6 -> 0.4 | C85: =$E6 -> 0.2738 | D85: =$E6 -> 0.2738 | E85: =$E6 -> 0.2738 | F85: =$E6 -> 0.2738
A86: World Equities | B86: =C7 -> 0.2 | C86: =$E7 -> 0.279 | D86: =$E7 -> 0.279 | E86: =$E7 -> 0.279 | F86: =$E7 -> 0.279
A87: Emerging Markets | B87: =C8 -> 0 | C87: =$E8 -> 0.0672 | D87: =$E8 -> 0.0672 | E87: =$E8 -> 0.0672 | F87: =$E8 -> 0.0672
A88: Listed Property | B88: =C9 -> 0.1 | C88: =$E9+$E$11*(1-0)*Inputs!$B$75 -> 0.0867 | D88: =$E9+$E$11*(1-Inputs!$B$70)*Inputs!$B$75 -> 0.0867 | E88: =$E9+$E$11*(1-Inputs!$B$71)*Inputs!$B$75 -> 0.0867 | F88: =$E9+$E$11*(1-1)*Inputs!$B$75 -> 0.0867
A89: Commodities | B89: =C10 -> 0 | C89: =$E10 -> 0.0244 | D89: =$E10 -> 0.0244 | E89: =$E10 -> 0.0244 | F89: =$E10 -> 0.0244
A90: Direct Property | B90: =C11 -> 0 | C90: =$E11*0 -> 0 | D90: =$E11*Inputs!$B$70 -> 0 | E90: =$E11*Inputs!$B$71 -> 0 | F90: =$E11*1 -> 0
A91: Hedge Funds | B91: =C12 -> 0 | C91: =$E12 -> 0 | D91: =$E12 -> 0 | E91: =$E12 -> 0 | F91: =$E12 -> 0
A92: Private Equity | B92: =C13 -> 0 | C92: =$E13*0 -> 0 | D92: =$E13*Inputs!$B$72 -> 0 | E92: =$E13*Inputs!$B$73 -> 0 | F92: =$E13*Inputs!$B$74 -> 0
A93: Australian Fixed Income | B93: =C14 -> 0.15 | C93: =$E14+$E$11*(1-0)*(1-Inputs!$B$75) -> 0.12 | D93: =$E14+$E$11*(1-Inputs!$B$70)*(1-Inputs!$B$75) -> 0.12 | E93: =$E14+$E$11*(1-Inputs!$B$71)*(1-Inputs!$B$75) -> 0.12 | F93: =$E14+$E$11*(1-1)*(1-Inputs!$B$75) -> 0.12
A94: World Fixed Income | B94: =C15 -> 0.08 | C94: =$E15 -> 0.1289 | D94: =$E15 -> 0.1289 | E94: =$E15 -> 0.1289 | F94: =$E15 -> 0.1289
A95: Cash | B95: =C16 -> 0.07 | C95: =$E16+$E$13*(1-0) -> 0.02 | D95: =$E16+$E$13*(1-Inputs!$B$72) -> 0.02 | E95: =$E16+$E$13*(1-Inputs!$B$73) -> 0.02 | F95: =$E16+$E$13*(1-Inputs!$B$74) -> 0.02
A96: Total | B96: =SUM(B85:B95) -> 1 | C96: =SUM(C85:C95) -> 1 | D96: =SUM(D85:D95) -> 1 | E96: =SUM(E85:E95) -> 1 | F96: =SUM(F85:F95) -> 1
A97: Expected return (net) | B97: =SUMPRODUCT(MMULT(Risk!$B$54:$L$54,B$85:B$95)) -> 0.069624615 | C97: =SUMPRODUCT(MMULT(Risk!$B$54:$L$54,C$85:C$95)) -> 0.070032106 | D97: =SUMPRODUCT(MMULT(Risk!$B$54:$L$54,D$85:D$95)) -> 0.070032106 | E97: =SUMPRODUCT(MMULT(Risk!$B$54:$L$54,E$85:E$95)) -> 0.070032106 | F97: =SUMPRODUCT(MMULT(Risk!$B$54:$L$54,F$85:F$95)) -> 0.070032106
A98: Volatility | B98: =SQRT(SUMPRODUCT(MMULT(Risk!$B$41:$L$51,B$85:B$95),B$85:B$95)) -> 0.083833964 | C98: =SQRT(SUMPRODUCT(MMULT(Risk!$B$41:$L$51,C$85:C$95),C$85:C$95)) -> 0.078389128 | D98: =SQRT(SUMPRODUCT(MMULT(Risk!$B$41:$L$51,D$85:D$95),D$85:D$95)) -> 0.078389128 | E98: =SQRT(SUMPRODUCT(MMULT(Risk!$B$41:$L$51,E$85:E$95),E$85:E$95)) -> 0.078389128 | F98: =SQRT(SUMPRODUCT(MMULT(Risk!$B$41:$L$51,F$85:F$95),F$85:F$95)) -> 0.078389128
A99: Tracking error | B99: =SQRT(SUMPRODUCT(MMULT(Risk!$B$41:$L$51,B$85:B$95-Portfolio!$D$6:$D$16),B$85:B$95-Portfolio!$D$6:$D$16)) -> 0.021585026 | C99: =SQRT(SUMPRODUCT(MMULT(Risk!$B$41:$L$51,C$85:C$95-Portfolio!$D$6:$D$16),C$85:C$95-Portfolio!$D$6:$D$16)) -> 0.011002382 | D99: =SQRT(SUMPRODUCT(MMULT(Risk!$B$41:$L$51,D$85:D$95-Portfolio!$D$6:$D$16),D$85:D$95-Portfolio!$D$6:$D$16)) -> 0.011002382 | E99: =SQRT(SUMPRODUCT(MMULT(Risk!$B$41:$L$51,E$85:E$95-Portfolio!$D$6:$D$16),E$85:E$95-Portfolio!$D$6:$D$16)) -> 0.011002382 | F99: =SQRT(SUMPRODUCT(MMULT(Risk!$B$41:$L$51,F$85:F$95-Portfolio!$D$6:$D$16),F$85:F$95-Portfolio!$D$6:$D$16)) -> 0.011002382
A100: Equity weight | B100: =SUMPRODUCT(B85:B95,Inputs!$G$5:$G$15) -> 0.6 | C100: =SUMPRODUCT(C85:C95,Inputs!$G$5:$G$15) -> 0.62 | D100: =SUMPRODUCT(D85:D95,Inputs!$G$5:$G$15) -> 0.62 | E100: =SUMPRODUCT(E85:E95,Inputs!$G$5:$G$15) -> 0.62 | F100: =SUMPRODUCT(F85:F95,Inputs!$G$5:$G$15) -> 0.62
A101: Illiquid weight | B101: =SUMPRODUCT(B85:B95,Inputs!$H$5:$H$15) -> 0 | C101: =SUMPRODUCT(C85:C95,Inputs!$H$5:$H$15) -> 0 | D101: =SUMPRODUCT(D85:D95,Inputs!$H$5:$H$15) -> 0 | E101: =SUMPRODUCT(E85:E95,Inputs!$H$5:$H$15) -> 0 | F101: =SUMPRODUCT(F85:F95,Inputs!$H$5:$H$15) -> 0
A102: Brief constraints (TE 1.5% brief limit, equity band, illiquid, cash) | B102: n/a: starting point | C102: =IF(AND(C99<=Inputs!$B$27+0.00001,C100>=Inputs!$B$31-0.00001,C100<=Inputs!$B$32+0.00001,C101<=Inputs!$B$33,C95>=Inputs!$B$34-0.00001),"MET","NOT MET") -> MET | D102: =IF(AND(D99<=Inputs!$B$27+0.00001,D100>=Inputs!$B$31-0.00001,D100<=Inputs!$B$32+0.00001,D101<=Inputs!$B$33,D95>=Inputs!$B$34-0.00001),"MET","NOT MET") -> MET | E102: =IF(AND(E99<=Inputs!$B$27+0.00001,E100>=Inputs!$B$31-0.00001,E100<=Inputs!$B$32+0.00001,E101<=Inputs!$B$33,E95>=Inputs!$B$34-0.00001),"MET","NOT MET") -> MET | F102: =IF(AND(F99<=Inputs!$B$27+0.00001,F100>=Inputs!$B$31-0.00001,F100<=Inputs!$B$32+0.00001,F101<=Inputs!$B$33,F95>=Inputs!$B$34-0.00001),"MET","NOT MET") -> MET
A105: 7. After-tax view: franking credits on Australian equities (the brief is pre-tax; this is a sensitivity)
A106: Portfolio | B106: Australian equity weight | C106: Expected return (pre-tax, compound) | D106: Franking uplift | E106: Return incl. franking
A107: Franking credit yield on Australian equities | D107: =Inputs!$B$77*Inputs!$B$78*Inputs!$B$79/(1-Inputs!$B$79)*Inputs!$B$80 -> 0.01029
A108: Current fund | B108: =C6 -> 0.4 | C108: =(Risk!$N$56-Risk!$M$56^2/2) -> 0.066110548 | D108: =B108*$D$107 -> 0.004116 | E108: =C108+D108 -> 0.070226548
A109: Benchmark | B109: =D6 -> 0.25 | C109: =(Risk!$N$57-Risk!$M$57^2/2) -> 0.063796067 | D109: =B109*$D$107 -> 0.0025725 | E109: =C109+D109 -> 0.066368567
A110: Recommended | B110: =E6 -> 0.2738 | C110: =(Risk!$N$58-Risk!$M$58^2/2) -> 0.066959679 | D110: =B110*$D$107 -> 0.002817402 | E110: =C110+D110 -> 0.069777081
A111: Recommended less current | B111: =B110-B108 -> -0.1262 | C111: =C110-C108 -> 0.00084913061 | D111: =D110-D108 -> -0.001298598 | E111: =E110-E108 -> -0.00044946739
A112: Status (advantage including franking) | E112: =IF(E111>=0,"PASS","REVIEW") -> REVIEW
A115: 8. Equity definition sensitivity: listed property counted as equity
A116: Portfolio | B116: Equity (brief definition) | C116: Listed property | D116: Equity incl. listed property
A117: Current fund | B117: =SUMPRODUCT(C6:C16,Inputs!$G$5:$G$15) -> 0.6 | C117: =C9 -> 0.1 | D117: =B117+C117 -> 0.7
A118: Benchmark | B118: =SUMPRODUCT(D6:D16,Inputs!$G$5:$G$15) -> 0.52 | C118: =D9 -> 0.07 | D118: =B118+C118 -> 0.59
...

Sheet Methods
A1: Methods
A2: Selected method | B2: =INDEX(D5:H5,Inputs!$B$49) -> Robust MVO
A3: 1. Method weights (alternatives optimised; Australian fixed income floor 12%; risk parity holds the scorecard alternatives)
A5: Asset class | B5: Current | C5: Benchmark | D5: Robust MVO | E5: Sample MVO | F5: Resampled MVO | G5: Minimum variance | H5: Risk parity | I5: Selected
A6: Australian Equities | B6: =Inputs!B5 -> 0.4 | C6: =Inputs!C5 -> 0.25 | D6: 0.2738 | E6: 0.2732 | F6: 0.2597 | G6: 0.2087 | H6: 0.1931 | I6: =INDEX(D6:H6,Inputs!$B$49) -> 0.2738
A7: World Equities | B7: =Inputs!B6 -> 0.2 | C7: =Inputs!C6 -> 0.24 | D7: 0.279 | E7: 0.2879 | F7: 0.2594 | G7: 0.2024 | H7: 0.1992 | I7: =INDEX(D7:H7,Inputs!$B$49) -> 0.279
A8: Emerging Markets | B8: =Inputs!B7 -> 0 | C8: =Inputs!C7 -> 0.03 | D8: 0.0672 | E8: 0.0589 | F8: 0.0475 | G8: 0.0279 | H8: 0.08 | I8: =INDEX(D8:H8,Inputs!$B$49) -> 0.0672
A9: Listed Property | B9: =Inputs!B8 -> 0.1 | C9: =Inputs!C8 -> 0.07 | D9: 0.0867 | E9: 0.08 | F9: 0.0773 | G9: 0.0566 | H9: 0.1117 | I9: =INDEX(D9:H9,Inputs!$B$49) -> 0.0867
A10: Commodities | B10: =Inputs!B9 -> 0 | C10: =Inputs!C9 -> 0.02 | D10: 0.0244 | E10: 0.0243 | F10: 0.0249 | G10: 0.0208 | H10: 0.03 | I10: =INDEX(D10:H10,Inputs!$B$49) -> 0.0244
A11: Direct Property | B11: =Inputs!B10 -> 0 | C11: =Inputs!C10 -> 0.05 | D11: 0 | E11: 0 | F11: 0.0262 | G11: 0.0493 | H11: 0.05 | I11: =INDEX(D11:H11,Inputs!$B$49) -> 0
A12: Hedge Funds | B12: =Inputs!B11 -> 0 | C12: =Inputs!C11 -> 0.03 | D12: 0 | E12: 0 | F12: 0.0106 | G12: 0.0361 | H12: 0 | I12: =INDEX(D12:H12,Inputs!$B$49) -> 0
A13: Private Equity | B13: =Inputs!B12 -> 0 | C13: =Inputs!C12 -> 0.03 | D13: 0 | E13: 0 | F13: 0.0226 | G13: 0.026 | H13: 0.01 | I13: =INDEX(D13:H13,Inputs!$B$49) -> 0
A14: Australian Fixed Income | B14: =Inputs!B13 -> 0.15 | C14: =Inputs!C13 -> 0.14 | D14: 0.12 | E14: 0.12 | F14: 0.1424 | G14: 0.1446 | H14: 0.1391 | I14: =INDEX(D14:H14,Inputs!$B$49) -> 0.12
A15: World Fixed Income | B15: =Inputs!B14 -> 0.08 | C15: =Inputs!C14 -> 0.11 | D15: 0.1289 | E15: 0.1357 | F15: 0.1015 | G15: 0.1276 | H15: 0.1669 | I15: =INDEX(D15:H15,Inputs!$B$49) -> 0.1289
A16: Cash | B16: =Inputs!B15 -> 0.07 | C16: =Inputs!C15 -> 0.03 | D16: 0.02 | E16: 0.02 | F16: 0.0279 | G16: 0.1 | H16: 0.02 | I16: =INDEX(D16:H16,Inputs!$B$49) -> 0.02
A17: Total | B17: =SUM(B6:B16) -> 1 | C17: =SUM(C6:C16) -> 1 | D17: =SUM(D6:D16) -> 1 | E17: =SUM(E6:E16) -> 1 | F17: =SUM(F6:F16) -> 1 | G17: =SUM(G6:G16) -> 1 | H17: =SUM(H6:H16) -> 1 | I17: =SUM(I6:I16) -> 1
A20: 2. Scorecard
A21: Portfolio | B21: Expected return (arithmetic) | C21: Volatility | D21: Sharpe ratio | E21: Tracking error | F21: Annual fee | G21: Turnover from current | H21: Effective N | I21: Diversification ratio | J21: 5-year loss prob. (normal) | K21: GFC | L21: US$150 oil | M21: Meets brief?
A22: Robust MVO | B22: =SUMPRODUCT(D$6:D$16,Forecast!$G$6:$G$16) -> 0.070032106 | C22: =SQRT(SUMPRODUCT(D$6:D$16,MMULT(Risk!$B$41:$L$51,D$6:D$16))) -> 0.078389128 | D22: =(B22-Inputs!$B$26)/C22 -> 0.30657448 | E22: =SQRT(SUMPRODUCT(D$6:D$16-Inputs!$C$5:$C$15,MMULT(Risk!$B$41:$L$51,D$6:D$16-Inputs!$C$5:$C$15))) -> 0.011002382 | F22: =SUMPRODUCT(D$6:D$16,Inputs!$D$5:$D$15) -> 0.0013311 | G22: =SUMPRODUCT(ABS(D$6:D$16-$B$6:$B$16))/2 -> 0.2195 | H22: =1/SUMSQ(D$6:D$16) -> 5.0799911 | I22: =SUMPRODUCT(D$6:D$16,Forecast!$H$6:$H$16)/C22 -> 1.4771559 | J22: =NORMSDIST(-(B22-C22^2/2)*SQRT(5)/C22) -> 0.028064013 | K22: =SUMPRODUCT(D$6:D$16,Stress!$B$11:$B$21) -> -0.2350248 | L22: =SUMPRODUCT(D$6:D$16,Oil!$F$28:$F$38) -> -0.08363891 | M22: =IF(AND(E22<=Inputs!$B$27+0.00005,SUMPRODUCT(D$6:D$16,Inputs!$G$5:$G$15)>=Inputs!$B$31-0.000001,SUMPRODUCT(D$6:D$16,Inputs!$G$5:$G$15)<=Inputs!$B$32+0.000001,D16>=Inputs!$B$34-0.000001,SUMPRODUCT(D$6:D$16,Inputs!$H$5:$H$15)<=Inputs!$B$33,MIN(D$6:D$16)>=0),"MET","NOT MET") -> MET
A23: Sample MVO | B23: =SUMPRODUCT(E$6:E$16,Forecast!$G$6:$G$16) -> 0.069911884 | C23: =SQRT(SUMPRODUCT(E$6:E$16,MMULT(Risk!$B$41:$L$51,E$6:E$16))) -> 0.078033813 | D23: =(B23-Inputs!$B$26)/C23 -> 0.30642977 | E23: =SQRT(SUMPRODUCT(E$6:E$16-Inputs!$C$5:$C$15,MMULT(Risk!$B$41:$L$51,E$6:E$16-Inputs!$C$5:$C$15))) -> 0.010637134 | F23: =SUMPRODUCT(E$6:E$16,Inputs!$D$5:$D$15) -> 0.00132715 | G23: =SUMPRODUCT(ABS(E$6:E$16-$B$6:$B$16))/2 -> 0.2268 | H23: =1/SUMSQ(E$6:E$16) -> 4.9702076 | I23: =SUMPRODUCT(E$6:E$16,Forecast!$H$6:$H$16)/C23 -> 1.4748932 | J23: =NORMSDIST(-(B23-C23^2/2)*SQRT(5)/C23) -> 0.027676903 | K23: =SUMPRODUCT(E$6:E$16,Stress!$B$11:$B$21) -> -0.23111348 | L23: =SUMPRODUCT(E$6:E$16,Oil!$F$28:$F$38) -> -0.083186357 | M23: =IF(AND(E23<=Inputs!$B$27+0.00005,SUMPRODUCT(E$6:E$16,Inputs!$G$5:$G$15)>=Inputs!$B$31-0.000001,SUMPRODUCT(E$6:E$16,Inputs!$G$5:$G$15)<=Inputs!$B$32+0.000001,E16>=Inputs!$B$34-0.000001,SUMPRODUCT(E$6:E$16,Inputs!$H$5:$H$15)<=Inputs!$B$33,MIN(E$6:E$16)>=0),"MET","NOT MET") -> MET
A24: Resampled MVO | B24: =SUMPRODUCT(F$6:F$16,Forecast!$G$6:$G$16) -> 0.06807754 | C24: =SQRT(SUMPRODUCT(F$6:F$16,MMULT(Risk!$B$41:$L$51,F$6:F$16))) -> 0.074319311 | D24: =(B24-Inputs!$B$26)/C24 -> 0.2970633 | E24: =SQRT(SUMPRODUCT(F$6:F$16-Inputs!$C$5:$C$15,MMULT(Risk!$B$41:$L$51,F$6:F$16-Inputs!$C$5:$C$15))) -> 0.005492545 | F24: =SUMPRODUCT(F$6:F$16,Inputs!$D$5:$D$15) -> 0.00247405 | G24: =SUMPRODUCT(ABS(F$6:F$16-$B$6:$B$16))/2 -> 0.2127 | H24: =1/SUMSQ(F$6:F$16) -> 5.6736951 | I24: =SUMPRODUCT(F$6:F$16,Forecast!$H$6:$H$16)/C24 -> 1.5293317 | J24: =NORMSDIST(-(B24-C24^2/2)*SQRT(5)/C24) -> 0.024696799 | K24: =SUMPRODUCT(F$6:F$16,Stress!$B$11:$B$21) -> -0.21530002 | L24: =SUMPRODUCT(F$6:F$16,Oil!$F$28:$F$38) -> -0.077804977 | M24: =IF(AND(E24<=Inputs!$B$27+0.00005,SUMPRODUCT(F$6:F$16,Inputs!$G$5:$G$15)>=Inputs!$B$31-0.000001,SUMPRODUCT(F$6:F$16,Inputs!$G$5:$G$15)<=Inputs!$B$32+0.000001,F16>=Inputs!$B$34-0.000001,SUMPRODUCT(F$6:F$16,Inputs!$H$5:$H$15)<=Inputs!$B$33,MIN(F$6:F$16)>=0),"MET","NOT MET") -> MET
A25: Minimum variance | B25: =SUMPRODUCT(G$6:G$16,Forecast!$G$6:$G$16) -> 0.063481367 | C25: =SQRT(SUMPRODUCT(G$6:G$16,MMULT(Risk!$B$41:$L$51,G$6:G$16))) -> 0.059513407 | D25: =(B25-Inputs!$B$26)/C25 -> 0.29373829 | E25: =SQRT(SUMPRODUCT(G$6:G$16-Inputs!$C$5:$C$15,MMULT(Risk!$B$41:$L$51,G$6:G$16-Inputs!$C$5:$C$15))) -> 0.011007069 | F25: =SUMPRODUCT(G$6:G$16,Inputs!$D$5:$D$15) -> 0.0033151 | G25: =SUMPRODUCT(ABS(G$6:G$16-$B$6:$B$16))/2 -> 0.2401 | H25: =1/SUMSQ(G$6:G$16) -> 7.1155801 | I25: =SUMPRODUCT(G$6:G$16,Forecast!$H$6:$H$16)/C25 -> 1.6523888 | J25: =NORMSDIST(-(B25-C25^2/2)*SQRT(5)/C25) -> 0.01020793 | K25: =SUMPRODUCT(G$6:G$16,Stress!$B$11:$B$21) -> -0.14443638 | L25: =SUMPRODUCT(G$6:G$16,Oil!$F$28:$F$38) -> -0.064395856 | M25: =IF(AND(E25<=Inputs!$B$27+0.00005,SUMPRODUCT(G$6:G$16,Inputs!$G$5:$G$15)>=Inputs!$B$31-0.000001,SUMPRODUCT(G$6:G$16,Inputs!$G$5:$G$15)<=Inputs!$B$32+0.000001,G16>=Inputs!$B$34-0.000001,SUMPRODUCT(G$6:G$16,Inputs!$H$5:$H$15)<=Inputs!$B$33,MIN(G$6:G$16)>=0),"MET","NOT MET") -> MET
A26: Risk parity | B26: =SUMPRODUCT(H$6:H$16,Forecast!$G$6:$G$16) -> 0.066570324 | C26: =SQRT(SUMPRODUCT(H$6:H$16,MMULT(Risk!$B$41:$L$51,H$6:H$16))) -> 0.066508938 | D26: =(B26-Inputs!$B$26)/C26 -> 0.30928661 | E26: =SQRT(SUMPRODUCT(H$6:H$16-Inputs!$C$5:$C$15,MMULT(Risk!$B$41:$L$51,H$6:H$16-Inputs!$C$5:$C$15))) -> 0.010999556 | F26: =SUMPRODUCT(H$6:H$16,Inputs!$D$5:$D$15) -> 0.0021839 | G26: =SUMPRODUCT(ABS(H$6:H$16-$B$6:$B$16))/2 -> 0.2686 | H26: =1/SUMSQ(H$6:H$16) -> 6.8050561 | I26: =SUMPRODUCT(H$6:H$16,Forecast!$H$6:$H$16)/C26 -> 1.6315121 | J26: =NORMSDIST(-(B26-C26^2/2)*SQRT(5)/C26) -> 0.015240904 | K26: =SUMPRODUCT(H$6:H$16,Stress!$B$11:$B$21) -> -0.19027822 | L26: =SUMPRODUCT(H$6:H$16,Oil!$F$28:$F$38) -> -0.072014579 | M26: =IF(AND(E26<=Inputs!$B$27+0.00005,SUMPRODUCT(H$6:H$16,Inputs!$G$5:$G$15)>=Inputs!$B$31-0.000001,SUMPRODUCT(H$6:H$16,Inputs!$G$5:$G$15)<=Inputs!$B$32+0.000001,H16>=Inputs!$B$34-0.000001,SUMPRODUCT(H$6:H$16,Inputs!$H$5:$H$15)<=Inputs!$B$33,MIN(H$6:H$16)>=0),"MET","NOT MET") -> MET
A27: Current fund | B27: =SUMPRODUCT(B$6:B$16,Forecast!$G$6:$G$16) -> 0.069624615 | C27: =SQRT(SUMPRODUCT(B$6:B$16,MMULT(Risk!$B$41:$L$51,B$6:B$16))) -> 0.083833964 | D27: =(B27-Inputs!$B$26)/C27 -> 0.28180243 | E27: =SQRT(SUMPRODUCT(B$6:B$16-Inputs!$C$5:$C$15,MMULT(Risk!$B$41:$L$51,B$6:B$16-Inputs!$C$5:$C$15))) -> 0.021585026 | F27: =SUMPRODUCT(B$6:B$16,Inputs!$D$5:$D$15) -> 0.00112 | G27: =SUMPRODUCT(ABS(B$6:B$16-$B$6:$B$16))/2 -> 0 | H27: =1/SUMSQ(B$6:B$16) -> 4.1017227 | I27: =SUMPRODUCT(B$6:B$16,Forecast!$H$6:$H$16)/C27 -> 1.3609241 | J27: =NORMSDIST(-(B27-C27^2/2)*SQRT(5)/C27) -> 0.038921685 | K27: =SUMPRODUCT(B$6:B$16,Stress!$B$11:$B$21) -> -0.24167171 | L27: =SUMPRODUCT(B$6:B$16,Oil!$F$28:$F$38) -> -0.082609308 | M27: =IF(AND(E27<=Inputs!$B$27+0.00005,SUMPRODUCT(B$6:B$16,Inputs!$G$5:$G$15)>=Inputs!$B$31-0.000001,SUMPRODUCT(B$6:B$16,Inputs!$G$5:$G$15)<=Inputs!$B$32+0.000001,B16>=Inputs!$B$34-0.000001,SUMPRODUCT(B$6:B$16,Inputs!$H$5:$H$15)<=Inputs!$B$33,MIN(B$6:B$16)>=0),"MET","NOT MET") -> NOT MET
A28: Benchmark | B28: =SUMPRODUCT(C$6:C$16,Forecast!$G$6:$G$16) -> 0.066255464 | C28: =SQRT(SUMPRODUCT(C$6:C$16,MMULT(Risk!$B$41:$L$51,C$6:C$16))) -> 0.070134112 | D28: =(B28-Inputs!$B$26)/C28 -> 0.28881044 | E28: =SQRT(SUMPRODUCT(C$6:C$16-Inputs!$C$5:$C$15,MMULT(Risk!$B$41:$L$51,C$6:C$16-Inputs!$C$5:$C$15))) -> 0 | F28: =SUMPRODUCT(C$6:C$16,Inputs!$D$5:$D$15) -> 0.00338 | G28: =SUMPRODUCT(ABS(C$6:C$16-$B$6:$B$16))/2 -> 0.23 | H28: =1/SUMSQ(C$6:C$16) -> 6.127451 | I28: =SUMPRODUCT(C$6:C$16,Forecast!$H$6:$H$16)/C28 -> 1.5726575 | J28: =NORMSDIST(-(B28-C28^2/2)*SQRT(5)/C28) -> 0.020976115 | K28: =SUMPRODUCT(C$6:C$16,Stress!$B$11:$B$21) -> -0.19300089 | L28: =SUMPRODUCT(C$6:C$16,Oil!$F$28:$F$38) -> -0.073910247 | M28: =IF(AND(E28<=Inputs!$B$27+0.00005,SUMPRODUCT(C$6:C$16,Inputs!$G$5:$G$15)>=Inputs!$B$31-0.000001,SUMPRODUCT(C$6:C$16,Inputs!$G$5:$G$15)<=Inputs!$B$32+0.000001,C16>=Inputs!$B$34-0.000001,SUMPRODUCT(C$6:C$16,Inputs!$H$5:$H$15)<=Inputs!$B$33,MIN(C$6:C$16)>=0),"MET","NOT MET") -> MET
A31: 3. Stability check: robust vs resampled
A32: Check | B32: Robust MVO | C32: Resampled MVO | D32: Difference | E32: Limit | F32: Status | J32: Yellow cells: Solver decision variables (Robust MVO)
A33: Largest asset-weight difference | D33: =MAX(E41:E51) -> 0.0274 | E33: 0.03 | F33: =IF(D33<=E33,"WITHIN LIMIT","ABOVE LIMIT") -> WITHIN LIMIT
A34: Expected return | B34: =B22 -> 0.070032106 | C34: =B24 -> 0.06807754 | D34: =ABS(B34-C34) -> 0.0019545667 | E34: 0.005 | F34: =IF(D34<=E34,"WITHIN LIMIT","ABOVE LIMIT") -> WITHIN LIMIT
A35: Volatility | B35: =C22 -> 0.078389128 | C35: =C24 -> 0.074319311 | D35: =ABS(B35-C35) -> 0.004069817 | E35: 0.005 | F35: =IF(D35<=E35,"WITHIN LIMIT","ABOVE LIMIT") -> WITHIN LIMIT
A36: Asset with the largest difference | B36: =INDEX(A41:A51,MATCH(D33,E41:E51,0)) -> World Fixed Income
A37: Largest gap inside resampling spread? | B37: =INDEX(I41:I51,MATCH(D33,E41:E51,0)) -> Yes
A39: 4. Resampling spread (150 resampled input sets)
A40: Asset class | B40: Robust MVO | C40: Resampled average | D40: Difference | E40: Absolute difference | F40: Spread (std dev) | G40: 10th percentile | H40: 90th percentile | I40: Gap within spread?
A41: Australian Equities | B41: =D6 -> 0.2738 | C41: =F6 -> 0.2597 | D41: =B41-C41 -> 0.0141 | E41: =ABS(D41) -> 0.0141 | F41: 0.0308 | G41: 0.2172 | H41: 0.3005 | I41: =IF(E41<=F41,"Yes","No") -> Yes
A42: World Equities | B42: =D7 -> 0.279 | C42: =F7 -> 0.2594 | D42: =B42-C42 -> 0.0196 | E42: =ABS(D42) -> 0.0196 | F42: 0.0317 | G42: 0.216 | H42: 0.2991 | I42: =IF(E42<=F42,"Yes","No") -> Yes
A43: Emerging Markets | B43: =D8 -> 0.0672 | C43: =F8 -> 0.0475 | D43: =B43-C43 -> 0.0197 | E43: =ABS(D43) -> 0.0197 | F43: 0.0299 | G43: 0 | H43: 0.08 | I43: =IF(E43<=F43,"Yes","No") -> Yes
A44: Listed Property | B44: =D9 -> 0.0867 | C44: =F9 -> 0.0773 | D44: =B44-C44 -> 0.0094 | E44: =ABS(D44) -> 0.0094 | F44: 0.0284 | G44: 0.0371 | H44: 0.1132 | I44: =IF(E44<=F44,"Yes","No") -> Yes
A45: Commodities | B45: =D10 -> 0.0244 | C45: =F10 -> 0.0249 | D45: =B45-C45 -> -0.0005 | E45: =ABS(D45) -> 0.0005 | F45: 0.0182 | G45: 0 | H45: 0.0485 | I45: =IF(E45<=F45,"Yes","No") -> Yes
A46: Direct Property | B46: =D11 -> 0 | C46: =F11 -> 0.0262 | D46: =B46-C46 -> -0.0262 | E46: =ABS(D46) -> 0.0262 | F46: 0.0299 | G46: 0 | H46: 0.0766 | I46: =IF(E46<=F46,"Yes","No") -> Yes
A47: Hedge Funds | B47: =D12 -> 0 | C47: =F12 -> 0.0106 | D47: =B47-C47 -> -0.0106 | E47: =ABS(D47) -> 0.0106 | F47: 0.0225 | G47: 0 | H47: 0.0534 | I47: =IF(E47<=F47,"Yes","No") -> Yes
A48: Private Equity | B48: =D13 -> 0 | C48: =F13 -> 0.0226 | D48: =B48-C48 -> -0.0226 | E48: =ABS(D48) -> 0.0226 | F48: 0.0252 | G48: 0 | H48: 0.0611 | I48: =IF(E48<=F48,"Yes","No") -> Yes
A49: Australian Fixed Income | B49: =D14 -> 0.12 | C49: =F14 -> 0.1424 | D49: =B49-C49 -> -0.0224 | E49: =ABS(D49) -> 0.0224 | F49: 0.0379 | G49: 0.12 | H49: 0.1998 | I49: =IF(E49<=F49,"Yes","No") -> Yes
A50: World Fixed Income | B50: =D15 -> 0.1289 | C50: =F15 -> 0.1015 | D50: =B50-C50 -> 0.0274 | E50: =ABS(D50) -> 0.0274 | F50: 0.05 | G50: 0.05 | H50: 0.1859 | I50: =IF(E50<=F50,"Yes","No") -> Yes
A51: Cash | B51: =D16 -> 0.02 | C51: =F16 -> 0.0279 | D51: =B51-C51 -> -0.0079 | E51: =ABS(D51) -> 0.0079 | F51: 0.0208 | G51: 0.02 | H51: 0.0607 | I51: =IF(E51<=F51,"Yes","No") -> Yes

Sheet Bootstrap
A1: Bootstrap
A4: 1. Results (1,000 paths x 5 annual draws)
A5: Measure | B5: Current | C5: Benchmark | D5: Recommended | E5: Limit
A6: 5-year loss probability (bootstrap) | B6: =COUNTIF(G102:G1101,"<0")/COUNT(G102:G1101) -> 0.077 | C6: =COUNTIF(H102:H1101,"<0")/COUNT(H102:H1101) -> 0.062 | D6: =COUNTIF(I102:I1101,"<0")/COUNT(I102:I1101) -> 0.073 | E6: =Inputs!$B$28 -> 0.25
A7: 5-year loss probability (normal) | B7: =NORMSDIST(-(Risk!N56-Risk!M56^2/2)*SQRT(5)/Risk!M56) -> 0.038921685 | C7: =NORMSDIST(-(Risk!N57-Risk!M57^2/2)*SQRT(5)/Risk!M57) -> 0.020976115 | D7: =NORMSDIST(-(Risk!N58-Risk!M58^2/2)*SQRT(5)/Risk!M58) -> 0.028064013 | E7: =Inputs!$B$28 -> 0.25
A8: 5th percentile 5-year return | B8: =PERCENTILE(G102:G1101,0.05) -> -0.066525065 | C8: =PERCENTILE(H102:H1101,0.05) -> -0.025344705 | D8: =PERCENTILE(I102:I1101,0.05) -> -0.053347643
A9: Median 5-year return | B9: =MEDIAN(G102:G1101) -> 0.39414359 | C9: =MEDIAN(H102:H1101) -> 0.3749255 | D9: =MEDIAN(I102:I1101) -> 0.39501952
A10: 95th percentile 5-year return | B10: =PERCENTILE(G102:G1101,0.95) -> 0.85174786 | C10: =PERCENTILE(H102:H1101,0.95) -> 0.79305245 | D10: =PERCENTILE(I102:I1101,0.95) -> 0.87315897
A11: Median return, annualised | B11: =(1+B9)^(1/5)-1 -> 0.068714006 | C11: =(1+C9)^(1/5)-1 -> 0.065751208 | D11: =(1+D9)^(1/5)-1 -> 0.068848266
A12: Tracking error (bootstrap) | B12: =STDEV(J102:J1101)/SQRT(5) -> 0.0156484 | C12: 0 | D12: =STDEV(K102:K1101)/SQRT(5) -> 0.011821602 | E12: =Inputs!$B$27 -> 0.015
A13: Tracking error (parametric) | B13: =Risk!O56 -> 0.021585026 | C13: 0 | D13: =Risk!O58 -> 0.011002382 | E13: =Inputs!$B$27 -> 0.015
A14: Within limit (loss / TE) | B14: =IF(D6<=E6,"MET","NOT MET") -> MET | C14: =IF(D12<=E12,"MET","NOT MET") -> MET
A18: 2. Annual windows (adjusted returns, mean shifted to net forecast)
A20: Window | B20: Year ending | C20: Australian Equities | D20: World Equities | E20: Emerging Markets | F20: Listed Property | G20: Commodities | H20: Direct Property | I20: Hedge Funds | J20: Private Equity | K20: Australian Fixed Income | L20: World Fixed Income | M20: Cash | O20: Australian Equities (shifted) | P20: World Equities (shifted) | Q20: Emerging Markets (shifted) | R20: Listed Property (shifted) | S20: Commodities (shifted) | T20: Direct Property (shifted) | U20: Hedge Funds (shifted) | V20: Private Equity (shifted) | W20: Australian Fixed Income (shifted) | X20: World Fixed Income (shifted) | Y20: Cash (shifted) | Z20: Current | AA20: Benchmark | AB20: Recommended | AC20: Alternatives fixed by scorecard | AD20: No alternatives | AE20: Alternatives at benchmark weights | AF20: Core five only
A21: 1 | B21: ='Quarterly returns'!A9 -> 39171 | C21: =(1+'Quarterly returns'!N6)*(1+'Quarterly returns'!N7)*(1+'Quarterly returns'!N8)*(1+'Quarterly returns'!N9)-1 -> 0.22335287 | D21: =(1+'Quarterly returns'!O6)*(1+'Quarterly returns'!O7)*(1+'Quarterly returns'!O8)*(1+'Quarterly returns'!O9)-1 -> -0.013477703 | E21: =(1+'Quarterly returns'!P6)*(1+'Quarterly returns'!P7)*(1+'Quarterly returns'!P8)*(1+'Quarterly returns'!P9)-1 -> 0.061278297 | F21: =(1+'Quarterly returns'!Q6)*(1+'Quarterly returns'!Q7)*(1+'Quarterly returns'!Q8)*(1+'Quarterly returns'!Q9)-1 -> 0.12203701 | G21: =(1+'Quarterly returns'!R6)*(1+'Quarterly returns'!R7)*(1+'Quarterly returns'!R8)*(1+'Quarterly returns'!R9)-1 -> -0.20038571 | H21: =(1+'Quarterly returns'!S6)*(1+'Quarterly returns'!S7)*(1+'Quarterly returns'!S8)*(1+'Quarterly returns'!S9)-1 -> 0.089363022 | I21: =(1+'Quarterly returns'!T6)*(1+'Quarterly returns'!T7)*(1+'Quarterly returns'!T8)*(1+'Quarterly returns'!T9)-1 -> 0.11983848 | J21: =(1+'Quarterly returns'!U6)*(1+'Quarterly returns'!U7)*(1+'Quarterly returns'!U8)*(1+'Quarterly returns'!U9)-1 -> 0.25909107 | ... M21: =(1+'Quarterly returns'!X6)*(1+'Quarterly returns'!X7)*(1+'Quarterly returns'!X8)*(1+'Quarterly returns'!X9)-1 -> 0.062119266 | O21: =C21-AVERAGE(C$21:C$97)+Forecast!$G$6 -> 0.21855716 | P21: =D21-AVERAGE(D$21:D$97)+Forecast!$G$7 -> -0.041601494 | Q21: =E21-AVERAGE(E$21:E$97)+Forecast!$G$8 -> 0.042885569 | R21: =F21-AVERAGE(F$21:F$97)+Forecast!$G$9 -> 0.12867484 | S21: =G21-AVERAGE(G$21:G$97)+Forecast!$G$10 -> -0.14745011 | T21: =H21-AVERAGE(H$21:H$97)+Forecast!$G$11 -> 0.070619093 | U21: =I21-AVERAGE(I$21:I$97)+Forecast!$G$12 -> 0.077509425 | V21: =J21-AVERAGE(J$21:J$97)+Forecast!$G$13 -> 0.18725134 | W21: =K21-AVERAGE(K$21:K$97)+Forecast!$G$14 -> 0.04494977 | X21: =L21-AVERAGE(L$21:L$97)+Forecast!$G$15 -> 0.072008777 | Y21: =M21-AVERAGE(M$21:M$97)+Forecast!$G$16 -> 0.077174338 | Z21: =SUMPRODUCT($O21:$Y21,Risk!$B$56:$L$56) -> 0.10987542 | AA21: =SUMPRODUCT($O21:$Y21,Risk!$B$57:$L$57) -> 0.080002677 | AB21: =SUMPRODUCT($O21:$Y21,Risk!$B$58:$L$58) -> 0.074893761 | AC21: =SUMPRODUCT(MMULT($O21:$Y21,Portfolio!$C$127:$C$137)) -> 0.075530096 | AD21: =SUMPRODUCT(MMULT($O21:$Y21,Portfolio!$D$127:$D$137)) -> 0.080222913 | AE21: =SUMPRODUCT(MMULT($O21:$Y21,Portfolio!$E$127:$E$137)) -> 0.081997639 | AF21: =SUMPRODUCT(MMULT($O21:$Y21,Portfolio!$F$127:$F$137)) -> 0.079060113
A22: 2 | B22: ='Quarterly returns'!A10 -> 39262 | C22: =(1+'Quarterly returns'!N7)*(1+'Quarterly returns'!N8)*(1+'Quarterly returns'!N9)*(1+'Quarterly returns'!N10)-1 -> 0.3028133 | D22: =(1+'Quarterly returns'!O7)*(1+'Quarterly returns'!O8)*(1+'Quarterly returns'!O9)*(1+'Quarterly returns'!O10)-1 -> 0.069490787 | E22: =(1+'Quarterly returns'!P7)*(1+'Quarterly returns'!P8)*(1+'Quarterly returns'!P9)*(1+'Quarterly returns'!P10)-1 -> 0.22137832 | F22: =(1+'Quarterly returns'!Q7)*(1+'Quarterly returns'!Q8)*(1+'Quarterly returns'!Q9)*(1+'Quarterly returns'!Q10)-1 -> 0.042161147 | G22: =(1+'Quarterly returns'!R7)*(1+'Quarterly returns'!R8)*(1+'Quarterly returns'!R9)*(1+'Quarterly returns'!R10)-1 -> -0.24683502 | H22: =(1+'Quarterly returns'!S7)*(1+'Quarterly returns'!S8)*(1+'Quarterly returns'!S9)*(1+'Quarterly returns'!S10)-1 -> 0.11738199 | I22: =(1+'Quarterly returns'!T7)*(1+'Quarterly returns'!T8)*(1+'Quarterly returns'!T9)*(1+'Quarterly returns'!T10)-1 -> 0.12329036 | J22: =(1+'Quarterly returns'!U7)*(1+'Quarterly returns'!U8)*(1+'Quarterly returns'!U9)*(1+'Quarterly returns'!U10)-1 -> 0.27380445 | ... M22: =(1+'Quarterly returns'!X7)*(1+'Quarterly returns'!X8)*(1+'Quarterly returns'!X9)*(1+'Quarterly returns'!X10)-1 -> 0.064233762 | O22: =C22-AVERAGE(C$21:C$97)+Forecast!$G$6 -> 0.29801759 | P22: =D22-AVERAGE(D$21:D$97)+Forecast!$G$7 -> 0.041366996 | Q22: =E22-AVERAGE(E$21:E$97)+Forecast!$G$8 -> 0.20298559 | R22: =F22-AVERAGE(F$21:F$97)+Forecast!$G$9 -> 0.04879898 | S22: =G22-AVERAGE(G$21:G$97)+Forecast!$G$10 -> -0.19389942 | T22: =H22-AVERAGE(H$21:H$97)+Forecast!$G$11 -> 0.098638059 | U22: =I22-AVERAGE(I$21:I$97)+Forecast!$G$12 -> 0.0809613 | V22: =J22-AVERAGE(J$21:J$97)+Forecast!$G$13 -> 0.20196472 | W22: =K22-AVERAGE(K$21:K$97)+Forecast!$G$14 -> 0.047809359 | X22: =L22-AVERAGE(L$21:L$97)+Forecast!$G$15 -> 0.065417538 | Y22: =M22-AVERAGE(M$21:M$97)+Forecast!$G$16 -> 0.079288834 | Z22: =SUMPRODUCT($O22:$Y22,Risk!$B$56:$L$56) -> 0.15031536 | AA22: =SUMPRODUCT($O22:$Y22,Risk!$B$57:$L$57) -> 0.11974757 | AB22: =SUMPRODUCT($O22:$Y22,Risk!$B$58:$L$58) -> 0.12203419 | AC22: =SUMPRODUCT(MMULT($O22:$Y22,Portfolio!$C$127:$C$137)) -> 0.12156051 | AD22: =SUMPRODUCT(MMULT($O22:$Y22,Portfolio!$D$127:$D$137)) -> 0.12886434 | AE22: =SUMPRODUCT(MMULT($O22:$Y22,Portfolio!$E$127:$E$137)) -> 0.12440187 | AF22: =SUMPRODUCT(MMULT($O22:$Y22,Portfolio!$F$127:$F$137)) -> 0.12858027
A23: 3 | B23: ='Quarterly returns'!A11 -> 39353 | C23: =(1+'Quarterly returns'!N8)*(1+'Quarterly returns'!N9)*(1+'Quarterly returns'!N10)*(1+'Quarterly returns'!N11)-1 -> 0.33576768 | D23: =(1+'Quarterly returns'!O8)*(1+'Quarterly returns'!O9)*(1+'Quarterly returns'!O10)*(1+'Quarterly returns'!O11)-1 -> -0.021076003 | E23: =(1+'Quarterly returns'!P8)*(1+'Quarterly returns'!P9)*(1+'Quarterly returns'!P10)*(1+'Quarterly returns'!P11)-1 -> 0.25529845 | F23: =(1+'Quarterly returns'!Q8)*(1+'Quarterly returns'!Q9)*(1+'Quarterly returns'!Q10)*(1+'Quarterly returns'!Q11)-1 -> -0.087905931 | G23: =(1+'Quarterly returns'!R8)*(1+'Quarterly returns'!R9)*(1+'Quarterly returns'!R10)*(1+'Quarterly returns'!R11)-1 -> -0.04297006 | H23: =(1+'Quarterly returns'!S8)*(1+'Quarterly returns'!S9)*(1+'Quarterly returns'!S10)*(1+'Quarterly returns'!S11)-1 -> 0.15643506 | I23: =(1+'Quarterly returns'!T8)*(1+'Quarterly returns'!T9)*(1+'Quarterly returns'!T10)*(1+'Quarterly returns'!T11)-1 -> 0.13724465 | J23: =(1+'Quarterly returns'!U8)*(1+'Quarterly returns'!U9)*(1+'Quarterly returns'!U10)*(1+'Quarterly returns'!U11)-1 -> 0.16476239 | ... M23: =(1+'Quarterly returns'!X8)*(1+'Quarterly returns'!X9)*(1+'Quarterly returns'!X10)*(1+'Quarterly returns'!X11)-1 -> 0.065426174 | O23: =C23-AVERAGE(C$21:C$97)+Forecast!$G$6 -> 0.33097198 | P23: =D23-AVERAGE(D$21:D$97)+Forecast!$G$7 -> -0.049199795 | Q23: =E23-AVERAGE(E$21:E$97)+Forecast!$G$8 -> 0.23690572 | R23: =F23-AVERAGE(F$21:F$97)+Forecast!$G$9 -> -0.081268098 | S23: =G23-AVERAGE(G$21:G$97)+Forecast!$G$10 -> 0.009965537 | T23: =H23-AVERAGE(H$21:H$97)+Forecast!$G$11 -> 0.13769113 | U23: =I23-AVERAGE(I$21:I$97)+Forecast!$G$12 -> 0.094915592 | V23: =J23-AVERAGE(J$21:J$97)+Forecast!$G$13 -> 0.092922664 | W23: =K23-AVERAGE(K$21:K$97)+Forecast!$G$14 -> 0.042662658 | X23: =L23-AVERAGE(L$21:L$97)+Forecast!$G$15 -> 0.058786507 | Y23: =M23-AVERAGE(M$21:M$97)+Forecast!$G$16 -> 0.080481246 | Z23: =SUMPRODUCT($O23:$Y23,Risk!$B$56:$L$56) -> 0.13115803 | AA23: =SUMPRODUCT($O23:$Y23,Risk!$B$57:$L$57) -> 0.099926188 | AB23: =SUMPRODUCT($O23:$Y23,Risk!$B$58:$L$58) -> 0.10031739 | AC23: =SUMPRODUCT(MMULT($O23:$Y23,Portfolio!$C$127:$C$137)) -> 0.10164916 | AD23: =SUMPRODUCT(MMULT($O23:$Y23,Portfolio!$D$127:$D$137)) -> 0.10291496 | AE23: =SUMPRODUCT(MMULT($O23:$Y23,Portfolio!$E$127:$E$137)) -> 0.098530854 | AF23: =SUMPRODUCT(MMULT($O23:$Y23,Portfolio!$F$127:$F$137)) -> 0.10910103
A24: 4 | B24: ='Quarterly returns'!A12 -> 39447 | C24: =(1+'Quarterly returns'!N9)*(1+'Quarterly returns'!N10)*(1+'Quarterly returns'!N11)*(1+'Quarterly returns'!N12)-1 -> 0.17953359 | D24: =(1+'Quarterly returns'!O9)*(1+'Quarterly returns'!O10)*(1+'Quarterly returns'!O11)*(1+'Quarterly returns'!O12)-1 -> -0.055648782 | E24: =(1+'Quarterly returns'!P9)*(1+'Quarterly returns'!P10)*(1+'Quarterly returns'!P11)*(1+'Quarterly returns'!P12)-1 -> 0.19921791 | F24: =(1+'Quarterly returns'!Q9)*(1+'Quarterly returns'!Q10)*(1+'Quarterly returns'!Q11)*(1+'Quarterly returns'!Q12)-1 -> -0.23045326 | G24: =(1+'Quarterly returns'!R9)*(1+'Quarterly returns'!R10)*(1+'Quarterly returns'!R11)*(1+'Quarterly returns'!R12)-1 -> 0.19095744 | H24: =(1+'Quarterly returns'!S9)*(1+'Quarterly returns'!S10)*(1+'Quarterly returns'!S11)*(1+'Quarterly returns'!S12)-1 -> 0.18456716 | I24: =(1+'Quarterly returns'!T9)*(1+'Quarterly returns'!T10)*(1+'Quarterly returns'!T11)*(1+'Quarterly returns'!T12)-1 -> 0.15020038 | J24: =(1+'Quarterly returns'!U9)*(1+'Quarterly returns'!U10)*(1+'Quarterly returns'!U11)*(1+'Quarterly returns'!U12)-1 -> 0.12160223 | ... M24: =(1+'Quarterly returns'!X9)*(1+'Quarterly returns'!X10)*(1+'Quarterly returns'!X11)*(1+'Quarterly returns'!X12)-1 -> 0.067307017 | O24: =C24-AVERAGE(C$21:C$97)+Forecast!$G$6 -> 0.17473789 | P24: =D24-AVERAGE(D$21:D$97)+Forecast!$G$7 -> -0.083772573 | Q24: =E24-AVERAGE(E$21:E$97)+Forecast!$G$8 -> 0.18082518 | R24: =F24-AVERAGE(F$21:F$97)+Forecast!$G$9 -> -0.22381542 | S24: =G24-AVERAGE(G$21:G$97)+Forecast!$G$10 -> 0.24389303 | T24: =H24-AVERAGE(H$21:H$97)+Forecast!$G$11 -> 0.16582323 | U24: =I24-AVERAGE(I$21:I$97)+Forecast!$G$12 -> 0.10787132 | V24: =J24-AVERAGE(J$21:J$97)+Forecast!$G$13 -> 0.049762499 | W24: =K24-AVERAGE(K$21:K$97)+Forecast!$G$14 -> 0.042558523 | X24: =L24-AVERAGE(L$21:L$97)+Forecast!$G$15 -> 0.074512587 | Y24: =M24-AVERAGE(M$21:M$97)+Forecast!$G$16 -> 0.08236209 | Z24: =SUMPRODUCT($O24:$Y24,Risk!$B$56:$L$56) -> 0.048869229 | AA24: =SUMPRODUCT($O24:$Y24,Risk!$B$57:$L$57) -> 0.047860207 | AB24: =SUMPRODUCT($O24:$Y24,Risk!$B$58:$L$58) -> 0.039527267 | AC24: =SUMPRODUCT(MMULT($O24:$Y24,Portfolio!$C$127:$C$137)) -> 0.042969048 | AD24: =SUMPRODUCT(MMULT($O24:$Y24,Portfolio!$D$127:$D$137)) -> 0.037486636 | AE24: =SUMPRODUCT(MMULT($O24:$Y24,Portfolio!$E$127:$E$137)) -> 0.035992425 | AF24: =SUMPRODUCT(MMULT($O24:$Y24,Portfolio!$F$127:$F$137)) -> 0.052618263
A25: 5 | B25: ='Quarterly returns'!A13 -> 39538 | C25: =(1+'Quarterly returns'!N10)*(1+'Quarterly returns'!N11)*(1+'Quarterly returns'!N12)*(1+'Quarterly returns'!N13)-1 -> -0.060177176 | D25: =(1+'Quarterly returns'!O10)*(1+'Quarterly returns'!O11)*(1+'Quarterly returns'!O12)*(1+'Quarterly returns'!O13)-1 -> -0.19656652 | E25: =(1+'Quarterly returns'!P10)*(1+'Quarterly returns'!P11)*(1+'Quarterly returns'!P12)*(1+'Quarterly returns'!P13)-1 -> 0.028820031 | F25: =(1+'Quarterly returns'!Q10)*(1+'Quarterly returns'!Q11)*(1+'Quarterly returns'!Q12)*(1+'Quarterly returns'!Q13)-1 -> -0.30881072 | G25: =(1+'Quarterly returns'!R10)*(1+'Quarterly returns'!R11)*(1+'Quarterly returns'!R12)*(1+'Quarterly returns'!R13)-1 -> 0.2267831 | H25: =(1+'Quarterly returns'!S10)*(1+'Quarterly returns'!S11)*(1+'Quarterly returns'!S12)*(1+'Quarterly returns'!S13)-1 -> 0.12530999 | I25: =(1+'Quarterly returns'!T10)*(1+'Quarterly returns'!T11)*(1+'Quarterly returns'!T12)*(1+'Quarterly returns'!T13)-1 -> 0.11395006 | J25: =(1+'Quarterly returns'!U10)*(1+'Quarterly returns'!U11)*(1+'Quarterly returns'!U12)*(1+'Quarterly returns'!U13)-1 -> 0.088001893 | ... M25: =(1+'Quarterly returns'!X10)*(1+'Quarterly returns'!X11)*(1+'Quarterly returns'!X12)*(1+'Quarterly returns'!X13)-1 -> 0.069862055 | O25: =C25-AVERAGE(C$21:C$97)+Forecast!$G$6 -> -0.064972884 | P25: =D25-AVERAGE(D$21:D$97)+Forecast!$G$7 -> -0.22469031 | Q25: =E25-AVERAGE(E$21:E$97)+Forecast!$G$8 -> 0.010427303 | R25: =F25-AVERAGE(F$21:F$97)+Forecast!$G$9 -> -0.30217289 | S25: =G25-AVERAGE(G$21:G$97)+Forecast!$G$10 -> 0.27971869 | T25: =H25-AVERAGE(H$21:H$97)+Forecast!$G$11 -> 0.10656606 | U25: =I25-AVERAGE(I$21:I$97)+Forecast!$G$12 -> 0.071621006 | V25: =J25-AVERAGE(J$21:J$97)+Forecast!$G$13 -> 0.016162163 | W25: =K25-AVERAGE(K$21:K$97)+Forecast!$G$14 -> 0.050834226 | X25: =L25-AVERAGE(L$21:L$97)+Forecast!$G$15 -> 0.088339777 | Y25: =M25-AVERAGE(M$21:M$97)+Forecast!$G$16 -> 0.084917128 | Z25: =SUMPRODUCT($O25:$Y25,Risk!$B$56:$L$56) -> -0.08050799 | AA25: =SUMPRODUCT($O25:$Y25,Risk!$B$57:$L$57) -> -0.058070326 | AB25: =SUMPRODUCT($O25:$Y25,Risk!$B$58:$L$58) -> -0.079965264 | AC25: =SUMPRODUCT(MMULT($O25:$Y25,Portfolio!$C$127:$C$137)) -> -0.077490067 | AD25: =SUMPRODUCT(MMULT($O25:$Y25,Portfolio!$D$127:$D$137)) -> -0.082187735 | AE25: =SUMPRODUCT(MMULT($O25:$Y25,Portfolio!$E$127:$E$137)) -> -0.08474823 | AF25: =SUMPRODUCT(MMULT($O25:$Y25,Portfolio!$F$127:$F$137)) -> -0.061640975
A26: 6 | B26: ='Quarterly returns'!A14 -> 39629 | C26: =(1+'Quarterly returns'!N11)*(1+'Quarterly returns'!N12)*(1+'Quarterly returns'!N13)*(1+'Quarterly returns'!N14)-1 -> -0.12115374 | D26: =(1+'Quarterly returns'!O11)*(1+'Quarterly returns'!O12)*(1+'Quarterly returns'!O13)*(1+'Quarterly returns'!O14)-1 -> -0.24991221 | E26: =(1+'Quarterly returns'!P11)*(1+'Quarterly returns'!P12)*(1+'Quarterly returns'!P13)*(1+'Quarterly returns'!P14)-1 -> -0.10137998 | F26: =(1+'Quarterly returns'!Q11)*(1+'Quarterly returns'!Q12)*(1+'Quarterly returns'!Q13)*(1+'Quarterly returns'!Q14)-1 -> -0.32105485 | G26: =(1+'Quarterly returns'!R11)*(1+'Quarterly returns'!R12)*(1+'Quarterly returns'!R13)*(1+'Quarterly returns'!R14)-1 -> 0.55582438 | H26: =(1+'Quarterly returns'!S11)*(1+'Quarterly returns'!S12)*(1+'Quarterly returns'!S13)*(1+'Quarterly returns'!S14)-1 -> -0.021364262 | I26: =(1+'Quarterly returns'!T11)*(1+'Quarterly returns'!T12)*(1+'Quarterly returns'!T13)*(1+'Quarterly returns'!T14)-1 -> 0.13594368 | J26: =(1+'Quarterly returns'!U11)*(1+'Quarterly returns'!U12)*(1+'Quarterly returns'!U13)*(1+'Quarterly returns'!U14)-1 -> -0.045085385 | ... M26: =(1+'Quarterly returns'!X11)*(1+'Quarterly returns'!X12)*(1+'Quarterly returns'!X13)*(1+'Quarterly returns'!X14)-1 -> 0.073398254 | O26: =C26-AVERAGE(C$21:C$97)+Forecast!$G$6 -> -0.12594945 | P26: =D26-AVERAGE(D$21:D$97)+Forecast!$G$7 -> -0.278036 | Q26: =E26-AVERAGE(E$21:E$97)+Forecast!$G$8 -> -0.11977271 | R26: =F26-AVERAGE(F$21:F$97)+Forecast!$G$9 -> -0.31441702 | S26: =G26-AVERAGE(G$21:G$97)+Forecast!$G$10 -> 0.60875998 | T26: =H26-AVERAGE(H$21:H$97)+Forecast!$G$11 -> -0.040108192 | U26: =I26-AVERAGE(I$21:I$97)+Forecast!$G$12 -> 0.093614624 | V26: =J26-AVERAGE(J$21:J$97)+Forecast!$G$13 -> -0.11692511 | W26: =K26-AVERAGE(K$21:K$97)+Forecast!$G$14 -> 0.052137151 | X26: =L26-AVERAGE(L$21:L$97)+Forecast!$G$15 -> 0.087289741 | Y26: =M26-AVERAGE(M$21:M$97)+Forecast!$G$16 -> 0.088453327 | Z26: =SUMPRODUCT($O26:$Y26,Risk!$B$56:$L$56) -> -0.11643319 | AA26: =SUMPRODUCT($O26:$Y26,Risk!$B$57:$L$57) -> -0.094793226 | AB26: =SUMPRODUCT($O26:$Y26,Risk!$B$58:$L$58) -> -0.11323477 | AC26: =SUMPRODUCT(MMULT($O26:$Y26,Portfolio!$C$127:$C$137)) -> -0.11562491 | AD26: =SUMPRODUCT(MMULT($O26:$Y26,Portfolio!$D$127:$D$137)) -> -0.12363603 | AE26: =SUMPRODUCT(MMULT($O26:$Y26,Portfolio!$E$127:$E$137)) -> -0.12471636 | AF26: =SUMPRODUCT(MMULT($O26:$Y26,Portfolio!$F$127:$F$137)) -> -0.097042974
A27: 7 | B27: ='Quarterly returns'!A15 -> 39721 | C27: =(1+'Quarterly returns'!N12)*(1+'Quarterly returns'!N13)*(1+'Quarterly returns'!N14)*(1+'Quarterly returns'!N15)-1 -> -0.2658937 | D27: =(1+'Quarterly returns'!O12)*(1+'Quarterly returns'!O13)*(1+'Quarterly returns'!O14)*(1+'Quarterly returns'!O15)-1 -> -0.15467771 | E27: =(1+'Quarterly returns'!P12)*(1+'Quarterly returns'!P13)*(1+'Quarterly returns'!P14)*(1+'Quarterly returns'!P15)-1 -> -0.19764563 | F27: =(1+'Quarterly returns'!Q12)*(1+'Quarterly returns'!Q13)*(1+'Quarterly returns'!Q14)*(1+'Quarterly returns'!Q15)-1 -> -0.13453207 | G27: =(1+'Quarterly returns'!R12)*(1+'Quarterly returns'!R13)*(1+'Quarterly returns'!R14)*(1+'Quarterly returns'!R15)-1 -> 0.2645613 | H27: =(1+'Quarterly returns'!S12)*(1+'Quarterly returns'!S13)*(1+'Quarterly returns'!S14)*(1+'Quarterly returns'!S15)-1 -> -0.08475359 | I27: =(1+'Quarterly returns'!T12)*(1+'Quarterly returns'!T13)*(1+'Quarterly returns'!T14)*(1+'Quarterly returns'!T15)-1 -> 0.10913578 | J27: =(1+'Quarterly returns'!U12)*(1+'Quarterly returns'!U13)*(1+'Quarterly returns'!U14)*(1+'Quarterly returns'!U15)-1 -> -0.0086868498 | ... M27: =(1+'Quarterly returns'!X12)*(1+'Quarterly returns'!X13)*(1+'Quarterly returns'!X14)*(1+'Quarterly returns'!X15)-1 -> 0.076533079 | O27: =C27-AVERAGE(C$21:C$97)+Forecast!$G$6 -> -0.27068941 | P27: =D27-AVERAGE(D$21:D$97)+Forecast!$G$7 -> -0.1828015 | Q27: =E27-AVERAGE(E$21:E$97)+Forecast!$G$8 -> -0.21603836 | R27: =F27-AVERAGE(F$21:F$97)+Forecast!$G$9 -> -0.12789424 | S27: =G27-AVERAGE(G$21:G$97)+Forecast!$G$10 -> 0.3174969 | T27: =H27-AVERAGE(H$21:H$97)+Forecast!$G$11 -> -0.10349752 | U27: =I27-AVERAGE(I$21:I$97)+Forecast!$G$12 -> 0.066806717 | V27: =J27-AVERAGE(J$21:J$97)+Forecast!$G$13 -> -0.08052658 | W27: =K27-AVERAGE(K$21:K$97)+Forecast!$G$14 -> 0.091661321 | X27: =L27-AVERAGE(L$21:L$97)+Forecast!$G$15 -> 0.077877804 | Y27: =M27-AVERAGE(M$21:M$97)+Forecast!$G$16 -> 0.091588151 | Z27: =SUMPRODUCT($O27:$Y27,Risk!$B$56:$L$56) -> -0.1312349 | AA27: =SUMPRODUCT($O27:$Y27,Risk!$B$57:$L$57) -> -0.10206821 | AB27: =SUMPRODUCT($O27:$Y27,Risk!$B$58:$L$58) -> -0.12010609 | AC27: =SUMPRODUCT(MMULT($O27:$Y27,Portfolio!$C$127:$C$137)) -> -0.12479564 | AD27: =SUMPRODUCT(MMULT($O27:$Y27,Portfolio!$D$127:$D$137)) -> -0.12505912 | AE27: =SUMPRODUCT(MMULT($O27:$Y27,Portfolio!$E$127:$E$137)) -> -0.12688278 | AF27: =SUMPRODUCT(MMULT($O27:$Y27,Portfolio!$F$127:$F$137)) -> -0.10886939
A28: 8 | B28: ='Quarterly returns'!A16 -> 39813 | C28: =(1+'Quarterly returns'!N13)*(1+'Quarterly returns'!N14)*(1+'Quarterly returns'!N15)*(1+'Quarterly returns'!N16)-1 -> -0.4038479 | D28: =(1+'Quarterly returns'!O13)*(1+'Quarterly returns'!O14)*(1+'Quarterly returns'!O15)*(1+'Quarterly returns'!O16)-1 -> -0.22299166 | E28: =(1+'Quarterly returns'!P13)*(1+'Quarterly returns'!P14)*(1+'Quarterly returns'!P15)*(1+'Quarterly returns'!P16)-1 -> -0.31677088 | F28: =(1+'Quarterly returns'!Q13)*(1+'Quarterly returns'!Q14)*(1+'Quarterly returns'!Q15)*(1+'Quarterly returns'!Q16)-1 -> -0.26961283 | G28: =(1+'Quarterly returns'!R13)*(1+'Quarterly returns'!R14)*(1+'Quarterly returns'!R15)*(1+'Quarterly returns'!R16)-1 -> -0.32606841 | H28: =(1+'Quarterly returns'!S13)*(1+'Quarterly returns'!S14)*(1+'Quarterly returns'!S15)*(1+'Quarterly returns'!S16)-1 -> -0.11962049 | I28: =(1+'Quarterly returns'!T13)*(1+'Quarterly returns'!T14)*(1+'Quarterly returns'!T15)*(1+'Quarterly returns'!T16)-1 -> 0.14524141 | J28: =(1+'Quarterly returns'!U13)*(1+'Quarterly returns'!U14)*(1+'Quarterly returns'!U15)*(1+'Quarterly returns'!U16)-1 -> -0.17635652 | ... M28: =(1+'Quarterly returns'!X13)*(1+'Quarterly returns'!X14)*(1+'Quarterly returns'!X15)*(1+'Quarterly returns'!X16)-1 -> 0.076012653 | O28: =C28-AVERAGE(C$21:C$97)+Forecast!$G$6 -> -0.40864361 | P28: =D28-AVERAGE(D$21:D$97)+Forecast!$G$7 -> -0.25111546 | Q28: =E28-AVERAGE(E$21:E$97)+Forecast!$G$8 -> -0.33516361 | R28: =F28-AVERAGE(F$21:F$97)+Forecast!$G$9 -> -0.262975 | S28: =G28-AVERAGE(G$21:G$97)+Forecast!$G$10 -> -0.27313282 | T28: =H28-AVERAGE(H$21:H$97)+Forecast!$G$11 -> -0.13836442 | U28: =I28-AVERAGE(I$21:I$97)+Forecast!$G$12 -> 0.10291235 | V28: =J28-AVERAGE(J$21:J$97)+Forecast!$G$13 -> -0.24819625 | W28: =K28-AVERAGE(K$21:K$97)+Forecast!$G$14 -> 0.15742469 | X28: =L28-AVERAGE(L$21:L$97)+Forecast!$G$15 -> 0.10053746 | Y28: =M28-AVERAGE(M$21:M$97)+Forecast!$G$16 -> 0.091067725 | Z28: =SUMPRODUCT($O28:$Y28,Risk!$B$56:$L$56) -> -0.20194659 | AA28: =SUMPRODUCT($O28:$Y28,Risk!$B$57:$L$57) -> -0.17180055 | AB28: =SUMPRODUCT($O28:$Y28,Risk!$B$58:$L$58) -> -0.2002636 | AC28: =SUMPRODUCT(MMULT($O28:$Y28,Portfolio!$C$127:$C$137)) -> -0.21128545 | AD28: =SUMPRODUCT(MMULT($O28:$Y28,Portfolio!$D$127:$D$137)) -> -0.18962601 | AE28: =SUMPRODUCT(MMULT($O28:$Y28,Portfolio!$E$127:$E$137)) -> -0.20887792 | AF28: =SUMPRODUCT(MMULT($O28:$Y28,Portfolio!$F$127:$F$137)) -> -0.15805438
A29: 9 | B29: ='Quarterly returns'!A17 -> 39903 | C29: =(1+'Quarterly returns'!N14)*(1+'Quarterly returns'!N15)*(1+'Quarterly returns'!N16)*(1+'Quarterly returns'!N17)-1 -> -0.31297256 | D29: =(1+'Quarterly returns'!O14)*(1+'Quarterly returns'!O15)*(1+'Quarterly returns'!O16)*(1+'Quarterly returns'!O17)-1 -> -0.17192276 | E29: =(1+'Quarterly returns'!P14)*(1+'Quarterly returns'!P15)*(1+'Quarterly returns'!P16)*(1+'Quarterly returns'!P17)-1 -> -0.16596511 | F29: =(1+'Quarterly returns'!Q14)*(1+'Quarterly returns'!Q15)*(1+'Quarterly returns'!Q16)*(1+'Quarterly returns'!Q17)-1 -> -0.39576538 | G29: =(1+'Quarterly returns'!R14)*(1+'Quarterly returns'!R15)*(1+'Quarterly returns'!R16)*(1+'Quarterly returns'!R17)-1 -> -0.42847359 | H29: =(1+'Quarterly returns'!S14)*(1+'Quarterly returns'!S15)*(1+'Quarterly returns'!S16)*(1+'Quarterly returns'!S17)-1 -> -0.048181229 | I29: =(1+'Quarterly returns'!T14)*(1+'Quarterly returns'!T15)*(1+'Quarterly returns'!T16)*(1+'Quarterly returns'!T17)-1 -> 0.18365663 | J29: =(1+'Quarterly returns'!U14)*(1+'Quarterly returns'!U15)*(1+'Quarterly returns'!U16)*(1+'Quarterly returns'!U17)-1 -> -0.19263941 | ... M29: =(1+'Quarterly returns'!X14)*(1+'Quarterly returns'!X15)*(1+'Quarterly returns'!X16)*(1+'Quarterly returns'!X17)-1 -> 0.066948708 | O29: =C29-AVERAGE(C$21:C$97)+Forecast!$G$6 -> -0.31776827 | P29: =D29-AVERAGE(D$21:D$97)+Forecast!$G$7 -> -0.20004655 | Q29: =E29-AVERAGE(E$21:E$97)+Forecast!$G$8 -> -0.18435783 | R29: =F29-AVERAGE(F$21:F$97)+Forecast!$G$9 -> -0.38912755 | S29: =G29-AVERAGE(G$21:G$97)+Forecast!$G$10 -> -0.37553799 | T29: =H29-AVERAGE(H$21:H$97)+Forecast!$G$11 -> -0.066925159 | U29: =I29-AVERAGE(I$21:I$97)+Forecast!$G$12 -> 0.14132757 | V29: =J29-AVERAGE(J$21:J$97)+Forecast!$G$13 -> -0.26447914 | W29: =K29-AVERAGE(K$21:K$97)+Forecast!$G$14 -> 0.13566869 | X29: =L29-AVERAGE(L$21:L$97)+Forecast!$G$15 -> 0.078353356 | Y29: =M29-AVERAGE(M$21:M$97)+Forecast!$G$16 -> 0.08200378 | Z29: =SUMPRODUCT($O29:$Y29,Risk!$B$56:$L$56) -> -0.17367054 | AA29: =SUMPRODUCT($O29:$Y29,Risk!$B$57:$L$57) -> -0.14470187 | AB29: =SUMPRODUCT($O29:$Y29,Risk!$B$58:$L$58) -> -0.17008721 | AC29: =SUMPRODUCT(MMULT($O29:$Y29,Portfolio!$C$127:$C$137)) -> -0.17980481 | AD29: =SUMPRODUCT(MMULT($O29:$Y29,Portfolio!$D$127:$D$137)) -> -0.15675581 | AE29: =SUMPRODUCT(MMULT($O29:$Y29,Portfolio!$E$127:$E$137)) -> -0.17970814 | AF29: =SUMPRODUCT(MMULT($O29:$Y29,Portfolio!$F$127:$F$137)) -> -0.12198752
A30: 10 | B30: ='Quarterly returns'!A18 -> 39994 | C30: =(1+'Quarterly returns'!N15)*(1+'Quarterly returns'!N16)*(1+'Quarterly returns'!N17)*(1+'Quarterly returns'!N18)-1 -> -0.22145824 | D30: =(1+'Quarterly returns'!O15)*(1+'Quarterly returns'!O16)*(1+'Quarterly returns'!O17)*(1+'Quarterly returns'!O18)-1 -> -0.11950003 | E30: =(1+'Quarterly returns'!P15)*(1+'Quarterly returns'!P16)*(1+'Quarterly returns'!P17)*(1+'Quarterly returns'!P18)-1 -> -0.046944878 | F30: =(1+'Quarterly returns'!Q15)*(1+'Quarterly returns'!Q16)*(1+'Quarterly returns'!Q17)*(1+'Quarterly returns'!Q18)-1 -> -0.26060245 | G30: =(1+'Quarterly returns'!R15)*(1+'Quarterly returns'!R16)*(1+'Quarterly returns'!R17)*(1+'Quarterly returns'!R18)-1 -> -0.52139285 | H30: =(1+'Quarterly returns'!S15)*(1+'Quarterly returns'!S16)*(1+'Quarterly returns'!S17)*(1+'Quarterly returns'!S18)-1 -> 0.10586663 | I30: =(1+'Quarterly returns'!T15)*(1+'Quarterly returns'!T16)*(1+'Quarterly returns'!T17)*(1+'Quarterly returns'!T18)-1 -> 0.11366254 | J30: =(1+'Quarterly returns'!U15)*(1+'Quarterly returns'!U16)*(1+'Quarterly returns'!U17)*(1+'Quarterly returns'!U18)-1 -> -0.15706374 | ... M30: =(1+'Quarterly returns'!X15)*(1+'Quarterly returns'!X16)*(1+'Quarterly returns'!X17)*(1+'Quarterly returns'!X18)-1 -> 0.054753514 | O30: =C30-AVERAGE(C$21:C$97)+Forecast!$G$6 -> -0.22625395 | P30: =D30-AVERAGE(D$21:D$97)+Forecast!$G$7 -> -0.14762382 | Q30: =E30-AVERAGE(E$21:E$97)+Forecast!$G$8 -> -0.065337606 | R30: =F30-AVERAGE(F$21:F$97)+Forecast!$G$9 -> -0.25396462 | S30: =G30-AVERAGE(G$21:G$97)+Forecast!$G$10 -> -0.46845726 | T30: =H30-AVERAGE(H$21:H$97)+Forecast!$G$11 -> 0.087122705 | U30: =I30-AVERAGE(I$21:I$97)+Forecast!$G$12 -> 0.071333478 | V30: =J30-AVERAGE(J$21:J$97)+Forecast!$G$13 -> -0.22890347 | W30: =K30-AVERAGE(K$21:K$97)+Forecast!$G$14 -> 0.11614812 | X30: =L30-AVERAGE(L$21:L$97)+Forecast!$G$15 -> 0.10778221 | Y30: =M30-AVERAGE(M$21:M$97)+Forecast!$G$16 -> 0.069808586 | Z30: =SUMPRODUCT($O30:$Y30,Risk!$B$56:$L$56) -> -0.11449141 | AA30: =SUMPRODUCT($O30:$Y30,Risk!$B$57:$L$57) -> -0.091259927 | AB30: =SUMPRODUCT($O30:$Y30,Risk!$B$58:$L$58) -> -0.11174808 | AC30: =SUMPRODUCT(MMULT($O30:$Y30,Portfolio!$C$127:$C$137)) -> -0.116823 | AD30: =SUMPRODUCT(MMULT($O30:$Y30,Portfolio!$D$127:$D$137)) -> -0.09577792 | AE30: =SUMPRODUCT(MMULT($O30:$Y30,Portfolio!$E$127:$E$137)) -> -0.12001483 | AF30: =SUMPRODUCT(MMULT($O30:$Y30,Portfolio!$F$127:$F$137)) -> -0.074688179
A31: 11 | B31: ='Quarterly returns'!A19 -> 40086 | C31: =(1+'Quarterly returns'!N16)*(1+'Quarterly returns'!N17)*(1+'Quarterly returns'!N18)*(1+'Quarterly returns'!N19)-1 -> 0.074009587 | D31: =(1+'Quarterly returns'!O16)*(1+'Quarterly returns'!O17)*(1+'Quarterly returns'!O18)*(1+'Quarterly returns'!O19)-1 -> -0.14088503 | E31: =(1+'Quarterly returns'!P16)*(1+'Quarterly returns'!P17)*(1+'Quarterly returns'!P18)*(1+'Quarterly returns'!P19)-1 -> 0.05914805 | F31: =(1+'Quarterly returns'!Q16)*(1+'Quarterly returns'!Q17)*(1+'Quarterly returns'!Q18)*(1+'Quarterly returns'!Q19)-1 -> -0.2818556 | G31: =(1+'Quarterly returns'!R16)*(1+'Quarterly returns'!R17)*(1+'Quarterly returns'!R18)*(1+'Quarterly returns'!R19)-1 -> -0.50413963 | H31: =(1+'Quarterly returns'!S16)*(1+'Quarterly returns'!S17)*(1+'Quarterly returns'!S18)*(1+'Quarterly returns'!S19)-1 -> 0.21066024 | I31: =(1+'Quarterly returns'!T16)*(1+'Quarterly returns'!T17)*(1+'Quarterly returns'!T18)*(1+'Quarterly returns'!T19)-1 -> 0.09272698 | J31: =(1+'Quarterly returns'!U16)*(1+'Quarterly returns'!U17)*(1+'Quarterly returns'!U18)*(1+'Quarterly returns'!U19)-1 -> -0.047673541 | ... M31: =(1+'Quarterly returns'!X16)*(1+'Quarterly returns'!X17)*(1+'Quarterly returns'!X18)*(1+'Quarterly returns'!X19)-1 -> 0.043050901 | O31: =C31-AVERAGE(C$21:C$97)+Forecast!$G$6 -> 0.069213879 | P31: =D31-AVERAGE(D$21:D$97)+Forecast!$G$7 -> -0.16900882 | Q31: =E31-AVERAGE(E$21:E$97)+Forecast!$G$8 -> 0.040755322 | R31: =F31-AVERAGE(F$21:F$97)+Forecast!$G$9 -> -0.27521777 | S31: =G31-AVERAGE(G$21:G$97)+Forecast!$G$10 -> -0.45120403 | T31: =H31-AVERAGE(H$21:H$97)+Forecast!$G$11 -> 0.19191631 | U31: =I31-AVERAGE(I$21:I$97)+Forecast!$G$12 -> 0.050397922 | V31: =J31-AVERAGE(J$21:J$97)+Forecast!$G$13 -> -0.11951327 | W31: =K31-AVERAGE(K$21:K$97)+Forecast!$G$14 -> 0.078675479 | X31: =L31-AVERAGE(L$21:L$97)+Forecast!$G$15 -> 0.1281097 | Y31: =M31-AVERAGE(M$21:M$97)+Forecast!$G$16 -> 0.058105973 | Z31: =SUMPRODUCT($O31:$Y31,Risk!$B$56:$L$56) -> -0.0075204748 | AA31: =SUMPRODUCT($O31:$Y31,Risk!$B$57:$L$57) -> -0.015953145 | AB31: =SUMPRODUCT($O31:$Y31,Risk!$B$58:$L$58) -> -0.033218187 | AC31: =SUMPRODUCT(MMULT($O31:$Y31,Portfolio!$C$127:$C$137)) -> -0.034674874 | AD31: =SUMPRODUCT(MMULT($O31:$Y31,Portfolio!$D$127:$D$137)) -> -0.016616858 | AE31: =SUMPRODUCT(MMULT($O31:$Y31,Portfolio!$E$127:$E$137)) -> -0.038415044 | AF31: =SUMPRODUCT(MMULT($O31:$Y31,Portfolio!$F$127:$F$137)) -> 0.0094124153
A32: 12 | B32: ='Quarterly returns'!A20 -> 40178 | C32: =(1+'Quarterly returns'!N17)*(1+'Quarterly returns'!N18)*(1+'Quarterly returns'!N19)*(1+'Quarterly returns'!N20)-1 -> 0.39578084 | D32: =(1+'Quarterly returns'!O17)*(1+'Quarterly returns'!O18)*(1+'Quarterly returns'!O19)*(1+'Quarterly returns'!O20)-1 -> -0.019242585 | E32: =(1+'Quarterly returns'!P17)*(1+'Quarterly returns'!P18)*(1+'Quarterly returns'!P19)*(1+'Quarterly returns'!P20)-1 -> 0.26176449 | F32: =(1+'Quarterly returns'!Q17)*(1+'Quarterly returns'!Q18)*(1+'Quarterly returns'!Q19)*(1+'Quarterly returns'!Q20)-1 -> -0.013953674 | G32: =(1+'Quarterly returns'!R17)*(1+'Quarterly returns'!R18)*(1+'Quarterly returns'!R19)*(1+'Quarterly returns'!R20)-1 -> -0.12023439 | H32: =(1+'Quarterly returns'!S17)*(1+'Quarterly returns'!S18)*(1+'Quarterly returns'!S19)*(1+'Quarterly returns'!S20)-1 -> 0.30427874 | I32: =(1+'Quarterly returns'!T17)*(1+'Quarterly returns'!T18)*(1+'Quarterly returns'!T19)*(1+'Quarterly returns'!T20)-1 -> 0.019979247 | J32: =(1+'Quarterly returns'!U17)*(1+'Quarterly returns'!U18)*(1+'Quarterly returns'!U19)*(1+'Quarterly returns'!U20)-1 -> 0.12440691 | ... M32: =(1+'Quarterly returns'!X17)*(1+'Quarterly returns'!X18)*(1+'Quarterly returns'!X19)*(1+'Quarterly returns'!X20)-1 -> 0.034749247 | O32: =C32-AVERAGE(C$21:C$97)+Forecast!$G$6 -> 0.39098513 | P32: =D32-AVERAGE(D$21:D$97)+Forecast!$G$7 -> -0.047366377 | Q32: =E32-AVERAGE(E$21:E$97)+Forecast!$G$8 -> 0.24337177 | R32: =F32-AVERAGE(F$21:F$97)+Forecast!$G$9 -> -0.0073158412 | S32: =G32-AVERAGE(G$21:G$97)+Forecast!$G$10 -> -0.067298792 | T32: =H32-AVERAGE(H$21:H$97)+Forecast!$G$11 -> 0.28553481 | U32: =I32-AVERAGE(I$21:I$97)+Forecast!$G$12 -> -0.022349812 | V32: =J32-AVERAGE(J$21:J$97)+Forecast!$G$13 -> 0.052567181 | W32: =K32-AVERAGE(K$21:K$97)+Forecast!$G$14 -> 0.02527314 | X32: =L32-AVERAGE(L$21:L$97)+Forecast!$G$15 -> 0.088558278 | Y32: =M32-AVERAGE(M$21:M$97)+Forecast!$G$16 -> 0.049804319 | Z32: =SUMPRODUCT($O32:$Y32,Risk!$B$56:$L$56) -> 0.16055113 | AA32: =SUMPRODUCT($O32:$Y32,Risk!$B$57:$L$57) -> 0.12177846 | AB32: =SUMPRODUCT($O32:$Y32,Risk!$B$58:$L$58) -> 0.12335874 | AC32: =SUMPRODUCT(MMULT($O32:$Y32,Portfolio!$C$127:$C$137)) -> 0.12979671 | AD32: =SUMPRODUCT(MMULT($O32:$Y32,Portfolio!$D$127:$D$137)) -> 0.12837822 | AE32: =SUMPRODUCT(MMULT($O32:$Y32,Portfolio!$E$127:$E$137)) -> 0.1230715 | AF32: =SUMPRODUCT(MMULT($O32:$Y32,Portfolio!$F$127:$F$137)) -> 0.1310705
... A97: 77 | B97: ='Quarterly returns'!A85 -> 46112 | C97: =(1+'Quarterly returns'!N82)*(1+'Quarterly returns'!N83)*(1+'Quarterly returns'!N84)*(1+'Quarterly returns'!N85)-1 -> 0.11289283 | D97: =(1+'Quarterly returns'!O82)*(1+'Quarterly returns'!O83)*(1+'Quarterly returns'!O84)*(1+'Quarterly returns'!O85)-1 -> 0.076715847 | E97: =(1+'Quarterly returns'!P82)*(1+'Quarterly returns'!P83)*(1+'Quarterly returns'!P84)*(1+'Quarterly returns'!P85)-1 -> 0.19514665 | F97: =(1+'Quarterly returns'!Q82)*(1+'Quarterly returns'!Q83)*(1+'Quarterly returns'!Q84)*(1+'Quarterly returns'!Q85)-1 -> -0.023292145 | G97: =(1+'Quarterly returns'!R82)*(1+'Quarterly returns'!R83)*(1+'Quarterly returns'!R84)*(1+'Quarterly returns'!R85)-1 -> 0.30103221 | H97: =(1+'Quarterly returns'!S82)*(1+'Quarterly returns'!S83)*(1+'Quarterly returns'!S84)*(1+'Quarterly returns'!S85)-1 -> 0.1099981 | I97: =(1+'Quarterly returns'!T82)*(1+'Quarterly returns'!T83)*(1+'Quarterly returns'!T84)*(1+'Quarterly returns'!T85)-1 -> 0.077523115 | J97: =(1+'Quarterly returns'!U82)*(1+'Quarterly returns'!U83)*(1+'Quarterly returns'!U84)*(1+'Quarterly returns'!U85)-1 -> -0.14855998 | ... M97: =(1+'Quarterly returns'!X82)*(1+'Quarterly returns'!X83)*(1+'Quarterly returns'!X84)*(1+'Quarterly returns'!X85)-1 -> 0.037995149 | O97: =C97-AVERAGE(C$21:C$97)+Forecast!$G$6 -> 0.10809713 | P97: =D97-AVERAGE(D$21:D$97)+Forecast!$G$7 -> 0.048592055 | Q97: =E97-AVERAGE(E$21:E$97)+Forecast!$G$8 -> 0.17675392 | R97: =F97-AVERAGE(F$21:F$97)+Forecast!$G$9 -> -0.016654312 | S97: =G97-AVERAGE(G$21:G$97)+Forecast!$G$10 -> 0.3539678 | T97: =H97-AVERAGE(H$21:H$97)+Forecast!$G$11 -> 0.091254175 | U97: =I97-AVERAGE(I$21:I$97)+Forecast!$G$12 -> 0.035194057 | V97: =J97-AVERAGE(J$21:J$97)+Forecast!$G$13 -> -0.22039971 | W97: =K97-AVERAGE(K$21:K$97)+Forecast!$G$14 -> 0.021508175 | X97: =L97-AVERAGE(L$21:L$97)+Forecast!$G$15 -> 0.021381427 | Y97: =M97-AVERAGE(M$21:M$97)+Forecast!$G$16 -> 0.053050222 | Z97: =SUMPRODUCT($O97:$Y97,Risk!$B$56:$L$56) -> 0.059942086 | AA97: =SUMPRODUCT($O97:$Y97,Risk!$B$57:$L$57) -> 0.055863694 | AB97: =SUMPRODUCT($O97:$Y97,Risk!$B$58:$L$58) -> 0.068622977 | AC97: =SUMPRODUCT(MMULT($O97:$Y97,Portfolio!$C$127:$C$137)) -> 0.069243304 | AD97: =SUMPRODUCT(MMULT($O97:$Y97,Portfolio!$D$127:$D$137)) -> 0.060997114 | AE97: =SUMPRODUCT(MMULT($O97:$Y97,Portfolio!$E$127:$E$137)) -> 0.056924931 | AF97: =SUMPRODUCT(MMULT($O97:$Y97,Portfolio!$F$127:$F$137)) -> 0.057596215
A99: 3. Simulated paths (draws pasted, seed in Inputs)
A101: Path | B101: Draw 1 | C101: Draw 2 | D101: Draw 3 | E101: Draw 4 | F101: Draw 5 | G101: Current | H101: Benchmark | I101: Recommended | J101: Relative: current (log) | K101: Relative: recommended (log) | L101: Alternatives fixed by scorecard | M101: No alternatives | N101: Alternatives at benchmark weights | O101: Core five only | P101: Relative: alternatives fixed by scorecard (log) | Q101: Relative: no alternatives (log) | R101: Relative: alternatives at benchmark weights (log) | S101: Relative: core five only (log)
A102: 1 | B102: 56 | C102: 27 | D102: 32 | E102: 43 | F102: 73 | G102: =(1+INDEX($Z$21:$Z$97,B102))*(1+INDEX($Z$21:$Z$97,C102))*(1+INDEX($Z$21:$Z$97,D102))*(1+INDEX($Z$21:$Z$97,E102))*(1+INDEX($Z$21:$Z$97,F102))-1 -> 0.51041739 | H102: =(1+INDEX($AA$21:$AA$97,B102))*(1+INDEX($AA$21:$AA$97,C102))*(1+INDEX($AA$21:$AA$97,D102))*(1+INDEX($AA$21:$AA$97,E102))*(1+INDEX($AA$21:$AA$97,F102))-1 -> 0.49384738 | I102: =(1+INDEX($AB$21:$AB$97,B102))*(1+INDEX($AB$21:$AB$97,C102))*(1+INDEX($AB$21:$AB$97,D102))*(1+INDEX($AB$21:$AB$97,E102))*(1+INDEX($AB$21:$AB$97,F102))-1 -> 0.56468446 | J102: =LN((1+G102)/(1+H102)) -> 0.011031103 | K102: =LN((1+I102)/(1+H102)) -> 0.046329251 | L102: =(1+INDEX($AC$21:$AC$97,B102))*(1+INDEX($AC$21:$AC$97,C102))*(1+INDEX($AC$21:$AC$97,D102))*(1+INDEX($AC$21:$AC$97,E102))*(1+INDEX($AC$21:$AC$97,F102))-1 -> 0.5456404 | M102: =(1+INDEX($AD$21:$AD$97,B102))*(1+INDEX($AD$21:$AD$97,C102))*(1+INDEX($AD$21:$AD$97,D102))*(1+INDEX($AD$21:$AD$97,E102))*(1+INDEX($AD$21:$AD$97,F102))-1 -> 0.57754588 | N102: =(1+INDEX($AE$21:$AE$97,B102))*(1+INDEX($AE$21:$AE$97,C102))*(1+INDEX($AE$21:$AE$97,D102))*(1+INDEX($AE$21:$AE$97,E102))*(1+INDEX($AE$21:$AE$97,F102))-1 -> 0.53391564 | O102: =(1+INDEX($AF$21:$AF$97,B102))*(1+INDEX($AF$21:$AF$97,C102))*(1+INDEX($AF$21:$AF$97,D102))*(1+INDEX($AF$21:$AF$97,E102))*(1+INDEX($AF$21:$AF$97,F102))-1 -> 0.52718194 | P102: =LN((1+L102)/(1+H102)) -> 0.034083393 | Q102: =LN((1+M102)/(1+H102)) -> 0.054515469 | R102: =LN((1+N102)/(1+H102)) -> 0.026468783 | S102: =LN((1+O102)/(1+H102)) -> 0.022069239
A103: 2 | B103: 49 | C103: 59 | D103: 39 | E103: 14 | F103: 56 | G103: =(1+INDEX($Z$21:$Z$97,B103))*(1+INDEX($Z$21:$Z$97,C103))*(1+INDEX($Z$21:$Z$97,D103))*(1+INDEX($Z$21:$Z$97,E103))*(1+INDEX($Z$21:$Z$97,F103))-1 -> 0.64829911 | H103: =(1+INDEX($AA$21:$AA$97,B103))*(1+INDEX($AA$21:$AA$97,C103))*(1+INDEX($AA$21:$AA$97,D103))*(1+INDEX($AA$21:$AA$97,E103))*(1+INDEX($AA$21:$AA$97,F103))-1 -> 0.54694713 | I103: =(1+INDEX($AB$21:$AB$97,B103))*(1+INDEX($AB$21:$AB$97,C103))*(1+INDEX($AB$21:$AB$97,D103))*(1+INDEX($AB$21:$AB$97,E103))*(1+INDEX($AB$21:$AB$97,F103))-1 -> 0.59679731 | J103: =LN((1+G103)/(1+H103)) -> 0.063460519 | K103: =LN((1+I103)/(1+H103)) -> 0.031716544 | L103: =(1+INDEX($AC$21:$AC$97,B103))*(1+INDEX($AC$21:$AC$97,C103))*(1+INDEX($AC$21:$AC$97,D103))*(1+INDEX($AC$21:$AC$97,E103))*(1+INDEX($AC$21:$AC$97,F103))-1 -> 0.59431387 | M103: =(1+INDEX($AD$21:$AD$97,B103))*(1+INDEX($AD$21:$AD$97,C103))*(1+INDEX($AD$21:$AD$97,D103))*(1+INDEX($AD$21:$AD$97,E103))*(1+INDEX($AD$21:$AD$97,F103))-1 -> 0.59681726 | N103: =(1+INDEX($AE$21:$AE$97,B103))*(1+INDEX($AE$21:$AE$97,C103))*(1+INDEX($AE$21:$AE$97,D103))*(1+INDEX($AE$21:$AE$97,E103))*(1+INDEX($AE$21:$AE$97,F103))-1 -> 0.58984953 | O103: =(1+INDEX($AF$21:$AF$97,B103))*(1+INDEX($AF$21:$AF$97,C103))*(1+INDEX($AF$21:$AF$97,D103))*(1+INDEX($AF$21:$AF$97,E103))*(1+INDEX($AF$21:$AF$97,F103))-1 -> 0.55478749 | P103: =LN((1+L103)/(1+H103)) -> 0.03016007 | Q103: =LN((1+M103)/(1+H103)) -> 0.031729037 | R103: =LN((1+N103)/(1+H103)) -> 0.027355978 | S103: =LN((1+O103)/(1+H103)) -> 0.0050554774
A104: 3 | B104: 73 | C104: 20 | D104: 44 | E104: 16 | F104: 7 | G104: =(1+INDEX($Z$21:$Z$97,B104))*(1+INDEX($Z$21:$Z$97,C104))*(1+INDEX($Z$21:$Z$97,D104))*(1+INDEX($Z$21:$Z$97,E104))*(1+INDEX($Z$21:$Z$97,F104))-1 -> -0.019247502 | H104: =(1+INDEX($AA$21:$AA$97,B104))*(1+INDEX($AA$21:$AA$97,C104))*(1+INDEX($AA$21:$AA$97,D104))*(1+INDEX($AA$21:$AA$97,E104))*(1+INDEX($AA$21:$AA$97,F104))-1 -> 0.0071575325 | I104: =(1+INDEX($AB$21:$AB$97,B104))*(1+INDEX($AB$21:$AB$97,C104))*(1+INDEX($AB$21:$AB$97,D104))*(1+INDEX($AB$21:$AB$97,E104))*(1+INDEX($AB$21:$AB$97,F104))-1 -> -0.00030552176 | J104: =LN((1+G104)/(1+H104)) -> -0.026567186 | K104: =LN((1+I104)/(1+H104)) -> -0.0074376074 | L104: =(1+INDEX($AC$21:$AC$97,B104))*(1+INDEX($AC$21:$AC$97,C104))*(1+INDEX($AC$21:$AC$97,D104))*(1+INDEX($AC$21:$AC$97,E104))*(1+INDEX($AC$21:$AC$97,F104))-1 -> -0.027559187 | M104: =(1+INDEX($AD$21:$AD$97,B104))*(1+INDEX($AD$21:$AD$97,C104))*(1+INDEX($AD$21:$AD$97,D104))*(1+INDEX($AD$21:$AD$97,E104))*(1+INDEX($AD$21:$AD$97,F104))-1 -> -0.0034137471 | N104: =(1+INDEX($AE$21:$AE$97,B104))*(1+INDEX($AE$21:$AE$97,C104))*(1+INDEX($AE$21:$AE$97,D104))*(1+INDEX($AE$21:$AE$97,E104))*(1+INDEX($AE$21:$AE$97,F104))-1 -> -0.039028079 | O104: =(1+INDEX($AF$21:$AF$97,B104))*(1+INDEX($AF$21:$AF$97,C104))*(1+INDEX($AF$21:$AF$97,D104))*(1+INDEX($AF$21:$AF$97,E104))*(1+INDEX($AF$21:$AF$97,F104))-1 -> 0.012150737 | P104: =LN((1+L104)/(1+H104)) -> -0.035078105 | Q104: =LN((1+M104)/(1+H104)) -> -0.010551626 | R104: =LN((1+N104)/(1+H104)) -> -0.046942128 | S104: =LN((1+O104)/(1+H104)) -> 0.0049454709
A105: 4 | B105: 43 | C105: 8 | D105: 53 | E105: 26 | F105: 64 | G105: =(1+INDEX($Z$21:$Z$97,B105))*(1+INDEX($Z$21:$Z$97,C105))*(1+INDEX($Z$21:$Z$97,D105))*(1+INDEX($Z$21:$Z$97,E105))*(1+INDEX($Z$21:$Z$97,F105))-1 -> -0.11124541 | H105: =(1+INDEX($AA$21:$AA$97,B105))*(1+INDEX($AA$21:$AA$97,C105))*(1+INDEX($AA$21:$AA$97,D105))*(1+INDEX($AA$21:$AA$97,E105))*(1+INDEX($AA$21:$AA$97,F105))-1 -> -0.058971036 | I105: =(1+INDEX($AB$21:$AB$97,B105))*(1+INDEX($AB$21:$AB$97,C105))*(1+INDEX($AB$21:$AB$97,D105))*(1+INDEX($AB$21:$AB$97,E105))*(1+INDEX($AB$21:$AB$97,F105))-1 -> -0.078779339 | J105: =LN((1+G105)/(1+H105)) -> -0.05715277 | K105: =LN((1+I105)/(1+H105)) -> -0.021274323 | L105: =(1+INDEX($AC$21:$AC$97,B105))*(1+INDEX($AC$21:$AC$97,C105))*(1+INDEX($AC$21:$AC$97,D105))*(1+INDEX($AC$21:$AC$97,E105))*(1+INDEX($AC$21:$AC$97,F105))-1 -> -0.090003008 | M105: =(1+INDEX($AD$21:$AD$97,B105))*(1+INDEX($AD$21:$AD$97,C105))*(1+INDEX($AD$21:$AD$97,D105))*(1+INDEX($AD$21:$AD$97,E105))*(1+INDEX($AD$21:$AD$97,F105))-1 -> -0.074942348 | N105: =(1+INDEX($AE$21:$AE$97,B105))*(1+INDEX($AE$21:$AE$97,C105))*(1+INDEX($AE$21:$AE$97,D105))*(1+INDEX($AE$21:$AE$97,E105))*(1+INDEX($AE$21:$AE$97,F105))-1 -> -0.092332522 | O105: =(1+INDEX($AF$21:$AF$97,B105))*(1+INDEX($AF$21:$AF$97,C105))*(1+INDEX($AF$21:$AF$97,D105))*(1+INDEX($AF$21:$AF$97,E105))*(1+INDEX($AF$21:$AF$97,F105))-1 -> -0.038957378 | P105: =LN((1+L105)/(1+H105)) -> -0.033532626 | Q105: =LN((1+M105)/(1+H105)) -> -0.017117857 | R105: =LN((1+N105)/(1+H105)) -> -0.036095821 | S105: =LN((1+O105)/(1+H105)) -> 0.02104484
A106: 5 | B106: 4 | C106: 9 | D106: 64 | E106: 58 | F106: 56 | G106: =(1+INDEX($Z$21:$Z$97,B106))*(1+INDEX($Z$21:$Z$97,C106))*(1+INDEX($Z$21:$Z$97,D106))*(1+INDEX($Z$21:$Z$97,E106))*(1+INDEX($Z$21:$Z$97,F106))-1 -> -0.036921436 | H106: =(1+INDEX($AA$21:$AA$97,B106))*(1+INDEX($AA$21:$AA$97,C106))*(1+INDEX($AA$21:$AA$97,D106))*(1+INDEX($AA$21:$AA$97,E106))*(1+INDEX($AA$21:$AA$97,F106))-1 -> -0.0074054058 | I106: =(1+INDEX($AB$21:$AB$97,B106))*(1+INDEX($AB$21:$AB$97,C106))*(1+INDEX($AB$21:$AB$97,D106))*(1+INDEX($AB$21:$AB$97,E106))*(1+INDEX($AB$21:$AB$97,F106))-1 -> -0.045328087 | J106: =LN((1+G106)/(1+H106)) -> -0.030187326 | K106: =LN((1+I106)/(1+H106)) -> -0.038954582 | L106: =(1+INDEX($AC$21:$AC$97,B106))*(1+INDEX($AC$21:$AC$97,C106))*(1+INDEX($AC$21:$AC$97,D106))*(1+INDEX($AC$21:$AC$97,E106))*(1+INDEX($AC$21:$AC$97,F106))-1 -> -0.042528915 | M106: =(1+INDEX($AD$21:$AD$97,B106))*(1+INDEX($AD$21:$AD$97,C106))*(1+INDEX($AD$21:$AD$97,D106))*(1+INDEX($AD$21:$AD$97,E106))*(1+INDEX($AD$21:$AD$97,F106))-1 -> -0.047831386 | N106: =(1+INDEX($AE$21:$AE$97,B106))*(1+INDEX($AE$21:$AE$97,C106))*(1+INDEX($AE$21:$AE$97,D106))*(1+INDEX($AE$21:$AE$97,E106))*(1+INDEX($AE$21:$AE$97,F106))-1 -> -0.048458074 | O106: =(1+INDEX($AF$21:$AF$97,B106))*(1+INDEX($AF$21:$AF$97,C106))*(1+INDEX($AF$21:$AF$97,D106))*(1+INDEX($AF$21:$AF$97,E106))*(1+INDEX($AF$21:$AF$97,F106))-1 -> 0.012657387 | P106: =LN((1+L106)/(1+H106)) -> -0.036026795 | Q106: =LN((1+M106)/(1+H106)) -> -0.041580182 | R106: =LN((1+N106)/(1+H106)) -> -0.042238568 | S106: =LN((1+O106)/(1+H106)) -> 0.020010914
A107: 6 | B107: 2 | C107: 63 | D107: 12 | E107: 3 | F107: 39 | G107: =(1+INDEX($Z$21:$Z$97,B107))*(1+INDEX($Z$21:$Z$97,C107))*(1+INDEX($Z$21:$Z$97,D107))*(1+INDEX($Z$21:$Z$97,E107))*(1+INDEX($Z$21:$Z$97,F107))-1 -> 0.49723621 | H107: =(1+INDEX($AA$21:$AA$97,B107))*(1+INDEX($AA$21:$AA$97,C107))*(1+INDEX($AA$21:$AA$97,D107))*(1+INDEX($AA$21:$AA$97,E107))*(1+INDEX($AA$21:$AA$97,F107))-1 -> 0.34279373 | I107: =(1+INDEX($AB$21:$AB$97,B107))*(1+INDEX($AB$21:$AB$97,C107))*(1+INDEX($AB$21:$AB$97,D107))*(1+INDEX($AB$21:$AB$97,E107))*(1+INDEX($AB$21:$AB$97,F107))-1 -> 0.35657138 | J107: =LN((1+G107)/(1+H107)) -> 0.10886857 | K107: =LN((1+I107)/(1+H107)) -> 0.010208157 | L107: =(1+INDEX($AC$21:$AC$97,B107))*(1+INDEX($AC$21:$AC$97,C107))*(1+INDEX($AC$21:$AC$97,D107))*(1+INDEX($AC$21:$AC$97,E107))*(1+INDEX($AC$21:$AC$97,F107))-1 -> 0.3644147 | M107: =(1+INDEX($AD$21:$AD$97,B107))*(1+INDEX($AD$21:$AD$97,C107))*(1+INDEX($AD$21:$AD$97,D107))*(1+INDEX($AD$21:$AD$97,E107))*(1+INDEX($AD$21:$AD$97,F107))-1 -> 0.36054255 | N107: =(1+INDEX($AE$21:$AE$97,B107))*(1+INDEX($AE$21:$AE$97,C107))*(1+INDEX($AE$21:$AE$97,D107))*(1+INDEX($AE$21:$AE$97,E107))*(1+INDEX($AE$21:$AE$97,F107))-1 -> 0.35114928 | O107: =(1+INDEX($AF$21:$AF$97,B107))*(1+INDEX($AF$21:$AF$97,C107))*(1+INDEX($AF$21:$AF$97,D107))*(1+INDEX($AF$21:$AF$97,E107))*(1+INDEX($AF$21:$AF$97,F107))-1 -> 0.37250017 | P107: =LN((1+L107)/(1+H107)) -> 0.015973229 | Q107: =LN((1+M107)/(1+H107)) -> 0.013131237 | R107: =LN((1+N107)/(1+H107)) -> 0.0062032364 | S107: =LN((1+O107)/(1+H107)) -> 0.021881708
A108: 7 | B108: 21 | C108: 73 | D108: 41 | E108: 77 | F108: 30 | G108: =(1+INDEX($Z$21:$Z$97,B108))*(1+INDEX($Z$21:$Z$97,C108))*(1+INDEX($Z$21:$Z$97,D108))*(1+INDEX($Z$21:$Z$97,E108))*(1+INDEX($Z$21:$Z$97,F108))-1 -> 0.42938239 | H108: =(1+INDEX($AA$21:$AA$97,B108))*(1+INDEX($AA$21:$AA$97,C108))*(1+INDEX($AA$21:$AA$97,D108))*(1+INDEX($AA$21:$AA$97,E108))*(1+INDEX($AA$21:$AA$97,F108))-1 -> 0.41575601 | I108: =(1+INDEX($AB$21:$AB$97,B108))*(1+INDEX($AB$21:$AB$97,C108))*(1+INDEX($AB$21:$AB$97,D108))*(1+INDEX($AB$21:$AB$97,E108))*(1+INDEX($AB$21:$AB$97,F108))-1 -> 0.46292797 | J108: =LN((1+G108)/(1+H108)) -> 0.0095787871 | K108: =LN((1+I108)/(1+H108)) -> 0.032776218 | L108: =(1+INDEX($AC$21:$AC$97,B108))*(1+INDEX($AC$21:$AC$97,C108))*(1+INDEX($AC$21:$AC$97,D108))*(1+INDEX($AC$21:$AC$97,E108))*(1+INDEX($AC$21:$AC$97,F108))-1 -> 0.45680053 | M108: =(1+INDEX($AD$21:$AD$97,B108))*(1+INDEX($AD$21:$AD$97,C108))*(1+INDEX($AD$21:$AD$97,D108))*(1+INDEX($AD$21:$AD$97,E108))*(1+INDEX($AD$21:$AD$97,F108))-1 -> 0.44798263 | N108: =(1+INDEX($AE$21:$AE$97,B108))*(1+INDEX($AE$21:$AE$97,C108))*(1+INDEX($AE$21:$AE$97,D108))*(1+INDEX($AE$21:$AE$97,E108))*(1+INDEX($AE$21:$AE$97,F108))-1 -> 0.42867149 | O108: =(1+INDEX($AF$21:$AF$97,B108))*(1+INDEX($AF$21:$AF$97,C108))*(1+INDEX($AF$21:$AF$97,D108))*(1+INDEX($AF$21:$AF$97,E108))*(1+INDEX($AF$21:$AF$97,F108))-1 -> 0.43391907 | P108: =LN((1+L108)/(1+H108)) -> 0.028578943 | Q108: =LN((1+M108)/(1+H108)) -> 0.02250763 | R108: =LN((1+N108)/(1+H108)) -> 0.0090813139 | S108: =LN((1+O108)/(1+H108)) -> 0.012747636
A109: 8 | B109: 31 | C109: 25 | D109: 33 | E109: 11 | F109: 38 | G109: =(1+INDEX($Z$21:$Z$97,B109))*(1+INDEX($Z$21:$Z$97,C109))*(1+INDEX($Z$21:$Z$97,D109))*(1+INDEX($Z$21:$Z$97,E109))*(1+INDEX($Z$21:$Z$97,F109))-1 -> 0.57761973 | H109: =(1+INDEX($AA$21:$AA$97,B109))*(1+INDEX($AA$21:$AA$97,C109))*(1+INDEX($AA$21:$AA$97,D109))*(1+INDEX($AA$21:$AA$97,E109))*(1+INDEX($AA$21:$AA$97,F109))-1 -> 0.51285443 | I109: =(1+INDEX($AB$21:$AB$97,B109))*(1+INDEX($AB$21:$AB$97,C109))*(1+INDEX($AB$21:$AB$97,D109))*(1+INDEX($AB$21:$AB$97,E109))*(1+INDEX($AB$21:$AB$97,F109))-1 -> 0.54883828 | J109: =LN((1+G109)/(1+H109)) -> 0.041918998 | K109: =LN((1+I109)/(1+H109)) -> 0.023506939 | L109: =(1+INDEX($AC$21:$AC$97,B109))*(1+INDEX($AC$21:$AC$97,C109))*(1+INDEX($AC$21:$AC$97,D109))*(1+INDEX($AC$21:$AC$97,E109))*(1+INDEX($AC$21:$AC$97,F109))-1 -> 0.52441341 | M109: =(1+INDEX($AD$21:$AD$97,B109))*(1+INDEX($AD$21:$AD$97,C109))*(1+INDEX($AD$21:$AD$97,D109))*(1+INDEX($AD$21:$AD$97,E109))*(1+INDEX($AD$21:$AD$97,F109))-1 -> 0.59560604 | N109: =(1+INDEX($AE$21:$AE$97,B109))*(1+INDEX($AE$21:$AE$97,C109))*(1+INDEX($AE$21:$AE$97,D109))*(1+INDEX($AE$21:$AE$97,E109))*(1+INDEX($AE$21:$AE$97,F109))-1 -> 0.52265856 | O109: =(1+INDEX($AF$21:$AF$97,B109))*(1+INDEX($AF$21:$AF$97,C109))*(1+INDEX($AF$21:$AF$97,D109))*(1+INDEX($AF$21:$AF$97,E109))*(1+INDEX($AF$21:$AF$97,F109))-1 -> 0.55048947 | P109: =LN((1+L109)/(1+H109)) -> 0.0076114736 | Q109: =LN((1+M109)/(1+H109)) -> 0.053255413 | R109: =LN((1+N109)/(1+H109)) -> 0.0064596476 | S109: =LN((1+O109)/(1+H109)) -> 0.024572452
A110: 9 | B110: 48 | C110: 20 | D110: 12 | E110: 56 | F110: 31 | G110: =(1+INDEX($Z$21:$Z$97,B110))*(1+INDEX($Z$21:$Z$97,C110))*(1+INDEX($Z$21:$Z$97,D110))*(1+INDEX($Z$21:$Z$97,E110))*(1+INDEX($Z$21:$Z$97,F110))-1 -> 0.26905085 | H110: =(1+INDEX($AA$21:$AA$97,B110))*(1+INDEX($AA$21:$AA$97,C110))*(1+INDEX($AA$21:$AA$97,D110))*(1+INDEX($AA$21:$AA$97,E110))*(1+INDEX($AA$21:$AA$97,F110))-1 -> 0.24528405 | I110: =(1+INDEX($AB$21:$AB$97,B110))*(1+INDEX($AB$21:$AB$97,C110))*(1+INDEX($AB$21:$AB$97,D110))*(1+INDEX($AB$21:$AB$97,E110))*(1+INDEX($AB$21:$AB$97,F110))-1 -> 0.24511446 | J110: =LN((1+G110)/(1+H110)) -> 0.018905607 | K110: =LN((1+I110)/(1+H110)) -> -0.00013619295 | L110: =(1+INDEX($AC$21:$AC$97,B110))*(1+INDEX($AC$21:$AC$97,C110))*(1+INDEX($AC$21:$AC$97,D110))*(1+INDEX($AC$21:$AC$97,E110))*(1+INDEX($AC$21:$AC$97,F110))-1 -> 0.22774035 | M110: =(1+INDEX($AD$21:$AD$97,B110))*(1+INDEX($AD$21:$AD$97,C110))*(1+INDEX($AD$21:$AD$97,D110))*(1+INDEX($AD$21:$AD$97,E110))*(1+INDEX($AD$21:$AD$97,F110))-1 -> 0.26455549 | N110: =(1+INDEX($AE$21:$AE$97,B110))*(1+INDEX($AE$21:$AE$97,C110))*(1+INDEX($AE$21:$AE$97,D110))*(1+INDEX($AE$21:$AE$97,E110))*(1+INDEX($AE$21:$AE$97,F110))-1 -> 0.22462241 | O110: =(1+INDEX($AF$21:$AF$97,B110))*(1+INDEX($AF$21:$AF$97,C110))*(1+INDEX($AF$21:$AF$97,D110))*(1+INDEX($AF$21:$AF$97,E110))*(1+INDEX($AF$21:$AF$97,F110))-1 -> 0.27983738 | P110: =LN((1+L110)/(1+H110)) -> -0.014188292 | Q110: =LN((1+M110)/(1+H110)) -> 0.015357013 | R110: =LN((1+N110)/(1+H110)) -> -0.016731092 | S110: =LN((1+O110)/(1+H110)) -> 0.027369367
A111: 10 | B111: 63 | C111: 29 | D111: 6 | E111: 28 | F111: 54 | G111: =(1+INDEX($Z$21:$Z$97,B111))*(1+INDEX($Z$21:$Z$97,C111))*(1+INDEX($Z$21:$Z$97,D111))*(1+INDEX($Z$21:$Z$97,E111))*(1+INDEX($Z$21:$Z$97,F111))-1 -> 0.093949881 | H111: =(1+INDEX($AA$21:$AA$97,B111))*(1+INDEX($AA$21:$AA$97,C111))*(1+INDEX($AA$21:$AA$97,D111))*(1+INDEX($AA$21:$AA$97,E111))*(1+INDEX($AA$21:$AA$97,F111))-1 -> 0.14802252 | I111: =(1+INDEX($AB$21:$AB$97,B111))*(1+INDEX($AB$21:$AB$97,C111))*(1+INDEX($AB$21:$AB$97,D111))*(1+INDEX($AB$21:$AB$97,E111))*(1+INDEX($AB$21:$AB$97,F111))-1 -> 0.15731098 | J111: =LN((1+G111)/(1+H111)) -> -0.048246028 | K111: =LN((1+I111)/(1+H111)) -> 0.0080582778 | L111: =(1+INDEX($AC$21:$AC$97,B111))*(1+INDEX($AC$21:$AC$97,C111))*(1+INDEX($AC$21:$AC$97,D111))*(1+INDEX($AC$21:$AC$97,E111))*(1+INDEX($AC$21:$AC$97,F111))-1 -> 0.15962952 | M111: =(1+INDEX($AD$21:$AD$97,B111))*(1+INDEX($AD$21:$AD$97,C111))*(1+INDEX($AD$21:$AD$97,D111))*(1+INDEX($AD$21:$AD$97,E111))*(1+INDEX($AD$21:$AD$97,F111))-1 -> 0.12676688 | N111: =(1+INDEX($AE$21:$AE$97,B111))*(1+INDEX($AE$21:$AE$97,C111))*(1+INDEX($AE$21:$AE$97,D111))*(1+INDEX($AE$21:$AE$97,E111))*(1+INDEX($AE$21:$AE$97,F111))-1 -> 0.14433571 | O111: =(1+INDEX($AF$21:$AF$97,B111))*(1+INDEX($AF$21:$AF$97,C111))*(1+INDEX($AF$21:$AF$97,D111))*(1+INDEX($AF$21:$AF$97,E111))*(1+INDEX($AF$21:$AF$97,F111))-1 -> 0.15618809 | P111: =LN((1+L111)/(1+H111)) -> 0.010059659 | Q111: =LN((1+M111)/(1+H111)) -> -0.018688558 | R111: =LN((1+N111)/(1+H111)) -> -0.0032166191 | S111: =LN((1+O111)/(1+H111)) -> 0.0070875419
A112: 11 | B112: 43 | C112: 41 | D112: 72 | E112: 41 | F112: 33 | G112: =(1+INDEX($Z$21:$Z$97,B112))*(1+INDEX($Z$21:$Z$97,C112))*(1+INDEX($Z$21:$Z$97,D112))*(1+INDEX($Z$21:$Z$97,E112))*(1+INDEX($Z$21:$Z$97,F112))-1 -> 0.82447433 | H112: =(1+INDEX($AA$21:$AA$97,B112))*(1+INDEX($AA$21:$AA$97,C112))*(1+INDEX($AA$21:$AA$97,D112))*(1+INDEX($AA$21:$AA$97,E112))*(1+INDEX($AA$21:$AA$97,F112))-1 -> 0.80969171 | I112: =(1+INDEX($AB$21:$AB$97,B112))*(1+INDEX($AB$21:$AB$97,C112))*(1+INDEX($AB$21:$AB$97,D112))*(1+INDEX($AB$21:$AB$97,E112))*(1+INDEX($AB$21:$AB$97,F112))-1 -> 0.92525773 | J112: =LN((1+G112)/(1+H112)) -> 0.0081354038 | K112: =LN((1+I112)/(1+H112)) -> 0.061903341 | L112: =(1+INDEX($AC$21:$AC$97,B112))*(1+INDEX($AC$21:$AC$97,C112))*(1+INDEX($AC$21:$AC$97,D112))*(1+INDEX($AC$21:$AC$97,E112))*(1+INDEX($AC$21:$AC$97,F112))-1 -> 0.92689707 | M112: =(1+INDEX($AD$21:$AD$97,B112))*(1+INDEX($AD$21:$AD$97,C112))*(1+INDEX($AD$21:$AD$97,D112))*(1+INDEX($AD$21:$AD$97,E112))*(1+INDEX($AD$21:$AD$97,F112))-1 -> 0.91220962 | N112: =(1+INDEX($AE$21:$AE$97,B112))*(1+INDEX($AE$21:$AE$97,C112))*(1+INDEX($AE$21:$AE$97,D112))*(1+INDEX($AE$21:$AE$97,E112))*(1+INDEX($AE$21:$AE$97,F112))-1 -> 0.90871926 | O112: =(1+INDEX($AF$21:$AF$97,B112))*(1+INDEX($AF$21:$AF$97,C112))*(1+INDEX($AF$21:$AF$97,D112))*(1+INDEX($AF$21:$AF$97,E112))*(1+INDEX($AF$21:$AF$97,F112))-1 -> 0.82198112 | P112: =LN((1+L112)/(1+H112)) -> 0.062754467 | Q112: =LN((1+M112)/(1+H112)) -> 0.055102937 | R112: =LN((1+N112)/(1+H112)) -> 0.053275969 | S112: =LN((1+O112)/(1+H112)) -> 0.0067679291
A113: 12 | B113: 44 | C113: 14 | D113: 13 | E113: 34 | F113: 53 | G113: =(1+INDEX($Z$21:$Z$97,B113))*(1+INDEX($Z$21:$Z$97,C113))*(1+INDEX($Z$21:$Z$97,D113))*(1+INDEX($Z$21:$Z$97,E113))*(1+INDEX($Z$21:$Z$97,F113))-1 -> 0.62107001 | H113: =(1+INDEX($AA$21:$AA$97,B113))*(1+INDEX($AA$21:$AA$97,C113))*(1+INDEX($AA$21:$AA$97,D113))*(1+INDEX($AA$21:$AA$97,E113))*(1+INDEX($AA$21:$AA$97,F113))-1 -> 0.57984811 | I113: =(1+INDEX($AB$21:$AB$97,B113))*(1+INDEX($AB$21:$AB$97,C113))*(1+INDEX($AB$21:$AB$97,D113))*(1+INDEX($AB$21:$AB$97,E113))*(1+INDEX($AB$21:$AB$97,F113))-1 -> 0.62948558 | J113: =LN((1+G113)/(1+H113)) -> 0.025757724 | K113: =LN((1+I113)/(1+H113)) -> 0.030935665 | L113: =(1+INDEX($AC$21:$AC$97,B113))*(1+INDEX($AC$21:$AC$97,C113))*(1+INDEX($AC$21:$AC$97,D113))*(1+INDEX($AC$21:$AC$97,E113))*(1+INDEX($AC$21:$AC$97,F113))-1 -> 0.63118593 | M113: =(1+INDEX($AD$21:$AD$97,B113))*(1+INDEX($AD$21:$AD$97,C113))*(1+INDEX($AD$21:$AD$97,D113))*(1+INDEX($AD$21:$AD$97,E113))*(1+INDEX($AD$21:$AD$97,F113))-1 -> 0.65913896 | N113: =(1+INDEX($AE$21:$AE$97,B113))*(1+INDEX($AE$21:$AE$97,C113))*(1+INDEX($AE$21:$AE$97,D113))*(1+INDEX($AE$21:$AE$97,E113))*(1+INDEX($AE$21:$AE$97,F113))-1 -> 0.60975461 | O113: =(1+INDEX($AF$21:$AF$97,B113))*(1+INDEX($AF$21:$AF$97,C113))*(1+INDEX($AF$21:$AF$97,D113))*(1+INDEX($AF$21:$AF$97,E113))*(1+INDEX($AF$21:$AF$97,F113))-1 -> 0.57612673 | P113: =LN((1+L113)/(1+H113)) -> 0.031978608 | Q113: =LN((1+M113)/(1+H113)) -> 0.048970064 | R113: =LN((1+N113)/(1+H113)) -> 0.018753043 | S113: =LN((1+O113)/(1+H113)) -> -0.0023583083
... A1101: 1000 | B1101: 16 | C1101: 72 | D1101: 22 | E1101: 50 | F1101: 60 | G1101: =(1+INDEX($Z$21:$Z$97,B1101))*(1+INDEX($Z$21:$Z$97,C1101))*(1+INDEX($Z$21:$Z$97,D1101))*(1+INDEX($Z$21:$Z$97,E1101))*(1+INDEX($Z$21:$Z$97,F1101))-1 -> 0.53241822 | H1101: =(1+INDEX($AA$21:$AA$97,B1101))*(1+INDEX($AA$21:$AA$97,C1101))*(1+INDEX($AA$21:$AA$97,D1101))*(1+INDEX($AA$21:$AA$97,E1101))*(1+INDEX($AA$21:$AA$97,F1101))-1 -> 0.51713427 | I1101: =(1+INDEX($AB$21:$AB$97,B1101))*(1+INDEX($AB$21:$AB$97,C1101))*(1+INDEX($AB$21:$AB$97,D1101))*(1+INDEX($AB$21:$AB$97,E1101))*(1+INDEX($AB$21:$AB$97,F1101))-1 -> 0.56719865 | J1101: =LN((1+G1101)/(1+H1101)) -> 0.010023812 | K1101: =LN((1+I1101)/(1+H1101)) -> 0.032466517 | L1101: =(1+INDEX($AC$21:$AC$97,B1101))*(1+INDEX($AC$21:$AC$97,C1101))*(1+INDEX($AC$21:$AC$97,D1101))*(1+INDEX($AC$21:$AC$97,E1101))*(1+INDEX($AC$21:$AC$97,F1101))-1 -> 0.55721318 | M1101: =(1+INDEX($AD$21:$AD$97,B1101))*(1+INDEX($AD$21:$AD$97,C1101))*(1+INDEX($AD$21:$AD$97,D1101))*(1+INDEX($AD$21:$AD$97,E1101))*(1+INDEX($AD$21:$AD$97,F1101))-1 -> 0.54745277 | N1101: =(1+INDEX($AE$21:$AE$97,B1101))*(1+INDEX($AE$21:$AE$97,C1101))*(1+INDEX($AE$21:$AE$97,D1101))*(1+INDEX($AE$21:$AE$97,E1101))*(1+INDEX($AE$21:$AE$97,F1101))-1 -> 0.55899551 | O1101: =(1+INDEX($AF$21:$AF$97,B1101))*(1+INDEX($AF$21:$AF$97,C1101))*(1+INDEX($AF$21:$AF$97,D1101))*(1+INDEX($AF$21:$AF$97,E1101))*(1+INDEX($AF$21:$AF$97,F1101))-1 -> 0.49118875 | P1101: =LN((1+L1101)/(1+H1101)) -> 0.026074592 | Q1101: =LN((1+M1101)/(1+H1101)) -> 0.019786998 | R1101: =LN((1+N1101)/(1+H1101)) -> 0.027218499 | S1101: =LN((1+O1101)/(1+H1101)) -> -0.017249591

Sheet Stress
A1: Stress
A3: 1. Historical windows
A4: Scenario | B4: Start (quarter end) | C4: End (quarter end)
A5: Global financial crisis | B5: 39447 | C5: 39903
A6: COVID shock | B6: 43921 | C6: 43921
A7: Inflation sell-off (2022) | B7: 44651 | C7: 44925
A9: 2. Asset returns in each scenario
A10: Asset class | B10: Global financial crisis | C10: COVID shock | D10: Inflation sell-off (2022) | E10: US$150 oil (Oil tab)
A11: Australian Equities | B11: =EXP(SUMPRODUCT(LN(1+INDEX('Quarterly returns'!N$6:N$85,MATCH($B$5,'Quarterly returns'!$A$6:$A$85,0)):INDEX('Quarterly returns'!N$6:N$85,MATCH($C$5,'Quarterly returns'!$A$6:$A$85,0)))))-1 -> -0.42395461 | C11: =EXP(SUMPRODUCT(LN(1+INDEX('Quarterly returns'!N$6:N$85,MATCH($B$6,'Quarterly returns'!$A$6:$A$85,0)):INDEX('Quarterly returns'!N$6:N$85,MATCH($C$6,'Quarterly returns'!$A$6:$A$85,0)))))-1 -> -0.23923021 | D11: =EXP(SUMPRODUCT(LN(1+INDEX('Quarterly returns'!N$6:N$85,MATCH($B$7,'Quarterly returns'!$A$6:$A$85,0)):INDEX('Quarterly returns'!N$6:N$85,MATCH($C$7,'Quarterly returns'!$A$6:$A$85,0)))))-1 -> -0.029586588 | E11: =Oil!F28 -> -0.0848026
A12: World Equities | B12: =EXP(SUMPRODUCT(LN(1+INDEX('Quarterly returns'!O$6:O$85,MATCH($B$5,'Quarterly returns'!$A$6:$A$85,0)):INDEX('Quarterly returns'!O$6:O$85,MATCH($C$5,'Quarterly returns'!$A$6:$A$85,0)))))-1 -> -0.31268062 | C12: =EXP(SUMPRODUCT(LN(1+INDEX('Quarterly returns'!O$6:O$85,MATCH($B$6,'Quarterly returns'!$A$6:$A$85,0)):INDEX('Quarterly returns'!O$6:O$85,MATCH($C$6,'Quarterly returns'!$A$6:$A$85,0)))))-1 -> -0.080905967 | D12: =EXP(SUMPRODUCT(LN(1+INDEX('Quarterly returns'!O$6:O$85,MATCH($B$7,'Quarterly returns'!$A$6:$A$85,0)):INDEX('Quarterly returns'!O$6:O$85,MATCH($C$7,'Quarterly returns'!$A$6:$A$85,0)))))-1 -> -0.095374399 | E12: =Oil!F29 -> -0.12992958
A13: Emerging Markets | B13: =EXP(SUMPRODUCT(LN(1+INDEX('Quarterly returns'!P$6:P$85,MATCH($B$5,'Quarterly returns'!$A$6:$A$85,0)):INDEX('Quarterly returns'!P$6:P$85,MATCH($C$5,'Quarterly returns'!$A$6:$A$85,0)))))-1 -> -0.25904312 | C13: =EXP(SUMPRODUCT(LN(1+INDEX('Quarterly returns'!P$6:P$85,MATCH($B$6,'Quarterly returns'!$A$6:$A$85,0)):INDEX('Quarterly returns'!P$6:P$85,MATCH($C$6,'Quarterly returns'!$A$6:$A$85,0)))))-1 -> -0.069947634 | D13: =EXP(SUMPRODUCT(LN(1+INDEX('Quarterly returns'!P$6:P$85,MATCH($B$7,'Quarterly returns'!$A$6:$A$85,0)):INDEX('Quarterly returns'!P$6:P$85,MATCH($C$7,'Quarterly returns'!$A$6:$A$85,0)))))-1 -> -0.090464646 | E13: =Oil!F30 -> -0.13708873
A14: Listed Property | B14: =EXP(SUMPRODUCT(LN(1+INDEX('Quarterly returns'!Q$6:Q$85,MATCH($B$5,'Quarterly returns'!$A$6:$A$85,0)):INDEX('Quarterly returns'!Q$6:Q$85,MATCH($C$5,'Quarterly returns'!$A$6:$A$85,0)))))-1 -> -0.5052704 | C14: =EXP(SUMPRODUCT(LN(1+INDEX('Quarterly returns'!Q$6:Q$85,MATCH($B$6,'Quarterly returns'!$A$6:$A$85,0)):INDEX('Quarterly returns'!Q$6:Q$85,MATCH($C$6,'Quarterly returns'!$A$6:$A$85,0)))))-1 -> -0.16646922 | D14: =EXP(SUMPRODUCT(LN(1+INDEX('Quarterly returns'!Q$6:Q$85,MATCH($B$7,'Quarterly returns'!$A$6:$A$85,0)):INDEX('Quarterly returns'!Q$6:Q$85,MATCH($C$7,'Quarterly returns'!$A$6:$A$85,0)))))-1 -> -0.16027289 | E14: =Oil!F31 -> -0.11553691
A15: Commodities | B15: =EXP(SUMPRODUCT(LN(1+INDEX('Quarterly returns'!R$6:R$85,MATCH($B$5,'Quarterly returns'!$A$6:$A$85,0)):INDEX('Quarterly returns'!R$6:R$85,MATCH($C$5,'Quarterly returns'!$A$6:$A$85,0)))))-1 -> -0.32006394 | C15: =EXP(SUMPRODUCT(LN(1+INDEX('Quarterly returns'!R$6:R$85,MATCH($B$6,'Quarterly returns'!$A$6:$A$85,0)):INDEX('Quarterly returns'!R$6:R$85,MATCH($C$6,'Quarterly returns'!$A$6:$A$85,0)))))-1 -> -0.33781993 | D15: =EXP(SUMPRODUCT(LN(1+INDEX('Quarterly returns'!R$6:R$85,MATCH($B$7,'Quarterly returns'!$A$6:$A$85,0)):INDEX('Quarterly returns'!R$6:R$85,MATCH($C$7,'Quarterly returns'!$A$6:$A$85,0)))))-1 -> 0.35070542 | E15: =Oil!F32 -> 0.29013882
A16: Direct Property | B16: =EXP(SUMPRODUCT(LN(1+INDEX('Quarterly returns'!S$6:S$85,MATCH($B$5,'Quarterly returns'!$A$6:$A$85,0)):INDEX('Quarterly returns'!S$6:S$85,MATCH($C$5,'Quarterly returns'!$A$6:$A$85,0)))))-1 -> -0.059832983 | C16: =EXP(SUMPRODUCT(LN(1+INDEX('Quarterly returns'!S$6:S$85,MATCH($B$6,'Quarterly returns'!$A$6:$A$85,0)):INDEX('Quarterly returns'!S$6:S$85,MATCH($C$6,'Quarterly returns'!$A$6:$A$85,0)))))-1 -> -0.023906178 | D16: =EXP(SUMPRODUCT(LN(1+INDEX('Quarterly returns'!S$6:S$85,MATCH($B$7,'Quarterly returns'!$A$6:$A$85,0)):INDEX('Quarterly returns'!S$6:S$85,MATCH($C$7,'Quarterly returns'!$A$6:$A$85,0)))))-1 -> -0.14837279 | E16: =Oil!F33 -> 0.023268684
A17: Hedge Funds | B17: =EXP(SUMPRODUCT(LN(1+INDEX('Quarterly returns'!T$6:T$85,MATCH($B$5,'Quarterly returns'!$A$6:$A$85,0)):INDEX('Quarterly returns'!T$6:T$85,MATCH($C$5,'Quarterly returns'!$A$6:$A$85,0)))))-1 -> 0.20371951 | C17: =EXP(SUMPRODUCT(LN(1+INDEX('Quarterly returns'!T$6:T$85,MATCH($B$6,'Quarterly returns'!$A$6:$A$85,0)):INDEX('Quarterly returns'!T$6:T$85,MATCH($C$6,'Quarterly returns'!$A$6:$A$85,0)))))-1 -> 0.1267819 | D17: =EXP(SUMPRODUCT(LN(1+INDEX('Quarterly returns'!T$6:T$85,MATCH($B$7,'Quarterly returns'!$A$6:$A$85,0)):INDEX('Quarterly returns'!T$6:T$85,MATCH($C$7,'Quarterly returns'!$A$6:$A$85,0)))))-1 -> 0.023911745 | E17: =Oil!F34 -> -0.041538442
A18: Private Equity | B18: =EXP(SUMPRODUCT(LN(1+INDEX('Quarterly returns'!U$6:U$85,MATCH($B$5,'Quarterly returns'!$A$6:$A$85,0)):INDEX('Quarterly returns'!U$6:U$85,MATCH($C$5,'Quarterly returns'!$A$6:$A$85,0)))))-1 -> -0.15344471 | C18: =EXP(SUMPRODUCT(LN(1+INDEX('Quarterly returns'!U$6:U$85,MATCH($B$6,'Quarterly returns'!$A$6:$A$85,0)):INDEX('Quarterly returns'!U$6:U$85,MATCH($C$6,'Quarterly returns'!$A$6:$A$85,0)))))-1 -> -0.09197953 | D18: =EXP(SUMPRODUCT(LN(1+INDEX('Quarterly returns'!U$6:U$85,MATCH($B$7,'Quarterly returns'!$A$6:$A$85,0)):INDEX('Quarterly returns'!U$6:U$85,MATCH($C$7,'Quarterly returns'!$A$6:$A$85,0)))))-1 -> 0.0094939572 | E18: =Oil!F35 -> -0.09842712
A19: Australian Fixed Income | B19: =EXP(SUMPRODUCT(LN(1+INDEX('Quarterly returns'!V$6:V$85,MATCH($B$5,'Quarterly returns'!$A$6:$A$85,0)):INDEX('Quarterly returns'!V$6:V$85,MATCH($C$5,'Quarterly returns'!$A$6:$A$85,0)))))-1 -> 0.15561261 | C19: =EXP(SUMPRODUCT(LN(1+INDEX('Quarterly returns'!V$6:V$85,MATCH($B$6,'Quarterly returns'!$A$6:$A$85,0)):INDEX('Quarterly returns'!V$6:V$85,MATCH($C$6,'Quarterly returns'!$A$6:$A$85,0)))))-1 -> 0.033109728 | D19: =EXP(SUMPRODUCT(LN(1+INDEX('Quarterly returns'!V$6:V$85,MATCH($B$7,'Quarterly returns'!$A$6:$A$85,0)):INDEX('Quarterly returns'!V$6:V$85,MATCH($C$7,'Quarterly returns'!$A$6:$A$85,0)))))-1 -> -0.1108247 | E19: =Oil!F36 -> -0.04884397
A20: World Fixed Income | B20: =EXP(SUMPRODUCT(LN(1+INDEX('Quarterly returns'!W$6:W$85,MATCH($B$5,'Quarterly returns'!$A$6:$A$85,0)):INDEX('Quarterly returns'!W$6:W$85,MATCH($C$5,'Quarterly returns'!$A$6:$A$85,0)))))-1 -> 0.12829729 | C20: =EXP(SUMPRODUCT(LN(1+INDEX('Quarterly returns'!W$6:W$85,MATCH($B$6,'Quarterly returns'!$A$6:$A$85,0)):INDEX('Quarterly returns'!W$6:W$85,MATCH($C$6,'Quarterly returns'!$A$6:$A$85,0)))))-1 -> 0.030592829 | D20: =EXP(SUMPRODUCT(LN(1+INDEX('Quarterly returns'!W$6:W$85,MATCH($B$7,'Quarterly returns'!$A$6:$A$85,0)):INDEX('Quarterly returns'!W$6:W$85,MATCH($C$7,'Quarterly returns'!$A$6:$A$85,0)))))-1 -> -0.12590993 | E20: =Oil!F37 -> -0.047775824
A21: Cash | B21: =EXP(SUMPRODUCT(LN(1+INDEX('Quarterly returns'!X$6:X$85,MATCH($B$5,'Quarterly returns'!$A$6:$A$85,0)):INDEX('Quarterly returns'!X$6:X$85,MATCH($C$5,'Quarterly returns'!$A$6:$A$85,0)))))-1 -> 0.1052518 | C21: =EXP(SUMPRODUCT(LN(1+INDEX('Quarterly returns'!X$6:X$85,MATCH($B$6,'Quarterly returns'!$A$6:$A$85,0)):INDEX('Quarterly returns'!X$6:X$85,MATCH($C$6,'Quarterly returns'!$A$6:$A$85,0)))))-1 -> 0.0025612734 | D21: =EXP(SUMPRODUCT(LN(1+INDEX('Quarterly returns'!X$6:X$85,MATCH($B$7,'Quarterly returns'!$A$6:$A$85,0)):INDEX('Quarterly returns'!X$6:X$85,MATCH($C$7,'Quarterly returns'!$A$6:$A$85,0)))))-1 -> 0.012555222 | E21: =Oil!F38 -> 0
A24: 3. Portfolio impact
A25: Portfolio | B25: Global financial crisis | C25: COVID shock | D25: Inflation sell-off (2022) | E25: US$150 oil
A26: Current fund | B26: =SUMPRODUCT(B$11:B$21,Portfolio!$C$6:$C$16) -> -0.24167171 | C26: =SUMPRODUCT(C$11:C$21,Portfolio!$C$6:$C$16) -> -0.12092703 | D26: =SUMPRODUCT(D$11:D$21,Portfolio!$C$6:$C$16) -> -0.072754437 | E26: =SUMPRODUCT(E$11:E$21,Portfolio!$C$6:$C$16) -> -0.082609308
A27: Benchmark | B27: =SUMPRODUCT(B$11:B$21,Portfolio!$D$6:$D$16) -> -0.19300089 | C27: =SUMPRODUCT(C$11:C$21,Portfolio!$D$6:$D$16) -> -0.091806485 | D27: =SUMPRODUCT(D$11:D$21,Portfolio!$D$6:$D$16) -> -0.072610798 | E27: =SUMPRODUCT(E$11:E$21,Portfolio!$D$6:$D$16) -> -0.073910247
A28: Recommended | B28: =SUMPRODUCT(B$11:B$21,Portfolio!$E$6:$E$16) -> -0.2350248 | C28: =SUMPRODUCT(C$11:C$21,Portfolio!$E$6:$E$16) -> -0.10748236 | D28: =SUMPRODUCT(D$11:D$21,Portfolio!$E$6:$E$16) -> -0.075405586 | E28: =SUMPRODUCT(E$11:E$21,Portfolio!$E$6:$E$16) -> -0.08363891
A29: Recommended less current | B29: =B28-B26 -> 0.0066469095 | C29: =C28-C26 -> 0.013444668 | D29: =D28-D26 -> -0.0026511484 | E29: =E28-E26 -> -0.0010296018
A30: Recommended less benchmark | B30: =B28-B27 -> -0.042023911 | C30: =C28-C27 -> -0.015675872 | D30: =D28-D27 -> -0.002794788 | E30: =E28-E27 -> -0.0097286627

Sheet Oil
A1: Oil
A3: 1. Scenario | N3: Monthly panel, Jan-1968 to Jan-2026 (from Additional data and Data tabs) | AG3: Panel extension: AU 5-year yield (RBA 5Y yield tab) and 12-month asset-class log returns (Data tab)
A4: Current WTI (US$/bbl) | B4: 96.41 | C4: FRED, 22-Sep-26 | N4: Month end | O4: WTI | P4: ln WTI | Q4: US equity log index | R4: Aus equity ln level | S4: AU 3-month rate (%) | T4: 1m oil (log) | U4: 1m US equity (log) | V4: 1m Aus equity (log) | W4: 1m rate change (pp) | X4: 12m oil (log) | Y4: 12m US equity (log) | Z4: 12m Aus equity (log) | AA4: 12m rate change (pp) | AB4: 60m oil (log) | AC4: 60m US equity (log) | AD4: 60m Aus equity (log) | AE4: 60m rate change (pp) | AG4: Month end | AH4: AU 5-year yield (%) | AI4: 1m yield change (pp) | AJ4: 12m yield change (pp) | AK4: 60m yield change (pp) | AL4: 12m Australian Equities (log) | AM4: 12m World Equities (log) | AN4: 12m Emerging Markets (log) | AO4: 12m Listed Property (log) | AP4: 12m Commodities (log) | AQ4: 12m Direct Property (log) | AR4: 12m Hedge Funds (log) | AS4: 12m Private Equity (log) | AT4: 12m Australian Fixed Income (log) | AU4: 12m World Fixed Income (log) | AV4: 12m Cash (log)
A5: Scenario WTI (US$/bbl) | B5: 150 | C5: Brief | N5: 24868 | O5: =INDEX('Additional data'!$B$2:$B$965,MATCH(DATE(YEAR(N5),MONTH(N5),1),'Additional data'!$A$2:$A$965,0)) -> 3.07 | P5: =LN(O5) -> 1.1216776 | Q5: =LN(1+INDEX('Additional data'!$H$2:$H$1196,MATCH(N5,'Additional data'!$G$2:$G$1196,1))+INDEX('Additional data'!$I$2:$I$1196,MATCH(N5,'Additional data'!$G$2:$G$1196,1))) -> -0.036975236 | S5: =IF(INDEX('Additional data'!$E$2:$E$699,MATCH(DATE(YEAR(N5),MONTH(N5),1),'Additional data'!$D$2:$D$699,0))=0,(INDEX('Additional data'!$E$2:$E$699,MATCH(DATE(YEAR(N5),MONTH(N5),1),'Additional data'!$D$2:$D$699,0)-1)+INDEX('Additional data'!$E$2:$E$699,MATCH(DATE(YEAR(N5),MONTH(N5),1),'Additional data'!$D$2:$D$699,0)+1))/2,INDEX('Additional data'!$E$2:$E$699,MATCH(DATE(YEAR(N5),MONTH(N5),1),'Additional data'!$D$2:$D$699,0))) -> 5.1 | AG5: =N5 -> 24868 | AH5: =IFERROR(INDEX('RBA 5Y yield'!$B$5:$B$661,MATCH(N5,'RBA 5Y yield'!$A$5:$A$661,1))*100,"")
A6: Oil price change | B6: =B5/B4-1 -> 0.5558552 | N6: 24897 | O6: =INDEX('Additional data'!$B$2:$B$965,MATCH(DATE(YEAR(N6),MONTH(N6),1),'Additional data'!$A$2:$A$965,0)) -> 3.07 | P6: =LN(O6) -> 1.1216776 | Q6: =Q5+LN(1+INDEX('Additional data'!$H$2:$H$1196,MATCH(N6,'Additional data'!$G$2:$G$1196,1))+INDEX('Additional data'!$I$2:$I$1196,MATCH(N6,'Additional data'!$G$2:$G$1196,1))) -> -0.071049216 | S6: =IF(INDEX('Additional data'!$E$2:$E$699,MATCH(DATE(YEAR(N6),MONTH(N6),1),'Additional data'!$D$2:$D$699,0))=0,(INDEX('Additional data'!$E$2:$E$699,MATCH(DATE(YEAR(N6),MONTH(N6),1),'Additional data'!$D$2:$D$699,0)-1)+INDEX('Additional data'!$E$2:$E$699,MATCH(DATE(YEAR(N6),MONTH(N6),1),'Additional data'!$D$2:$D$699,0)+1))/2,INDEX('Additional data'!$E$2:$E$699,MATCH(DATE(YEAR(N6),MONTH(N6),1),'Additional data'!$D$2:$D$699,0))) -> 5.15 | T6: =P6-P5 -> 0 | U6: =Q6-Q5 -> -0.03407398 | W6: =S6-S5 -> 0.05 | AG6: =N6 -> 24897 | AH6: =IFERROR(INDEX('RBA 5Y yield'!$B$5:$B$661,MATCH(N6,'RBA 5Y yield'!$A$5:$A$661,1))*100,"") | AI6: =IF(AND(ISNUMBER(AH6),ISNUMBER(AH5)),AH6-AH5,"")
A7: Log change | B7: =LN(B5/B4) -> 0.44202536 | N7: 24928 | O7: =INDEX('Additional data'!$B$2:$B$965,MATCH(DATE(YEAR(N7),MONTH(N7),1),'Additional data'!$A$2:$A$965,0)) -> 3.07 | P7: =LN(O7) -> 1.1216776 | Q7: =Q6+LN(1+INDEX('Additional data'!$H$2:$H$1196,MATCH(N7,'Additional data'!$G$2:$G$1196,1))+INDEX('Additional data'!$I$2:$I$1196,MATCH(N7,'Additional data'!$G$2:$G$1196,1))) -> -0.065166553 | S7: =IF(INDEX('Additional data'!$E$2:$E$699,MATCH(DATE(YEAR(N7),MONTH(N7),1),'Additional data'!$D$2:$D$699,0))=0,(INDEX('Additional data'!$E$2:$E$699,MATCH(DATE(YEAR(N7),MONTH(N7),1),'Additional data'!$D$2:$D$699,0)-1)+INDEX('Additional data'!$E$2:$E$699,MATCH(DATE(YEAR(N7),MONTH(N7),1),'Additional data'!$D$2:$D$699,0)+1))/2,INDEX('Additional data'!$E$2:$E$699,MATCH(DATE(YEAR(N7),MONTH(N7),1),'Additional data'!$D$2:$D$699,0))) -> 5.15 | T7: =P7-P6 -> 0 | U7: =Q7-Q6 -> 0.0058826632 | W7: =S7-S6 -> 0 | AG7: =N7 -> 24928 | AH7: =IFERROR(INDEX('RBA 5Y yield'!$B$5:$B$661,MATCH(N7,'RBA 5Y yield'!$A$5:$A$661,1))*100,"") | AI7: =IF(AND(ISNUMBER(AH7),ISNUMBER(AH6)),AH7-AH6,"")
N8: 24958 | O8: =INDEX('Additional data'!$B$2:$B$965,MATCH(DATE(YEAR(N8),MONTH(N8),1),'Additional data'!$A$2:$A$965,0)) -> 3.07 | P8: =LN(O8) -> 1.1216776 | Q8: =Q7+LN(1+INDEX('Additional data'!$H$2:$H$1196,MATCH(N8,'Additional data'!$G$2:$G$1196,1))+INDEX('Additional data'!$I$2:$I$1196,MATCH(N8,'Additional data'!$G$2:$G$1196,1))) -> 0.025131085 | S8: =IF(INDEX('Additional data'!$E$2:$E$699,MATCH(DATE(YEAR(N8),MONTH(N8),1),'Additional data'!$D$2:$D$699,0))=0,(INDEX('Additional data'!$E$2:$E$699,MATCH(DATE(YEAR(N8),MONTH(N8),1),'Additional data'!$D$2:$D$699,0)-1)+INDEX('Additional data'!$E$2:$E$699,MATCH(DATE(YEAR(N8),MONTH(N8),1),'Additional data'!$D$2:$D$699,0)+1))/2,INDEX('Additional data'!$E$2:$E$699,MATCH(DATE(YEAR(N8),MONTH(N8),1),'Additional data'!$D$2:$D$699,0))) -> 5.15 | T8: =P8-P7 -> 0 | U8: =Q8-Q7 -> 0.090297638 | W8: =S8-S7 -> 0 | AG8: =N8 -> 24958 | AH8: =IFERROR(INDEX('RBA 5Y yield'!$B$5:$B$661,MATCH(N8,'RBA 5Y yield'!$A$5:$A$661,1))*100,"") | AI8: =IF(AND(ISNUMBER(AH8),ISNUMBER(AH7)),AH8-AH7,"")
A9: 2. Oil and equity returns / interest rates, monthly to 5-year horizons | N9: 24989 | O9: =INDEX('Additional data'!$B$2:$B$965,MATCH(DATE(YEAR(N9),MONTH(N9),1),'Additional data'!$A$2:$A$965,0)) -> 3.07 | P9: =LN(O9) -> 1.1216776 | Q9: =Q8+LN(1+INDEX('Additional data'!$H$2:$H$1196,MATCH(N9,'Additional data'!$G$2:$G$1196,1))+INDEX('Additional data'!$I$2:$I$1196,MATCH(N9,'Additional data'!$G$2:$G$1196,1))) -> 0.052065086 | S9: =IF(INDEX('Additional data'!$E$2:$E$699,MATCH(DATE(YEAR(N9),MONTH(N9),1),'Additional data'!$D$2:$D$699,0))=0,(INDEX('Additional data'!$E$2:$E$699,MATCH(DATE(YEAR(N9),MONTH(N9),1),'Additional data'!$D$2:$D$699,0)-1)+INDEX('Additional data'!$E$2:$E$699,MATCH(DATE(YEAR(N9),MONTH(N9),1),'Additional data'!$D$2:$D$699,0)+1))/2,INDEX('Additional data'!$E$2:$E$699,MATCH(DATE(YEAR(N9),MONTH(N9),1),'Additional data'!$D$2:$D$699,0))) -> 5.3 | T9: =P9-P8 -> 0 | U9: =Q9-Q8 -> 0.026934001 | W9: =S9-S8 -> 0.15 | AG9: =N9 -> 24989 | AH9: =IFERROR(INDEX('RBA 5Y yield'!$B$5:$B$661,MATCH(N9,'RBA 5Y yield'!$A$5:$A$661,1))*100,"") | AI9: =IF(AND(ISNUMBER(AH9),ISNUMBER(AH8)),AH9-AH8,"")
