Workbook

Sheet Summary
A1: EPPIB Strategic Investment Plan
A2: Model status | B2: =Checks!B4 -> ALL CHECKS PASS | D2: Method | E2: =Methods!B2 -> Robust MVO
A4: 1. Strategic asset allocation | H4: 2. Brief compliance
A5: Asset class | B5: Current | C5: Benchmark | D5: Recommended | E5: Change vs current | F5: Trade (A$m) | H5: Requirement | I5: Limit | J5: Recommended | K5: Status
A6: Australian Equities | B6: =Portfolio!C6 -> 0.4 | C6: =Portfolio!D6 -> 0.25 | D6: =Portfolio!E6 -> 0.2697 | E6: =Portfolio!I6 -> -0.1303 | F6: =Portfolio!J6 -> -390.9 | H6: (a) Return: bond yield + 4% | I6: =Inputs!$B$25 -> 0.08988 | J6: =Risk!N58 -> 0.071373051 | K6: =IF(J6>=I6,"MET",IF(Forecast!G18<I6,"MAX FEASIBLE","NOT MET")) -> MAX FEASIBLE
A7: World Equities | B7: =Portfolio!C7 -> 0.2 | C7: =Portfolio!D7 -> 0.24 | D7: =Portfolio!E7 -> 0.2732 | E7: =Portfolio!I7 -> 0.0732 | F7: =Portfolio!J7 -> 219.6 | H7: (b) Risk no higher than current fund | I7: =Risk!M56 -> 0.083833964 | J7: =Risk!M58 -> 0.078750643 | K7: =IF(J7<=I7,"MET","NOT MET") -> MET
A8: Emerging Markets | B8: =Portfolio!C8 -> 0 | C8: =Portfolio!D8 -> 0.03 | D8: =Portfolio!E8 -> 0.0771 | E8: =Portfolio!I8 -> 0.0771 | F8: =Portfolio!J8 -> 231.3 | H8: (c) 5-year loss probability, bootstrap | I8: =Inputs!$B$28 -> 0.25 | J8: =Bootstrap!D6 -> 0.074 | K8: =IF(J8<=I8,"MET","NOT MET") -> MET
A9: Listed Property | B9: =Portfolio!C9 -> 0.1 | C9: =Portfolio!D9 -> 0.07 | D9: =Portfolio!E9 -> 0.0754 | E9: =Portfolio!I9 -> -0.0246 | F9: =Portfolio!J9 -> -73.8 | H9: (c) 5-year loss probability, normal | I9: =Inputs!$B$28 -> 0.25 | J9: =Bootstrap!D7 -> 0.026278647 | K9: =IF(J9<=I9,"MET","NOT MET") -> MET
A10: Commodities | B10: =Portfolio!C10 -> 0 | C10: =Portfolio!D10 -> 0.02 | D10: =Portfolio!E10 -> 0.03 | E10: =Portfolio!I10 -> 0.03 | F10: =Portfolio!J10 -> 90 | H10: (d) Tracking error, parametric | I10: =Inputs!$B$27 -> 0.015 | J10: =Risk!O58 -> 0.010997193 | K10: =IF(J10<=I10,"MET","NOT MET") -> MET
A11: Direct Property | B11: =Portfolio!C11 -> 0 | C11: =Portfolio!D11 -> 0.05 | D11: =Portfolio!E11 -> 0.05 | E11: =Portfolio!I11 -> 0.05 | F11: =Portfolio!J11 -> 150 | H11: (d) Tracking error, bootstrap | I11: =Inputs!$B$27 -> 0.015 | J11: =Bootstrap!D12 -> 0.014051075 | K11: =IF(J11<=I11,"MET","NOT MET") -> MET
A12: Hedge Funds | B12: =Portfolio!C12 -> 0 | C12: =Portfolio!D12 -> 0.03 | D12: =Portfolio!E12 -> 0 | E12: =Portfolio!I12 -> 0 | F12: =Portfolio!J12 -> 0 | H12: (e) Equity minimum | I12: =Inputs!$B$31 -> 0.42 | J12: =Portfolio!B34 -> 0.62 | K12: =IF(J12>=I12-0.000001,"MET","NOT MET") -> MET
A13: Private Equity | B13: =Portfolio!C13 -> 0 | C13: =Portfolio!D13 -> 0.03 | D13: =Portfolio!E13 -> 0.01 | E13: =Portfolio!I13 -> 0.01 | F13: =Portfolio!J13 -> 30 | H13: (e) Equity maximum | I13: =Inputs!$B$32 -> 0.62 | J13: =Portfolio!B34 -> 0.62 | K13: =IF(J13<=I13+0.000001,"MET","NOT MET") -> MET
A14: Australian Fixed Income | B14: =Portfolio!C14 -> 0.15 | C14: =Portfolio!D14 -> 0.14 | D14: =Portfolio!E14 -> 0.1309 | E14: =Portfolio!I14 -> -0.0191 | F14: =Portfolio!J14 -> -57.3 | H14: (e) Illiquid maximum | I14: =Inputs!$B$33 -> 0.3 | J14: =Portfolio!B35 -> 0.06 | K14: =IF(J14<=I14,"MET","NOT MET") -> MET
A15: World Fixed Income | B15: =Portfolio!C15 -> 0.08 | C15: =Portfolio!D15 -> 0.11 | D15: =Portfolio!E15 -> 0.0637 | E15: =Portfolio!I15 -> -0.0163 | F15: =Portfolio!J15 -> -48.9 | H15: (e) Cash minimum | I15: =Inputs!$B$34 -> 0.02 | J15: =Portfolio!B36 -> 0.02 | K15: =IF(J15>=I15,"MET","NOT MET") -> MET
A16: Cash | B16: =Portfolio!C16 -> 0.07 | C16: =Portfolio!D16 -> 0.03 | D16: =Portfolio!E16 -> 0.02 | E16: =Portfolio!I16 -> -0.05 | F16: =Portfolio!J16 -> -150 | H16: (e) No short sales or borrowing | I16: =0 -> 0 | J16: =MIN(Portfolio!E6:E16) -> 0 | K16: =IF(J16>=I16-0.000001,"MET","NOT MET") -> MET
A17: Total | B17: =SUM(B6:B16) -> 1 | C17: =SUM(C6:C16) -> 1 | D17: =SUM(D6:D16) -> 1 | E17: =SUM(E6:E16) -> -5.5511151e-17 | F17: =SUM(F6:F16) -> 0
A18: One-way turnover | D18: =SUMPRODUCT(ABS(Portfolio!I6:I16))/2 -> 0.2403
A19: Change in fees (A$m p.a.) | D19: =(SUMPRODUCT(Portfolio!E6:E16,Inputs!$D$5:$D$15)-SUMPRODUCT(Portfolio!C6:C16,Inputs!$D$5:$D$15))*Inputs!$B$22 -> 3.08475
A22: 3. Expected outcomes (net of fees) | H22: 4. Stress tests (portfolio return)
A23: Metric | B23: Current | C23: Benchmark | D23: Recommended | E23: Change vs current | H23: Scenario | I23: Current | J23: Benchmark | K23: Recommended
A24: Expected return (p.a.) | B24: =Risk!N56 -> 0.071036034 | C24: =Risk!N57 -> 0.067685257 | D24: =Risk!N58 -> 0.071373051 | E24: =D24-B24 -> 0.00033701752 | H24: Global financial crisis | I24: =Stress!B26 -> -0.24167171 | J24: =Stress!B27 -> -0.19300089 | K24: =Stress!B28 -> -0.24131527
A25: Volatility (p.a.) | B25: =Risk!M56 -> 0.083833964 | C25: =Risk!M57 -> 0.070134112 | D25: =Risk!M58 -> 0.078750643 | E25: =D25-B25 -> -0.0050833216 | H25: COVID shock | I25: =Stress!C26 -> -0.12092703 | J25: =Stress!C27 -> -0.091806485 | K25: =Stress!C28 -> -0.11048429
A26: Tracking error, parametric | B26: =Risk!O56 -> 0.021585026 | C26: =Risk!O57 -> 0 | D26: =Risk!O58 -> 0.010997193 | E26: =D26-B26 -> -0.010587833 | H26: Inflation sell-off (2022) | I26: =Stress!D26 -> -0.072754437 | J26: =Stress!D27 -> -0.072610798 | K26: =Stress!D28 -> -0.072174037
A27: Tracking error, bootstrap | B27: =Bootstrap!B12 -> 0.015627427 | C27: =Bootstrap!C12 -> 0 | D27: =Bootstrap!D12 -> 0.014051075 | E27: =D27-B27 -> -0.0015763524 | H27: US$150 oil (central case) | I27: =Stress!E26 -> -0.082609308 | J27: =Stress!E27 -> -0.073910247 | K27: =Stress!E28 -> -0.078202714
A28: 5-year loss probability, bootstrap | B28: =Bootstrap!B6 -> 0.074 | C28: =Bootstrap!C6 -> 0.062 | D28: =Bootstrap!D6 -> 0.074 | E28: =D28-B28 -> 0
A29: Median 5-year cumulative return | B29: =Bootstrap!B9 -> 0.40339615 | C29: =Bootstrap!C9 -> 0.38418584 | D29: =Bootstrap!D9 -> 0.40425217 | E29: =D29-B29 -> 0.00085602612 | H29: 5. Oil: 5-year regression on oil (log) change
A30: Management fee (p.a.) | B30: =SUMPRODUCT(Portfolio!C6:C16,Inputs!$D$5:$D$15) -> 0.00112 | C30: =SUMPRODUCT(Portfolio!D6:D16,Inputs!$D$5:$D$15) -> 0.00338 | D30: =SUMPRODUCT(Portfolio!E6:E16,Inputs!$D$5:$D$15) -> 0.00214825 | E30: =D30-B30 -> 0.00102825 | H30: Series | I30: Beta | J30: t-stat (adj.) | K30: R-squared
H31: US equities | I31: =Oil!C13 -> -0.22998127 | J31: =Oil!E13 -> -1.5542333 | K31: =Oil!F13 -> 0.1858332
H32: Australian equities | I32: =Oil!C16 -> 0.087571808 | J32: =Oil!E16 -> 0.57873507 | K32: =Oil!F16 -> 0.044450857
H33: AU 3-month rate (pp) | I33: =Oil!C19 -> 2.6328845 | J33: =Oil!E19 -> 1.4633798 | K33: =Oil!F19 -> 0.16829169
H34: Likelihood: 12-month rise of this size | K34: =Oil!B51 -> 0.10656934
H36: 6. Out-of-sample (2016-26) and sensitivity
H37: Measure | I37: Robust | J37: Naive MVO | K37: Current
H38: Realised return, annualised | I38: =Validation!B47 -> 0.090015267 | J38: =Validation!C47 -> 0.069929434 | K38: =Validation!D47 -> 0.078948234
H39: Realised volatility | I39: =Validation!B49 -> 0.081380343 | J39: =Validation!C49 -> 0.066488181 | K39: =Validation!D49 -> 0.085331791
H40: Return per unit of risk | I40: =Validation!B50 -> 1.1061058 | J40: =Validation!C50 -> 1.0517574 | K40: =Validation!D50 -> 0.92519133
H41: Max weight move (sensitivity) | K41: =MAX(Validation!E58:E60) -> #VALUE!
H43: 7. Track record: rolling 5-year windows since 2011
H44: Measure | I44: Current | J44: Benchmark | K44: Recommended
H45: Met return target | I45: ='Track record'!M13 -> 0.73770492 | J45: ='Track record'!N13 -> 0.78688525 | K45: ='Track record'!O13 -> 0.78688525
H46: Negative 5-year return | I46: ='Track record'!M14 -> 0.06557377 | J46: ='Track record'!N14 -> 0.016393443 | K46: ='Track record'!O14 -> 0.081967213
H47: Average realised TE | I47: ='Track record'!M16 -> 0.02026313 | J47: 0 | K47: ='Track record'!O16 -> 0.011703948
H49: 8. Methods and forecast risk
H50: Measure | I50: Value
H51: Methods meeting every brief constraint | K51: =COUNTIF(Methods!M22:M26,"MET")&" of 5" -> 5 of 5
H52: Robust vs resampled: largest weight gap | K52: =Methods!D33 -> 0.0375
H53: Return cost of the TE limit | K53: =Portfolio!D58 -> 0.0014354874
H54: Smallest forecast error that removes advantage | K54: =Validation!H79 -> 0.0025864736

Sheet Report figures
A1: Report figures
A3: Figure index
A4: Figure | B4: Title | F4: Source tab
A5: Figure 1 | B5: Risk-return opportunity set | F5: Validation, Methods
A6: Figure 2 | B6: Strategic asset allocation | F6: Portfolio
A7: Figure 3 | B7: Fund performance since 2006 | F7: Quarterly returns, RBA 5Y yield
A8: Figure 4 | B8: Annualised returns to March 2026 | F8: Track record
A9: Figure 5 | B9: Stress tests | F9: Stress
A10: Figure 6 | B10: Five-year outcomes (forecast-adjusted bootstrap) | F10: Bootstrap
A11: Figure 7 | B11: How far the return target is out of reach | F11: Portfolio
A12: Figure 8 | B12: US$150 oil: estimates by method | F12: Oil
A13: Figure 9 | B13: Oil and equity returns by horizon | F13: Oil
A14: Figure 10 | B14: Rolling 5-year return against the target | F14: Track record
A15: Figure 11 | B15: Portfolio construction methods | F15: Methods
... A17: Figure 13 | B17: Forecast stress test | F17: Validation
A20: Figure 1. Risk-return opportunity set | N20: Chart data, figure 1
N21: Point | O21: Vol (no TE limit) | P21: Return (no TE limit) | Q21: Vol (TE limit) | R21: Return (TE limit)
N22: Point 1 | O22: =Validation!B125 -> 0.0494331 | P22: =Validation!B124 -> 0.062369554 | Q22: =Validation!B143 -> 0.060281372 | R22: =Validation!B142 -> 0.06497858
N23: Point 2 | O23: =Validation!C125 -> 0.052676263 | P23: =Validation!C124 -> 0.063528969 | Q23: =Validation!C143 -> 0.060923936 | R23: =Validation!C142 -> 0.065688535
N24: Point 3 | O24: =Validation!D125 -> 0.056100289 | P24: =Validation!D124 -> 0.064690288 | Q24: =Validation!D143 -> 0.062220178 | R24: =Validation!D142 -> 0.066400049
N25: Point 4 | O25: =Validation!E125 -> 0.059637711 | P25: =Validation!E124 -> 0.065848632 | Q25: =Validation!E143 -> 0.064037807 | R25: =Validation!E142 -> 0.067110268
N26: Point 5 | O26: =Validation!F125 -> 0.063204876 | P26: =Validation!F124 -> 0.06700914 | Q26: =Validation!F143 -> 0.066071092 | R26: =Validation!F142 -> 0.067819562
N27: Point 6 | O27: =Validation!G125 -> 0.066799937 | P27: =Validation!G124 -> 0.068168636 | Q27: =Validation!G143 -> 0.06823897 | R27: =Validation!G142 -> 0.068533369
N28: Point 7 | O28: =Validation!H125 -> 0.070451556 | P28: =Validation!H124 -> 0.0693304 | Q28: =Validation!H143 -> 0.070487668 | R28: =Validation!H142 -> 0.069245261
N29: Point 8 | O29: =Validation!I125 -> 0.074469912 | P29: =Validation!I124 -> 0.070489157 | Q29: =Validation!I143 -> 0.072813398 | R29: =Validation!I142 -> 0.069954397
N30: Point 9 | O30: =Validation!J125 -> 0.079018483 | P30: =Validation!J124 -> 0.071648333 | Q30: =Validation!J143 -> 0.075320167 | R30: =Validation!J142 -> 0.070662223
N31: Point 10 | O31: =Validation!K125 -> 0.088695808 | P31: =Validation!K124 -> 0.072808539 | Q31: =Validation!K143 -> 0.078750521 | R31: =Validation!K142 -> 0.071373064
N32: Portfolio | O32: Volatility | P32: Expected return
N33: Current fund | O33: =Risk!M56 -> 0.083833964 | P33: =Risk!N56 -> 0.071036034
N34: Benchmark | O34: =Risk!M57 -> 0.070134112 | P34: =Risk!N57 -> 0.067685257
N35: Recommended | O35: =Risk!M58 -> 0.078750643 | P35: =Risk!N58 -> 0.071373051
N36: Sample MVO | O36: =Methods!C23 -> 0.07771727 | P36: =Methods!B23 -> 0.071087443
N37: Resampled MVO | O37: =Methods!C24 -> 0.075055184 | P37: =Methods!B24 -> 0.069908335
N38: Minimum variance | O38: =Methods!C25 -> 0.060281232 | P38: =Methods!B25 -> 0.064978594
N39: Risk parity | O39: =Methods!C26 -> 0.066508938 | P39: =Methods!B26 -> 0.067165834
A46: Figure 2. Strategic asset allocation | N46: Chart data, figure 2
N47: Asset class | O47: Current fund | P47: Benchmark | Q47: Recommended
N48: Australian Equities | O48: =Summary!B6 -> 0.4 | P48: =Summary!C6 -> 0.25 | Q48: =Summary!D6 -> 0.2697
N49: World Equities | O49: =Summary!B7 -> 0.2 | P49: =Summary!C7 -> 0.24 | Q49: =Summary!D7 -> 0.2732
N50: Emerging Markets | O50: =Summary!B8 -> 0 | P50: =Summary!C8 -> 0.03 | Q50: =Summary!D8 -> 0.0771
N51: Listed Property | O51: =Summary!B9 -> 0.1 | P51: =Summary!C9 -> 0.07 | Q51: =Summary!D9 -> 0.0754
N52: Commodities | O52: =Summary!B10 -> 0 | P52: =Summary!C10 -> 0.02 | Q52: =Summary!D10 -> 0.03
N53: Direct Property | O53: =Summary!B11 -> 0 | P53: =Summary!C11 -> 0.05 | Q53: =Summary!D11 -> 0.05
N54: Hedge Funds | O54: =Summary!B12 -> 0 | P54: =Summary!C12 -> 0.03 | Q54: =Summary!D12 -> 0
N55: Private Equity | O55: =Summary!B13 -> 0 | P55: =Summary!C13 -> 0.03 | Q55: =Summary!D13 -> 0.01
N56: Australian Fixed Income | O56: =Summary!B14 -> 0.15 | P56: =Summary!C14 -> 0.14 | Q56: =Summary!D14 -> 0.1309
N57: World Fixed Income | O57: =Summary!B15 -> 0.08 | P57: =Summary!C15 -> 0.11 | Q57: =Summary!D15 -> 0.0637
N58: Cash | O58: =Summary!B16 -> 0.07 | P58: =Summary!C16 -> 0.03 | Q58: =Summary!D16 -> 0.02
A72: Figure 3. Fund performance since 2006 | V72: Chart data, figure 3
V73: Quarter end | W73: Current fund | X73: Benchmark | Y73: Recommended | Z73: Target: yield + 4%
V74: ='Quarterly returns'!A5 -> 38807 | W74: 1 | X74: 1 | Y74: 1 | Z74: 1
V75: ='Quarterly returns'!A6 -> 38898 | W75: =W74*(1+'Quarterly returns'!Z6) -> 0.98149065 | X75: =X74*(1+'Quarterly returns'!AA6) -> 0.98692795 | Y75: =Y74*(1+'Quarterly returns'!AB6) -> 0.97823154 | Z75: =Z74*(1+INDEX('RBA 5Y yield'!$B$5:$B$661,MATCH(V74,'RBA 5Y yield'!$A$5:$A$661,1))+Inputs!$B$24)^0.25 -> 1.0224749
V76: ='Quarterly returns'!A7 -> 38989 | W76: =W75*(1+'Quarterly returns'!Z7) -> 1.0180659 | X76: =X75*(1+'Quarterly returns'!AA7) -> 1.0183374 | Y76: =Y75*(1+'Quarterly returns'!AB7) -> 1.0090353 | Z76: =Z75*(1+INDEX('RBA 5Y yield'!$B$5:$B$661,MATCH(V75,'RBA 5Y yield'!$A$5:$A$661,1))+Inputs!$B$24)^0.25 -> 1.046531
V77: ='Quarterly returns'!A8 -> 39080 | W77: =W76*(1+'Quarterly returns'!Z8) -> 1.0745821 | X77: =X76*(1+'Quarterly returns'!AA8) -> 1.0613561 | Y77: =Y76*(1+'Quarterly returns'!AB8) -> 1.0548918 | Z77: =Z76*(1+INDEX('RBA 5Y yield'!$B$5:$B$661,MATCH(V76,'RBA 5Y yield'!$A$5:$A$661,1))+Inputs!$B$24)^0.25 -> 1.0713773
V78: ='Quarterly returns'!A9 -> 39171 | W78: =W77*(1+'Quarterly returns'!Z9) -> 1.1120479 | X78: =X77*(1+'Quarterly returns'!AA9) -> 1.0875778 | Y78: =Y77*(1+'Quarterly returns'!AB9) -> 1.0801701 | Z78: =Z77*(1+INDEX('RBA 5Y yield'!$B$5:$B$661,MATCH(V77,'RBA 5Y yield'!$A$5:$A$661,1))+Inputs!$B$24)^0.25 -> 1.0967023
V79: ='Quarterly returns'!A10 -> 39262 | W79: =W78*(1+'Quarterly returns'!Z10) -> 1.1302954 | X79: =X78*(1+'Quarterly returns'!AA10) -> 1.1113934 | Y79: =Y78*(1+'Quarterly returns'!AB10) -> 1.1046184 | Z79: =Z78*(1+INDEX('RBA 5Y yield'!$B$5:$B$661,MATCH(V78,'RBA 5Y yield'!$A$5:$A$661,1))+Inputs!$B$24)^0.25 -> 1.1230585
V80: ='Quarterly returns'!A11 -> 39353 | W80: =W79*(1+'Quarterly returns'!Z11) -> 1.1473411 | X80: =X79*(1+'Quarterly returns'!AA11) -> 1.1236588 | Y80: =Y79*(1+'Quarterly returns'!AB11) -> 1.1188356 | Z80: =Z79*(1+INDEX('RBA 5Y yield'!$B$5:$B$661,MATCH(V79,'RBA 5Y yield'!$A$5:$A$661,1))+Inputs!$B$24)^0.25 -> 1.150327
V81: ='Quarterly returns'!A12 -> 39447 | W81: =W80*(1+'Quarterly returns'!Z12) -> 1.1257386 | X81: =X80*(1+'Quarterly returns'!AA12) -> 1.1176064 | Y81: =Y80*(1+'Quarterly returns'!AB12) -> 1.1108583 | Z81: =Z80*(1+INDEX('RBA 5Y yield'!$B$5:$B$661,MATCH(V80,'RBA 5Y yield'!$A$5:$A$661,1))+Inputs!$B$24)^0.25 -> 1.1784178
V82: ='Quarterly returns'!A13 -> 39538 | W82: =W81*(1+'Quarterly returns'!Z13) -> 1.0244561 | X82: =X81*(1+'Quarterly returns'!AA13) -> 1.0303181 | Y82: =Y81*(1+'Quarterly returns'!AB13) -> 1.0062939 | Z82: =Z81*(1+INDEX('RBA 5Y yield'!$B$5:$B$661,MATCH(V81,'RBA 5Y yield'!$A$5:$A$661,1))+Inputs!$B$24)^0.25 -> 1.2081036
V83: ='Quarterly returns'!A14 -> 39629 | W83: =W82*(1+'Quarterly returns'!Z14) -> 0.99802062 | X83: =X82*(1+'Quarterly returns'!AA14) -> 1.007644 | Y83: =Y82*(1+'Quarterly returns'!AB14) -> 0.97949433 | Z83: =Z82*(1+INDEX('RBA 5Y yield'!$B$5:$B$661,MATCH(V82,'RBA 5Y yield'!$A$5:$A$661,1))+Inputs!$B$24)^0.25 -> 1.2375174
V84: ='Quarterly returns'!A15 -> 39721 | W84: =W83*(1+'Quarterly returns'!Z15) -> 0.99952576 | X84: =X83*(1+'Quarterly returns'!AA15) -> 1.0169578 | Y84: =Y83*(1+'Quarterly returns'!AB15) -> 0.98512081 | Z84: =Z83*(1+INDEX('RBA 5Y yield'!$B$5:$B$661,MATCH(V83,'RBA 5Y yield'!$A$5:$A$661,1))+Inputs!$B$24)^0.25 -> 1.2693422
V85: ='Quarterly returns'!A16 -> 39813 | W85: =W84*(1+'Quarterly returns'!Z16) -> 0.88805352 | X85: =X84*(1+'Quarterly returns'!AA16) -> 0.92449835 | Y85: =Y84*(1+'Quarterly returns'!AB16) -> 0.87569224 | Z85: =Z84*(1+INDEX('RBA 5Y yield'!$B$5:$B$661,MATCH(V84,'RBA 5Y yield'!$A$5:$A$661,1))+Inputs!$B$24)^0.25 -> 1.2985788
V86: ='Quarterly returns'!A17 -> 39903 | W86: =W85*(1+'Quarterly returns'!Z17) -> 0.84551522 | X86: =X85*(1+'Quarterly returns'!AA17) -> 0.88577356 | Y86: =Y85*(1+'Quarterly returns'!AB17) -> 0.83500261 | Z86: =Z85*(1+INDEX('RBA 5Y yield'!$B$5:$B$661,MATCH(V85,'RBA 5Y yield'!$A$5:$A$661,1))+Inputs!$B$24)^0.25 -> 1.3229533
... V97: ='Quarterly returns'!A28 -> 40907 | W97: =W96*(1+'Quarterly returns'!Z28) -> 1.0384037 | X97: =X96*(1+'Quarterly returns'!AA28) -> 1.0584282 | Y97: =Y96*(1+'Quarterly returns'!AB28) -> 0.98149358 | Z97: =Z96*(1+INDEX('RBA 5Y yield'!$B$5:$B$661,MATCH(V96,'RBA 5Y yield'!$A$5:$A$661,1))+Inputs!$B$24)^0.25 -> 1.6707357
A98: Figure 4. Annualised returns to March 2026 | N98: Chart data, figure 4 | V98: ='Quarterly returns'!A29 -> 40998 | W98: =W97*(1+'Quarterly returns'!Z29) -> 1.1106982 | X98: =X97*(1+'Quarterly returns'!AA29) -> 1.1261733 | Y98: =Y97*(1+'Quarterly returns'!AB29) -> 1.0528049 | Z98: =Z97*(1+INDEX('RBA 5Y yield'!$B$5:$B$661,MATCH(V97,'RBA 5Y yield'!$A$5:$A$661,1))+Inputs!$B$24)^0.25 -> 1.7015044
N99: Horizon | O99: Current fund | P99: Benchmark | Q99: Recommended | R99: Target: yield + 4% | V99: ='Quarterly returns'!A30 -> 41089 | W99: =W98*(1+'Quarterly returns'!Z30) -> 1.0952232 | X99: =X98*(1+'Quarterly returns'!AA30) -> 1.113116 | Y99: =Y98*(1+'Quarterly returns'!AB30) -> 1.0334451 | Z99: =Z98*(1+INDEX('RBA 5Y yield'!$B$5:$B$661,MATCH(V98,'RBA 5Y yield'!$A$5:$A$661,1))+Inputs!$B$24)^0.25 -> 1.7330309
N100: 5 years | O100: ='Track record'!M5 -> 0.070238277 | P100: ='Track record'!N5 -> 0.075762595 | Q100: ='Track record'!O5 -> 0.084806042 | R100: ='Track record'!P5 -> 0.04708 | V100: ='Quarterly returns'!A31 -> 41180 | W100: =W99*(1+'Quarterly returns'!Z31) -> 1.1482523 | X100: =X99*(1+'Quarterly returns'!AA31) -> 1.1587431 | Y100: =Y99*(1+'Quarterly returns'!AB31) -> 1.0805689 | Z100: =Z99*(1+INDEX('RBA 5Y yield'!$B$5:$B$661,MATCH(V99,'RBA 5Y yield'!$A$5:$A$661,1))+Inputs!$B$24)^0.25 -> 1.7615634
N101: 10 years | O101: ='Track record'!M6 -> 0.078948234 | P101: ='Track record'!N6 -> 0.082621318 | Q101: ='Track record'!O6 -> 0.090714536 | R101: ='Track record'!P6 -> 0.06134 | V101: ='Quarterly returns'!A32 -> 41274 | W101: =W100*(1+'Quarterly returns'!Z32) -> 1.1949499 | X101: =X100*(1+'Quarterly returns'!AA32) -> 1.1990838 | Y101: =Y100*(1+'Quarterly returns'!AB32) -> 1.1228867 | Z101: =Z100*(1+INDEX('RBA 5Y yield'!$B$5:$B$661,MATCH(V100,'RBA 5Y yield'!$A$5:$A$661,1))+Inputs!$B$24)^0.25 -> 1.7908487
N102: 15 years | O102: ='Track record'!M7 -> 0.083517286 | P102: ='Track record'!N7 -> 0.086621873 | Q102: ='Track record'!O7 -> 0.092163514 | R102: ='Track record'!P7 -> 0.092075 | V102: ='Quarterly returns'!A33 -> 41362 | W102: =W101*(1+'Quarterly returns'!Z33) -> 1.268528 | X102: =X101*(1+'Quarterly returns'!AA33) -> 1.2612455 | Y102: =Y101*(1+'Quarterly returns'!AB33) -> 1.1835736 | Z102: =Z101*(1+INDEX('RBA 5Y yield'!$B$5:$B$661,MATCH(V101,'RBA 5Y yield'!$A$5:$A$661,1))+Inputs!$B$24)^0.25 -> 1.8206527
N103: 20 years | O103: ='Track record'!M8 -> 0.066782824 | P103: ='Track record'!N8 -> 0.069169199 | Q103: ='Track record'!O8 -> 0.070415783 | R103: ='Track record'!P8 -> 0.092976 | V103: ='Quarterly returns'!A34 -> 41453 | W103: =W102*(1+'Quarterly returns'!Z34) -> 1.3072155 | X103: =X102*(1+'Quarterly returns'!AA34) -> 1.3202339 | Y103: =Y102*(1+'Quarterly returns'!AB34) -> 1.2504495 | Z103: =Z102*(1+INDEX('RBA 5Y yield'!$B$5:$B$661,MATCH(V102,'RBA 5Y yield'!$A$5:$A$661,1))+Inputs!$B$24)^0.25 -> 1.8517969
V104: ='Quarterly returns'!A35 -> 41547 | W104: =W103*(1+'Quarterly returns'!Z35) -> 1.374995 | X104: =X103*(1+'Quarterly returns'!AA35) -> 1.3765225 | Y104: =Y103*(1+'Quarterly returns'!AB35) -> 1.307816 | Z104: =Z103*(1+INDEX('RBA 5Y yield'!$B$5:$B$661,MATCH(V103,'RBA 5Y yield'!$A$5:$A$661,1))+Inputs!$B$24)^0.25 -> 1.88245
V105: ='Quarterly returns'!A36 -> 41639 | W105: =W104*(1+'Quarterly returns'!Z36) -> 1.4394491 | X105: =X104*(1+'Quarterly returns'!AA36) -> 1.4546503 | Y105: =Y104*(1+'Quarterly returns'!AB36) -> 1.3895435 | Z105: =Z104*(1+INDEX('RBA 5Y yield'!$B$5:$B$661,MATCH(V104,'RBA 5Y yield'!$A$5:$A$661,1))+Inputs!$B$24)^0.25 -> 1.9160408
V106: ='Quarterly returns'!A37 -> 41729 | W106: =W105*(1+'Quarterly returns'!Z37) -> 1.4566785 | X106: =X105*(1+'Quarterly returns'!AA37) -> 1.4623973 | Y106: =Y105*(1+'Quarterly returns'!AB37) -> 1.3908958 | Z106: =Z105*(1+INDEX('RBA 5Y yield'!$B$5:$B$661,MATCH(V105,'RBA 5Y yield'!$A$5:$A$661,1))+Inputs!$B$24)^0.25 -> 1.9508212
V107: ='Quarterly returns'!A38 -> 41820 | W107: =W106*(1+'Quarterly returns'!Z38) -> 1.4864219 | X107: =X106*(1+'Quarterly returns'!AA38) -> 1.4972875 | Y107: =Y106*(1+'Quarterly returns'!AB38) -> 1.4242615 | Z107: =Z106*(1+INDEX('RBA 5Y yield'!$B$5:$B$661,MATCH(V106,'RBA 5Y yield'!$A$5:$A$661,1))+Inputs!$B$24)^0.25 -> 1.9860019
V108: ='Quarterly returns'!A39 -> 41912 | W108: =W107*(1+'Quarterly returns'!Z39) -> 1.5253086 | X108: =X107*(1+'Quarterly returns'!AA39) -> 1.5466594 | Y108: =Y107*(1+'Quarterly returns'!AB39) -> 1.4761863 | Z108: =Z107*(1+INDEX('RBA 5Y yield'!$B$5:$B$661,MATCH(V107,'RBA 5Y yield'!$A$5:$A$661,1))+Inputs!$B$24)^0.25 -> 2.0204368
V109: ='Quarterly returns'!A40 -> 42004 | W109: =W108*(1+'Quarterly returns'!Z40) -> 1.6168843 | X109: =X108*(1+'Quarterly returns'!AA40) -> 1.6339847 | Y109: =Y108*(1+'Quarterly returns'!AB40) -> 1.5632946 | Z109: =Z108*(1+INDEX('RBA 5Y yield'!$B$5:$B$661,MATCH(V108,'RBA 5Y yield'!$A$5:$A$661,1))+Inputs!$B$24)^0.25 -> 2.0550993
V110: ='Quarterly returns'!A41 -> 42094 | W110: =W109*(1+'Quarterly returns'!Z41) -> 1.7555198 | X110: =X109*(1+'Quarterly returns'!AA41) -> 1.7614219 | Y110: =Y109*(1+'Quarterly returns'!AB41) -> 1.6998069 | Z110: =Z109*(1+INDEX('RBA 5Y yield'!$B$5:$B$661,MATCH(V109,'RBA 5Y yield'!$A$5:$A$661,1))+Inputs!$B$24)^0.25 -> 2.0873916
V111: ='Quarterly returns'!A42 -> 42185 | W111: =W110*(1+'Quarterly returns'!Z42) -> 1.6856711 | X111: =X110*(1+'Quarterly returns'!AA42) -> 1.7245972 | Y111: =Y110*(1+'Quarterly returns'!AB42) -> 1.6624936 | Z111: =Z110*(1+INDEX('RBA 5Y yield'!$B$5:$B$661,MATCH(V110,'RBA 5Y yield'!$A$5:$A$661,1))+Inputs!$B$24)^0.25 -> 2.1179117
V112: ='Quarterly returns'!A43 -> 42277 | W112: =W111*(1+'Quarterly returns'!Z43) -> 1.677062 | X112: =X111*(1+'Quarterly returns'!AA43) -> 1.7205212 | Y112: =Y111*(1+'Quarterly returns'!AB43) -> 1.6499257 | Z112: =Z111*(1+INDEX('RBA 5Y yield'!$B$5:$B$661,MATCH(V111,'RBA 5Y yield'!$A$5:$A$661,1))+Inputs!$B$24)^0.25 -> 2.1504479
V113: ='Quarterly returns'!A44 -> 42369 | W113: =W112*(1+'Quarterly returns'!Z44) -> 1.7342118 | X113: =X112*(1+'Quarterly returns'!AA44) -> 1.7574522 | Y113: =Y112*(1+'Quarterly returns'!AB44) -> 1.6801611 | Z113: =Z112*(1+INDEX('RBA 5Y yield'!$B$5:$B$661,MATCH(V112,'RBA 5Y yield'!$A$5:$A$661,1))+Inputs!$B$24)^0.25 -> 2.1825228
V114: ='Quarterly returns'!A45 -> 42460 | W114: =W113*(1+'Quarterly returns'!Z45) -> 1.7041751 | X114: =X113*(1+'Quarterly returns'!AA45) -> 1.7225151 | Y114: =Y113*(1+'Quarterly returns'!AB45) -> 1.6365869 | Z114: =Z113*(1+INDEX('RBA 5Y yield'!$B$5:$B$661,MATCH(V113,'RBA 5Y yield'!$A$5:$A$661,1))+Inputs!$B$24)^0.25 -> 2.2160306
V115: ='Quarterly returns'!A46 -> 42551 | W115: =W114*(1+'Quarterly returns'!Z46) -> 1.7738938 | X115: =X114*(1+'Quarterly returns'!AA46) -> 1.7976807 | Y115: =Y114*(1+'Quarterly returns'!AB46) -> 1.7149564 | Z115: =Z114*(1+INDEX('RBA 5Y yield'!$B$5:$B$661,MATCH(V114,'RBA 5Y yield'!$A$5:$A$661,1))+Inputs!$B$24)^0.25 -> 2.2492586
... V123: ='Quarterly returns'!A54 -> 43280 | W123: =W122*(1+'Quarterly returns'!Z54) -> 2.117876 | X123: =X122*(1+'Quarterly returns'!AA54) -> 2.1462962 | Y123: =Y122*(1+'Quarterly returns'!AB54) -> 2.0891901 | Z123: =Z122*(1+INDEX('RBA 5Y yield'!$B$5:$B$661,MATCH(V122,'RBA 5Y yield'!$A$5:$A$661,1))+Inputs!$B$24)^0.25 -> 2.5301516
A124: Figure 5. Stress tests | N124: Chart data, figure 5 | V124: ='Quarterly returns'!A55 -> 43371 | W124: =W123*(1+'Quarterly returns'!Z55) -> 2.1743275 | X124: =X123*(1+'Quarterly returns'!AA55) -> 2.2037908 | Y124: =Y123*(1+'Quarterly returns'!AB55) -> 2.1528883 | Z124: =Z123*(1+INDEX('RBA 5Y yield'!$B$5:$B$661,MATCH(V123,'RBA 5Y yield'!$A$5:$A$661,1))+Inputs!$B$24)^0.25 -> 2.5697877
N125: Scenario | O125: Current fund | P125: Benchmark | Q125: Recommended | V125: ='Quarterly returns'!A56 -> 43465 | W125: =W124*(1+'Quarterly returns'!Z56) -> 2.0550632 | X125: =X124*(1+'Quarterly returns'!AA56) -> 2.0883596 | Y125: =Y124*(1+'Quarterly returns'!AB56) -> 2.0170762 | Z125: =Z124*(1+INDEX('RBA 5Y yield'!$B$5:$B$661,MATCH(V124,'RBA 5Y yield'!$A$5:$A$661,1))+Inputs!$B$24)^0.25 -> 2.6089649
N126: GFC 2007-09 | O126: =Stress!B26 -> -0.24167171 | P126: =Stress!B27 -> -0.19300089 | Q126: =Stress!B28 -> -0.24131527 | V126: ='Quarterly returns'!A57 -> 43553 | W126: =W125*(1+'Quarterly returns'!Z57) -> 2.2376319 | X126: =X125*(1+'Quarterly returns'!AA57) -> 2.2506098 | Y126: =Y125*(1+'Quarterly returns'!AB57) -> 2.194059 | Z126: =Z125*(1+INDEX('RBA 5Y yield'!$B$5:$B$661,MATCH(V125,'RBA 5Y yield'!$A$5:$A$661,1))+Inputs!$B$24)^0.25 -> 2.6478539
N127: COVID 2020 | O127: =Stress!C26 -> -0.12092703 | P127: =Stress!C27 -> -0.091806485 | Q127: =Stress!C28 -> -0.11048429 | V127: ='Quarterly returns'!A58 -> 43644 | W127: =W126*(1+'Quarterly returns'!Z58) -> 2.3520053 | X127: =X126*(1+'Quarterly returns'!AA58) -> 2.3512321 | Y127: =Y126*(1+'Quarterly returns'!AB58) -> 2.2956167 | Z127: =Z126*(1+INDEX('RBA 5Y yield'!$B$5:$B$661,MATCH(V126,'RBA 5Y yield'!$A$5:$A$661,1))+Inputs!$B$24)^0.25 -> 2.6850781
N128: Inflation 2022 | O128: =Stress!D26 -> -0.072754437 | P128: =Stress!D27 -> -0.072610798 | Q128: =Stress!D28 -> -0.072174037 | V128: ='Quarterly returns'!A59 -> 43738 | W128: =W127*(1+'Quarterly returns'!Z59) -> 2.4440619 | X128: =X127*(1+'Quarterly returns'!AA59) -> 2.4456431 | Y128: =Y127*(1+'Quarterly returns'!AB59) -> 2.391753 | Z128: =Z127*(1+INDEX('RBA 5Y yield'!$B$5:$B$661,MATCH(V127,'RBA 5Y yield'!$A$5:$A$661,1))+Inputs!$B$24)^0.25 -> 2.7199113
N129: US$150 oil | O129: =Stress!E26 -> -0.082609308 | P129: =Stress!E27 -> -0.073910247 | Q129: =Stress!E28 -> -0.078202714 | V129: ='Quarterly returns'!A60 -> 43830 | W129: =W128*(1+'Quarterly returns'!Z60) -> 2.451595 | X129: =X128*(1+'Quarterly returns'!AA60) -> 2.4731689 | Y129: =Y128*(1+'Quarterly returns'!AB60) -> 2.4266778 | Z129: =Z128*(1+INDEX('RBA 5Y yield'!$B$5:$B$661,MATCH(V128,'RBA 5Y yield'!$A$5:$A$661,1))+Inputs!$B$24)^0.25 -> 2.7520443
V130: ='Quarterly returns'!A61 -> 43921 | W130: =W129*(1+'Quarterly returns'!Z61) -> 2.1551309 | X130: =X129*(1+'Quarterly returns'!AA61) -> 2.246116 | Y130: =Y129*(1+'Quarterly returns'!AB61) -> 2.1585681 | Z130: =Z129*(1+INDEX('RBA 5Y yield'!$B$5:$B$661,MATCH(V129,'RBA 5Y yield'!$A$5:$A$661,1))+Inputs!$B$24)^0.25 -> 2.7849819
V131: ='Quarterly returns'!A62 -> 44012 | W131: =W130*(1+'Quarterly returns'!Z62) -> 2.331277 | X131: =X130*(1+'Quarterly returns'!AA62) -> 2.3672702 | Y131: =Y130*(1+'Quarterly returns'!AB62) -> 2.2923699 | Z131: =Z130*(1+INDEX('RBA 5Y yield'!$B$5:$B$661,MATCH(V130,'RBA 5Y yield'!$A$5:$A$661,1))+Inputs!$B$24)^0.25 -> 2.8157977
V132: ='Quarterly returns'!A63 -> 44104 | W132: =W131*(1+'Quarterly returns'!Z63) -> 2.3529438 | X132: =X131*(1+'Quarterly returns'!AA63) -> 2.4098369 | Y132: =Y131*(1+'Quarterly returns'!AB63) -> 2.3318077 | Z132: =Z131*(1+INDEX('RBA 5Y yield'!$B$5:$B$661,MATCH(V131,'RBA 5Y yield'!$A$5:$A$661,1))+Inputs!$B$24)^0.25 -> 2.8462936
V133: ='Quarterly returns'!A64 -> 44196 | W133: =W132*(1+'Quarterly returns'!Z64) -> 2.5168491 | X133: =X132*(1+'Quarterly returns'!AA64) -> 2.549676 | Y133: =Y132*(1+'Quarterly returns'!AB64) -> 2.4847651 | Z133: =Z132*(1+INDEX('RBA 5Y yield'!$B$5:$B$661,MATCH(V132,'RBA 5Y yield'!$A$5:$A$661,1))+Inputs!$B$24)^0.25 -> 2.8770509
V134: ='Quarterly returns'!A65 -> 44286 | W134: =W133*(1+'Quarterly returns'!Z65) -> 2.5948837 | X134: =X133*(1+'Quarterly returns'!AA65) -> 2.6445183 | Y134: =Y133*(1+'Quarterly returns'!AB65) -> 2.5959098 | Z134: =Z133*(1+INDEX('RBA 5Y yield'!$B$5:$B$661,MATCH(V133,'RBA 5Y yield'!$A$5:$A$661,1))+Inputs!$B$24)^0.25 -> 2.9077922
V135: ='Quarterly returns'!A66 -> 44377 | W135: =W134*(1+'Quarterly returns'!Z66) -> 2.7720576 | X135: =X134*(1+'Quarterly returns'!AA66) -> 2.8297057 | Y135: =Y134*(1+'Quarterly returns'!AB66) -> 2.7917973 | Z135: =Z134*(1+INDEX('RBA 5Y yield'!$B$5:$B$661,MATCH(V134,'RBA 5Y yield'!$A$5:$A$661,1))+Inputs!$B$24)^0.25 -> 2.9414288
V136: ='Quarterly returns'!A67 -> 44469 | W136: =W135*(1+'Quarterly returns'!Z67) -> 2.8351341 | X136: =X135*(1+'Quarterly returns'!AA67) -> 2.9059907 | Y136: =Y135*(1+'Quarterly returns'!AB67) -> 2.8623155 | Z136: =Z135*(1+INDEX('RBA 5Y yield'!$B$5:$B$661,MATCH(V135,'RBA 5Y yield'!$A$5:$A$661,1))+Inputs!$B$24)^0.25 -> 2.9756249
V137: ='Quarterly returns'!A68 -> 44561 | W137: =W136*(1+'Quarterly returns'!Z68) -> 2.9338209 | X137: =X136*(1+'Quarterly returns'!AA68) -> 3.0055677 | Y137: =Y136*(1+'Quarterly returns'!AB68) -> 2.9668668 | Z137: =Z136*(1+INDEX('RBA 5Y yield'!$B$5:$B$661,MATCH(V136,'RBA 5Y yield'!$A$5:$A$661,1))+Inputs!$B$24)^0.25 -> 3.0097298
V138: ='Quarterly returns'!A69 -> 44651 | W138: =W137*(1+'Quarterly returns'!Z69) -> 2.8501668 | X138: =X137*(1+'Quarterly returns'!AA69) -> 2.9113319 | Y138: =Y137*(1+'Quarterly returns'!AB69) -> 2.8751325 | Z138: =Z137*(1+INDEX('RBA 5Y yield'!$B$5:$B$661,MATCH(V137,'RBA 5Y yield'!$A$5:$A$661,1))+Inputs!$B$24)^0.25 -> 3.0490135
V139: ='Quarterly returns'!A70 -> 44742 | W139: =W138*(1+'Quarterly returns'!Z70) -> 2.6167816 | X139: =X138*(1+'Quarterly returns'!AA70) -> 2.7186335 | Y139: =Y138*(1+'Quarterly returns'!AB70) -> 2.6854752 | Z139: =Z138*(1+INDEX('RBA 5Y yield'!$B$5:$B$661,MATCH(V138,'RBA 5Y yield'!$A$5:$A$661,1))+Inputs!$B$24)^0.25 -> 3.0952854
V140: ='Quarterly returns'!A71 -> 44834 | W140: =W139*(1+'Quarterly returns'!Z71) -> 2.620491 | X140: =X139*(1+'Quarterly returns'!AA71) -> 2.7054961 | Y140: =Y139*(1+'Quarterly returns'!AB71) -> 2.6748317 | Z140: =Z139*(1+INDEX('RBA 5Y yield'!$B$5:$B$661,MATCH(V139,'RBA 5Y yield'!$A$5:$A$661,1))+Inputs!$B$24)^0.25 -> 3.151721
...

Sheet Inputs
A1: Inputs
A3: 1. Asset classes (linked to Fund balance sheet and Fee schedule)
A4: Asset class | B4: Current fund | C4: Benchmark | D4: Fee (p.a.) | E4: Lower bound | F4: Upper bound | G4: Equity (1/0) | H4: Illiquid (1/0) | J4: Blue = input
A5: Australian Equities | B5: =N('Fund balance sheet'!C7) -> 0.4 | C5: =N('Fund balance sheet'!D7) -> 0.25 | D5: ='Fee schedule'!B6 -> 0.001 | E5: 0.15 | F5: 0.35 | G5: 1 | H5: 0 | J5: Black = formula
A6: World Equities | B6: =N('Fund balance sheet'!C8) -> 0.2 | C6: =N('Fund balance sheet'!D8) -> 0.24 | D6: ='Fee schedule'!B7 -> 0.0015 | E6: 0.15 | F6: 0.35 | G6: 1 | H6: 0 | J6: Yellow = Solver decision cell
A7: Emerging Markets | B7: =N('Fund balance sheet'!C9) -> 0 | C7: =N('Fund balance sheet'!D9) -> 0.03 | D7: ='Fee schedule'!B8 -> 0.002 | E7: 0 | F7: 0.08 | G7: 1 | H7: 0
A8: Listed Property | B8: =N('Fund balance sheet'!C19) -> 0.1 | C8: =N('Fund balance sheet'!D19) -> 0.07 | D8: ='Fee schedule'!B9 -> 0.0015 | E8: 0 | F8: 0.12 | G8: 0 | H8: 0
A9: Commodities | B9: =N('Fund balance sheet'!C26) -> 0 | C9: =N('Fund balance sheet'!D26) -> 0.02 | D9: ='Fee schedule'!B17 -> 0.0025 | E9: 0 | F9: 0.08 | G9: 0 | H9: 0
A10: Direct Property | B10: =N('Fund balance sheet'!C20) -> 0 | C10: =N('Fund balance sheet'!D20) -> 0.05 | D10: ='Fee schedule'!B14 -> 0.012 | E10: 0 | F10: 0.1 | G10: 0 | H10: 1
A11: Hedge Funds | B11: =N('Fund balance sheet'!C24) -> 0 | C11: =N('Fund balance sheet'!D24) -> 0.03 | D11: ='Fee schedule'!B15 -> 0.025 | E11: 0 | F11: 0.08 | G11: 0 | H11: 1
A12: Private Equity | B12: =N('Fund balance sheet'!C25) -> 0 | C12: =N('Fund balance sheet'!D25) -> 0.03 | D12: ='Fee schedule'!B16 -> 0.03 | E12: 0 | F12: 0.08 | G12: 0 | H12: 1
A13: Australian Fixed Income | B13: =N('Fund balance sheet'!C13) -> 0.15 | C13: =N('Fund balance sheet'!D13) -> 0.14 | D13: ='Fee schedule'!B10 -> 0.001 | E13: 0.05 | F13: 0.25 | G13: 0 | H13: 0
A14: World Fixed Income | B14: =N('Fund balance sheet'!C14) -> 0.08 | C14: =N('Fund balance sheet'!D14) -> 0.11 | D14: ='Fee schedule'!B11 -> 0.0015 | E14: 0.05 | F14: 0.2 | G14: 0 | H14: 0
A15: Cash | B15: =N('Fund balance sheet'!C15) -> 0.07 | C15: =N('Fund balance sheet'!D15) -> 0.03 | D15: ='Fee schedule'!B5 -> 0 | E15: 0.02 | F15: 0.1 | G15: 0 | H15: 0
A16: Total | B16: =SUM(B5:B15) -> 1 | C16: =SUM(C5:C15) -> 1
A20: 2. Mandate and constraints
A21: Parameter | B21: Value | C21: Source
A22: Funds under management (A$m) | B22: ='Fund balance sheet'!B29 -> 3000 | C22: Fund balance sheet
A23: 5-year bond yield | B23: 0.04988 | C23: RBA F2, 22-Sep-26
A24: Target spread | B24: 0.04 | C24: Brief
A25: Required return (yield + spread) | B25: =B23+B24 -> 0.08988 | C25: Calc
A26: Australian cash rate | B26: 0.046 | C26: RBA, 29-Sep-26
A27: Tracking error limit | B27: 0.015 | C27: Brief
A28: 5-year loss probability limit | B28: 0.25 | C28: Brief
A29: Equity band (+/-) | B29: 0.1 | C29: Brief
A30: Benchmark equity weight | B30: =SUMPRODUCT(C5:C15,G5:G15) -> 0.52 | C30: Calc
A31: Equity minimum | B31: =B30-B29 -> 0.42 | C31: Calc
A32: Equity maximum | B32: =B30+B29 -> 0.62 | C32: Calc
A33: Illiquid maximum | B33: 0.3 | C33: Brief
A34: Cash minimum | B34: 0.02 | C34: Brief
A36: 3. Model settings
A37: Parameter | B37: Value | C37: Source
A38: Shrinkage intensity | B38: 0.35 | C38: Ledoit-Wolf (2004)
A39: Direct property smoothing | B39: 0.65 | C39: Lag-1 autocorrelation
A40: Private equity smoothing | B40: 0.24 | C40: Lag-1 autocorrelation
A41: Risk aversion (delta) | B41: 4 | C41: Black-Litterman
A42: Max confidence in building blocks | B42: 0.65 | C42: Judgement
A43: Min confidence in building blocks | B43: 0.2 | C43: Judgement
A44: Method dispersion at min confidence | B44: 0.04 | C44: Judgement
A45: TE limit in optimiser | B45: 0.011 | C45: Calibrated: bootstrap TE < 1.5%
A46: Equal Aus/world equity returns (1 = yes) | B46: 1 | C46: Lecture 5
A47: Stage 2 overweight cap | B47: 0.02 | C47: Judgement
A48: Bootstrap seed | B48: 20261016 | C48: Fixed seed
A49: Selected method (1 Robust, 2 Sample, 3 Resampled, 4 Min var, 5 Risk parity) | B49: 1 | C49: Methods tab

Sheet Forecast
A1: Forecast
A3: 1. Summary
A5: Asset class | B5: Building-block composite | C5: Equilibrium prior | D5: Confidence | E5: Gross forecast | F5: Fee | G5: Net forecast | H5: Volatility | I5: Method dispersion
A6: Australian Equities | B6: =D59 -> 0.084754476 | C6: =Inputs!$B$23+Inputs!$B$41*SUMPRODUCT(MMULT(Risk!$B$41:$L$41,Inputs!$C$5:$C$15)) -> 0.085434421 | D6: =Inputs!$B$42-(Inputs!$B$42-Inputs!$B$43)*MIN(1,I6/Inputs!$B$44) -> 0.49408803 | E6: =IF(Inputs!$B$46=1,AVERAGE((D6*B6+(1-D6)*C6),(D7*B7+(1-D7)*C7)),(D6*B6+(1-D6)*C6)) -> 0.083659384 | F6: =Inputs!D5 -> 0.001 | G6: =E6-F6 -> 0.082659384 | H6: =Risk!M41 -> 0.15381532 | I6: =STDEV(B56:B58) -> 0.013858842
A7: World Equities | B7: =D65 -> 0.088623855 | C7: =Inputs!$B$23+Inputs!$B$41*SUMPRODUCT(MMULT(Risk!$B$42:$L$42,Inputs!$C$5:$C$15)) -> 0.077973432 | D7: =Inputs!$B$42-(Inputs!$B$42-Inputs!$B$43)*MIN(1,I7/Inputs!$B$44) -> 0.39875113 | E7: =IF(Inputs!$B$46=1,AVERAGE((D6*B6+(1-D6)*C6),(D7*B7+(1-D7)*C7)),(D7*B7+(1-D7)*C7)) -> 0.083659384 | F7: =Inputs!D6 -> 0.0015 | G7: =E7-F7 -> 0.082159384 | H7: =Risk!M42 -> 0.12748315 | I7: =STDEV(B62:B64) -> 0.022333233
A8: Emerging Markets | B8: =D70 -> 0.10011391 | C8: =Inputs!$B$23+Inputs!$B$41*SUMPRODUCT(MMULT(Risk!$B$43:$L$43,Inputs!$C$5:$C$15)) -> 0.066679499 | D8: =Inputs!$B$42-(Inputs!$B$42-Inputs!$B$43)*MIN(1,I8/Inputs!$B$44) -> 0.42129531 | E8: =(D8*B8+(1-D8)*C8) -> 0.080765261 | F8: =Inputs!D7 -> 0.002 | G8: =E8-F8 -> 0.078765261 | H8: =Risk!M43 -> 0.1049906 | I8: =STDEV(B68:B69) -> 0.020329306
A9: Listed Property | B9: =D76 -> 0.071009812 | C9: =Inputs!$B$23+Inputs!$B$41*SUMPRODUCT(MMULT(Risk!$B$44:$L$44,Inputs!$C$5:$C$15)) -> 0.07862403 | D9: =Inputs!$B$42-(Inputs!$B$42-Inputs!$B$43)*MIN(1,I9/Inputs!$B$44) -> 0.5110096 | E9: =(D9*B9+(1-D9)*C9) -> 0.074733091 | F9: =Inputs!D8 -> 0.0015 | G9: =E9-F9 -> 0.073233091 | H9: =Risk!M44 -> 0.16766255 | I9: =STDEV(B73:B75) -> 0.012354702
A10: Commodities | B10: =D81 -> 0.023213975 | C10: =Inputs!$B$23+Inputs!$B$41*SUMPRODUCT(MMULT(Risk!$B$45:$L$45,Inputs!$C$5:$C$15)) -> 0.066007581 | D10: =Inputs!$B$42-(Inputs!$B$42-Inputs!$B$43)*MIN(1,I10/Inputs!$B$44) -> 0.30961632 | E10: =(D10*B10+(1-D10)*C10) -> 0.052757982 | F10: =Inputs!D9 -> 0.0025 | G10: =E10-F10 -> 0.050257982 | H10: =Risk!M45 -> 0.24588035 | I10: =STDEV(B79:B80) -> 0.030256327
A11: Direct Property | B11: =D87 -> 0.073981617 | C11: =Inputs!$B$23+Inputs!$B$41*SUMPRODUCT(MMULT(Risk!$B$46:$L$46,Inputs!$C$5:$C$15)) -> 0.057809544 | D11: =Inputs!$B$42-(Inputs!$B$42-Inputs!$B$43)*MIN(1,I11/Inputs!$B$44) -> 0.5315161 | E11: =(D11*B11+(1-D11)*C11) -> 0.066405261 | F11: =Inputs!D10 -> 0.012 | G11: =E11-F11 -> 0.054405261 | H11: =Risk!M46 -> 0.095333549 | I11: =STDEV(B84:B86) -> 0.010531902
A12: Hedge Funds | B12: =D92 -> 0.065868087 | C12: =Inputs!$B$23+Inputs!$B$41*SUMPRODUCT(MMULT(Risk!$B$47:$L$47,Inputs!$C$5:$C$15)) -> 0.049701287 | D12: =Inputs!$B$42-(Inputs!$B$42-Inputs!$B$43)*MIN(1,I12/Inputs!$B$44) -> 0.52859314 | E12: =(D12*B12+(1-D12)*C12) -> 0.058246947 | F12: =Inputs!D11 -> 0.025 | G12: =E12-F12 -> 0.033246947 | H12: =Risk!M47 -> 0.071939397 | I12: =STDEV(B90:B91) -> 0.010791721
A13: Private Equity | B13: =D97 -> 0.10270697 | C13: =Inputs!$B$23+Inputs!$B$41*SUMPRODUCT(MMULT(Risk!$B$48:$L$48,Inputs!$C$5:$C$15)) -> 0.067396811 | D13: =Inputs!$B$42-(Inputs!$B$42-Inputs!$B$43)*MIN(1,I13/Inputs!$B$44) -> 0.60266541 | E13: =(D13*B13+(1-D13)*C13) -> 0.08867702 | F13: =Inputs!D12 -> 0.03 | G13: =E13-F13 -> 0.05867702 | H13: =Risk!M48 -> 0.12724606 | I13: =STDEV(B95:B96) -> 0.0042075187
A14: Australian Fixed Income | B14: =D102 -> 0.047311576 | C14: =Inputs!$B$23+Inputs!$B$41*SUMPRODUCT(MMULT(Risk!$B$49:$L$49,Inputs!$C$5:$C$15)) -> 0.050887359 | D14: =Inputs!$B$42-(Inputs!$B$42-Inputs!$B$43)*MIN(1,I14/Inputs!$B$44) -> 0.56827326 | E14: =(D14*B14+(1-D14)*C14) -> 0.048855337 | F14: =Inputs!D13 -> 0.001 | G14: =E14-F14 -> 0.047855337 | H14: =Risk!M49 -> 0.042489011 | I14: =STDEV(B100:B101) -> 0.0072645995
A15: World Fixed Income | B15: =D108 -> 0.047902908 | C15: =Inputs!$B$23+Inputs!$B$41*SUMPRODUCT(MMULT(Risk!$B$50:$L$50,Inputs!$C$5:$C$15)) -> 0.051289318 | D15: =Inputs!$B$42-(Inputs!$B$42-Inputs!$B$43)*MIN(1,I15/Inputs!$B$44) -> 0.60995668 | E15: =(D15*B15+(1-D15)*C15) -> 0.049223755 | F15: =Inputs!D14 -> 0.0015 | G15: =E15-F15 -> 0.047723755 | H15: =Risk!M50 -> 0.040530808 | I15: =STDEV(B105:B107) -> 0.0035594059
A16: Cash | B16: =D113 -> 0.042582357 | C16: =Inputs!$B$23+Inputs!$B$41*SUMPRODUCT(MMULT(Risk!$B$51:$L$51,Inputs!$C$5:$C$15)) -> 0.049641723 | D16: =Inputs!$B$42-(Inputs!$B$42-Inputs!$B$43)*MIN(1,I16/Inputs!$B$44) -> 0.51406408 | E16: =(D16*B16+(1-D16)*C16) -> 0.046012756 | F16: =Inputs!D15 -> 0 | G16: =E16-F16 -> 0.046012756 | H16: =Risk!M51 -> 0.0098119767 | I16: =STDEV(B111:B112) -> 0.012083193
A18: Best single-asset forecast | G18: =MAX(G6:G16) -> 0.082659384
A19: Return target (bond yield + 4%) | G19: =Inputs!$B$25 -> 0.08988
A20: Target reachable? | G20: =IF(G18>=G19,"YES","NO") -> NO
A23: 2. Historical returns (adjusted quarterly data) | K23: Parameters
A24: Asset class | B24: 20-year CAGR | C24: 10-year CAGR | D24: 5-year CAGR | E24: Excess vs cash, 20y | F24: Excess vs cash, 10y | G24: Excess vs cash, 5y | H24: Weighted excess | K24: Excess weight: 20 years | L24: 0.5
A25: Australian Equities | B25: =EXP(SUMPRODUCT(LN(1+'Quarterly returns'!N$6:N$85))*4/80)-1 -> 0.06950125 | C25: =EXP(SUMPRODUCT(LN(1+'Quarterly returns'!N$46:N$85))*4/40)-1 -> 0.094599768 | D25: =EXP(SUMPRODUCT(LN(1+'Quarterly returns'!N$66:N$85))*4/20)-1 -> 0.0836422 | E25: =B25-B$35 -> 0.0364421 | F25: =C25-C$35 -> 0.072734217 | G25: =D25-D$35 -> 0.054730416 | H25: =$L$24*E25+$L$25*F25+$L$26*G25 -> 0.050987399 | K25: Excess weight: 10 years | L25: 0.3
A26: World Equities | B26: =EXP(SUMPRODUCT(LN(1+'Quarterly returns'!O$6:O$85))*4/80)-1 -> 0.088450813 | C26: =EXP(SUMPRODUCT(LN(1+'Quarterly returns'!O$46:O$85))*4/40)-1 -> 0.14009824 | D26: =EXP(SUMPRODUCT(LN(1+'Quarterly returns'!O$66:O$85))*4/20)-1 -> 0.13819307 | E26: =B26-B$35 -> 0.055391663 | F26: =C26-C$35 -> 0.11823269 | G26: =D26-D$35 -> 0.10928129 | H26: =$L$24*E26+$L$25*F26+$L$26*G26 -> 0.085021896 | K26: Excess weight: 5 years | L26: 0.2
A27: Emerging Markets | B27: =EXP(SUMPRODUCT(LN(1+'Quarterly returns'!P$6:P$85))*4/80)-1 -> 0.079988928 | C27: =EXP(SUMPRODUCT(LN(1+'Quarterly returns'!P$46:P$85))*4/40)-1 -> 0.11222714 | D27: =EXP(SUMPRODUCT(LN(1+'Quarterly returns'!P$66:P$85))*4/20)-1 -> 0.089739489 | E27: =B27-B$35 -> 0.046929778 | F27: =C27-C$35 -> 0.090361593 | G27: =D27-D$35 -> 0.060827705 | H27: =$L$24*E27+$L$25*F27+$L$26*G27 -> 0.062738908 | K27: Equity premium floor | L27: 0.025
A28: Listed Property | B28: =EXP(SUMPRODUCT(LN(1+'Quarterly returns'!Q$6:Q$85))*4/80)-1 -> 0.053753446 | C28: =EXP(SUMPRODUCT(LN(1+'Quarterly returns'!Q$46:Q$85))*4/40)-1 -> 0.059762085 | D28: =EXP(SUMPRODUCT(LN(1+'Quarterly returns'!Q$66:Q$85))*4/20)-1 -> 0.070428794 | E28: =B28-B$35 -> 0.020694296 | F28: =C28-C$35 -> 0.037896534 | G28: =D28-D$35 -> 0.04151701 | H28: =$L$24*E28+$L$25*F28+$L$26*G28 -> 0.03001951 | K28: Equity premium cap | L28: 0.065
A29: Commodities | B29: =EXP(SUMPRODUCT(LN(1+'Quarterly returns'!R$6:R$85))*4/80)-1 -> -0.0067382599 | C29: =EXP(SUMPRODUCT(LN(1+'Quarterly returns'!R$46:R$85))*4/40)-1 -> 0.1127272 | D29: =EXP(SUMPRODUCT(LN(1+'Quarterly returns'!R$66:R$85))*4/20)-1 -> 0.22123504 | E29: =B29-B$35 -> -0.039797409 | F29: =C29-C$35 -> 0.090861648 | G29: =D29-D$35 -> 0.19232325 | H29: =$L$24*E29+$L$25*F29+$L$26*G29 -> 0.04582444 | K29: Property premium floor | L29: 0.015
A30: Direct Property | B30: =EXP(SUMPRODUCT(LN(1+'Quarterly returns'!S$6:S$85))*4/80)-1 -> 0.060608487 | C30: =EXP(SUMPRODUCT(LN(1+'Quarterly returns'!S$46:S$85))*4/40)-1 -> 0.056636213 | D30: =EXP(SUMPRODUCT(LN(1+'Quarterly returns'!S$66:S$85))*4/20)-1 -> 0.046465511 | E30: =B30-B$35 -> 0.027549338 | F30: =C30-C$35 -> 0.034770662 | G30: =D30-D$35 -> 0.017553727 | H30: =$L$24*E30+$L$25*F30+$L$26*G30 -> 0.027716613 | K30: Property premium cap | L30: 0.045
A31: Hedge Funds | B31: =EXP(SUMPRODUCT(LN(1+'Quarterly returns'!T$6:T$85))*4/80)-1 -> 0.076551345 | C31: =EXP(SUMPRODUCT(LN(1+'Quarterly returns'!T$46:T$85))*4/40)-1 -> 0.075066369 | D31: =EXP(SUMPRODUCT(LN(1+'Quarterly returns'!T$66:T$85))*4/20)-1 -> 0.083698848 | E31: =B31-B$35 -> 0.043492196 | F31: =C31-C$35 -> 0.053200818 | G31: =D31-D$35 -> 0.054787063 | H31: =$L$24*E31+$L$25*F31+$L$26*G31 -> 0.048663756 | K31: Commodities: share of long-run excess | L31: 0.25
A32: Private Equity | B32: =EXP(SUMPRODUCT(LN(1+'Quarterly returns'!U$6:U$85))*4/80)-1 -> 0.1068722 | C32: =EXP(SUMPRODUCT(LN(1+'Quarterly returns'!U$46:U$85))*4/40)-1 -> 0.10920514 | D32: =EXP(SUMPRODUCT(LN(1+'Quarterly returns'!U$66:U$85))*4/20)-1 -> 0.10226788 | E32: =B32-B$35 -> 0.073813048 | F32: =C32-C$35 -> 0.08733959 | G32: =D32-D$35 -> 0.073356092 | H32: =$L$24*E32+$L$25*F32+$L$26*G32 -> 0.077779619 | K32: World-AU spread: weight on 20 years | L32: 0.7
A33: Australian Fixed Income | B33: =EXP(SUMPRODUCT(LN(1+'Quarterly returns'!V$6:V$85))*4/80)-1 -> 0.039606305 | C33: =EXP(SUMPRODUCT(LN(1+'Quarterly returns'!V$46:V$85))*4/40)-1 -> 0.016560819 | D33: =EXP(SUMPRODUCT(LN(1+'Quarterly returns'!V$66:V$85))*4/20)-1 -> -0.0008978244 | E33: =B33-B$35 -> 0.0065471554 | F33: =C33-C$35 -> -0.0053047319 | G33: =D33-D$35 -> -0.029809609 | H33: =$L$24*E33+$L$25*F33+$L$26*G33 -> -0.0042797636 | K33: World-AU spread floor | L33: -0.01
A34: World Fixed Income | B34: =EXP(SUMPRODUCT(LN(1+'Quarterly returns'!W$6:W$85))*4/80)-1 -> 0.043020943 | C34: =EXP(SUMPRODUCT(LN(1+'Quarterly returns'!W$46:W$85))*4/40)-1 -> 0.0093981374 | D34: =EXP(SUMPRODUCT(LN(1+'Quarterly returns'!W$66:W$85))*4/20)-1 -> -0.011384459 | E34: =B34-B$35 -> 0.0099617934 | F34: =C34-C$35 -> -0.012467414 | G34: =D34-D$35 -> -0.040296243 | H34: =$L$24*E34+$L$25*F34+$L$26*G34 -> -0.006818576 | K34: World-AU spread cap | L34: 0.01
A35: Cash | B35: =EXP(SUMPRODUCT(LN(1+'Quarterly returns'!X$6:X$85))*4/80)-1 -> 0.033059149 | C35: =EXP(SUMPRODUCT(LN(1+'Quarterly returns'!X$46:X$85))*4/40)-1 -> 0.021865551 | D35: =EXP(SUMPRODUCT(LN(1+'Quarterly returns'!X$66:X$85))*4/20)-1 -> 0.028911784 | E35: =B35-B$35 -> 0 | F35: =C35-C$35 -> 0 | G35: =D35-D$35 -> 0 | H35: =$L$24*E35+$L$25*F35+$L$26*G35 -> 0 | K35: Private-market premium | L35: 0.01
K36: Hedge fund alpha allowance | L36: 0
K37: HF replication: world equities | L37: 0.45
A38: 3. Implied equity returns | K38: HF replication: world fixed income | L38: 0.35
A39: Item | B39: Australian equities | C39: World equities | D39: Source | K39: HF replication: commodities | L39: 0.2
A40: As at | B40: 46265 | C40: 46265 | K40: PE proxy: world equities | L40: 0.8
A41: Dividend yield (trailing) | B41: 0.0343 | C41: 0.015 | D41: Market data | K41: PE proxy: emerging markets | L41: 0.2
A42: P/E (trailing) | B42: 20.39 | C42: 23.2 | K42: Listed property factor: world equities | L42: 0.65
A43: P/E (forward) | B43: 18.82 | C43: 18.55 | K43: Listed property factor: Aus fixed income | L43: 0.35
A44: Expected inflation | B44: 0.025 | C44: 0.02 | D44: RBA target band | K44: Direct property factor: listed property | L44: 0.8
A45: Real growth | B45: 0.02 | C45: 0.02 | K45: Direct property factor: Aus fixed income | L45: 0.2
A46: Forward dividend yield | B46: =B41*B42/B43 -> 0.037161371 | C46: =C41*C42/C43 -> 0.018760108 | K46: World FI factor: Aus fixed income | L46: 0.75
A47: Nominal growth | B47: =B44+B45 -> 0.045 | C47: =C44+C45 -> 0.04 | K47: World FI factor: cash | L47: 0.25
A48: DDM: D1/P0 + g | B48: =B46+B47 -> 0.082161371 | C48: =C46+C47 -> 0.058760108
A49: Earnings yield + inflation | B49: =1/B43+B44 -> 0.078134963 | C49: =1/C43+C44 -> 0.073908356
A50: Implied return (average) | B50: =AVERAGE(B48:B49) -> 0.080148167 | C50: =AVERAGE(C48:C49) -> 0.066334232
A53: 4. Building blocks
A54: Method | B54: Estimate | C54: Weight | D54: Contribution
A55: Australian Equities
A56: Cash + equity premium | B56: =Inputs!$B$26+MIN(MAX(H25,$L$27),$L$28) -> 0.096987399 | C56: 0.4 | D56: =B56*C56 -> 0.038794959
A57: Implied return (DDM, earnings yield) | B57: =$B$50 -> 0.080148167 | C57: 0.4 | D57: =B57*C57 -> 0.032059267
A58: 20-year history | B58: =B25 -> 0.06950125 | C58: 0.2 | D58: =B58*C58 -> 0.01390025
A59: Composite | C59: =SUM(C56:C58) -> 1 | D59: =SUM(D56:D58) -> 0.084754476
A61: World Equities
A62: Cash + equity premium | B62: =Inputs!$B$26+MIN(MAX(H26,$L$27),$L$28) -> 0.111 | C62: 0.4 | D62: =B62*C62 -> 0.0444
A63: Implied return (DDM, earnings yield) | B63: =$C$50 -> 0.066334232 | C63: 0.4 | D63: =B63*C63 -> 0.026533693
A64: 20-year history | B64: =B26 -> 0.088450813 | C64: 0.2 | D64: =B64*C64 -> 0.017690163
A65: Composite | C65: =SUM(C62:C64) -> 1 | D65: =SUM(D62:D64) -> 0.088623855
A67: Emerging Markets
A68: Cash + equity premium | B68: =Inputs!$B$26+MIN(MAX(H27,$L$27),$L$28) -> 0.10873891 | C68: 0.7 | D68: =B68*C68 -> 0.076117235
A69: 20-year history | B69: =B27 -> 0.079988928 | C69: 0.3 | D69: =B69*C69 -> 0.023996678
A70: Composite | C70: =SUM(C68:C69) -> 1 | D70: =SUM(D68:D69) -> 0.10011391
A72: Listed Property
A73: Cash + property premium | B73: =Inputs!$B$26+MIN(MAX(H28,$L$29),$L$30) -> 0.07601951 | C73: 0.5 | D73: =B73*C73 -> 0.038009755
A74: Equity-rate factor model | B74: =$L$42*$B$7+$L$43*$B$14 -> 0.074164558 | C74: 0.3 | D74: =B74*C74 -> 0.022249367
A75: 20-year history | B75: =B28 -> 0.053753446 | C75: 0.2 | D75: =B75*C75 -> 0.010750689
A76: Composite | C76: =SUM(C73:C75) -> 1 | D76: =SUM(D73:D75) -> 0.071009812
A78: Commodities
A79: Collateral + share of long-run excess | B79: =Inputs!$B$26+$L$31*E29 -> 0.036050648 | C79: 0.7 | D79: =B79*C79 -> 0.025235453
A80: 20-year history | B80: =B29 -> -0.0067382599 | C80: 0.3 | D80: =B80*C80 -> -0.002021478
A81: Composite | C81: =SUM(C79:C80) -> 1 | D81: =SUM(D79:D80) -> 0.023213975
A83: Direct Property
A84: Listed property + private-market premium | B84: =$B$9+$L$35 -> 0.081009812 | C84: 0.6 | D84: =B84*C84 -> 0.048605887
A85: Listed property and rate factor model | B85: =$L$44*$B$9+$L$45*$B$14 -> 0.066270164 | C85: 0.2 | D85: =B85*C85 -> 0.013254033
A86: 20-year history (unsmoothed) | B86: =B30 -> 0.060608487 | C86: 0.2 | D86: =B86*C86 -> 0.012121697
A87: Composite | C87: =SUM(C84:C86) -> 1 | D87: =SUM(D84:D86) -> 0.073981617
A89: Hedge Funds
A90: Beta replication + alpha allowance | B90: =$L$37*$B$7+$L$38*$B$15+$L$39*$B$10+$L$36 -> 0.061289548 | C90: 0.7 | D90: =B90*C90 -> 0.042902683
A91: 20-year history | B91: =B31 -> 0.076551345 | C91: 0.3 | D91: =B91*C91 -> 0.022965404
A92: Composite | C92: =SUM(C90:C91) -> 1 | D92: =SUM(D90:D91) -> 0.065868087
A94: Private Equity
A95: Public-equity proxy + private-market premium | B95: =$L$40*$B$7+$L$41*$B$8+$L$35 -> 0.10092187 | C95: 0.7 | D95: =B95*C95 -> 0.070645307
A96: 20-year history (unsmoothed) | B96: =B32 -> 0.1068722 | C96: 0.3 | D96: =B96*C96 -> 0.032061659
A97: Composite | C97: =SUM(C95:C96) -> 1 | D97: =SUM(D95:D96) -> 0.10270697
A99: Australian Fixed Income
A100: Current 5-year yield | B100: =Inputs!$B$23 -> 0.04988 | C100: 0.75 | D100: =B100*C100 -> 0.03741
A101: 20-year history | B101: =B33 -> 0.039606305 | C101: 0.25 | D101: =B101*C101 -> 0.0099015762
A102: Composite | C102: =SUM(C100:C101) -> 1 | D102: =SUM(D100:D101) -> 0.047311576
A104: World Fixed Income
A105: AU yield + world-AU return spread | B105: =Inputs!$B$23+MIN(MAX($L$32*(B34-B33)+(1-$L$32)*(C34-C33),$L$33),$L$34) -> 0.050121442 | C105: 0.6 | D105: =B105*C105 -> 0.030072865
A106: Aus fixed income and cash factor model | B106: =$L$46*$B$14+$L$47*$B$16 -> 0.046129271 | C106: 0.2 | D106: =B106*C106 -> 0.0092258543
A107: 20-year history | B107: =B34 -> 0.043020943 | C107: 0.2 | D107: =B107*C107 -> 0.0086041886
A108: Composite | C108: =SUM(C105:C107) -> 1 | D108: =SUM(D105:D107) -> 0.047902908
A110: Cash
A111: Current cash rate | B111: =Inputs!$B$26 -> 0.046 | C111: 0.8 | D111: =B111*C111 -> 0.0368
A112: 5-year history | B112: =D35 -> 0.028911784 | C112: 0.2 | D112: =B112*C112 -> 0.0057823569
A113: Composite | C113: =SUM(C111:C112) -> 1 | D113: =SUM(D111:D112) -> 0.042582357

Sheet Risk
A1: Risk
A3: 1. Sample covariance (annualised, adjusted quarterly returns)
A4: Asset class | B4: Australian Equities | C4: World Equities | D4: Emerging Markets | E4: Listed Property | F4: Commodities | G4: Direct Property | H4: Hedge Funds | I4: Private Equity | J4: Australian Fixed Income | K4: World Fixed Income | L4: Cash | M4: Sample vol
A5: Australian Equities | B5: =_xlfn.COVARIANCE.S('Quarterly returns'!$N$6:$N$85,'Quarterly returns'!$N$6:$N$85)*4 -> 0.023659152 | C5: =_xlfn.COVARIANCE.S('Quarterly returns'!$N$6:$N$85,'Quarterly returns'!$O$6:$O$85)*4 -> 0.010201113 | D5: =_xlfn.COVARIANCE.S('Quarterly returns'!$N$6:$N$85,'Quarterly returns'!$P$6:$P$85)*4 -> 0.0093962404 | E5: =_xlfn.COVARIANCE.S('Quarterly returns'!$N$6:$N$85,'Quarterly returns'!$Q$6:$Q$85)*4 -> 0.011218765 | F5: =_xlfn.COVARIANCE.S('Quarterly returns'!$N$6:$N$85,'Quarterly returns'!$R$6:$R$85)*4 -> 0.0093552336 | G5: =_xlfn.COVARIANCE.S('Quarterly returns'!$N$6:$N$85,'Quarterly returns'!$S$6:$S$85)*4 -> 0.003164105 | H5: =_xlfn.COVARIANCE.S('Quarterly returns'!$N$6:$N$85,'Quarterly returns'!$T$6:$T$85)*4 -> -0.0020963989 | I5: =_xlfn.COVARIANCE.S('Quarterly returns'!$N$6:$N$85,'Quarterly returns'!$U$6:$U$85)*4 -> 0.010511054 | J5: =_xlfn.COVARIANCE.S('Quarterly returns'!$N$6:$N$85,'Quarterly returns'!$V$6:$V$85)*4 -> -0.0010678114 | K5: =_xlfn.COVARIANCE.S('Quarterly returns'!$N$6:$N$85,'Quarterly returns'!$W$6:$W$85)*4 -> 0.00017412555 | L5: =_xlfn.COVARIANCE.S('Quarterly returns'!$N$6:$N$85,'Quarterly returns'!$X$6:$X$85)*4 -> -0.00028218901 | M5: =SQRT(B5) -> 0.15381532
A6: World Equities | B6: =_xlfn.COVARIANCE.S('Quarterly returns'!$O$6:$O$85,'Quarterly returns'!$N$6:$N$85)*4 -> 0.010201113 | C6: =_xlfn.COVARIANCE.S('Quarterly returns'!$O$6:$O$85,'Quarterly returns'!$O$6:$O$85)*4 -> 0.016251953 | D6: =_xlfn.COVARIANCE.S('Quarterly returns'!$O$6:$O$85,'Quarterly returns'!$P$6:$P$85)*4 -> 0.0091897284 | E6: =_xlfn.COVARIANCE.S('Quarterly returns'!$O$6:$O$85,'Quarterly returns'!$Q$6:$Q$85)*4 -> 0.014691055 | F6: =_xlfn.COVARIANCE.S('Quarterly returns'!$O$6:$O$85,'Quarterly returns'!$R$6:$R$85)*4 -> 0.0060217523 | G6: =_xlfn.COVARIANCE.S('Quarterly returns'!$O$6:$O$85,'Quarterly returns'!$S$6:$S$85)*4 -> 0.0034416564 | H6: =_xlfn.COVARIANCE.S('Quarterly returns'!$O$6:$O$85,'Quarterly returns'!$T$6:$T$85)*4 -> -0.00025929381 | I6: =_xlfn.COVARIANCE.S('Quarterly returns'!$O$6:$O$85,'Quarterly returns'!$U$6:$U$85)*4 -> 0.0074619821 | J6: =_xlfn.COVARIANCE.S('Quarterly returns'!$O$6:$O$85,'Quarterly returns'!$V$6:$V$85)*4 -> -0.00021924073 | K6: =_xlfn.COVARIANCE.S('Quarterly returns'!$O$6:$O$85,'Quarterly returns'!$W$6:$W$85)*4 -> -0.00063739192 | L6: =_xlfn.COVARIANCE.S('Quarterly returns'!$O$6:$O$85,'Quarterly returns'!$X$6:$X$85)*4 -> -0.00033337705 | M6: =SQRT(C6) -> 0.12748315
A7: Emerging Markets | B7: =_xlfn.COVARIANCE.S('Quarterly returns'!$P$6:$P$85,'Quarterly returns'!$N$6:$N$85)*4 -> 0.0093962404 | C7: =_xlfn.COVARIANCE.S('Quarterly returns'!$P$6:$P$85,'Quarterly returns'!$O$6:$O$85)*4 -> 0.0091897284 | D7: =_xlfn.COVARIANCE.S('Quarterly returns'!$P$6:$P$85,'Quarterly returns'!$P$6:$P$85)*4 -> 0.011023027 | E7: =_xlfn.COVARIANCE.S('Quarterly returns'!$P$6:$P$85,'Quarterly returns'!$Q$6:$Q$85)*4 -> 0.0067816259 | F7: =_xlfn.COVARIANCE.S('Quarterly returns'!$P$6:$P$85,'Quarterly returns'!$R$6:$R$85)*4 -> 0.0051228004 | G7: =_xlfn.COVARIANCE.S('Quarterly returns'!$P$6:$P$85,'Quarterly returns'!$S$6:$S$85)*4 -> 0.0041754167 | H7: =_xlfn.COVARIANCE.S('Quarterly returns'!$P$6:$P$85,'Quarterly returns'!$T$6:$T$85)*4 -> -6.2837013e-05 | I7: =_xlfn.COVARIANCE.S('Quarterly returns'!$P$6:$P$85,'Quarterly returns'!$U$6:$U$85)*4 -> 0.0040455748 | J7: =_xlfn.COVARIANCE.S('Quarterly returns'!$P$6:$P$85,'Quarterly returns'!$V$6:$V$85)*4 -> -0.00055660691 | K7: =_xlfn.COVARIANCE.S('Quarterly returns'!$P$6:$P$85,'Quarterly returns'!$W$6:$W$85)*4 -> -0.00032363921 | L7: =_xlfn.COVARIANCE.S('Quarterly returns'!$P$6:$P$85,'Quarterly returns'!$X$6:$X$85)*4 -> -0.00018014153 | M7: =SQRT(D7) -> 0.1049906
A8: Listed Property | B8: =_xlfn.COVARIANCE.S('Quarterly returns'!$Q$6:$Q$85,'Quarterly returns'!$N$6:$N$85)*4 -> 0.011218765 | C8: =_xlfn.COVARIANCE.S('Quarterly returns'!$Q$6:$Q$85,'Quarterly returns'!$O$6:$O$85)*4 -> 0.014691055 | D8: =_xlfn.COVARIANCE.S('Quarterly returns'!$Q$6:$Q$85,'Quarterly returns'!$P$6:$P$85)*4 -> 0.0067816259 | E8: =_xlfn.COVARIANCE.S('Quarterly returns'!$Q$6:$Q$85,'Quarterly returns'!$Q$6:$Q$85)*4 -> 0.028110729 | F8: =_xlfn.COVARIANCE.S('Quarterly returns'!$Q$6:$Q$85,'Quarterly returns'!$R$6:$R$85)*4 -> 0.0032896337 | G8: =_xlfn.COVARIANCE.S('Quarterly returns'!$Q$6:$Q$85,'Quarterly returns'!$S$6:$S$85)*4 -> 0.0016672375 | H8: =_xlfn.COVARIANCE.S('Quarterly returns'!$Q$6:$Q$85,'Quarterly returns'!$T$6:$T$85)*4 -> -0.0019657819 | I8: =_xlfn.COVARIANCE.S('Quarterly returns'!$Q$6:$Q$85,'Quarterly returns'!$U$6:$U$85)*4 -> 0.007622374 | J8: =_xlfn.COVARIANCE.S('Quarterly returns'!$Q$6:$Q$85,'Quarterly returns'!$V$6:$V$85)*4 -> 0.0011424276 | K8: =_xlfn.COVARIANCE.S('Quarterly returns'!$Q$6:$Q$85,'Quarterly returns'!$W$6:$W$85)*4 -> 0.0011450282 | L8: =_xlfn.COVARIANCE.S('Quarterly returns'!$Q$6:$Q$85,'Quarterly returns'!$X$6:$X$85)*4 -> -0.00029733142 | M8: =SQRT(E8) -> 0.16766255
A9: Commodities | B9: =_xlfn.COVARIANCE.S('Quarterly returns'!$R$6:$R$85,'Quarterly returns'!$N$6:$N$85)*4 -> 0.0093552336 | C9: =_xlfn.COVARIANCE.S('Quarterly returns'!$R$6:$R$85,'Quarterly returns'!$O$6:$O$85)*4 -> 0.0060217523 | D9: =_xlfn.COVARIANCE.S('Quarterly returns'!$R$6:$R$85,'Quarterly returns'!$P$6:$P$85)*4 -> 0.0051228004 | E9: =_xlfn.COVARIANCE.S('Quarterly returns'!$R$6:$R$85,'Quarterly returns'!$Q$6:$Q$85)*4 -> 0.0032896337 | F9: =_xlfn.COVARIANCE.S('Quarterly returns'!$R$6:$R$85,'Quarterly returns'!$R$6:$R$85)*4 -> 0.060457147 | G9: =_xlfn.COVARIANCE.S('Quarterly returns'!$R$6:$R$85,'Quarterly returns'!$S$6:$S$85)*4 -> 0.0048364771 | H9: =_xlfn.COVARIANCE.S('Quarterly returns'!$R$6:$R$85,'Quarterly returns'!$T$6:$T$85)*4 -> -0.0029536532 | I9: =_xlfn.COVARIANCE.S('Quarterly returns'!$R$6:$R$85,'Quarterly returns'!$U$6:$U$85)*4 -> -0.00028250152 | J9: =_xlfn.COVARIANCE.S('Quarterly returns'!$R$6:$R$85,'Quarterly returns'!$V$6:$V$85)*4 -> -0.0054720198 | K9: =_xlfn.COVARIANCE.S('Quarterly returns'!$R$6:$R$85,'Quarterly returns'!$W$6:$W$85)*4 -> -0.0054841287 | L9: =_xlfn.COVARIANCE.S('Quarterly returns'!$R$6:$R$85,'Quarterly returns'!$X$6:$X$85)*4 -> -0.0003053015 | M9: =SQRT(F9) -> 0.24588035
A10: Direct Property | B10: =_xlfn.COVARIANCE.S('Quarterly returns'!$S$6:$S$85,'Quarterly returns'!$N$6:$N$85)*4 -> 0.003164105 | C10: =_xlfn.COVARIANCE.S('Quarterly returns'!$S$6:$S$85,'Quarterly returns'!$O$6:$O$85)*4 -> 0.0034416564 | D10: =_xlfn.COVARIANCE.S('Quarterly returns'!$S$6:$S$85,'Quarterly returns'!$P$6:$P$85)*4 -> 0.0041754167 | E10: =_xlfn.COVARIANCE.S('Quarterly returns'!$S$6:$S$85,'Quarterly returns'!$Q$6:$Q$85)*4 -> 0.0016672375 | F10: =_xlfn.COVARIANCE.S('Quarterly returns'!$S$6:$S$85,'Quarterly returns'!$R$6:$R$85)*4 -> 0.0048364771 | G10: =_xlfn.COVARIANCE.S('Quarterly returns'!$S$6:$S$85,'Quarterly returns'!$S$6:$S$85)*4 -> 0.0090884856 | H10: =_xlfn.COVARIANCE.S('Quarterly returns'!$S$6:$S$85,'Quarterly returns'!$T$6:$T$85)*4 -> 0.0004080026 | I10: =_xlfn.COVARIANCE.S('Quarterly returns'!$S$6:$S$85,'Quarterly returns'!$U$6:$U$85)*4 -> 0.0023270627 | J10: =_xlfn.COVARIANCE.S('Quarterly returns'!$S$6:$S$85,'Quarterly returns'!$V$6:$V$85)*4 -> -0.0011143499 | K10: =_xlfn.COVARIANCE.S('Quarterly returns'!$S$6:$S$85,'Quarterly returns'!$W$6:$W$85)*4 -> -0.00067265871 | L10: =_xlfn.COVARIANCE.S('Quarterly returns'!$S$6:$S$85,'Quarterly returns'!$X$6:$X$85)*4 -> -0.00013132648 | M10: =SQRT(G10) -> 0.095333549
A11: Hedge Funds | B11: =_xlfn.COVARIANCE.S('Quarterly returns'!$T$6:$T$85,'Quarterly returns'!$N$6:$N$85)*4 -> -0.0020963989 | C11: =_xlfn.COVARIANCE.S('Quarterly returns'!$T$6:$T$85,'Quarterly returns'!$O$6:$O$85)*4 -> -0.00025929381 | D11: =_xlfn.COVARIANCE.S('Quarterly returns'!$T$6:$T$85,'Quarterly returns'!$P$6:$P$85)*4 -> -6.2837013e-05 | E11: =_xlfn.COVARIANCE.S('Quarterly returns'!$T$6:$T$85,'Quarterly returns'!$Q$6:$Q$85)*4 -> -0.0019657819 | F11: =_xlfn.COVARIANCE.S('Quarterly returns'!$T$6:$T$85,'Quarterly returns'!$R$6:$R$85)*4 -> -0.0029536532 | G11: =_xlfn.COVARIANCE.S('Quarterly returns'!$T$6:$T$85,'Quarterly returns'!$S$6:$S$85)*4 -> 0.0004080026 | H11: =_xlfn.COVARIANCE.S('Quarterly returns'!$T$6:$T$85,'Quarterly returns'!$T$6:$T$85)*4 -> 0.0051752768 | I11: =_xlfn.COVARIANCE.S('Quarterly returns'!$T$6:$T$85,'Quarterly returns'!$U$6:$U$85)*4 -> -0.00063140198 | J11: =_xlfn.COVARIANCE.S('Quarterly returns'!$T$6:$T$85,'Quarterly returns'!$V$6:$V$85)*4 -> 0.00035220021 | K11: =_xlfn.COVARIANCE.S('Quarterly returns'!$T$6:$T$85,'Quarterly returns'!$W$6:$W$85)*4 -> 5.021398e-06 | L11: =_xlfn.COVARIANCE.S('Quarterly returns'!$T$6:$T$85,'Quarterly returns'!$X$6:$X$85)*4 -> 0.00010340346 | M11: =SQRT(H11) -> 0.071939397
A12: Private Equity | B12: =_xlfn.COVARIANCE.S('Quarterly returns'!$U$6:$U$85,'Quarterly returns'!$N$6:$N$85)*4 -> 0.010511054 | C12: =_xlfn.COVARIANCE.S('Quarterly returns'!$U$6:$U$85,'Quarterly returns'!$O$6:$O$85)*4 -> 0.0074619821 | D12: =_xlfn.COVARIANCE.S('Quarterly returns'!$U$6:$U$85,'Quarterly returns'!$P$6:$P$85)*4 -> 0.0040455748 | E12: =_xlfn.COVARIANCE.S('Quarterly returns'!$U$6:$U$85,'Quarterly returns'!$Q$6:$Q$85)*4 -> 0.007622374 | F12: =_xlfn.COVARIANCE.S('Quarterly returns'!$U$6:$U$85,'Quarterly returns'!$R$6:$R$85)*4 -> -0.00028250152 | G12: =_xlfn.COVARIANCE.S('Quarterly returns'!$U$6:$U$85,'Quarterly returns'!$S$6:$S$85)*4 -> 0.0023270627 | H12: =_xlfn.COVARIANCE.S('Quarterly returns'!$U$6:$U$85,'Quarterly returns'!$T$6:$T$85)*4 -> -0.00063140198 | I12: =_xlfn.COVARIANCE.S('Quarterly returns'!$U$6:$U$85,'Quarterly returns'!$U$6:$U$85)*4 -> 0.01619156 | J12: =_xlfn.COVARIANCE.S('Quarterly returns'!$U$6:$U$85,'Quarterly returns'!$V$6:$V$85)*4 -> 0.00032821521 | K12: =_xlfn.COVARIANCE.S('Quarterly returns'!$U$6:$U$85,'Quarterly returns'!$W$6:$W$85)*4 -> 0.00042088405 | L12: =_xlfn.COVARIANCE.S('Quarterly returns'!$U$6:$U$85,'Quarterly returns'!$X$6:$X$85)*4 -> -0.00013855702 | M12: =SQRT(I12) -> 0.12724606
A13: Australian Fixed Income | B13: =_xlfn.COVARIANCE.S('Quarterly returns'!$V$6:$V$85,'Quarterly returns'!$N$6:$N$85)*4 -> -0.0010678114 | C13: =_xlfn.COVARIANCE.S('Quarterly returns'!$V$6:$V$85,'Quarterly returns'!$O$6:$O$85)*4 -> -0.00021924073 | D13: =_xlfn.COVARIANCE.S('Quarterly returns'!$V$6:$V$85,'Quarterly returns'!$P$6:$P$85)*4 -> -0.00055660691 | E13: =_xlfn.COVARIANCE.S('Quarterly returns'!$V$6:$V$85,'Quarterly returns'!$Q$6:$Q$85)*4 -> 0.0011424276 | F13: =_xlfn.COVARIANCE.S('Quarterly returns'!$V$6:$V$85,'Quarterly returns'!$R$6:$R$85)*4 -> -0.0054720198 | G13: =_xlfn.COVARIANCE.S('Quarterly returns'!$V$6:$V$85,'Quarterly returns'!$S$6:$S$85)*4 -> -0.0011143499 | H13: =_xlfn.COVARIANCE.S('Quarterly returns'!$V$6:$V$85,'Quarterly returns'!$T$6:$T$85)*4 -> 0.00035220021 | I13: =_xlfn.COVARIANCE.S('Quarterly returns'!$V$6:$V$85,'Quarterly returns'!$U$6:$U$85)*4 -> 0.00032821521 | J13: =_xlfn.COVARIANCE.S('Quarterly returns'!$V$6:$V$85,'Quarterly returns'!$V$6:$V$85)*4 -> 0.0018053161 | K13: =_xlfn.COVARIANCE.S('Quarterly returns'!$V$6:$V$85,'Quarterly returns'!$W$6:$W$85)*4 -> 0.0014020089 | L13: =_xlfn.COVARIANCE.S('Quarterly returns'!$V$6:$V$85,'Quarterly returns'!$X$6:$X$85)*4 -> 0.00014748733 | M13: =SQRT(J13) -> 0.042489011
A14: World Fixed Income | B14: =_xlfn.COVARIANCE.S('Quarterly returns'!$W$6:$W$85,'Quarterly returns'!$N$6:$N$85)*4 -> 0.00017412555 | C14: =_xlfn.COVARIANCE.S('Quarterly returns'!$W$6:$W$85,'Quarterly returns'!$O$6:$O$85)*4 -> -0.00063739192 | D14: =_xlfn.COVARIANCE.S('Quarterly returns'!$W$6:$W$85,'Quarterly returns'!$P$6:$P$85)*4 -> -0.00032363921 | E14: =_xlfn.COVARIANCE.S('Quarterly returns'!$W$6:$W$85,'Quarterly returns'!$Q$6:$Q$85)*4 -> 0.0011450282 | F14: =_xlfn.COVARIANCE.S('Quarterly returns'!$W$6:$W$85,'Quarterly returns'!$R$6:$R$85)*4 -> -0.0054841287 | G14: =_xlfn.COVARIANCE.S('Quarterly returns'!$W$6:$W$85,'Quarterly returns'!$S$6:$S$85)*4 -> -0.00067265871 | H14: =_xlfn.COVARIANCE.S('Quarterly returns'!$W$6:$W$85,'Quarterly returns'!$T$6:$T$85)*4 -> 5.021398e-06 | I14: =_xlfn.COVARIANCE.S('Quarterly returns'!$W$6:$W$85,'Quarterly returns'!$U$6:$U$85)*4 -> 0.00042088405 | J14: =_xlfn.COVARIANCE.S('Quarterly returns'!$W$6:$W$85,'Quarterly returns'!$V$6:$V$85)*4 -> 0.0014020089 | K14: =_xlfn.COVARIANCE.S('Quarterly returns'!$W$6:$W$85,'Quarterly returns'!$W$6:$W$85)*4 -> 0.0016427464 | L14: =_xlfn.COVARIANCE.S('Quarterly returns'!$W$6:$W$85,'Quarterly returns'!$X$6:$X$85)*4 -> 0.00013721798 | M14: =SQRT(K14) -> 0.040530808
A15: Cash | B15: =_xlfn.COVARIANCE.S('Quarterly returns'!$X$6:$X$85,'Quarterly returns'!$N$6:$N$85)*4 -> -0.00028218901 | C15: =_xlfn.COVARIANCE.S('Quarterly returns'!$X$6:$X$85,'Quarterly returns'!$O$6:$O$85)*4 -> -0.00033337705 | D15: =_xlfn.COVARIANCE.S('Quarterly returns'!$X$6:$X$85,'Quarterly returns'!$P$6:$P$85)*4 -> -0.00018014153 | E15: =_xlfn.COVARIANCE.S('Quarterly returns'!$X$6:$X$85,'Quarterly returns'!$Q$6:$Q$85)*4 -> -0.00029733142 | F15: =_xlfn.COVARIANCE.S('Quarterly returns'!$X$6:$X$85,'Quarterly returns'!$R$6:$R$85)*4 -> -0.0003053015 | G15: =_xlfn.COVARIANCE.S('Quarterly returns'!$X$6:$X$85,'Quarterly returns'!$S$6:$S$85)*4 -> -0.00013132648 | H15: =_xlfn.COVARIANCE.S('Quarterly returns'!$X$6:$X$85,'Quarterly returns'!$T$6:$T$85)*4 -> 0.00010340346 | I15: =_xlfn.COVARIANCE.S('Quarterly returns'!$X$6:$X$85,'Quarterly returns'!$U$6:$U$85)*4 -> -0.00013855702 | J15: =_xlfn.COVARIANCE.S('Quarterly returns'!$X$6:$X$85,'Quarterly returns'!$V$6:$V$85)*4 -> 0.00014748733 | K15: =_xlfn.COVARIANCE.S('Quarterly returns'!$X$6:$X$85,'Quarterly returns'!$W$6:$W$85)*4 -> 0.00013721798 | L15: =_xlfn.COVARIANCE.S('Quarterly returns'!$X$6:$X$85,'Quarterly returns'!$X$6:$X$85)*4 -> 9.6274886e-05 | M15: =SQRT(L15) -> 0.0098119767
A18: 2. Correlation
A19: Asset class | B19: Australian Equities | C19: World Equities | D19: Emerging Markets | E19: Listed Property | F19: Commodities | G19: Direct Property | H19: Hedge Funds | I19: Private Equity | J19: Australian Fixed Income | K19: World Fixed Income | L19: Cash
A20: Australian Equities | B20: =B5/($M5*$M$5) -> 1 | C20: =C5/($M5*$M$6) -> 0.52022975 | D20: =D5/($M5*$M$7) -> 0.5818407 | E20: =E5/($M5*$M$8) -> 0.43502018 | F20: =F5/($M5*$M$9) -> 0.247361 | G20: =G5/($M5*$M$10) -> 0.2157772 | H20: =H5/($M5*$M$11) -> -0.18945564 | I20: =I5/($M5*$M$12) -> 0.53703467 | J20: =J5/($M5*$M$13) -> -0.16338731 | K20: =K5/($M5*$M$14) -> 0.027930433 | L20: =L5/($M5*$M$15) -> -0.1869752
A21: World Equities | B21: =B6/($M6*$M$5) -> 0.52022975 | C21: =C6/($M6*$M$6) -> 1 | D21: =D6/($M6*$M$7) -> 0.68659313 | E21: =E6/($M6*$M$8) -> 0.68732817 | F21: =F6/($M6*$M$9) -> 0.19210837 | G21: =G6/($M6*$M$10) -> 0.28318416 | H21: =H6/($M6*$M$11) -> -0.028273044 | I21: =I6/($M6*$M$12) -> 0.45999921 | J21: =J6/($M6*$M$13) -> -0.040475463 | K21: =K6/($M6*$M$14) -> -0.12335834 | L21: =L6/($M6*$M$15) -> -0.26651791
A22: Emerging Markets | B22: =B7/($M7*$M$5) -> 0.5818407 | C22: =C7/($M7*$M$6) -> 0.68659313 | D22: =D7/($M7*$M$7) -> 1 | E22: =E7/($M7*$M$8) -> 0.38525416 | F22: =F7/($M7*$M$9) -> 0.19844181 | G22: =G7/($M7*$M$10) -> 0.41716093 | H22: =H7/($M7*$M$11) -> -0.0083195206 | I22: =I7/($M7*$M$12) -> 0.30282063 | J22: =J7/($M7*$M$13) -> -0.12477326 | K22: =K7/($M7*$M$14) -> -0.076054592 | L22: =L7/($M7*$M$15) -> -0.17486662
A23: Listed Property | B23: =B8/($M8*$M$5) -> 0.43502018 | C23: =C8/($M8*$M$6) -> 0.68732817 | D23: =D8/($M8*$M$7) -> 0.38525416 | E23: =E8/($M8*$M$8) -> 1 | F23: =F8/($M8*$M$9) -> 0.079797201 | G23: =G8/($M8*$M$10) -> 0.10430753 | H23: =H8/($M8*$M$11) -> -0.16297931 | I23: =I8/($M8*$M$12) -> 0.35728095 | J23: =J8/($M8*$M$13) -> 0.16036736 | K23: =K8/($M8*$M$14) -> 0.16849804 | L23: =L8/($M8*$M$15) -> -0.18073749
A24: Commodities | B24: =B9/($M9*$M$5) -> 0.247361 | C24: =C9/($M9*$M$6) -> 0.19210837 | D24: =D9/($M9*$M$7) -> 0.19844181 | E24: =E9/($M9*$M$8) -> 0.079797201 | F24: =F9/($M9*$M$9) -> 1 | G24: =G9/($M9*$M$10) -> 0.20632865 | H24: =H9/($M9*$M$11) -> -0.1669817 | I24: =I9/($M9*$M$12) -> -0.0090292696 | J24: =J9/($M9*$M$13) -> -0.52377795 | K24: =K9/($M9*$M$14) -> -0.55029878 | L24: =L9/($M9*$M$15) -> -0.12654605
A25: Direct Property | B25: =B10/($M10*$M$5) -> 0.2157772 | C25: =C10/($M10*$M$6) -> 0.28318416 | D25: =D10/($M10*$M$7) -> 0.41716093 | E25: =E10/($M10*$M$8) -> 0.10430753 | F25: =F10/($M10*$M$9) -> 0.20632865 | G25: =G10/($M10*$M$10) -> 1 | H25: =H10/($M10*$M$11) -> 0.059490877 | I25: =I10/($M10*$M$12) -> 0.19183064 | J25: =J10/($M10*$M$13) -> -0.27510544 | K25: =K10/($M10*$M$14) -> -0.17408596 | L25: =L10/($M10*$M$15) -> -0.14039448
A26: Hedge Funds | B26: =B11/($M11*$M$5) -> -0.18945564 | C26: =C11/($M11*$M$6) -> -0.028273044 | D26: =D11/($M11*$M$7) -> -0.0083195206 | E26: =E11/($M11*$M$8) -> -0.16297931 | F26: =F11/($M11*$M$9) -> -0.1669817 | G26: =G11/($M11*$M$10) -> 0.059490877 | H26: =H11/($M11*$M$11) -> 1 | I26: =I11/($M11*$M$12) -> -0.068975492 | J26: =J11/($M11*$M$13) -> 0.11522486 | K26: =K11/($M11*$M$14) -> 0.0017221564 | L26: =L11/($M11*$M$15) -> 0.14649128
A27: Private Equity | B27: =B12/($M12*$M$5) -> 0.53703467 | C27: =C12/($M12*$M$6) -> 0.45999921 | D27: =D12/($M12*$M$7) -> 0.30282063 | E27: =E12/($M12*$M$8) -> 0.35728095 | F27: =F12/($M12*$M$9) -> -0.0090292696 | G27: =G12/($M12*$M$10) -> 0.19183064 | H27: =H12/($M12*$M$11) -> -0.068975492 | I27: =I12/($M12*$M$12) -> 1 | J27: =J12/($M12*$M$13) -> 0.060706856 | K27: =K12/($M12*$M$14) -> 0.081608025 | L27: =L12/($M12*$M$15) -> -0.11097565
A28: Australian Fixed Income | B28: =B13/($M13*$M$5) -> -0.16338731 | C28: =C13/($M13*$M$6) -> -0.040475463 | D28: =D13/($M13*$M$7) -> -0.12477326 | E28: =E13/($M13*$M$8) -> 0.16036736 | F28: =F13/($M13*$M$9) -> -0.52377795 | G28: =G13/($M13*$M$10) -> -0.27510544 | H28: =H13/($M13*$M$11) -> 0.11522486 | I28: =I13/($M13*$M$12) -> 0.060706856 | J28: =J13/($M13*$M$13) -> 1 | K28: =K13/($M13*$M$14) -> 0.81412085 | L28: =L13/($M13*$M$15) -> 0.35377048
A29: World Fixed Income | B29: =B14/($M14*$M$5) -> 0.027930433 | C29: =C14/($M14*$M$6) -> -0.12335834 | D29: =D14/($M14*$M$7) -> -0.076054592 | E29: =E14/($M14*$M$8) -> 0.16849804 | F29: =F14/($M14*$M$9) -> -0.55029878 | G29: =G14/($M14*$M$10) -> -0.17408596 | H29: =H14/($M14*$M$11) -> 0.0017221564 | I29: =I14/($M14*$M$12) -> 0.081608025 | J29: =J14/($M14*$M$13) -> 0.81412085 | K29: =K14/($M14*$M$14) -> 1 | L29: =L14/($M14*$M$15) -> 0.34503985
A30: Cash | B30: =B15/($M15*$M$5) -> -0.1869752 | C30: =C15/($M15*$M$6) -> -0.26651791 | D30: =D15/($M15*$M$7) -> -0.17486662 | E30: =E15/($M15*$M$8) -> -0.18073749 | F30: =F15/($M15*$M$9) -> -0.12654605 | G30: =G15/($M15*$M$10) -> -0.14039448 | H30: =H15/($M15*$M$11) -> 0.14649128 | I30: =I15/($M15*$M$12) -> -0.11097565 | J30: =J15/($M15*$M$13) -> 0.35377048 | K30: =K15/($M15*$M$14) -> 0.34503985 | L30: =L15/($M15*$M$15) -> 1
A32: Average correlation (target) | B32: =(SUM(B20:L30)-11)/110 -> 0.10095138
A38: 3. Shrunk covariance
A40: Asset class | B40: Australian Equities | C40: World Equities | D40: Emerging Markets | E40: Listed Property | F40: Commodities | G40: Direct Property | H40: Hedge Funds | I40: Private Equity | J40: Australian Fixed Income | K40: World Fixed Income | L40: Cash | M40: Shrunk vol
A41: Australian Equities | B41: =B5 -> 0.023659152 | C41: =(1-Inputs!$B$38)*C5+Inputs!$B$38*$B$32*$M5*$M$6 -> 0.0073235629 | D41: =(1-Inputs!$B$38)*D5+Inputs!$B$38*$B$32*$M5*$M$7 -> 0.0066781543 | E41: =(1-Inputs!$B$38)*E5+Inputs!$B$38*$B$32*$M5*$M$8 -> 0.0082034018 | F41: =(1-Inputs!$B$38)*F5+Inputs!$B$38*$B$32*$M5*$M$9 -> 0.007417201 | G41: =(1-Inputs!$B$38)*G5+Inputs!$B$38*$B$32*$M5*$M$10 -> 0.0025747826 | H41: =(1-Inputs!$B$38)*H5+Inputs!$B$38*$B$32*$M5*$M$11 -> -0.00097168636 | I41: =(1-Inputs!$B$38)*I5+Inputs!$B$38*$B$32*$M5*$M$12 -> 0.0075237358 | J41: =(1-Inputs!$B$38)*J5+Inputs!$B$38*$B$32*$M5*$M$13 -> -0.00046316007 | K41: =(1-Inputs!$B$38)*K5+Inputs!$B$38*$B$32*$M5*$M$14 -> 0.00033345657 | L41: =(1-Inputs!$B$38)*L5+Inputs!$B$38*$B$32*$M5*$M$15 -> -0.00013009718 | M41: =SQRT(B41) -> 0.15381532
A42: World Equities | B42: =(1-Inputs!$B$38)*B6+Inputs!$B$38*$B$32*$M6*$M$5 -> 0.0073235629 | C42: =C6 -> 0.016251953 | D42: =(1-Inputs!$B$38)*D6+Inputs!$B$38*$B$32*$M6*$M$7 -> 0.0064462389 | E42: =(1-Inputs!$B$38)*E6+Inputs!$B$38*$B$32*$M6*$M$8 -> 0.010304398 | F42: =(1-Inputs!$B$38)*F6+Inputs!$B$38*$B$32*$M6*$M$9 -> 0.0050216726 | G42: =(1-Inputs!$B$38)*G6+Inputs!$B$38*$B$32*$M6*$M$10 -> 0.0026664933 | H42: =(1-Inputs!$B$38)*H6+Inputs!$B$38*$B$32*$M6*$M$11 -> 0.00015549994 | I42: =(1-Inputs!$B$38)*I6+Inputs!$B$38*$B$32*$M6*$M$12 -> 0.0054234504 | J42: =(1-Inputs!$B$38)*J6+Inputs!$B$38*$B$32*$M6*$M$13 -> 4.8879317e-05 | K42: =(1-Inputs!$B$38)*K6+Inputs!$B$38*$B$32*$M6*$M$14 -> -0.00023173941 | L42: =(1-Inputs!$B$38)*L6+Inputs!$B$38*$B$32*$M6*$M$15 -> -0.00017249841 | M42: =SQRT(C42) -> 0.12748315
A43: Emerging Markets | B43: =(1-Inputs!$B$38)*B7+Inputs!$B$38*$B$32*$M7*$M$5 -> 0.0066781543 | C43: =(1-Inputs!$B$38)*C7+Inputs!$B$38*$B$32*$M7*$M$6 -> 0.0064462389 | D43: =D7 -> 0.011023027 | E43: =(1-Inputs!$B$38)*E7+Inputs!$B$38*$B$32*$M7*$M$8 -> 0.0050300231 | F43: =(1-Inputs!$B$38)*F7+Inputs!$B$38*$B$32*$M7*$M$9 -> 0.0042419457 | G43: =(1-Inputs!$B$38)*G7+Inputs!$B$38*$B$32*$M7*$M$10 -> 0.0030676732 | H43: =(1-Inputs!$B$38)*H7+Inputs!$B$38*$B$32*$M7*$M$11 -> 0.00022602456 | I43: =(1-Inputs!$B$38)*I7+Inputs!$B$38*$B$32*$M7*$M$12 -> 0.0031016595 | J43: =(1-Inputs!$B$38)*J7+Inputs!$B$38*$B$32*$M7*$M$13 -> -0.00020417593 | K43: =(1-Inputs!$B$38)*K7+Inputs!$B$38*$B$32*$M7*$M$14 -> -6.0011145e-05 | L43: =(1-Inputs!$B$38)*L7+Inputs!$B$38*$B$32*$M7*$M$15 -> -8.0693182e-05 | M43: =SQRT(D43) -> 0.1049906
A44: Listed Property | B44: =(1-Inputs!$B$38)*B8+Inputs!$B$38*$B$32*$M8*$M$5 -> 0.0082034018 | C44: =(1-Inputs!$B$38)*C8+Inputs!$B$38*$B$32*$M8*$M$6 -> 0.010304398 | D44: =(1-Inputs!$B$38)*D8+Inputs!$B$38*$B$32*$M8*$M$7 -> 0.0050300231 | E44: =E8 -> 0.028110729 | F44: =(1-Inputs!$B$38)*F8+Inputs!$B$38*$B$32*$M8*$M$9 -> 0.0035948614 | G44: =(1-Inputs!$B$38)*G8+Inputs!$B$38*$B$32*$M8*$M$10 -> 0.001648462 | H44: =(1-Inputs!$B$38)*H8+Inputs!$B$38*$B$32*$M8*$M$11 -> -0.00085158795 | I44: =(1-Inputs!$B$38)*I8+Inputs!$B$38*$B$32*$M8*$M$12 -> 0.005708351 | J44: =(1-Inputs!$B$38)*J8+Inputs!$B$38*$B$32*$M8*$M$13 -> 0.00099428356 | K44: =(1-Inputs!$B$38)*K8+Inputs!$B$38*$B$32*$M8*$M$14 -> 0.00098437353 | L44: =(1-Inputs!$B$38)*L8+Inputs!$B$38*$B$32*$M8*$M$15 -> -0.0001351391 | M44: =SQRT(E44) -> 0.16766255
A45: Commodities | B45: =(1-Inputs!$B$38)*B9+Inputs!$B$38*$B$32*$M9*$M$5 -> 0.007417201 | C45: =(1-Inputs!$B$38)*C9+Inputs!$B$38*$B$32*$M9*$M$6 -> 0.0050216726 | D45: =(1-Inputs!$B$38)*D9+Inputs!$B$38*$B$32*$M9*$M$7 -> 0.0042419457 | E45: =(1-Inputs!$B$38)*E9+Inputs!$B$38*$B$32*$M9*$M$8 -> 0.0035948614 | F45: =F9 -> 0.060457147 | G45: =(1-Inputs!$B$38)*G9+Inputs!$B$38*$B$32*$M9*$M$10 -> 0.003971938 | H45: =(1-Inputs!$B$38)*H9+Inputs!$B$38*$B$32*$M9*$M$11 -> -0.0012948877 | I45: =(1-Inputs!$B$38)*I9+Inputs!$B$38*$B$32*$M9*$M$12 -> 0.0009218478 | J45: =(1-Inputs!$B$38)*J9+Inputs!$B$38*$B$32*$M9*$M$13 -> -0.0031876817 | K45: =(1-Inputs!$B$38)*K9+Inputs!$B$38*$B$32*$M9*$M$14 -> -0.0032125647 | L45: =(1-Inputs!$B$38)*L9+Inputs!$B$38*$B$32*$M9*$M$15 -> -0.0001132026 | M45: =SQRT(F45) -> 0.24588035
A46: Direct Property | B46: =(1-Inputs!$B$38)*B10+Inputs!$B$38*$B$32*$M10*$M$5 -> 0.0025747826 | C46: =(1-Inputs!$B$38)*C10+Inputs!$B$38*$B$32*$M10*$M$6 -> 0.0026664933 | D46: =(1-Inputs!$B$38)*D10+Inputs!$B$38*$B$32*$M10*$M$7 -> 0.0030676732 | E46: =(1-Inputs!$B$38)*E10+Inputs!$B$38*$B$32*$M10*$M$8 -> 0.001648462 | F46: =(1-Inputs!$B$38)*F10+Inputs!$B$38*$B$32*$M10*$M$9 -> 0.003971938 | G46: =G10 -> 0.0090884856 | H46: =(1-Inputs!$B$38)*H10+Inputs!$B$38*$B$32*$M10*$M$11 -> 0.00050752368 | I46: =(1-Inputs!$B$38)*I10+Inputs!$B$38*$B$32*$M10*$M$12 -> 0.0019412087 | J46: =(1-Inputs!$B$38)*J10+Inputs!$B$38*$B$32*$M10*$M$13 -> -0.00058120664 | K46: =(1-Inputs!$B$38)*K10+Inputs!$B$38*$B$32*$M10*$M$14 -> -0.00030070344 | L46: =(1-Inputs!$B$38)*L10+Inputs!$B$38*$B$32*$M10*$M$15 -> -5.2311367e-05 | M46: =SQRT(G46) -> 0.095333549
A47: Hedge Funds | B47: =(1-Inputs!$B$38)*B11+Inputs!$B$38*$B$32*$M11*$M$5 -> -0.00097168636 | C47: =(1-Inputs!$B$38)*C11+Inputs!$B$38*$B$32*$M11*$M$6 -> 0.00015549994 | D47: =(1-Inputs!$B$38)*D11+Inputs!$B$38*$B$32*$M11*$M$7 -> 0.00022602456 | E47: =(1-Inputs!$B$38)*E11+Inputs!$B$38*$B$32*$M11*$M$8 -> -0.00085158795 | F47: =(1-Inputs!$B$38)*F11+Inputs!$B$38*$B$32*$M11*$M$9 -> -0.0012948877 | G47: =(1-Inputs!$B$38)*G11+Inputs!$B$38*$B$32*$M11*$M$10 -> 0.00050752368 | H47: =H11 -> 0.0051752768 | I47: =(1-Inputs!$B$38)*I11+Inputs!$B$38*$B$32*$M11*$M$12 -> -8.6973008e-05 | J47: =(1-Inputs!$B$38)*J11+Inputs!$B$38*$B$32*$M11*$M$13 -> 0.00033693012 | K47: =(1-Inputs!$B$38)*K11+Inputs!$B$38*$B$32*$M11*$M$14 -> 0.00010628647 | L47: =(1-Inputs!$B$38)*L11+Inputs!$B$38*$B$32*$M11*$M$15 -> 9.215266e-05 | M47: =SQRT(H47) -> 0.071939397
A48: Private Equity | B48: =(1-Inputs!$B$38)*B12+Inputs!$B$38*$B$32*$M12*$M$5 -> 0.0075237358 | C48: =(1-Inputs!$B$38)*C12+Inputs!$B$38*$B$32*$M12*$M$6 -> 0.0054234504 | D48: =(1-Inputs!$B$38)*D12+Inputs!$B$38*$B$32*$M12*$M$7 -> 0.0031016595 | E48: =(1-Inputs!$B$38)*E12+Inputs!$B$38*$B$32*$M12*$M$8 -> 0.005708351 | F48: =(1-Inputs!$B$38)*F12+Inputs!$B$38*$B$32*$M12*$M$9 -> 0.0009218478 | G48: =(1-Inputs!$B$38)*G12+Inputs!$B$38*$B$32*$M12*$M$10 -> 0.0019412087 | H48: =(1-Inputs!$B$38)*H12+Inputs!$B$38*$B$32*$M12*$M$11 -> -8.6973008e-05 | I48: =I12 -> 0.01619156 | J48: =(1-Inputs!$B$38)*J12+Inputs!$B$38*$B$32*$M12*$M$13 -> 0.00040436974 | K48: =(1-Inputs!$B$38)*K12+Inputs!$B$38*$B$32*$M12*$M$14 -> 0.00045580044 | L48: =(1-Inputs!$B$38)*L12+Inputs!$B$38*$B$32*$M12*$M$15 -> -4.5947589e-05 | M48: =SQRT(I48) -> 0.12724606
A49: Australian Fixed Income | B49: =(1-Inputs!$B$38)*B13+Inputs!$B$38*$B$32*$M13*$M$5 -> -0.00046316007 | C49: =(1-Inputs!$B$38)*C13+Inputs!$B$38*$B$32*$M13*$M$6 -> 4.8879317e-05 | D49: =(1-Inputs!$B$38)*D13+Inputs!$B$38*$B$32*$M13*$M$7 -> -0.00020417593 | E49: =(1-Inputs!$B$38)*E13+Inputs!$B$38*$B$32*$M13*$M$8 -> 0.00099428356 | F49: =(1-Inputs!$B$38)*F13+Inputs!$B$38*$B$32*$M13*$M$9 -> -0.0031876817 | G49: =(1-Inputs!$B$38)*G13+Inputs!$B$38*$B$32*$M13*$M$10 -> -0.00058120664 | H49: =(1-Inputs!$B$38)*H13+Inputs!$B$38*$B$32*$M13*$M$11 -> 0.00033693012 | I49: =(1-Inputs!$B$38)*I13+Inputs!$B$38*$B$32*$M13*$M$12 -> 0.00040436974 | J49: =J13 -> 0.0018053161 | K49: =(1-Inputs!$B$38)*K13+Inputs!$B$38*$B$32*$M13*$M$14 -> 0.00097215318 | L49: =(1-Inputs!$B$38)*L13+Inputs!$B$38*$B$32*$M13*$M$15 -> 0.00011059713 | M49: =SQRT(J49) -> 0.042489011
A50: World Fixed Income | B50: =(1-Inputs!$B$38)*B14+Inputs!$B$38*$B$32*$M14*$M$5 -> 0.00033345657 | C50: =(1-Inputs!$B$38)*C14+Inputs!$B$38*$B$32*$M14*$M$6 -> -0.00023173941 | D50: =(1-Inputs!$B$38)*D14+Inputs!$B$38*$B$32*$M14*$M$7 -> -6.0011145e-05 | E50: =(1-Inputs!$B$38)*E14+Inputs!$B$38*$B$32*$M14*$M$8 -> 0.00098437353 | F50: =(1-Inputs!$B$38)*F14+Inputs!$B$38*$B$32*$M14*$M$9 -> -0.0032125647 | G50: =(1-Inputs!$B$38)*G14+Inputs!$B$38*$B$32*$M14*$M$10 -> -0.00030070344 | H50: =(1-Inputs!$B$38)*H14+Inputs!$B$38*$B$32*$M14*$M$11 -> 0.00010628647 | I50: =(1-Inputs!$B$38)*I14+Inputs!$B$38*$B$32*$M14*$M$12 -> 0.00045580044 | J50: =(1-Inputs!$B$38)*J14+Inputs!$B$38*$B$32*$M14*$M$13 -> 0.00097215318 | K50: =K14 -> 0.0016427464 | L50: =(1-Inputs!$B$38)*L14+Inputs!$B$38*$B$32*$M14*$M$15 -> 0.00010324317 | M50: =SQRT(K50) -> 0.040530808
A51: Cash | B51: =(1-Inputs!$B$38)*B15+Inputs!$B$38*$B$32*$M15*$M$5 -> -0.00013009718 | C51: =(1-Inputs!$B$38)*C15+Inputs!$B$38*$B$32*$M15*$M$6 -> -0.00017249841 | D51: =(1-Inputs!$B$38)*D15+Inputs!$B$38*$B$32*$M15*$M$7 -> -8.0693182e-05 | E51: =(1-Inputs!$B$38)*E15+Inputs!$B$38*$B$32*$M15*$M$8 -> -0.0001351391 | F51: =(1-Inputs!$B$38)*F15+Inputs!$B$38*$B$32*$M15*$M$9 -> -0.0001132026 | G51: =(1-Inputs!$B$38)*G15+Inputs!$B$38*$B$32*$M15*$M$10 -> -5.2311367e-05 | H51: =(1-Inputs!$B$38)*H15+Inputs!$B$38*$B$32*$M15*$M$11 -> 9.215266e-05 | I51: =(1-Inputs!$B$38)*I15+Inputs!$B$38*$B$32*$M15*$M$12 -> -4.5947589e-05 | J51: =(1-Inputs!$B$38)*J15+Inputs!$B$38*$B$32*$M15*$M$13 -> 0.00011059713 | K51: =(1-Inputs!$B$38)*K15+Inputs!$B$38*$B$32*$M15*$M$14 -> 0.00010324317 | L51: =L15 -> 9.6274886e-05 | M51: =SQRT(L51) -> 0.0098119767
A53: 4. Portfolio metrics
A54: Net forecast return | B54: =Forecast!$G$6 -> 0.082659384 | C54: =Forecast!$G$7 -> 0.082159384 | D54: =Forecast!$G$8 -> 0.078765261 | E54: =Forecast!$G$9 -> 0.073233091 | F54: =Forecast!$G$10 -> 0.050257982 | G54: =Forecast!$G$11 -> 0.054405261 | H54: =Forecast!$G$12 -> 0.033246947 | I54: =Forecast!$G$13 -> 0.05867702 | J54: =Forecast!$G$14 -> 0.047855337 | K54: =Forecast!$G$15 -> 0.047723755 | L54: =Forecast!$G$16 -> 0.046012756
A55: Portfolio | B55: Australian Equities | C55: World Equities | D55: Emerging Markets | E55: Listed Property | F55: Commodities | G55: Direct Property | H55: Hedge Funds | I55: Private Equity | J55: Australian Fixed Income | K55: World Fixed Income | L55: Cash | M55: Volatility | N55: Expected return | O55: Tracking error | P55: Max weight gap vs recommended
A56: Current fund | B56: =Inputs!$B$5 -> 0.4 | C56: =Inputs!$B$6 -> 0.2 | D56: =Inputs!$B$7 -> 0 | E56: =Inputs!$B$8 -> 0.1 | F56: =Inputs!$B$9 -> 0 | G56: =Inputs!$B$10 -> 0 | H56: =Inputs!$B$11 -> 0 | I56: =Inputs!$B$12 -> 0 | J56: =Inputs!$B$13 -> 0.15 | K56: =Inputs!$B$14 -> 0.08 | L56: =Inputs!$B$15 -> 0.07 | M56: =SQRT(SUMPRODUCT(MMULT(B56:L56,$B$41:$L$51),B56:L56)) -> 0.083833964 | N56: =SUMPRODUCT($B$54:$L$54,B56:L56) -> 0.071036034 | O56: =SQRT(SUMPRODUCT(MMULT(B67:L67,$B$41:$L$51),B67:L67)) -> 0.021585026
A57: Benchmark | B57: =Inputs!$C$5 -> 0.25 | C57: =Inputs!$C$6 -> 0.24 | D57: =Inputs!$C$7 -> 0.03 | E57: =Inputs!$C$8 -> 0.07 | F57: =Inputs!$C$9 -> 0.02 | G57: =Inputs!$C$10 -> 0.05 | H57: =Inputs!$C$11 -> 0.03 | I57: =Inputs!$C$12 -> 0.03 | J57: =Inputs!$C$13 -> 0.14 | K57: =Inputs!$C$14 -> 0.11 | L57: =Inputs!$C$15 -> 0.03 | M57: =SQRT(SUMPRODUCT(MMULT(B57:L57,$B$41:$L$51),B57:L57)) -> 0.070134112 | N57: =SUMPRODUCT($B$54:$L$54,B57:L57) -> 0.067685257 | O57: 0
A58: Recommended | B58: =Portfolio!$E$6 -> 0.2697 | C58: =Portfolio!$E$7 -> 0.2732 | D58: =Portfolio!$E$8 -> 0.0771 | E58: =Portfolio!$E$9 -> 0.0754 | F58: =Portfolio!$E$10 -> 0.03 | G58: =Portfolio!$E$11 -> 0.05 | H58: =Portfolio!$E$12 -> 0 | I58: =Portfolio!$E$13 -> 0.01 | J58: =Portfolio!$E$14 -> 0.1309 | K58: =Portfolio!$E$15 -> 0.0637 | L58: =Portfolio!$E$16 -> 0.02 | M58: =SQRT(SUMPRODUCT(MMULT(B58:L58,$B$41:$L$51),B58:L58)) -> 0.078750643 | N58: =SUMPRODUCT($B$54:$L$54,B58:L58) -> 0.071373051 | O58: =SQRT(SUMPRODUCT(MMULT(B68:L68,$B$41:$L$51),B68:L68)) -> 0.010997193
A59: Naive MVO | B59: =Validation!$B$30 -> 0.2149 | C59: =Validation!$B$31 -> 0.35 | D59: =Validation!$B$32 -> 0.0551 | E59: =Validation!$B$33 -> 0.0372 | F59: =Validation!$B$34 -> 0.03 | G59: =Validation!$B$35 -> 0.05 | H59: =Validation!$B$36 -> 0 | I59: =Validation!$B$37 -> 0.01 | J59: =Validation!$B$38 -> 0.05 | K59: =Validation!$B$39 -> 0.1828 | L59: =Validation!$B$40 -> 0.02 | M59: =SQRT(SUMPRODUCT(MMULT(B59:L59,$B$41:$L$51),B59:L59)) -> 0.075341501 | N59: =SUMPRODUCT($B$54:$L$54,B59:L59) -> 0.07043522 | O59: =SQRT(SUMPRODUCT(MMULT(B69:L69,$B$41:$L$51),B69:L69)) -> 0.013477683 | P59: =SUMPRODUCT(MAX(ABS(B59:L59-$B$58:$L$58))) -> #VALUE!
A60: Unshrunk covariance | B60: =Validation!$C$30 -> 0.269 | C60: =Validation!$C$31 -> 0.2784 | D60: =Validation!$C$32 -> 0.0727 | E60: =Validation!$C$33 -> 0.0635 | F60: =Validation!$C$34 -> 0.03 | G60: =Validation!$C$35 -> 0.05 | H60: =Validation!$C$36 -> 0 | I60: =Validation!$C$37 -> 0.01 | J60: =Validation!$C$38 -> 0.1564 | K60: =Validation!$C$39 -> 0.05 | L60: =Validation!$C$40 -> 0.02 | M60: =SQRT(SUMPRODUCT(MMULT(B60:L60,$B$41:$L$51),B60:L60)) -> 0.077727303 | N60: =SUMPRODUCT($B$54:$L$54,B60:L60) -> 0.071090873 | O60: =SQRT(SUMPRODUCT(MMULT(B70:L70,$B$41:$L$51),B70:L70)) -> 0.010247201 | P60: =SUMPRODUCT(MAX(ABS(B60:L60-$B$58:$L$58))) -> #VALUE!
A61: Tight TE (0.75%) | B61: =Validation!$D$30 -> 0.2629 | C61: =Validation!$D$31 -> 0.2635 | D61: =Validation!$D$32 -> 0.0605 | E61: =Validation!$D$33 -> 0.0702 | F61: =Validation!$D$34 -> 0.03 | G61: =Validation!$D$35 -> 0.05 | H61: =Validation!$D$36 -> 0 | I61: =Validation!$D$37 -> 0.01 | J61: =Validation!$D$38 -> 0.1433 | K61: =Validation!$D$39 -> 0.0896 | L61: =Validation!$D$40 -> 0.02 | M61: =SQRT(SUMPRODUCT(MMULT(B61:L61,$B$41:$L$51),B61:L61)) -> 0.075433821 | N61: =SUMPRODUCT($B$54:$L$54,B61:L61) -> 0.070155157 | O61: =SQRT(SUMPRODUCT(MMULT(B71:L71,$B$41:$L$51),B71:L71)) -> 0.0075065338 | P61: =SUMPRODUCT(MAX(ABS(B61:L61-$B$58:$L$58))) -> #VALUE!
A62: Loose TE (1.5%) | B62: =Validation!$E$30 -> 0.2726 | C62: =Validation!$E$31 -> 0.2682 | D62: =Validation!$E$32 -> 0.0792 | E62: =Validation!$E$33 -> 0.1124 | F62: =Validation!$E$34 -> 0.03 | G62: =Validation!$E$35 -> 0.05 | H62: =Validation!$E$36 -> 0 | I62: =Validation!$E$37 -> 0.01 | J62: =Validation!$E$38 -> 0.1076 | K62: =Validation!$E$39 -> 0.05 | L62: =Validation!$E$40 -> 0.02 | M62: =SQRT(SUMPRODUCT(MMULT(B62:L62,$B$41:$L$51),B62:L62)) -> 0.082552799 | N62: =SUMPRODUCT($B$54:$L$54,B62:L62) -> 0.072308153 | O62: =SQRT(SUMPRODUCT(MMULT(B72:L72,$B$41:$L$51),B72:L72)) -> 0.014996813 | P62: =SUMPRODUCT(MAX(ABS(B62:L62-$B$58:$L$58))) -> #VALUE!
A63: OOS robust, fit 2006-16 | B63: =Validation!$B$17 -> 0.2744 | C63: =Validation!$B$18 -> 0.2734 | D63: =Validation!$B$19 -> 0.0603 | E63: =Validation!$B$20 -> 0.0846 | F63: =Validation!$B$21 -> 0.03 | G63: =Validation!$B$22 -> 0.05 | H63: =Validation!$B$23 -> 0 | I63: =Validation!$B$24 -> 0.01 | J63: =Validation!$B$25 -> 0.1473 | K63: =Validation!$B$26 -> 0.05 | L63: =Validation!$B$27 -> 0.02 | M63: =SQRT(SUMPRODUCT(MMULT(B63:L63,$B$41:$L$51),B63:L63)) -> 0.079226287 | N63: =SUMPRODUCT($B$54:$L$54,B63:L63) -> 0.071259482
A64: OOS naive, fit 2006-16 | B64: =Validation!$C$17 -> 0.2332 | C64: =Validation!$C$18 -> 0.15 | D64: =Validation!$C$19 -> 0.0516 | E64: =Validation!$C$20 -> 0.0927 | F64: =Validation!$C$21 -> 0.03 | G64: =Validation!$C$22 -> 0.05 | H64: =Validation!$C$23 -> 0 | I64: =Validation!$C$24 -> 0.01 | J64: =Validation!$C$25 -> 0.1625 | K64: =Validation!$C$26 -> 0.2 | L64: =Validation!$C$27 -> 0.02 | M64: =SQRT(SUMPRODUCT(MMULT(B64:L64,$B$41:$L$51),B64:L64)) -> 0.063216364 | N64: =SUMPRODUCT($B$54:$L$54,B64:L64) -> 0.065509342
A66: Active weights vs benchmark
A67: Current fund | B67: =B56-B$57 -> 0.15 | C67: =C56-C$57 -> -0.04 | D67: =D56-D$57 -> -0.03 | E67: =E56-E$57 -> 0.03 | F67: =F56-F$57 -> -0.02 | G67: =G56-G$57 -> -0.05 | H67: =H56-H$57 -> -0.03 | I67: =I56-I$57 -> -0.03 | ... L67: =L56-L$57 -> 0.04
A68: Recommended | B68: =B58-B$57 -> 0.0197 | C68: =C58-C$57 -> 0.0332 | D68: =D58-D$57 -> 0.0471 | E68: =E58-E$57 -> 0.0054 | F68: =F58-F$57 -> 0.01 | G68: =G58-G$57 -> 0 | H68: =H58-H$57 -> -0.03 | I68: =I58-I$57 -> -0.02 | ... L68: =L58-L$57 -> -0.01
A69: Naive MVO | B69: =B59-B$57 -> -0.0351 | C69: =C59-C$57 -> 0.11 | D69: =D59-D$57 -> 0.0251 | E69: =E59-E$57 -> -0.0328 | F69: =F59-F$57 -> 0.01 | G69: =G59-G$57 -> 0 | H69: =H59-H$57 -> -0.03 | I69: =I59-I$57 -> -0.02 | ... L69: =L59-L$57 -> -0.01
A70: Unshrunk covariance | B70: =B60-B$57 -> 0.019 | C70: =C60-C$57 -> 0.0384 | D70: =D60-D$57 -> 0.0427 | E70: =E60-E$57 -> -0.0065 | F70: =F60-F$57 -> 0.01 | G70: =G60-G$57 -> 0 | H70: =H60-H$57 -> -0.03 | I70: =I60-I$57 -> -0.02 | ... L70: =L60-L$57 -> -0.01
A71: Tight TE | B71: =B61-B$57 -> 0.0129 | C71: =C61-C$57 -> 0.0235 | D71: =D61-D$57 -> 0.0305 | E71: =E61-E$57 -> 0.0002 | F71: =F61-F$57 -> 0.01 | G71: =G61-G$57 -> 0 | H71: =H61-H$57 -> -0.03 | I71: =I61-I$57 -> -0.02 | ... L71: =L61-L$57 -> -0.01
A72: Loose TE | B72: =B62-B$57 -> 0.0226 | C72: =C62-C$57 -> 0.0282 | D72: =D62-D$57 -> 0.0492 | E72: =E62-E$57 -> 0.0424 | F72: =F62-F$57 -> 0.01 | G72: =G62-G$57 -> 0 | H72: =H62-H$57 -> -0.03 | I72: =I62-I$57 -> -0.02 | ... L72: =L62-L$57 -> -0.01

Sheet Portfolio
A1: Portfolio
A3: 1. Stage 1 (optimised) and Stage 2 (judgement)
A5: Asset class | B5: Stage | C5: Current | D5: Benchmark | E5: Recommended | F5: Lower | G5: Upper | H5: Active vs benchmark | I5: Change vs current | J5: Trade (A$m) | K5: Net forecast | L5: Return contribution
A6: Australian Equities | B6: 1: optimised | C6: =Inputs!B5 -> 0.4 | D6: =Inputs!C5 -> 0.25 | E6: =Methods!I6 -> 0.2697 | F6: =Inputs!E5 -> 0.15 | G6: =Inputs!F5 -> 0.35 | H6: =E6-D6 -> 0.0197 | I6: =E6-C6 -> -0.1303 | J6: =I6*Inputs!$B$22 -> -390.9 | K6: =Forecast!G6 -> 0.082659384 | L6: =E6*K6 -> 0.022293236
A7: World Equities | B7: 1: optimised | C7: =Inputs!B6 -> 0.2 | D7: =Inputs!C6 -> 0.24 | E7: =Methods!I7 -> 0.2732 | F7: =Inputs!E6 -> 0.15 | G7: =Inputs!F6 -> 0.35 | H7: =E7-D7 -> 0.0332 | I7: =E7-C7 -> 0.0732 | J7: =I7*Inputs!$B$22 -> 219.6 | K7: =Forecast!G7 -> 0.082159384 | L7: =E7*K7 -> 0.022445944
A8: Emerging Markets | B8: 1: optimised | C8: =Inputs!B7 -> 0 | D8: =Inputs!C7 -> 0.03 | E8: =Methods!I8 -> 0.0771 | F8: =Inputs!E7 -> 0 | G8: =Inputs!F7 -> 0.08 | H8: =E8-D8 -> 0.0471 | I8: =E8-C8 -> 0.0771 | J8: =I8*Inputs!$B$22 -> 231.3 | K8: =Forecast!G8 -> 0.078765261 | L8: =E8*K8 -> 0.0060728016
A9: Listed Property | B9: 1: optimised | C9: =Inputs!B8 -> 0.1 | D9: =Inputs!C8 -> 0.07 | E9: =Methods!I9 -> 0.0754 | F9: =Inputs!E8 -> 0 | G9: =Inputs!F8 -> 0.12 | H9: =E9-D9 -> 0.0054 | I9: =E9-C9 -> -0.0246 | J9: =I9*Inputs!$B$22 -> -73.8 | K9: =Forecast!G9 -> 0.073233091 | L9: =E9*K9 -> 0.0055217751
A10: Commodities | B10: 2: judgement | C10: =Inputs!B9 -> 0 | D10: =Inputs!C9 -> 0.02 | E10: =H23 -> 0.03 | F10: =Inputs!E9 -> 0 | G10: =Inputs!F9 -> 0.08 | H10: =E10-D10 -> 0.01 | I10: =E10-C10 -> 0.03 | J10: =I10*Inputs!$B$22 -> 90 | K10: =Forecast!G10 -> 0.050257982 | L10: =E10*K10 -> 0.0015077395
A11: Direct Property | B11: 2: judgement | C11: =Inputs!B10 -> 0 | D11: =Inputs!C10 -> 0.05 | E11: =H24 -> 0.05 | F11: =Inputs!E10 -> 0 | G11: =Inputs!F10 -> 0.1 | H11: =E11-D11 -> 0 | I11: =E11-C11 -> 0.05 | J11: =I11*Inputs!$B$22 -> 150 | K11: =Forecast!G11 -> 0.054405261 | L11: =E11*K11 -> 0.0027202631
A12: Hedge Funds | B12: 2: judgement | C12: =Inputs!B11 -> 0 | D12: =Inputs!C11 -> 0.03 | E12: =H25 -> 0 | F12: =Inputs!E11 -> 0 | G12: =Inputs!F11 -> 0.08 | H12: =E12-D12 -> -0.03 | I12: =E12-C12 -> 0 | J12: =I12*Inputs!$B$22 -> 0 | K12: =Forecast!G12 -> 0.033246947 | L12: =E12*K12 -> 0
A13: Private Equity | B13: 2: judgement | C13: =Inputs!B12 -> 0 | D13: =Inputs!C12 -> 0.03 | E13: =H26 -> 0.01 | F13: =Inputs!E12 -> 0 | G13: =Inputs!F12 -> 0.08 | H13: =E13-D13 -> -0.02 | I13: =E13-C13 -> 0.01 | J13: =I13*Inputs!$B$22 -> 30 | K13: =Forecast!G13 -> 0.05867702 | L13: =E13*K13 -> 0.0005867702
A14: Australian Fixed Income | B14: 1: optimised | C14: =Inputs!B13 -> 0.15 | D14: =Inputs!C13 -> 0.14 | E14: =Methods!I14 -> 0.1309 | F14: =Inputs!E13 -> 0.05 | G14: =Inputs!F13 -> 0.25 | H14: =E14-D14 -> -0.0091 | I14: =E14-C14 -> -0.0191 | J14: =I14*Inputs!$B$22 -> -57.3 | K14: =Forecast!G14 -> 0.047855337 | L14: =E14*K14 -> 0.0062642636
A15: World Fixed Income | B15: 1: optimised | C15: =Inputs!B14 -> 0.08 | D15: =Inputs!C14 -> 0.11 | E15: =Methods!I15 -> 0.0637 | F15: =Inputs!E14 -> 0.05 | G15: =Inputs!F14 -> 0.2 | H15: =E15-D15 -> -0.0463 | I15: =E15-C15 -> -0.0163 | J15: =I15*Inputs!$B$22 -> -48.9 | K15: =Forecast!G15 -> 0.047723755 | L15: =E15*K15 -> 0.0030400032
A16: Cash | B16: 1: optimised | C16: =Inputs!B15 -> 0.07 | D16: =Inputs!C15 -> 0.03 | E16: =Methods!I16 -> 0.02 | F16: =Inputs!E15 -> 0.02 | G16: =Inputs!F15 -> 0.1 | H16: =E16-D16 -> -0.01 | I16: =E16-C16 -> -0.05 | J16: =I16*Inputs!$B$22 -> -150 | K16: =Forecast!G16 -> 0.046012756 | L16: =E16*K16 -> 0.00092025513
A17: Total | C17: =SUM(C6:C16) -> 1 | D17: =SUM(D6:D16) -> 1 | E17: =SUM(E6:E16) -> 1 | H17: =SUM(H6:H16) -> -3.1225023e-17 | I17: =SUM(I6:I16) -> -5.5511151e-17 | J17: =SUM(J6:J16) -> 0 | L17: =SUM(L6:L16) -> 0.071373051
A20: 2. Stage 2 scorecard (1 to 5)
A22: Asset class | B22: Return | C22: Diversification | D22: Liquidity | E22: Data quality | F22: Implementation | G22: Average | H22: Weight set | I22: Benchmark
A23: Commodities | B23: 3 | C23: 5 | D23: 5 | E23: 3 | F23: 4 | G23: =AVERAGE(B23:F23) -> 4 | H23: 0.03 | I23: =Inputs!C9 -> 0.02
A24: Direct Property | B24: 3 | C24: 4 | D24: 1 | E24: 2 | F24: 2 | G24: =AVERAGE(B24:F24) -> 2.4 | H24: 0.05 | I24: =Inputs!C10 -> 0.05
A25: Hedge Funds | B25: 2 | C25: 3 | D25: 2 | E25: 2 | F25: 2 | G25: =AVERAGE(B25:F25) -> 2.2 | H25: 0 | I25: =Inputs!C11 -> 0.03
A26: Private Equity | B26: 4 | C26: 3 | D26: 1 | E26: 2 | F26: 2 | G26: =AVERAGE(B26:F26) -> 2.4 | H26: 0.01 | I26: =Inputs!C12 -> 0.03
A27: Total Stage 2 | H27: =SUM(H23:H26) -> 0.09 | I27: =SUM(I23:I26) -> 0.13
A30: 3. Solver constraints
A31: Metric | B31: Value | C31: Lower limit | D31: Upper limit | E31: Status
A32: Expected return (maximise) | B32: =SUMPRODUCT(E6:E16,K6:K16) -> 0.071373051 | E32: ="INFO" -> INFO
A33: Tracking error (parametric) | B33: =Risk!O58 -> 0.010997193 | D33: =Inputs!$B$45 -> 0.011 | E33: =IF(B33<=D33+0.00005,"MET","NOT MET") -> MET
A34: Equity allocation | B34: =SUMPRODUCT(E6:E16,Inputs!$G$5:$G$15) -> 0.62 | C34: =Inputs!$B$31 -> 0.42 | D34: =Inputs!$B$32 -> 0.62 | E34: =IF(AND(B34>=C34-0.000001,B34<=D34+0.000001),"MET","NOT MET") -> MET
A35: Illiquid allocation | B35: =SUMPRODUCT(E6:E16,Inputs!$H$5:$H$15) -> 0.06 | D35: =Inputs!$B$33 -> 0.3 | E35: =IF(B35<=D35,"MET","NOT MET") -> MET
A36: Cash allocation | B36: =E16 -> 0.02 | C36: =Inputs!$B$34 -> 0.02 | E36: =IF(B36>=C36,"MET","NOT MET") -> MET
A37: Weights sum to 100% | B37: =SUM(E6:E16) -> 1 | C37: 1 | D37: 1 | E37: =IF(ABS(B37-1)<0.000001,"MET","NOT MET") -> MET
A38: Share inside bounds | B38: =SUMPRODUCT((E6:E16>=F6:F16-0.000001)*(E6:E16<=G6:G16+0.000001))/11 -> 1 | C38: 1 | E38: =IF(B38>=C38,"MET","NOT MET") -> MET
A41: 4. What each constraint costs
A42: Asset class | B42: Base (recommended) | C42: TE limit 1.5% | D42: No TE limit | E42: Equity max 72% | F42: Alternatives optimised | G42: Long-only only
A43: Australian Equities | B43: =E6 -> 0.2697 | C43: 0.2726 | D43: 0.35 | E43: 0.2699 | F43: 0.2709 | G43: 0.98
A44: World Equities | B44: =E7 -> 0.2732 | C44: 0.2682 | D44: 0.27 | E44: 0.275 | F44: 0.2693 | G44: 0
A45: Emerging Markets | B45: =E8 -> 0.0771 | C45: 0.0792 | D45: 0 | E45: 0.0785 | F45: 0.0798 | G45: 0
A46: Listed Property | B46: =E9 -> 0.0754 | C46: 0.1124 | D46: 0.12 | E46: 0.0713 | F46: 0.0872 | G46: 0
A47: Commodities | B47: =E10 -> 0.03 | C47: 0.03 | D47: 0.03 | E47: 0.03 | F47: 0.0079 | G47: 0
A48: Direct Property | B48: =E11 -> 0.05 | C48: 0.05 | D48: 0.05 | E48: 0.05 | F48: 0.0494 | G48: 0
A49: Hedge Funds | B49: =E12 -> 0 | C49: 0 | D49: 0 | E49: 0 | F49: 0 | G49: 0
A50: Private Equity | B50: =E13 -> 0.01 | C50: 0.01 | D50: 0.01 | E50: 0.01 | F50: 0.0247 | G50: 0
A51: Australian Fixed Income | B51: =E14 -> 0.1309 | C51: 0.1076 | D51: 0.1 | E51: 0.1309 | F51: 0.1324 | G51: 0
A52: World Fixed Income | B52: =E15 -> 0.0637 | C52: 0.05 | D52: 0.05 | E52: 0.0644 | F52: 0.0584 | G52: 0
A53: Cash | B53: =E16 -> 0.02 | C53: 0.02 | D53: 0.02 | E53: 0.02 | F53: 0.02 | G53: 0.02
A55: Expected return | B55: =SUMPRODUCT(B43:B53,Forecast!$G$6:$G$16) -> 0.071373051 | C55: =SUMPRODUCT(C43:C53,Forecast!$G$6:$G$16) -> 0.072308153 | D55: =SUMPRODUCT(D43:D53,Forecast!$G$6:$G$16) -> 0.072808539 | E55: =SUMPRODUCT(E43:E53,Forecast!$G$6:$G$16) -> 0.071380892 | F55: =SUMPRODUCT(F43:F53,Forecast!$G$6:$G$16) -> 0.071766692 | G55: =SUMPRODUCT(G43:G53,Forecast!$G$6:$G$16) -> 0.081926452
A56: Volatility | B56: =SQRT(SUMPRODUCT(B43:B53,MMULT(Risk!$B$41:$L$51,B43:B53))) -> 0.078750643 | C56: =SQRT(SUMPRODUCT(C43:C53,MMULT(Risk!$B$41:$L$51,C43:C53))) -> 0.082552799 | D56: =SQRT(SUMPRODUCT(D43:D53,MMULT(Risk!$B$41:$L$51,D43:D53))) -> 0.088695808 | E56: =SQRT(SUMPRODUCT(E43:E53,MMULT(Risk!$B$41:$L$51,E43:E53))) -> 0.078638265 | F56: =SQRT(SUMPRODUCT(F43:F53,MMULT(Risk!$B$41:$L$51,F43:F53))) -> 0.079408205 | G56: =SQRT(SUMPRODUCT(G43:G53,MMULT(Risk!$B$41:$L$51,G43:G53))) -> 0.15072222
A57: Tracking error | B57: =SQRT(SUMPRODUCT(B43:B53-Inputs!$C$5:$C$15,MMULT(Risk!$B$41:$L$51,B43:B53-Inputs!$C$5:$C$15))) -> 0.010997193 | C57: =SQRT(SUMPRODUCT(C43:C53-Inputs!$C$5:$C$15,MMULT(Risk!$B$41:$L$51,C43:C53-Inputs!$C$5:$C$15))) -> 0.014996813 | D57: =SQRT(SUMPRODUCT(D43:D53-Inputs!$C$5:$C$15,MMULT(Risk!$B$41:$L$51,D43:D53-Inputs!$C$5:$C$15))) -> 0.020868796 | E57: =SQRT(SUMPRODUCT(E43:E53-Inputs!$C$5:$C$15,MMULT(Risk!$B$41:$L$51,E43:E53-Inputs!$C$5:$C$15))) -> 0.011003818 | F57: =SQRT(SUMPRODUCT(F43:F53-Inputs!$C$5:$C$15,MMULT(Risk!$B$41:$L$51,F43:F53-Inputs!$C$5:$C$15))) -> 0.010997147 | G57: =SQRT(SUMPRODUCT(G43:G53-Inputs!$C$5:$C$15,MMULT(Risk!$B$41:$L$51,G43:G53-Inputs!$C$5:$C$15))) -> 0.10107768
A58: Return gain vs base | B58: =B55-$B$55 -> 0 | C58: =C55-$B$55 -> 0.00093510193 | D58: =D55-$B$55 -> 0.0014354874 | E58: =E55-$B$55 -> 7.841088e-06 | F58: =F55-$B$55 -> 0.00039364108 | G58: =G55-$B$55 -> 0.010553401
A59: Reaches return target? | B59: =IF(B55>=Inputs!$B$25,"YES","NO") -> NO | C59: =IF(C55>=Inputs!$B$25,"YES","NO") -> NO | D59: =IF(D55>=Inputs!$B$25,"YES","NO") -> NO | E59: =IF(E55>=Inputs!$B$25,"YES","NO") -> NO | F59: =IF(F55>=Inputs!$B$25,"YES","NO") -> NO | G59: =IF(G55>=Inputs!$B$25,"YES","NO") -> NO

Sheet Methods
A1: Methods
A2: Selected method | B2: =INDEX(D5:H5,Inputs!$B$49) -> Robust MVO
A3: 1. Method weights (Stage 2 fixed; every method under the brief and the TE limit)
A5: Asset class | B5: Current | C5: Benchmark | D5: Robust MVO | E5: Sample MVO | F5: Resampled MVO | G5: Minimum variance | H5: Risk parity | I5: Selected
A6: Australian Equities | B6: =Inputs!B5 -> 0.4 | C6: =Inputs!C5 -> 0.25 | D6: 0.2697 | E6: 0.269 | F6: 0.256 | G6: 0.2117 | H6: 0.1931 | I6: =INDEX(D6:H6,Inputs!$B$49) -> 0.2697
A7: World Equities | B7: =Inputs!B6 -> 0.2 | C7: =Inputs!C6 -> 0.24 | D7: 0.2732 | E7: 0.2783 | F7: 0.2712 | G7: 0.2086 | H7: 0.1992 | I7: =INDEX(D7:H7,Inputs!$B$49) -> 0.2732
A8: Emerging Markets | B8: =Inputs!B7 -> 0 | C8: =Inputs!C7 -> 0.03 | D8: 0.0771 | E8: 0.0727 | F8: 0.0489 | G8: 0.0285 | H8: 0.08 | I8: =INDEX(D8:H8,Inputs!$B$49) -> 0.0771
A9: Listed Property | B9: =Inputs!B8 -> 0.1 | C9: =Inputs!C8 -> 0.07 | D9: 0.0754 | E9: 0.0635 | F9: 0.0744 | G9: 0.0557 | H9: 0.1117 | I9: =INDEX(D9:H9,Inputs!$B$49) -> 0.0754
A10: Commodities | B10: =Inputs!B9 -> 0 | C10: =Inputs!C9 -> 0.02 | D10: =Portfolio!H23 -> 0.03 | E10: =$D10 -> 0.03 | F10: =$D10 -> 0.03 | G10: =$D10 -> 0.03 | H10: =$D10 -> 0.03 | I10: =INDEX(D10:H10,Inputs!$B$49) -> 0.03
A11: Direct Property | B11: =Inputs!B10 -> 0 | C11: =Inputs!C10 -> 0.05 | D11: =Portfolio!H24 -> 0.05 | E11: =$D11 -> 0.05 | F11: =$D11 -> 0.05 | G11: =$D11 -> 0.05 | H11: =$D11 -> 0.05 | I11: =INDEX(D11:H11,Inputs!$B$49) -> 0.05
A12: Hedge Funds | B12: =Inputs!B11 -> 0 | C12: =Inputs!C11 -> 0.03 | D12: =Portfolio!H25 -> 0 | E12: =$D12 -> 0 | F12: =$D12 -> 0 | G12: =$D12 -> 0 | H12: =$D12 -> 0 | I12: =INDEX(D12:H12,Inputs!$B$49) -> 0
A13: Private Equity | B13: =Inputs!B12 -> 0 | C13: =Inputs!C12 -> 0.03 | D13: =Portfolio!H26 -> 0.01 | E13: =$D13 -> 0.01 | F13: =$D13 -> 0.01 | G13: =$D13 -> 0.01 | H13: =$D13 -> 0.01 | I13: =INDEX(D13:H13,Inputs!$B$49) -> 0.01
A14: Australian Fixed Income | B14: =Inputs!B13 -> 0.15 | C14: =Inputs!C13 -> 0.14 | D14: 0.1309 | E14: 0.1565 | F14: 0.1289 | G14: 0.1642 | H14: 0.1391 | I14: =INDEX(D14:H14,Inputs!$B$49) -> 0.1309
A15: World Fixed Income | B15: =Inputs!B14 -> 0.08 | C15: =Inputs!C14 -> 0.11 | D15: 0.0637 | E15: 0.05 | F15: 0.1012 | G15: 0.1413 | H15: 0.1669 | I15: =INDEX(D15:H15,Inputs!$B$49) -> 0.0637
A16: Cash | B16: =Inputs!B15 -> 0.07 | C16: =Inputs!C15 -> 0.03 | D16: 0.02 | E16: 0.02 | F16: 0.0294 | G16: 0.1 | H16: 0.02 | I16: =INDEX(D16:H16,Inputs!$B$49) -> 0.02
A17: Total | B17: =SUM(B6:B16) -> 1 | C17: =SUM(C6:C16) -> 1 | D17: =SUM(D6:D16) -> 1 | E17: =SUM(E6:E16) -> 1 | F17: =SUM(F6:F16) -> 1 | G17: =SUM(G6:G16) -> 1 | H17: =SUM(H6:H16) -> 1 | I17: =SUM(I6:I16) -> 1
A20: 2. Scorecard
A21: Portfolio | B21: Expected return | C21: Volatility | D21: Sharpe ratio | E21: Tracking error | F21: Annual fee | G21: Turnover from current | H21: Effective N | I21: Diversification ratio | J21: 5-year loss prob. (normal) | K21: GFC | L21: US$150 oil | M21: Meets brief?
A22: Robust MVO | B22: =SUMPRODUCT(D$6:D$16,Forecast!$G$6:$G$16) -> 0.071373051 | C22: =SQRT(SUMPRODUCT(D$6:D$16,MMULT(Risk!$B$41:$L$51,D$6:D$16))) -> 0.078750643 | D22: =(B22-Inputs!$B$26)/C22 -> 0.32219485 | E22: =SQRT(SUMPRODUCT(D$6:D$16-Inputs!$C$5:$C$15,MMULT(Risk!$B$41:$L$51,D$6:D$16-Inputs!$C$5:$C$15))) -> 0.010997193 | F22: =SUMPRODUCT(D$6:D$16,Inputs!$D$5:$D$15) -> 0.00214825 | G22: =SUMPRODUCT(ABS(D$6:D$16-$B$6:$B$16))/2 -> 0.2403 | H22: =1/SUMSQ(D$6:D$16) -> 5.4318777 | I22: =SUMPRODUCT(D$6:D$16,Forecast!$H$6:$H$16)/C22 -> 1.5086141 | J22: =NORMSDIST(-(B22-C22^2/2)*SQRT(5)/C22) -> 0.026278647 | K22: =SUMPRODUCT(D$6:D$16,Stress!$B$11:$B$21) -> -0.24131527 | L22: =SUMPRODUCT(D$6:D$16,Oil!$F$28:$F$38) -> -0.078202714 | M22: =IF(AND(E22<=Inputs!$B$27+0.00005,SUMPRODUCT(D$6:D$16,Inputs!$G$5:$G$15)>=Inputs!$B$31-0.000001,SUMPRODUCT(D$6:D$16,Inputs!$G$5:$G$15)<=Inputs!$B$32+0.000001,D16>=Inputs!$B$34-0.000001,SUMPRODUCT(D$6:D$16,Inputs!$H$5:$H$15)<=Inputs!$B$33,MIN(D$6:D$16)>=0),"MET","NOT MET") -> MET
A23: Sample MVO | B23: =SUMPRODUCT(E$6:E$16,Forecast!$G$6:$G$16) -> 0.071087443 | C23: =SQRT(SUMPRODUCT(E$6:E$16,MMULT(Risk!$B$41:$L$51,E$6:E$16))) -> 0.07771727 | D23: =(B23-Inputs!$B$26)/C23 -> 0.32280396 | E23: =SQRT(SUMPRODUCT(E$6:E$16-Inputs!$C$5:$C$15,MMULT(Risk!$B$41:$L$51,E$6:E$16-Inputs!$C$5:$C$15))) -> 0.010237183 | F23: =SUMPRODUCT(E$6:E$16,Inputs!$D$5:$D$15) -> 0.0021336 | G23: =SUMPRODUCT(ABS(E$6:E$16-$B$6:$B$16))/2 -> 0.2475 | H23: =1/SUMSQ(E$6:E$16) -> 5.2625574 | I23: =SUMPRODUCT(E$6:E$16,Forecast!$H$6:$H$16)/C23 -> 1.5108885 | J23: =NORMSDIST(-(B23-C23^2/2)*SQRT(5)/C23) -> 0.025090072 | K23: =SUMPRODUCT(E$6:E$16,Stress!$B$11:$B$21) -> -0.23323465 | L23: =SUMPRODUCT(E$6:E$16,Oil!$F$28:$F$38) -> -0.07742379 | M23: =IF(AND(E23<=Inputs!$B$27+0.00005,SUMPRODUCT(E$6:E$16,Inputs!$G$5:$G$15)>=Inputs!$B$31-0.000001,SUMPRODUCT(E$6:E$16,Inputs!$G$5:$G$15)<=Inputs!$B$32+0.000001,E16>=Inputs!$B$34-0.000001,SUMPRODUCT(E$6:E$16,Inputs!$H$5:$H$15)<=Inputs!$B$33,MIN(E$6:E$16)>=0),"MET","NOT MET") -> MET
A24: Resampled MVO | B24: =SUMPRODUCT(F$6:F$16,Forecast!$G$6:$G$16) -> 0.069908335 | C24: =SQRT(SUMPRODUCT(F$6:F$16,MMULT(Risk!$B$41:$L$51,F$6:F$16))) -> 0.075055184 | D24: =(B24-Inputs!$B$26)/C24 -> 0.31854342 | E24: =SQRT(SUMPRODUCT(F$6:F$16-Inputs!$C$5:$C$15,MMULT(Risk!$B$41:$L$51,F$6:F$16-Inputs!$C$5:$C$15))) -> 0.0071514981 | F24: =SUMPRODUCT(F$6:F$16,Inputs!$D$5:$D$15) -> 0.0021279 | G24: =SUMPRODUCT(ABS(F$6:F$16-$B$6:$B$16))/2 -> 0.2313 | H24: =1/SUMSQ(F$6:F$16) -> 5.6106326 | I24: =SUMPRODUCT(F$6:F$16,Forecast!$H$6:$H$16)/C24 -> 1.5300856 | J24: =NORMSDIST(-(B24-C24^2/2)*SQRT(5)/C24) -> 0.022814069 | K24: =SUMPRODUCT(F$6:F$16,Stress!$B$11:$B$21) -> -0.22158215 | L24: =SUMPRODUCT(F$6:F$16,Oil!$F$28:$F$38) -> -0.074493526 | M24: =IF(AND(E24<=Inputs!$B$27+0.00005,SUMPRODUCT(F$6:F$16,Inputs!$G$5:$G$15)>=Inputs!$B$31-0.000001,SUMPRODUCT(F$6:F$16,Inputs!$G$5:$G$15)<=Inputs!$B$32+0.000001,F16>=Inputs!$B$34-0.000001,SUMPRODUCT(F$6:F$16,Inputs!$H$5:$H$15)<=Inputs!$B$33,MIN(F$6:F$16)>=0),"MET","NOT MET") -> MET
A25: Minimum variance | B25: =SUMPRODUCT(G$6:G$16,Forecast!$G$6:$G$16) -> 0.064978594 | C25: =SQRT(SUMPRODUCT(G$6:G$16,MMULT(Risk!$B$41:$L$51,G$6:G$16))) -> 0.060281232 | D25: =(B25-Inputs!$B$26)/C25 -> 0.3148342 | E25: =SQRT(SUMPRODUCT(G$6:G$16-Inputs!$C$5:$C$15,MMULT(Risk!$B$41:$L$51,G$6:G$16-Inputs!$C$5:$C$15))) -> 0.011001412 | F25: =SUMPRODUCT(G$6:G$16,Inputs!$D$5:$D$15) -> 0.0020163 | G25: =SUMPRODUCT(ABS(G$6:G$16-$B$6:$B$16))/2 -> 0.2326 | H25: =1/SUMSQ(G$6:G$16) -> 6.5499501 | I25: =SUMPRODUCT(G$6:G$16,Forecast!$H$6:$H$16)/C25 -> 1.6354538 | J25: =NORMSDIST(-(B25-C25^2/2)*SQRT(5)/C25) -> 0.0095668672 | K25: =SUMPRODUCT(G$6:G$16,Stress!$B$11:$B$21) -> -0.1504255 | L25: =SUMPRODUCT(G$6:G$16,Oil!$F$28:$F$38) -> -0.061286031 | M25: =IF(AND(E25<=Inputs!$B$27+0.00005,SUMPRODUCT(G$6:G$16,Inputs!$G$5:$G$15)>=Inputs!$B$31-0.000001,SUMPRODUCT(G$6:G$16,Inputs!$G$5:$G$15)<=Inputs!$B$32+0.000001,G16>=Inputs!$B$34-0.000001,SUMPRODUCT(G$6:G$16,Inputs!$H$5:$H$15)<=Inputs!$B$33,MIN(G$6:G$16)>=0),"MET","NOT MET") -> MET
A26: Risk parity | B26: =SUMPRODUCT(H$6:H$16,Forecast!$G$6:$G$16) -> 0.067165834 | C26: =SQRT(SUMPRODUCT(H$6:H$16,MMULT(Risk!$B$41:$L$51,H$6:H$16))) -> 0.066508938 | D26: =(B26-Inputs!$B$26)/C26 -> 0.31824044 | E26: =SQRT(SUMPRODUCT(H$6:H$16-Inputs!$C$5:$C$15,MMULT(Risk!$B$41:$L$51,H$6:H$16-Inputs!$C$5:$C$15))) -> 0.010999556 | F26: =SUMPRODUCT(H$6:H$16,Inputs!$D$5:$D$15) -> 0.0021839 | G26: =SUMPRODUCT(ABS(H$6:H$16-$B$6:$B$16))/2 -> 0.2686 | H26: =1/SUMSQ(H$6:H$16) -> 6.8050561 | I26: =SUMPRODUCT(H$6:H$16,Forecast!$H$6:$H$16)/C26 -> 1.6315121 | J26: =NORMSDIST(-(B26-C26^2/2)*SQRT(5)/C26) -> 0.014488697 | K26: =SUMPRODUCT(H$6:H$16,Stress!$B$11:$B$21) -> -0.19027822 | L26: =SUMPRODUCT(H$6:H$16,Oil!$F$28:$F$38) -> -0.072014579 | M26: =IF(AND(E26<=Inputs!$B$27+0.00005,SUMPRODUCT(H$6:H$16,Inputs!$G$5:$G$15)>=Inputs!$B$31-0.000001,SUMPRODUCT(H$6:H$16,Inputs!$G$5:$G$15)<=Inputs!$B$32+0.000001,H16>=Inputs!$B$34-0.000001,SUMPRODUCT(H$6:H$16,Inputs!$H$5:$H$15)<=Inputs!$B$33,MIN(H$6:H$16)>=0),"MET","NOT MET") -> MET
A27: Current fund | B27: =SUMPRODUCT(B$6:B$16,Forecast!$G$6:$G$16) -> 0.071036034 | C27: =SQRT(SUMPRODUCT(B$6:B$16,MMULT(Risk!$B$41:$L$51,B$6:B$16))) -> 0.083833964 | D27: =(B27-Inputs!$B$26)/C27 -> 0.29863831 | E27: =SQRT(SUMPRODUCT(B$6:B$16-Inputs!$C$5:$C$15,MMULT(Risk!$B$41:$L$51,B$6:B$16-Inputs!$C$5:$C$15))) -> 0.021585026 | F27: =SUMPRODUCT(B$6:B$16,Inputs!$D$5:$D$15) -> 0.00112 | G27: =SUMPRODUCT(ABS(B$6:B$16-$B$6:$B$16))/2 -> 0 | H27: =1/SUMSQ(B$6:B$16) -> 4.1017227 | I27: =SUMPRODUCT(B$6:B$16,Forecast!$H$6:$H$16)/C27 -> 1.3609241 | J27: =NORMSDIST(-(B27-C27^2/2)*SQRT(5)/C27) -> 0.035852626 | K27: =SUMPRODUCT(B$6:B$16,Stress!$B$11:$B$21) -> -0.24167171 | L27: =SUMPRODUCT(B$6:B$16,Oil!$F$28:$F$38) -> -0.082609308 | M27: =IF(AND(E27<=Inputs!$B$27+0.00005,SUMPRODUCT(B$6:B$16,Inputs!$G$5:$G$15)>=Inputs!$B$31-0.000001,SUMPRODUCT(B$6:B$16,Inputs!$G$5:$G$15)<=Inputs!$B$32+0.000001,B16>=Inputs!$B$34-0.000001,SUMPRODUCT(B$6:B$16,Inputs!$H$5:$H$15)<=Inputs!$B$33,MIN(B$6:B$16)>=0),"MET","NOT MET") -> NOT MET
A28: Benchmark | B28: =SUMPRODUCT(C$6:C$16,Forecast!$G$6:$G$16) -> 0.067685257 | C28: =SQRT(SUMPRODUCT(C$6:C$16,MMULT(Risk!$B$41:$L$51,C$6:C$16))) -> 0.070134112 | D28: =(B28-Inputs!$B$26)/C28 -> 0.309197 | E28: =SQRT(SUMPRODUCT(C$6:C$16-Inputs!$C$5:$C$15,MMULT(Risk!$B$41:$L$51,C$6:C$16-Inputs!$C$5:$C$15))) -> 0 | F28: =SUMPRODUCT(C$6:C$16,Inputs!$D$5:$D$15) -> 0.00338 | G28: =SUMPRODUCT(ABS(C$6:C$16-$B$6:$B$16))/2 -> 0.23 | H28: =1/SUMSQ(C$6:C$16) -> 6.127451 | I28: =SUMPRODUCT(C$6:C$16,Forecast!$H$6:$H$16)/C28 -> 1.5726575 | J28: =NORMSDIST(-(B28-C28^2/2)*SQRT(5)/C28) -> 0.018782062 | K28: =SUMPRODUCT(C$6:C$16,Stress!$B$11:$B$21) -> -0.19300089 | L28: =SUMPRODUCT(C$6:C$16,Oil!$F$28:$F$38) -> -0.073910247 | M28: =IF(AND(E28<=Inputs!$B$27+0.00005,SUMPRODUCT(C$6:C$16,Inputs!$G$5:$G$15)>=Inputs!$B$31-0.000001,SUMPRODUCT(C$6:C$16,Inputs!$G$5:$G$15)<=Inputs!$B$32+0.000001,C16>=Inputs!$B$34-0.000001,SUMPRODUCT(C$6:C$16,Inputs!$H$5:$H$15)<=Inputs!$B$33,MIN(C$6:C$16)>=0),"MET","NOT MET") -> MET
A31: 3. Stability check: robust vs resampled
A32: Check | B32: Robust MVO | C32: Resampled MVO | D32: Difference | E32: Limit | F32: Status | J32: Yellow cells: Solver decision variables (Robust MVO)
A33: Largest asset-weight difference | D33: =MAX(E41:E51) -> 0.0375 | E33: 0.03 | F33: =IF(D33<=E33,"WITHIN LIMIT","ABOVE LIMIT") -> ABOVE LIMIT
A34: Expected return | B34: =B22 -> 0.071373051 | C34: =B24 -> 0.069908335 | D34: =ABS(B34-C34) -> 0.0014647158 | E34: 0.005 | F34: =IF(D34<=E34,"WITHIN LIMIT","ABOVE LIMIT") -> WITHIN LIMIT
A35: Volatility | B35: =C22 -> 0.078750643 | C35: =C24 -> 0.075055184 | D35: =ABS(B35-C35) -> 0.0036954585 | E35: 0.005 | F35: =IF(D35<=E35,"WITHIN LIMIT","ABOVE LIMIT") -> WITHIN LIMIT
A36: Asset with the largest difference | B36: =INDEX(A41:A51,MATCH(D33,E41:E51,0)) -> World Fixed Income
A37: Largest gap inside resampling spread? | B37: =INDEX(I41:I51,MATCH(D33,E41:E51,0)) -> Yes
A39: 4. Resampling spread (150 resampled input sets)
A40: Asset class | B40: Robust MVO | C40: Resampled average | D40: Difference | E40: Absolute difference | F40: Spread (std dev) | G40: 10th percentile | H40: 90th percentile | I40: Gap within spread?
A41: Australian Equities | B41: =D6 -> 0.2697 | C41: =F6 -> 0.256 | D41: =B41-C41 -> 0.0137 | E41: =ABS(D41) -> 0.0137 | F41: 0.0369 | G41: 0.2023 | H41: 0.3016 | I41: =IF(E41<=F41,"Yes","No") -> Yes
A42: World Equities | B42: =D7 -> 0.2732 | C42: =F7 -> 0.2712 | D42: =B42-C42 -> 0.002 | E42: =ABS(D42) -> 0.002 | F42: 0.0438 | G42: 0.2027 | H42: 0.3196 | I42: =IF(E42<=F42,"Yes","No") -> Yes
A43: Emerging Markets | B43: =D8 -> 0.0771 | C43: =F8 -> 0.0489 | D43: =B43-C43 -> 0.0282 | E43: =ABS(D43) -> 0.0282 | F43: 0.0314 | G43: 0 | H43: 0.08 | I43: =IF(E43<=F43,"Yes","No") -> Yes
A44: Listed Property | B44: =D9 -> 0.0754 | C44: =F9 -> 0.0744 | D44: =B44-C44 -> 0.001 | E44: =ABS(D44) -> 0.001 | F44: 0.0343 | G44: 0.0292 | H44: 0.12 | I44: =IF(E44<=F44,"Yes","No") -> Yes
A45: Commodities | B45: =D10 -> 0.03 | C45: =F10 -> 0.03 | D45: =B45-C45 -> 0 | E45: =ABS(D45) -> 0 | F45: 0 | G45: 0.03 | H45: 0.03 | I45: ="Stage 2 fixed" -> Stage 2 fixed
A46: Direct Property | B46: =D11 -> 0.05 | C46: =F11 -> 0.05 | D46: =B46-C46 -> 0 | E46: =ABS(D46) -> 0 | F46: 0 | G46: 0.05 | H46: 0.05 | I46: ="Stage 2 fixed" -> Stage 2 fixed
A47: Hedge Funds | B47: =D12 -> 0 | C47: =F12 -> 0 | D47: =B47-C47 -> 0 | E47: =ABS(D47) -> 0 | F47: 0 | G47: 0 | H47: 0 | I47: ="Stage 2 fixed" -> Stage 2 fixed
A48: Private Equity | B48: =D13 -> 0.01 | C48: =F13 -> 0.01 | D48: =B48-C48 -> 0 | E48: =ABS(D48) -> 0 | F48: 0 | G48: 0.01 | H48: 0.01 | I48: ="Stage 2 fixed" -> Stage 2 fixed
A49: Australian Fixed Income | B49: =D14 -> 0.1309 | C49: =F14 -> 0.1289 | D49: =B49-C49 -> 0.002 | E49: =ABS(D49) -> 0.002 | F49: 0.0574 | G49: 0.05 | H49: 0.2017 | I49: =IF(E49<=F49,"Yes","No") -> Yes
A50: World Fixed Income | B50: =D15 -> 0.0637 | C50: =F15 -> 0.1012 | D50: =B50-C50 -> -0.0375 | E50: =ABS(D50) -> 0.0375 | F50: 0.0587 | G50: 0.05 | H50: 0.2 | I50: =IF(E50<=F50,"Yes","No") -> Yes
A51: Cash | B51: =D16 -> 0.02 | C51: =F16 -> 0.0294 | D51: =B51-C51 -> -0.0094 | E51: =ABS(D51) -> 0.0094 | F51: 0.0242 | G51: 0.02 | H51: 0.0727 | I51: =IF(E51<=F51,"Yes","No") -> Yes

Sheet Bootstrap
A1: Bootstrap
A4: 1. Results (1,000 paths x 5 annual draws)
A5: Measure | B5: Current | C5: Benchmark | D5: Recommended | E5: Limit
A6: 5-year loss probability (bootstrap) | B6: =COUNTIF(G102:G1101,"<0")/COUNT(G102:G1101) -> 0.074 | C6: =COUNTIF(H102:H1101,"<0")/COUNT(H102:H1101) -> 0.062 | D6: =COUNTIF(I102:I1101,"<0")/COUNT(I102:I1101) -> 0.074 | E6: =Inputs!$B$28 -> 0.25
A7: 5-year loss probability (normal) | B7: =NORMSDIST(-(Risk!N56-Risk!M56^2/2)*SQRT(5)/Risk!M56) -> 0.035852626 | C7: =NORMSDIST(-(Risk!N57-Risk!M57^2/2)*SQRT(5)/Risk!M57) -> 0.018782062 | D7: =NORMSDIST(-(Risk!N58-Risk!M58^2/2)*SQRT(5)/Risk!M58) -> 0.026278647 | E7: =Inputs!$B$28 -> 0.25
A8: 5th percentile 5-year return | B8: =PERCENTILE(G102:G1101,0.05) -> -0.059777063 | C8: =PERCENTILE(H102:H1101,0.05) -> -0.018265939 | D8: =PERCENTILE(I102:I1101,0.05) -> -0.063457864
A9: Median 5-year return | B9: =MEDIAN(G102:G1101) -> 0.40339615 | C9: =MEDIAN(H102:H1101) -> 0.38418584 | D9: =MEDIAN(I102:I1101) -> 0.40425217
A10: 95th percentile 5-year return | B10: =PERCENTILE(G102:G1101,0.95) -> 0.86333979 | C10: =PERCENTILE(H102:H1101,0.95) -> 0.80449319 | D10: =PERCENTILE(I102:I1101,0.95) -> 0.89417567
A11: Median return, annualised | B11: =(1+B9)^(1/5)-1 -> 0.070128809 | C11: =(1+C9)^(1/5)-1 -> 0.067182956 | D11: =(1+D9)^(1/5)-1 -> 0.070259326
A12: Tracking error (bootstrap) | B12: =STDEV(J102:J1101)/SQRT(5) -> 0.015627427 | C12: 0 | D12: =STDEV(K102:K1101)/SQRT(5) -> 0.014051075 | E12: =Inputs!$B$27 -> 0.015
A13: Tracking error (parametric) | B13: =Risk!O56 -> 0.021585026 | C13: 0 | D13: =Risk!O58 -> 0.010997193 | E13: =Inputs!$B$27 -> 0.015
A14: Within limit (loss / TE) | B14: =IF(D6<=E6,"MET","NOT MET") -> MET | C14: =IF(D12<=E12,"MET","NOT MET") -> MET
A18: 2. Annual windows (adjusted returns, mean shifted to net forecast)
A20: Window | B20: Year ending | C20: Australian Equities | D20: World Equities | E20: Emerging Markets | F20: Listed Property | G20: Commodities | H20: Direct Property | I20: Hedge Funds | J20: Private Equity | K20: Australian Fixed Income | L20: World Fixed Income | M20: Cash | O20: Australian Equities (shifted) | P20: World Equities (shifted) | Q20: Emerging Markets (shifted) | R20: Listed Property (shifted) | S20: Commodities (shifted) | T20: Direct Property (shifted) | U20: Hedge Funds (shifted) | V20: Private Equity (shifted) | W20: Australian Fixed Income (shifted) | X20: World Fixed Income (shifted) | Y20: Cash (shifted) | Z20: Current | AA20: Benchmark | AB20: Recommended
A21: 1 | B21: ='Quarterly returns'!A9 -> 39171 | C21: =(1+'Quarterly returns'!N6)*(1+'Quarterly returns'!N7)*(1+'Quarterly returns'!N8)*(1+'Quarterly returns'!N9)-1 -> 0.22335287 | D21: =(1+'Quarterly returns'!O6)*(1+'Quarterly returns'!O7)*(1+'Quarterly returns'!O8)*(1+'Quarterly returns'!O9)-1 -> -0.013477703 | E21: =(1+'Quarterly returns'!P6)*(1+'Quarterly returns'!P7)*(1+'Quarterly returns'!P8)*(1+'Quarterly returns'!P9)-1 -> 0.061278297 | F21: =(1+'Quarterly returns'!Q6)*(1+'Quarterly returns'!Q7)*(1+'Quarterly returns'!Q8)*(1+'Quarterly returns'!Q9)-1 -> 0.12203701 | G21: =(1+'Quarterly returns'!R6)*(1+'Quarterly returns'!R7)*(1+'Quarterly returns'!R8)*(1+'Quarterly returns'!R9)-1 -> -0.20038571 | H21: =(1+'Quarterly returns'!S6)*(1+'Quarterly returns'!S7)*(1+'Quarterly returns'!S8)*(1+'Quarterly returns'!S9)-1 -> 0.089363022 | I21: =(1+'Quarterly returns'!T6)*(1+'Quarterly returns'!T7)*(1+'Quarterly returns'!T8)*(1+'Quarterly returns'!T9)-1 -> 0.11983848 | J21: =(1+'Quarterly returns'!U6)*(1+'Quarterly returns'!U7)*(1+'Quarterly returns'!U8)*(1+'Quarterly returns'!U9)-1 -> 0.25909107 | ... M21: =(1+'Quarterly returns'!X6)*(1+'Quarterly returns'!X7)*(1+'Quarterly returns'!X8)*(1+'Quarterly returns'!X9)-1 -> 0.062119266 | O21: =C21-AVERAGE(C$21:C$97)+Forecast!$G$6 -> 0.22341842 | P21: =D21-AVERAGE(D$21:D$97)+Forecast!$G$7 -> -0.036740235 | Q21: =E21-AVERAGE(E$21:E$97)+Forecast!$G$8 -> 0.050955722 | R21: =F21-AVERAGE(F$21:F$97)+Forecast!$G$9 -> 0.12278245 | S21: =G21-AVERAGE(G$21:G$97)+Forecast!$G$10 -> -0.16709689 | T21: =H21-AVERAGE(H$21:H$97)+Forecast!$G$11 -> 0.080799452 | U21: =I21-AVERAGE(I$21:I$97)+Forecast!$G$12 -> 0.073483834 | V21: =J21-AVERAGE(J$21:J$97)+Forecast!$G$13 -> 0.19442234 | W21: =K21-AVERAGE(K$21:K$97)+Forecast!$G$14 -> 0.042600196 | X21: =L21-AVERAGE(L$21:L$97)+Forecast!$G$15 -> 0.066437889 | Y21: =M21-AVERAGE(M$21:M$97)+Forecast!$G$16 -> 0.075488769 | Z21: =SUMPRODUCT($O21:$Y21,Risk!$B$56:$L$56) -> 0.11128684 | AA21: =SUMPRODUCT($O21:$Y21,Risk!$B$57:$L$57) -> 0.08143247 | AB21: =SUMPRODUCT($O21:$Y21,Risk!$B$58:$L$58) -> 0.075694523
A22: 2 | B22: ='Quarterly returns'!A10 -> 39262 | C22: =(1+'Quarterly returns'!N7)*(1+'Quarterly returns'!N8)*(1+'Quarterly returns'!N9)*(1+'Quarterly returns'!N10)-1 -> 0.3028133 | D22: =(1+'Quarterly returns'!O7)*(1+'Quarterly returns'!O8)*(1+'Quarterly returns'!O9)*(1+'Quarterly returns'!O10)-1 -> 0.069490787 | E22: =(1+'Quarterly returns'!P7)*(1+'Quarterly returns'!P8)*(1+'Quarterly returns'!P9)*(1+'Quarterly returns'!P10)-1 -> 0.22137832 | F22: =(1+'Quarterly returns'!Q7)*(1+'Quarterly returns'!Q8)*(1+'Quarterly returns'!Q9)*(1+'Quarterly returns'!Q10)-1 -> 0.042161147 | G22: =(1+'Quarterly returns'!R7)*(1+'Quarterly returns'!R8)*(1+'Quarterly returns'!R9)*(1+'Quarterly returns'!R10)-1 -> -0.24683502 | H22: =(1+'Quarterly returns'!S7)*(1+'Quarterly returns'!S8)*(1+'Quarterly returns'!S9)*(1+'Quarterly returns'!S10)-1 -> 0.11738199 | I22: =(1+'Quarterly returns'!T7)*(1+'Quarterly returns'!T8)*(1+'Quarterly returns'!T9)*(1+'Quarterly returns'!T10)-1 -> 0.12329036 | J22: =(1+'Quarterly returns'!U7)*(1+'Quarterly returns'!U8)*(1+'Quarterly returns'!U9)*(1+'Quarterly returns'!U10)-1 -> 0.27380445 | ... M22: =(1+'Quarterly returns'!X7)*(1+'Quarterly returns'!X8)*(1+'Quarterly returns'!X9)*(1+'Quarterly returns'!X10)-1 -> 0.064233762 | O22: =C22-AVERAGE(C$21:C$97)+Forecast!$G$6 -> 0.30287885 | P22: =D22-AVERAGE(D$21:D$97)+Forecast!$G$7 -> 0.046228255 | Q22: =E22-AVERAGE(E$21:E$97)+Forecast!$G$8 -> 0.21105575 | R22: =F22-AVERAGE(F$21:F$97)+Forecast!$G$9 -> 0.042906585 | S22: =G22-AVERAGE(G$21:G$97)+Forecast!$G$10 -> -0.21354621 | T22: =H22-AVERAGE(H$21:H$97)+Forecast!$G$11 -> 0.10881842 | U22: =I22-AVERAGE(I$21:I$97)+Forecast!$G$12 -> 0.076935709 | V22: =J22-AVERAGE(J$21:J$97)+Forecast!$G$13 -> 0.20913572 | W22: =K22-AVERAGE(K$21:K$97)+Forecast!$G$14 -> 0.045459784 | X22: =L22-AVERAGE(L$21:L$97)+Forecast!$G$15 -> 0.05984665 | Y22: =M22-AVERAGE(M$21:M$97)+Forecast!$G$16 -> 0.077603264 | Z22: =SUMPRODUCT($O22:$Y22,Risk!$B$56:$L$56) -> 0.15172678 | AA22: =SUMPRODUCT($O22:$Y22,Risk!$B$57:$L$57) -> 0.12117737 | AB22: =SUMPRODUCT($O22:$Y22,Risk!$B$58:$L$58) -> 0.12626441
A23: 3 | B23: ='Quarterly returns'!A11 -> 39353 | C23: =(1+'Quarterly returns'!N8)*(1+'Quarterly returns'!N9)*(1+'Quarterly returns'!N10)*(1+'Quarterly returns'!N11)-1 -> 0.33576768 | D23: =(1+'Quarterly returns'!O8)*(1+'Quarterly returns'!O9)*(1+'Quarterly returns'!O10)*(1+'Quarterly returns'!O11)-1 -> -0.021076003 | E23: =(1+'Quarterly returns'!P8)*(1+'Quarterly returns'!P9)*(1+'Quarterly returns'!P10)*(1+'Quarterly returns'!P11)-1 -> 0.25529845 | F23: =(1+'Quarterly returns'!Q8)*(1+'Quarterly returns'!Q9)*(1+'Quarterly returns'!Q10)*(1+'Quarterly returns'!Q11)-1 -> -0.087905931 | G23: =(1+'Quarterly returns'!R8)*(1+'Quarterly returns'!R9)*(1+'Quarterly returns'!R10)*(1+'Quarterly returns'!R11)-1 -> -0.04297006 | H23: =(1+'Quarterly returns'!S8)*(1+'Quarterly returns'!S9)*(1+'Quarterly returns'!S10)*(1+'Quarterly returns'!S11)-1 -> 0.15643506 | I23: =(1+'Quarterly returns'!T8)*(1+'Quarterly returns'!T9)*(1+'Quarterly returns'!T10)*(1+'Quarterly returns'!T11)-1 -> 0.13724465 | J23: =(1+'Quarterly returns'!U8)*(1+'Quarterly returns'!U9)*(1+'Quarterly returns'!U10)*(1+'Quarterly returns'!U11)-1 -> 0.16476239 | ... M23: =(1+'Quarterly returns'!X8)*(1+'Quarterly returns'!X9)*(1+'Quarterly returns'!X10)*(1+'Quarterly returns'!X11)-1 -> 0.065426174 | O23: =C23-AVERAGE(C$21:C$97)+Forecast!$G$6 -> 0.33583324 | P23: =D23-AVERAGE(D$21:D$97)+Forecast!$G$7 -> -0.044338535 | Q23: =E23-AVERAGE(E$21:E$97)+Forecast!$G$8 -> 0.24497587 | R23: =F23-AVERAGE(F$21:F$97)+Forecast!$G$9 -> -0.087160493 | S23: =G23-AVERAGE(G$21:G$97)+Forecast!$G$10 -> -0.0096812471 | T23: =H23-AVERAGE(H$21:H$97)+Forecast!$G$11 -> 0.14787149 | U23: =I23-AVERAGE(I$21:I$97)+Forecast!$G$12 -> 0.090890001 | V23: =J23-AVERAGE(J$21:J$97)+Forecast!$G$13 -> 0.10009366 | W23: =K23-AVERAGE(K$21:K$97)+Forecast!$G$14 -> 0.040313083 | X23: =L23-AVERAGE(L$21:L$97)+Forecast!$G$15 -> 0.053215619 | Y23: =M23-AVERAGE(M$21:M$97)+Forecast!$G$16 -> 0.078795677 | Z23: =SUMPRODUCT($O23:$Y23,Risk!$B$56:$L$56) -> 0.13256945 | AA23: =SUMPRODUCT($O23:$Y23,Risk!$B$57:$L$57) -> 0.10135598 | AB23: =SUMPRODUCT($O23:$Y23,Risk!$B$58:$L$58) -> 0.10912348
A24: 4 | B24: ='Quarterly returns'!A12 -> 39447 | C24: =(1+'Quarterly returns'!N9)*(1+'Quarterly returns'!N10)*(1+'Quarterly returns'!N11)*(1+'Quarterly returns'!N12)-1 -> 0.17953359 | D24: =(1+'Quarterly returns'!O9)*(1+'Quarterly returns'!O10)*(1+'Quarterly returns'!O11)*(1+'Quarterly returns'!O12)-1 -> -0.055648782 | E24: =(1+'Quarterly returns'!P9)*(1+'Quarterly returns'!P10)*(1+'Quarterly returns'!P11)*(1+'Quarterly returns'!P12)-1 -> 0.19921791 | F24: =(1+'Quarterly returns'!Q9)*(1+'Quarterly returns'!Q10)*(1+'Quarterly returns'!Q11)*(1+'Quarterly returns'!Q12)-1 -> -0.23045326 | G24: =(1+'Quarterly returns'!R9)*(1+'Quarterly returns'!R10)*(1+'Quarterly returns'!R11)*(1+'Quarterly returns'!R12)-1 -> 0.19095744 | H24: =(1+'Quarterly returns'!S9)*(1+'Quarterly returns'!S10)*(1+'Quarterly returns'!S11)*(1+'Quarterly returns'!S12)-1 -> 0.18456716 | I24: =(1+'Quarterly returns'!T9)*(1+'Quarterly returns'!T10)*(1+'Quarterly returns'!T11)*(1+'Quarterly returns'!T12)-1 -> 0.15020038 | J24: =(1+'Quarterly returns'!U9)*(1+'Quarterly returns'!U10)*(1+'Quarterly returns'!U11)*(1+'Quarterly returns'!U12)-1 -> 0.12160223 | ... M24: =(1+'Quarterly returns'!X9)*(1+'Quarterly returns'!X10)*(1+'Quarterly returns'!X11)*(1+'Quarterly returns'!X12)-1 -> 0.067307017 | O24: =C24-AVERAGE(C$21:C$97)+Forecast!$G$6 -> 0.17959915 | P24: =D24-AVERAGE(D$21:D$97)+Forecast!$G$7 -> -0.078911314 | Q24: =E24-AVERAGE(E$21:E$97)+Forecast!$G$8 -> 0.18889534 | R24: =F24-AVERAGE(F$21:F$97)+Forecast!$G$9 -> -0.22970782 | S24: =G24-AVERAGE(G$21:G$97)+Forecast!$G$10 -> 0.22424625 | T24: =H24-AVERAGE(H$21:H$97)+Forecast!$G$11 -> 0.17600359 | U24: =I24-AVERAGE(I$21:I$97)+Forecast!$G$12 -> 0.10384573 | V24: =J24-AVERAGE(J$21:J$97)+Forecast!$G$13 -> 0.056933499 | W24: =K24-AVERAGE(K$21:K$97)+Forecast!$G$14 -> 0.040208948 | X24: =L24-AVERAGE(L$21:L$97)+Forecast!$G$15 -> 0.068941698 | Y24: =M24-AVERAGE(M$21:M$97)+Forecast!$G$16 -> 0.08067652 | Z24: =SUMPRODUCT($O24:$Y24,Risk!$B$56:$L$56) -> 0.050280648 | AA24: =SUMPRODUCT($O24:$Y24,Risk!$B$57:$L$57) -> 0.04929 | AB24: =SUMPRODUCT($O24:$Y24,Risk!$B$58:$L$58) -> 0.051488549
A25: 5 | B25: ='Quarterly returns'!A13 -> 39538 | C25: =(1+'Quarterly returns'!N10)*(1+'Quarterly returns'!N11)*(1+'Quarterly returns'!N12)*(1+'Quarterly returns'!N13)-1 -> -0.060177176 | D25: =(1+'Quarterly returns'!O10)*(1+'Quarterly returns'!O11)*(1+'Quarterly returns'!O12)*(1+'Quarterly returns'!O13)-1 -> -0.19656652 | E25: =(1+'Quarterly returns'!P10)*(1+'Quarterly returns'!P11)*(1+'Quarterly returns'!P12)*(1+'Quarterly returns'!P13)-1 -> 0.028820031 | F25: =(1+'Quarterly returns'!Q10)*(1+'Quarterly returns'!Q11)*(1+'Quarterly returns'!Q12)*(1+'Quarterly returns'!Q13)-1 -> -0.30881072 | G25: =(1+'Quarterly returns'!R10)*(1+'Quarterly returns'!R11)*(1+'Quarterly returns'!R12)*(1+'Quarterly returns'!R13)-1 -> 0.2267831 | H25: =(1+'Quarterly returns'!S10)*(1+'Quarterly returns'!S11)*(1+'Quarterly returns'!S12)*(1+'Quarterly returns'!S13)-1 -> 0.12530999 | I25: =(1+'Quarterly returns'!T10)*(1+'Quarterly returns'!T11)*(1+'Quarterly returns'!T12)*(1+'Quarterly returns'!T13)-1 -> 0.11395006 | J25: =(1+'Quarterly returns'!U10)*(1+'Quarterly returns'!U11)*(1+'Quarterly returns'!U12)*(1+'Quarterly returns'!U13)-1 -> 0.088001893 | ... M25: =(1+'Quarterly returns'!X10)*(1+'Quarterly returns'!X11)*(1+'Quarterly returns'!X12)*(1+'Quarterly returns'!X13)-1 -> 0.069862055 | O25: =C25-AVERAGE(C$21:C$97)+Forecast!$G$6 -> -0.060111625 | P25: =D25-AVERAGE(D$21:D$97)+Forecast!$G$7 -> -0.21982905 | Q25: =E25-AVERAGE(E$21:E$97)+Forecast!$G$8 -> 0.018497455 | R25: =F25-AVERAGE(F$21:F$97)+Forecast!$G$9 -> -0.30806528 | S25: =G25-AVERAGE(G$21:G$97)+Forecast!$G$10 -> 0.26007191 | T25: =H25-AVERAGE(H$21:H$97)+Forecast!$G$11 -> 0.11674642 | U25: =I25-AVERAGE(I$21:I$97)+Forecast!$G$12 -> 0.067595414 | V25: =J25-AVERAGE(J$21:J$97)+Forecast!$G$13 -> 0.023333163 | W25: =K25-AVERAGE(K$21:K$97)+Forecast!$G$14 -> 0.048484651 | X25: =L25-AVERAGE(L$21:L$97)+Forecast!$G$15 -> 0.082768889 | Y25: =M25-AVERAGE(M$21:M$97)+Forecast!$G$16 -> 0.083231558 | Z25: =SUMPRODUCT($O25:$Y25,Risk!$B$56:$L$56) -> -0.079096571 | AA25: =SUMPRODUCT($O25:$Y25,Risk!$B$57:$L$57) -> -0.056640533 | AB25: =SUMPRODUCT($O25:$Y25,Risk!$B$58:$L$58) -> -0.070914911
A26: 6 | B26: ='Quarterly returns'!A14 -> 39629 | C26: =(1+'Quarterly returns'!N11)*(1+'Quarterly returns'!N12)*(1+'Quarterly returns'!N13)*(1+'Quarterly returns'!N14)-1 -> -0.12115374 | D26: =(1+'Quarterly returns'!O11)*(1+'Quarterly returns'!O12)*(1+'Quarterly returns'!O13)*(1+'Quarterly returns'!O14)-1 -> -0.24991221 | E26: =(1+'Quarterly returns'!P11)*(1+'Quarterly returns'!P12)*(1+'Quarterly returns'!P13)*(1+'Quarterly returns'!P14)-1 -> -0.10137998 | F26: =(1+'Quarterly returns'!Q11)*(1+'Quarterly returns'!Q12)*(1+'Quarterly returns'!Q13)*(1+'Quarterly returns'!Q14)-1 -> -0.32105485 | G26: =(1+'Quarterly returns'!R11)*(1+'Quarterly returns'!R12)*(1+'Quarterly returns'!R13)*(1+'Quarterly returns'!R14)-1 -> 0.55582438 | H26: =(1+'Quarterly returns'!S11)*(1+'Quarterly returns'!S12)*(1+'Quarterly returns'!S13)*(1+'Quarterly returns'!S14)-1 -> -0.021364262 | I26: =(1+'Quarterly returns'!T11)*(1+'Quarterly returns'!T12)*(1+'Quarterly returns'!T13)*(1+'Quarterly returns'!T14)-1 -> 0.13594368 | J26: =(1+'Quarterly returns'!U11)*(1+'Quarterly returns'!U12)*(1+'Quarterly returns'!U13)*(1+'Quarterly returns'!U14)-1 -> -0.045085385 | ... M26: =(1+'Quarterly returns'!X11)*(1+'Quarterly returns'!X12)*(1+'Quarterly returns'!X13)*(1+'Quarterly returns'!X14)-1 -> 0.073398254 | O26: =C26-AVERAGE(C$21:C$97)+Forecast!$G$6 -> -0.12108819 | P26: =D26-AVERAGE(D$21:D$97)+Forecast!$G$7 -> -0.27317474 | Q26: =E26-AVERAGE(E$21:E$97)+Forecast!$G$8 -> -0.11170255 | R26: =F26-AVERAGE(F$21:F$97)+Forecast!$G$9 -> -0.32030941 | S26: =G26-AVERAGE(G$21:G$97)+Forecast!$G$10 -> 0.5891132 | T26: =H26-AVERAGE(H$21:H$97)+Forecast!$G$11 -> -0.029927832 | U26: =I26-AVERAGE(I$21:I$97)+Forecast!$G$12 -> 0.089589033 | V26: =J26-AVERAGE(J$21:J$97)+Forecast!$G$13 -> -0.10975412 | W26: =K26-AVERAGE(K$21:K$97)+Forecast!$G$14 -> 0.049787576 | X26: =L26-AVERAGE(L$21:L$97)+Forecast!$G$15 -> 0.081718853 | Y26: =M26-AVERAGE(M$21:M$97)+Forecast!$G$16 -> 0.086767757 | Z26: =SUMPRODUCT($O26:$Y26,Risk!$B$56:$L$56) -> -0.11502178 | AA26: =SUMPRODUCT($O26:$Y26,Risk!$B$57:$L$57) -> -0.093363432 | AB26: =SUMPRODUCT($O26:$Y26,Risk!$B$58:$L$58) -> -0.11151492
A27: 7 | B27: ='Quarterly returns'!A15 -> 39721 | C27: =(1+'Quarterly returns'!N12)*(1+'Quarterly returns'!N13)*(1+'Quarterly returns'!N14)*(1+'Quarterly returns'!N15)-1 -> -0.2658937 | D27: =(1+'Quarterly returns'!O12)*(1+'Quarterly returns'!O13)*(1+'Quarterly returns'!O14)*(1+'Quarterly returns'!O15)-1 -> -0.15467771 | E27: =(1+'Quarterly returns'!P12)*(1+'Quarterly returns'!P13)*(1+'Quarterly returns'!P14)*(1+'Quarterly returns'!P15)-1 -> -0.19764563 | F27: =(1+'Quarterly returns'!Q12)*(1+'Quarterly returns'!Q13)*(1+'Quarterly returns'!Q14)*(1+'Quarterly returns'!Q15)-1 -> -0.13453207 | G27: =(1+'Quarterly returns'!R12)*(1+'Quarterly returns'!R13)*(1+'Quarterly returns'!R14)*(1+'Quarterly returns'!R15)-1 -> 0.2645613 | H27: =(1+'Quarterly returns'!S12)*(1+'Quarterly returns'!S13)*(1+'Quarterly returns'!S14)*(1+'Quarterly returns'!S15)-1 -> -0.08475359 | I27: =(1+'Quarterly returns'!T12)*(1+'Quarterly returns'!T13)*(1+'Quarterly returns'!T14)*(1+'Quarterly returns'!T15)-1 -> 0.10913578 | J27: =(1+'Quarterly returns'!U12)*(1+'Quarterly returns'!U13)*(1+'Quarterly returns'!U14)*(1+'Quarterly returns'!U15)-1 -> -0.0086868498 | ... M27: =(1+'Quarterly returns'!X12)*(1+'Quarterly returns'!X13)*(1+'Quarterly returns'!X14)*(1+'Quarterly returns'!X15)-1 -> 0.076533079 | O27: =C27-AVERAGE(C$21:C$97)+Forecast!$G$6 -> -0.26582815 | P27: =D27-AVERAGE(D$21:D$97)+Forecast!$G$7 -> -0.17794024 | Q27: =E27-AVERAGE(E$21:E$97)+Forecast!$G$8 -> -0.2079682 | R27: =F27-AVERAGE(F$21:F$97)+Forecast!$G$9 -> -0.13378664 | S27: =G27-AVERAGE(G$21:G$97)+Forecast!$G$10 -> 0.29785011 | T27: =H27-AVERAGE(H$21:H$97)+Forecast!$G$11 -> -0.09331716 | U27: =I27-AVERAGE(I$21:I$97)+Forecast!$G$12 -> 0.062781125 | V27: =J27-AVERAGE(J$21:J$97)+Forecast!$G$13 -> -0.07335558 | W27: =K27-AVERAGE(K$21:K$97)+Forecast!$G$14 -> 0.089311746 | X27: =L27-AVERAGE(L$21:L$97)+Forecast!$G$15 -> 0.072306916 | Y27: =M27-AVERAGE(M$21:M$97)+Forecast!$G$16 -> 0.089902581 | Z27: =SUMPRODUCT($O27:$Y27,Risk!$B$56:$L$56) -> -0.12982348 | AA27: =SUMPRODUCT($O27:$Y27,Risk!$B$57:$L$57) -> -0.10063841 | AB27: =SUMPRODUCT($O27:$Y27,Risk!$B$58:$L$58) -> -0.12479799
A28: 8 | B28: ='Quarterly returns'!A16 -> 39813 | C28: =(1+'Quarterly returns'!N13)*(1+'Quarterly returns'!N14)*(1+'Quarterly returns'!N15)*(1+'Quarterly returns'!N16)-1 -> -0.4038479 | D28: =(1+'Quarterly returns'!O13)*(1+'Quarterly returns'!O14)*(1+'Quarterly returns'!O15)*(1+'Quarterly returns'!O16)-1 -> -0.22299166 | E28: =(1+'Quarterly returns'!P13)*(1+'Quarterly returns'!P14)*(1+'Quarterly returns'!P15)*(1+'Quarterly returns'!P16)-1 -> -0.31677088 | F28: =(1+'Quarterly returns'!Q13)*(1+'Quarterly returns'!Q14)*(1+'Quarterly returns'!Q15)*(1+'Quarterly returns'!Q16)-1 -> -0.26961283 | G28: =(1+'Quarterly returns'!R13)*(1+'Quarterly returns'!R14)*(1+'Quarterly returns'!R15)*(1+'Quarterly returns'!R16)-1 -> -0.32606841 | H28: =(1+'Quarterly returns'!S13)*(1+'Quarterly returns'!S14)*(1+'Quarterly returns'!S15)*(1+'Quarterly returns'!S16)-1 -> -0.11962049 | I28: =(1+'Quarterly returns'!T13)*(1+'Quarterly returns'!T14)*(1+'Quarterly returns'!T15)*(1+'Quarterly returns'!T16)-1 -> 0.14524141 | J28: =(1+'Quarterly returns'!U13)*(1+'Quarterly returns'!U14)*(1+'Quarterly returns'!U15)*(1+'Quarterly returns'!U16)-1 -> -0.17635652 | ... M28: =(1+'Quarterly returns'!X13)*(1+'Quarterly returns'!X14)*(1+'Quarterly returns'!X15)*(1+'Quarterly returns'!X16)-1 -> 0.076012653 | O28: =C28-AVERAGE(C$21:C$97)+Forecast!$G$6 -> -0.40378235 | P28: =D28-AVERAGE(D$21:D$97)+Forecast!$G$7 -> -0.2462542 | Q28: =E28-AVERAGE(E$21:E$97)+Forecast!$G$8 -> -0.32709346 | R28: =F28-AVERAGE(F$21:F$97)+Forecast!$G$9 -> -0.26886739 | S28: =G28-AVERAGE(G$21:G$97)+Forecast!$G$10 -> -0.2927796 | T28: =H28-AVERAGE(H$21:H$97)+Forecast!$G$11 -> -0.12818406 | U28: =I28-AVERAGE(I$21:I$97)+Forecast!$G$12 -> 0.098886759 | V28: =J28-AVERAGE(J$21:J$97)+Forecast!$G$13 -> -0.24102525 | W28: =K28-AVERAGE(K$21:K$97)+Forecast!$G$14 -> 0.15507512 | X28: =L28-AVERAGE(L$21:L$97)+Forecast!$G$15 -> 0.094966574 | Y28: =M28-AVERAGE(M$21:M$97)+Forecast!$G$16 -> 0.089382155 | Z28: =SUMPRODUCT($O28:$Y28,Risk!$B$56:$L$56) -> -0.20053517 | AA28: =SUMPRODUCT($O28:$Y28,Risk!$B$57:$L$57) -> -0.17037076 | AB28: =SUMPRODUCT($O28:$Y28,Risk!$B$58:$L$58) -> -0.21113475
A29: 9 | B29: ='Quarterly returns'!A17 -> 39903 | C29: =(1+'Quarterly returns'!N14)*(1+'Quarterly returns'!N15)*(1+'Quarterly returns'!N16)*(1+'Quarterly returns'!N17)-1 -> -0.31297256 | D29: =(1+'Quarterly returns'!O14)*(1+'Quarterly returns'!O15)*(1+'Quarterly returns'!O16)*(1+'Quarterly returns'!O17)-1 -> -0.17192276 | E29: =(1+'Quarterly returns'!P14)*(1+'Quarterly returns'!P15)*(1+'Quarterly returns'!P16)*(1+'Quarterly returns'!P17)-1 -> -0.16596511 | F29: =(1+'Quarterly returns'!Q14)*(1+'Quarterly returns'!Q15)*(1+'Quarterly returns'!Q16)*(1+'Quarterly returns'!Q17)-1 -> -0.39576538 | G29: =(1+'Quarterly returns'!R14)*(1+'Quarterly returns'!R15)*(1+'Quarterly returns'!R16)*(1+'Quarterly returns'!R17)-1 -> -0.42847359 | H29: =(1+'Quarterly returns'!S14)*(1+'Quarterly returns'!S15)*(1+'Quarterly returns'!S16)*(1+'Quarterly returns'!S17)-1 -> -0.048181229 | I29: =(1+'Quarterly returns'!T14)*(1+'Quarterly returns'!T15)*(1+'Quarterly returns'!T16)*(1+'Quarterly returns'!T17)-1 -> 0.18365663 | J29: =(1+'Quarterly returns'!U14)*(1+'Quarterly returns'!U15)*(1+'Quarterly returns'!U16)*(1+'Quarterly returns'!U17)-1 -> -0.19263941 | ... M29: =(1+'Quarterly returns'!X14)*(1+'Quarterly returns'!X15)*(1+'Quarterly returns'!X16)*(1+'Quarterly returns'!X17)-1 -> 0.066948708 | O29: =C29-AVERAGE(C$21:C$97)+Forecast!$G$6 -> -0.31290701 | P29: =D29-AVERAGE(D$21:D$97)+Forecast!$G$7 -> -0.19518529 | Q29: =E29-AVERAGE(E$21:E$97)+Forecast!$G$8 -> -0.17628768 | R29: =F29-AVERAGE(F$21:F$97)+Forecast!$G$9 -> -0.39501995 | S29: =G29-AVERAGE(G$21:G$97)+Forecast!$G$10 -> -0.39518478 | T29: =H29-AVERAGE(H$21:H$97)+Forecast!$G$11 -> -0.056744799 | U29: =I29-AVERAGE(I$21:I$97)+Forecast!$G$12 -> 0.13730198 | V29: =J29-AVERAGE(J$21:J$97)+Forecast!$G$13 -> -0.25730814 | W29: =K29-AVERAGE(K$21:K$97)+Forecast!$G$14 -> 0.13331911 | X29: =L29-AVERAGE(L$21:L$97)+Forecast!$G$15 -> 0.072782468 | Y29: =M29-AVERAGE(M$21:M$97)+Forecast!$G$16 -> 0.080318211 | Z29: =SUMPRODUCT($O29:$Y29,Risk!$B$56:$L$56) -> -0.17225912 | AA29: =SUMPRODUCT($O29:$Y29,Risk!$B$57:$L$57) -> -0.14327208 | AB29: =SUMPRODUCT($O29:$Y29,Risk!$B$58:$L$58) -> -0.17466371
A30: 10 | B30: ='Quarterly returns'!A18 -> 39994 | C30: =(1+'Quarterly returns'!N15)*(1+'Quarterly returns'!N16)*(1+'Quarterly returns'!N17)*(1+'Quarterly returns'!N18)-1 -> -0.22145824 | D30: =(1+'Quarterly returns'!O15)*(1+'Quarterly returns'!O16)*(1+'Quarterly returns'!O17)*(1+'Quarterly returns'!O18)-1 -> -0.11950003 | E30: =(1+'Quarterly returns'!P15)*(1+'Quarterly returns'!P16)*(1+'Quarterly returns'!P17)*(1+'Quarterly returns'!P18)-1 -> -0.046944878 | F30: =(1+'Quarterly returns'!Q15)*(1+'Quarterly returns'!Q16)*(1+'Quarterly returns'!Q17)*(1+'Quarterly returns'!Q18)-1 -> -0.26060245 | G30: =(1+'Quarterly returns'!R15)*(1+'Quarterly returns'!R16)*(1+'Quarterly returns'!R17)*(1+'Quarterly returns'!R18)-1 -> -0.52139285 | H30: =(1+'Quarterly returns'!S15)*(1+'Quarterly returns'!S16)*(1+'Quarterly returns'!S17)*(1+'Quarterly returns'!S18)-1 -> 0.10586663 | I30: =(1+'Quarterly returns'!T15)*(1+'Quarterly returns'!T16)*(1+'Quarterly returns'!T17)*(1+'Quarterly returns'!T18)-1 -> 0.11366254 | J30: =(1+'Quarterly returns'!U15)*(1+'Quarterly returns'!U16)*(1+'Quarterly returns'!U17)*(1+'Quarterly returns'!U18)-1 -> -0.15706374 | ... M30: =(1+'Quarterly returns'!X15)*(1+'Quarterly returns'!X16)*(1+'Quarterly returns'!X17)*(1+'Quarterly returns'!X18)-1 -> 0.054753514 | O30: =C30-AVERAGE(C$21:C$97)+Forecast!$G$6 -> -0.22139269 | P30: =D30-AVERAGE(D$21:D$97)+Forecast!$G$7 -> -0.14276256 | Q30: =E30-AVERAGE(E$21:E$97)+Forecast!$G$8 -> -0.057267454 | R30: =F30-AVERAGE(F$21:F$97)+Forecast!$G$9 -> -0.25985701 | S30: =G30-AVERAGE(G$21:G$97)+Forecast!$G$10 -> -0.48810404 | T30: =H30-AVERAGE(H$21:H$97)+Forecast!$G$11 -> 0.097303065 | U30: =I30-AVERAGE(I$21:I$97)+Forecast!$G$12 -> 0.067307886 | V30: =J30-AVERAGE(J$21:J$97)+Forecast!$G$13 -> -0.22173247 | W30: =K30-AVERAGE(K$21:K$97)+Forecast!$G$14 -> 0.11379855 | X30: =L30-AVERAGE(L$21:L$97)+Forecast!$G$15 -> 0.10221132 | Y30: =M30-AVERAGE(M$21:M$97)+Forecast!$G$16 -> 0.068123017 | Z30: =SUMPRODUCT($O30:$Y30,Risk!$B$56:$L$56) -> -0.11307999 | AA30: =SUMPRODUCT($O30:$Y30,Risk!$B$57:$L$57) -> -0.089830134 | AB30: =SUMPRODUCT($O30:$Y30,Risk!$B$58:$L$58) -> -0.11194662
A31: 11 | B31: ='Quarterly returns'!A19 -> 40086 | C31: =(1+'Quarterly returns'!N16)*(1+'Quarterly returns'!N17)*(1+'Quarterly returns'!N18)*(1+'Quarterly returns'!N19)-1 -> 0.074009587 | D31: =(1+'Quarterly returns'!O16)*(1+'Quarterly returns'!O17)*(1+'Quarterly returns'!O18)*(1+'Quarterly returns'!O19)-1 -> -0.14088503 | E31: =(1+'Quarterly returns'!P16)*(1+'Quarterly returns'!P17)*(1+'Quarterly returns'!P18)*(1+'Quarterly returns'!P19)-1 -> 0.05914805 | F31: =(1+'Quarterly returns'!Q16)*(1+'Quarterly returns'!Q17)*(1+'Quarterly returns'!Q18)*(1+'Quarterly returns'!Q19)-1 -> -0.2818556 | G31: =(1+'Quarterly returns'!R16)*(1+'Quarterly returns'!R17)*(1+'Quarterly returns'!R18)*(1+'Quarterly returns'!R19)-1 -> -0.50413963 | H31: =(1+'Quarterly returns'!S16)*(1+'Quarterly returns'!S17)*(1+'Quarterly returns'!S18)*(1+'Quarterly returns'!S19)-1 -> 0.21066024 | I31: =(1+'Quarterly returns'!T16)*(1+'Quarterly returns'!T17)*(1+'Quarterly returns'!T18)*(1+'Quarterly returns'!T19)-1 -> 0.09272698 | J31: =(1+'Quarterly returns'!U16)*(1+'Quarterly returns'!U17)*(1+'Quarterly returns'!U18)*(1+'Quarterly returns'!U19)-1 -> -0.047673541 | ... M31: =(1+'Quarterly returns'!X16)*(1+'Quarterly returns'!X17)*(1+'Quarterly returns'!X18)*(1+'Quarterly returns'!X19)-1 -> 0.043050901 | O31: =C31-AVERAGE(C$21:C$97)+Forecast!$G$6 -> 0.074075138 | P31: =D31-AVERAGE(D$21:D$97)+Forecast!$G$7 -> -0.16414756 | Q31: =E31-AVERAGE(E$21:E$97)+Forecast!$G$8 -> 0.048825474 | R31: =F31-AVERAGE(F$21:F$97)+Forecast!$G$9 -> -0.28111017 | S31: =G31-AVERAGE(G$21:G$97)+Forecast!$G$10 -> -0.47085082 | T31: =H31-AVERAGE(H$21:H$97)+Forecast!$G$11 -> 0.20209667 | U31: =I31-AVERAGE(I$21:I$97)+Forecast!$G$12 -> 0.04637233 | V31: =J31-AVERAGE(J$21:J$97)+Forecast!$G$13 -> -0.11234227 | W31: =K31-AVERAGE(K$21:K$97)+Forecast!$G$14 -> 0.076325904 | X31: =L31-AVERAGE(L$21:L$97)+Forecast!$G$15 -> 0.12253881 | Y31: =M31-AVERAGE(M$21:M$97)+Forecast!$G$16 -> 0.056420403 | Z31: =SUMPRODUCT($O31:$Y31,Risk!$B$56:$L$56) -> -0.0061090559 | AA31: =SUMPRODUCT($O31:$Y31,Risk!$B$57:$L$57) -> -0.014523352 | AB31: =SUMPRODUCT($O31:$Y31,Risk!$B$58:$L$58) -> -0.028517235
A32: 12 | B32: ='Quarterly returns'!A20 -> 40178 | C32: =(1+'Quarterly returns'!N17)*(1+'Quarterly returns'!N18)*(1+'Quarterly returns'!N19)*(1+'Quarterly returns'!N20)-1 -> 0.39578084 | D32: =(1+'Quarterly returns'!O17)*(1+'Quarterly returns'!O18)*(1+'Quarterly returns'!O19)*(1+'Quarterly returns'!O20)-1 -> -0.019242585 | E32: =(1+'Quarterly returns'!P17)*(1+'Quarterly returns'!P18)*(1+'Quarterly returns'!P19)*(1+'Quarterly returns'!P20)-1 -> 0.26176449 | F32: =(1+'Quarterly returns'!Q17)*(1+'Quarterly returns'!Q18)*(1+'Quarterly returns'!Q19)*(1+'Quarterly returns'!Q20)-1 -> -0.013953674 | G32: =(1+'Quarterly returns'!R17)*(1+'Quarterly returns'!R18)*(1+'Quarterly returns'!R19)*(1+'Quarterly returns'!R20)-1 -> -0.12023439 | H32: =(1+'Quarterly returns'!S17)*(1+'Quarterly returns'!S18)*(1+'Quarterly returns'!S19)*(1+'Quarterly returns'!S20)-1 -> 0.30427874 | I32: =(1+'Quarterly returns'!T17)*(1+'Quarterly returns'!T18)*(1+'Quarterly returns'!T19)*(1+'Quarterly returns'!T20)-1 -> 0.019979247 | J32: =(1+'Quarterly returns'!U17)*(1+'Quarterly returns'!U18)*(1+'Quarterly returns'!U19)*(1+'Quarterly returns'!U20)-1 -> 0.12440691 | ... M32: =(1+'Quarterly returns'!X17)*(1+'Quarterly returns'!X18)*(1+'Quarterly returns'!X19)*(1+'Quarterly returns'!X20)-1 -> 0.034749247 | O32: =C32-AVERAGE(C$21:C$97)+Forecast!$G$6 -> 0.39584639 | P32: =D32-AVERAGE(D$21:D$97)+Forecast!$G$7 -> -0.042505117 | Q32: =E32-AVERAGE(E$21:E$97)+Forecast!$G$8 -> 0.25144192 | R32: =F32-AVERAGE(F$21:F$97)+Forecast!$G$9 -> -0.013208236 | S32: =G32-AVERAGE(G$21:G$97)+Forecast!$G$10 -> -0.086945576 | T32: =H32-AVERAGE(H$21:H$97)+Forecast!$G$11 -> 0.29571517 | U32: =I32-AVERAGE(I$21:I$97)+Forecast!$G$12 -> -0.026375404 | V32: =J32-AVERAGE(J$21:J$97)+Forecast!$G$13 -> 0.059738181 | W32: =K32-AVERAGE(K$21:K$97)+Forecast!$G$14 -> 0.022923565 | X32: =L32-AVERAGE(L$21:L$97)+Forecast!$G$15 -> 0.082987389 | Y32: =M32-AVERAGE(M$21:M$97)+Forecast!$G$16 -> 0.04811875 | Z32: =SUMPRODUCT($O32:$Y32,Risk!$B$56:$L$56) -> 0.16196255 | AA32: =SUMPRODUCT($O32:$Y32,Risk!$B$57:$L$57) -> 0.12320826 | AB32: =SUMPRODUCT($O32:$Y32,Risk!$B$58:$L$58) -> 0.13556178
... A97: 77 | B97: ='Quarterly returns'!A85 -> 46112 | C97: =(1+'Quarterly returns'!N82)*(1+'Quarterly returns'!N83)*(1+'Quarterly returns'!N84)*(1+'Quarterly returns'!N85)-1 -> 0.11289283 | D97: =(1+'Quarterly returns'!O82)*(1+'Quarterly returns'!O83)*(1+'Quarterly returns'!O84)*(1+'Quarterly returns'!O85)-1 -> 0.076715847 | E97: =(1+'Quarterly returns'!P82)*(1+'Quarterly returns'!P83)*(1+'Quarterly returns'!P84)*(1+'Quarterly returns'!P85)-1 -> 0.19514665 | F97: =(1+'Quarterly returns'!Q82)*(1+'Quarterly returns'!Q83)*(1+'Quarterly returns'!Q84)*(1+'Quarterly returns'!Q85)-1 -> -0.023292145 | G97: =(1+'Quarterly returns'!R82)*(1+'Quarterly returns'!R83)*(1+'Quarterly returns'!R84)*(1+'Quarterly returns'!R85)-1 -> 0.30103221 | H97: =(1+'Quarterly returns'!S82)*(1+'Quarterly returns'!S83)*(1+'Quarterly returns'!S84)*(1+'Quarterly returns'!S85)-1 -> 0.1099981 | I97: =(1+'Quarterly returns'!T82)*(1+'Quarterly returns'!T83)*(1+'Quarterly returns'!T84)*(1+'Quarterly returns'!T85)-1 -> 0.077523115 | J97: =(1+'Quarterly returns'!U82)*(1+'Quarterly returns'!U83)*(1+'Quarterly returns'!U84)*(1+'Quarterly returns'!U85)-1 -> -0.14855998 | ... M97: =(1+'Quarterly returns'!X82)*(1+'Quarterly returns'!X83)*(1+'Quarterly returns'!X84)*(1+'Quarterly returns'!X85)-1 -> 0.037995149 | O97: =C97-AVERAGE(C$21:C$97)+Forecast!$G$6 -> 0.11295838 | P97: =D97-AVERAGE(D$21:D$97)+Forecast!$G$7 -> 0.053453315 | Q97: =E97-AVERAGE(E$21:E$97)+Forecast!$G$8 -> 0.18482407 | R97: =F97-AVERAGE(F$21:F$97)+Forecast!$G$9 -> -0.022546707 | S97: =G97-AVERAGE(G$21:G$97)+Forecast!$G$10 -> 0.33432102 | T97: =H97-AVERAGE(H$21:H$97)+Forecast!$G$11 -> 0.10143453 | U97: =I97-AVERAGE(I$21:I$97)+Forecast!$G$12 -> 0.031168465 | V97: =J97-AVERAGE(J$21:J$97)+Forecast!$G$13 -> -0.21322871 | W97: =K97-AVERAGE(K$21:K$97)+Forecast!$G$14 -> 0.0191586 | X97: =L97-AVERAGE(L$21:L$97)+Forecast!$G$15 -> 0.015810539 | Y97: =M97-AVERAGE(M$21:M$97)+Forecast!$G$16 -> 0.051364652 | Z97: =SUMPRODUCT($O97:$Y97,Risk!$B$56:$L$56) -> 0.061353505 | AA97: =SUMPRODUCT($O97:$Y97,Risk!$B$57:$L$57) -> 0.057293487 | AB97: =SUMPRODUCT($O97:$Y97,Risk!$B$58:$L$58) -> 0.075129591
A99: 3. Simulated paths (draws pasted, seed in Inputs)
A101: Path | B101: Draw 1 | C101: Draw 2 | D101: Draw 3 | E101: Draw 4 | F101: Draw 5 | G101: Current | H101: Benchmark | I101: Recommended | J101: Relative: current (log) | K101: Relative: recommended (log)
A102: 1 | B102: 56 | C102: 27 | D102: 32 | E102: 43 | F102: 73 | G102: =(1+INDEX($Z$21:$Z$97,B102))*(1+INDEX($Z$21:$Z$97,C102))*(1+INDEX($Z$21:$Z$97,D102))*(1+INDEX($Z$21:$Z$97,E102))*(1+INDEX($Z$21:$Z$97,F102))-1 -> 0.52027455 | H102: =(1+INDEX($AA$21:$AA$97,B102))*(1+INDEX($AA$21:$AA$97,C102))*(1+INDEX($AA$21:$AA$97,D102))*(1+INDEX($AA$21:$AA$97,E102))*(1+INDEX($AA$21:$AA$97,F102))-1 -> 0.50374299 | I102: =(1+INDEX($AB$21:$AB$97,B102))*(1+INDEX($AB$21:$AB$97,C102))*(1+INDEX($AB$21:$AB$97,D102))*(1+INDEX($AB$21:$AB$97,E102))*(1+INDEX($AB$21:$AB$97,F102))-1 -> 0.56685675 | J102: =LN((1+G102)/(1+H102)) -> 0.010933622 | K102: =LN((1+I102)/(1+H102)) -> 0.041114218
A103: 2 | B103: 49 | C103: 59 | D103: 39 | E103: 14 | F103: 56 | G103: =(1+INDEX($Z$21:$Z$97,B103))*(1+INDEX($Z$21:$Z$97,C103))*(1+INDEX($Z$21:$Z$97,D103))*(1+INDEX($Z$21:$Z$97,E103))*(1+INDEX($Z$21:$Z$97,F103))-1 -> 0.65886905 | H103: =(1+INDEX($AA$21:$AA$97,B103))*(1+INDEX($AA$21:$AA$97,C103))*(1+INDEX($AA$21:$AA$97,D103))*(1+INDEX($AA$21:$AA$97,E103))*(1+INDEX($AA$21:$AA$97,F103))-1 -> 0.55712511 | I103: =(1+INDEX($AB$21:$AB$97,B103))*(1+INDEX($AB$21:$AB$97,C103))*(1+INDEX($AB$21:$AB$97,D103))*(1+INDEX($AB$21:$AB$97,E103))*(1+INDEX($AB$21:$AB$97,F103))-1 -> 0.60078157 | J103: =LN((1+G103)/(1+H103)) -> 0.063294833 | K103: =LN((1+I103)/(1+H103)) -> 0.027650745
A104: 3 | B104: 73 | C104: 20 | D104: 44 | E104: 16 | F104: 7 | G104: =(1+INDEX($Z$21:$Z$97,B104))*(1+INDEX($Z$21:$Z$97,C104))*(1+INDEX($Z$21:$Z$97,D104))*(1+INDEX($Z$21:$Z$97,E104))*(1+INDEX($Z$21:$Z$97,F104))-1 -> -0.012258844 | H104: =(1+INDEX($AA$21:$AA$97,B104))*(1+INDEX($AA$21:$AA$97,C104))*(1+INDEX($AA$21:$AA$97,D104))*(1+INDEX($AA$21:$AA$97,E104))*(1+INDEX($AA$21:$AA$97,F104))-1 -> 0.014382131 | I104: =(1+INDEX($AB$21:$AB$97,B104))*(1+INDEX($AB$21:$AB$97,C104))*(1+INDEX($AB$21:$AB$97,D104))*(1+INDEX($AB$21:$AB$97,E104))*(1+INDEX($AB$21:$AB$97,F104))-1 -> -0.020196404 | J104: =LN((1+G104)/(1+H104)) -> -0.026614293 | K104: =LN((1+I104)/(1+H104)) -> -0.034682829
A105: 4 | B105: 43 | C105: 8 | D105: 53 | E105: 26 | F105: 64 | G105: =(1+INDEX($Z$21:$Z$97,B105))*(1+INDEX($Z$21:$Z$97,C105))*(1+INDEX($Z$21:$Z$97,D105))*(1+INDEX($Z$21:$Z$97,E105))*(1+INDEX($Z$21:$Z$97,F105))-1 -> -0.10474659 | H105: =(1+INDEX($AA$21:$AA$97,B105))*(1+INDEX($AA$21:$AA$97,C105))*(1+INDEX($AA$21:$AA$97,D105))*(1+INDEX($AA$21:$AA$97,E105))*(1+INDEX($AA$21:$AA$97,F105))-1 -> -0.052091549 | I105: =(1+INDEX($AB$21:$AB$97,B105))*(1+INDEX($AB$21:$AB$97,C105))*(1+INDEX($AB$21:$AB$97,D105))*(1+INDEX($AB$21:$AB$97,E105))*(1+INDEX($AB$21:$AB$97,F105))-1 -> -0.079078009 | J105: =LN((1+G105)/(1+H105)) -> -0.057151104 | K105: =LN((1+I105)/(1+H105)) -> -0.028882595
A106: 5 | B106: 4 | C106: 9 | D106: 64 | E106: 58 | F106: 56 | G106: =(1+INDEX($Z$21:$Z$97,B106))*(1+INDEX($Z$21:$Z$97,C106))*(1+INDEX($Z$21:$Z$97,D106))*(1+INDEX($Z$21:$Z$97,E106))*(1+INDEX($Z$21:$Z$97,F106))-1 -> -0.030002301 | H106: =(1+INDEX($AA$21:$AA$97,B106))*(1+INDEX($AA$21:$AA$97,C106))*(1+INDEX($AA$21:$AA$97,D106))*(1+INDEX($AA$21:$AA$97,E106))*(1+INDEX($AA$21:$AA$97,F106))-1 -> -0.00023261616 | I106: =(1+INDEX($AB$21:$AB$97,B106))*(1+INDEX($AB$21:$AB$97,C106))*(1+INDEX($AB$21:$AB$97,D106))*(1+INDEX($AB$21:$AB$97,E106))*(1+INDEX($AB$21:$AB$97,F106))-1 -> -0.017592318 | J106: =LN((1+G106)/(1+H106)) -> -0.030228936 | K106: =LN((1+I106)/(1+H106)) -> -0.017516258
A107: 6 | B107: 2 | C107: 63 | D107: 12 | E107: 3 | F107: 39 | G107: =(1+INDEX($Z$21:$Z$97,B107))*(1+INDEX($Z$21:$Z$97,C107))*(1+INDEX($Z$21:$Z$97,D107))*(1+INDEX($Z$21:$Z$97,E107))*(1+INDEX($Z$21:$Z$97,F107))-1 -> 0.50704639 | H107: =(1+INDEX($AA$21:$AA$97,B107))*(1+INDEX($AA$21:$AA$97,C107))*(1+INDEX($AA$21:$AA$97,D107))*(1+INDEX($AA$21:$AA$97,E107))*(1+INDEX($AA$21:$AA$97,F107))-1 -> 0.35189401 | I107: =(1+INDEX($AB$21:$AB$97,B107))*(1+INDEX($AB$21:$AB$97,C107))*(1+INDEX($AB$21:$AB$97,D107))*(1+INDEX($AB$21:$AB$97,E107))*(1+INDEX($AB$21:$AB$97,F107))-1 -> 0.38818692 | J107: =LN((1+G107)/(1+H107)) -> 0.10864512 | K107: =LN((1+I107)/(1+H107)) -> 0.026491941
A108: 7 | B108: 21 | C108: 73 | D108: 41 | E108: 77 | F108: 30 | G108: =(1+INDEX($Z$21:$Z$97,B108))*(1+INDEX($Z$21:$Z$97,C108))*(1+INDEX($Z$21:$Z$97,D108))*(1+INDEX($Z$21:$Z$97,E108))*(1+INDEX($Z$21:$Z$97,F108))-1 -> 0.43880729 | H108: =(1+INDEX($AA$21:$AA$97,B108))*(1+INDEX($AA$21:$AA$97,C108))*(1+INDEX($AA$21:$AA$97,D108))*(1+INDEX($AA$21:$AA$97,E108))*(1+INDEX($AA$21:$AA$97,F108))-1 -> 0.42522915 | I108: =(1+INDEX($AB$21:$AB$97,B108))*(1+INDEX($AB$21:$AB$97,C108))*(1+INDEX($AB$21:$AB$97,D108))*(1+INDEX($AB$21:$AB$97,E108))*(1+INDEX($AB$21:$AB$97,F108))-1 -> 0.47500456 | J108: =LN((1+G108)/(1+H108)) -> 0.0094818908 | K108: =LN((1+I108)/(1+H108)) -> 0.034328474
A109: 8 | B109: 31 | C109: 25 | D109: 33 | E109: 11 | F109: 38 | G109: =(1+INDEX($Z$21:$Z$97,B109))*(1+INDEX($Z$21:$Z$97,C109))*(1+INDEX($Z$21:$Z$97,D109))*(1+INDEX($Z$21:$Z$97,E109))*(1+INDEX($Z$21:$Z$97,F109))-1 -> 0.58783219 | H109: =(1+INDEX($AA$21:$AA$97,B109))*(1+INDEX($AA$21:$AA$97,C109))*(1+INDEX($AA$21:$AA$97,D109))*(1+INDEX($AA$21:$AA$97,E109))*(1+INDEX($AA$21:$AA$97,F109))-1 -> 0.52286038 | I109: =(1+INDEX($AB$21:$AB$97,B109))*(1+INDEX($AB$21:$AB$97,C109))*(1+INDEX($AB$21:$AB$97,D109))*(1+INDEX($AB$21:$AB$97,E109))*(1+INDEX($AB$21:$AB$97,F109))-1 -> 0.52930378 | J109: =LN((1+G109)/(1+H109)) -> 0.041779287 | K109: =LN((1+I109)/(1+H109)) -> 0.0042221902
A110: 9 | B110: 48 | C110: 20 | D110: 12 | E110: 56 | F110: 31 | G110: =(1+INDEX($Z$21:$Z$97,B110))*(1+INDEX($Z$21:$Z$97,C110))*(1+INDEX($Z$21:$Z$97,D110))*(1+INDEX($Z$21:$Z$97,E110))*(1+INDEX($Z$21:$Z$97,F110))-1 -> 0.2776316 | H110: =(1+INDEX($AA$21:$AA$97,B110))*(1+INDEX($AA$21:$AA$97,C110))*(1+INDEX($AA$21:$AA$97,D110))*(1+INDEX($AA$21:$AA$97,E110))*(1+INDEX($AA$21:$AA$97,F110))-1 -> 0.25384144 | I110: =(1+INDEX($AB$21:$AB$97,B110))*(1+INDEX($AB$21:$AB$97,C110))*(1+INDEX($AB$21:$AB$97,D110))*(1+INDEX($AB$21:$AB$97,E110))*(1+INDEX($AB$21:$AB$97,F110))-1 -> 0.24170326 | J110: =LN((1+G110)/(1+H110)) -> 0.018796065 | K110: =LN((1+I110)/(1+H110)) -> -0.0097279529
A111: 10 | B111: 63 | C111: 29 | D111: 6 | E111: 28 | F111: 54 | G111: =(1+INDEX($Z$21:$Z$97,B111))*(1+INDEX($Z$21:$Z$97,C111))*(1+INDEX($Z$21:$Z$97,D111))*(1+INDEX($Z$21:$Z$97,E111))*(1+INDEX($Z$21:$Z$97,F111))-1 -> 0.10160966 | H111: =(1+INDEX($AA$21:$AA$97,B111))*(1+INDEX($AA$21:$AA$97,C111))*(1+INDEX($AA$21:$AA$97,D111))*(1+INDEX($AA$21:$AA$97,E111))*(1+INDEX($AA$21:$AA$97,F111))-1 -> 0.15608334 | I111: =(1+INDEX($AB$21:$AB$97,B111))*(1+INDEX($AB$21:$AB$97,C111))*(1+INDEX($AB$21:$AB$97,D111))*(1+INDEX($AB$21:$AB$97,E111))*(1+INDEX($AB$21:$AB$97,F111))-1 -> 0.17377332 | J111: =LN((1+G111)/(1+H111)) -> -0.048265421 | K111: =LN((1+I111)/(1+H111)) -> 0.015185759
A112: 11 | B112: 43 | C112: 41 | D112: 72 | E112: 41 | F112: 33 | G112: =(1+INDEX($Z$21:$Z$97,B112))*(1+INDEX($Z$21:$Z$97,C112))*(1+INDEX($Z$21:$Z$97,D112))*(1+INDEX($Z$21:$Z$97,E112))*(1+INDEX($Z$21:$Z$97,F112))-1 -> 0.83592933 | H112: =(1+INDEX($AA$21:$AA$97,B112))*(1+INDEX($AA$21:$AA$97,C112))*(1+INDEX($AA$21:$AA$97,D112))*(1+INDEX($AA$21:$AA$97,E112))*(1+INDEX($AA$21:$AA$97,F112))-1 -> 0.82122041 | I112: =(1+INDEX($AB$21:$AB$97,B112))*(1+INDEX($AB$21:$AB$97,C112))*(1+INDEX($AB$21:$AB$97,D112))*(1+INDEX($AB$21:$AB$97,E112))*(1+INDEX($AB$21:$AB$97,F112))-1 -> 0.95827106 | J112: =LN((1+G112)/(1+H112)) -> 0.0080439705 | K112: =LN((1+I112)/(1+H112)) -> 0.072555139
A113: 12 | B113: 44 | C113: 14 | D113: 13 | E113: 34 | F113: 53 | G113: =(1+INDEX($Z$21:$Z$97,B113))*(1+INDEX($Z$21:$Z$97,C113))*(1+INDEX($Z$21:$Z$97,D113))*(1+INDEX($Z$21:$Z$97,E113))*(1+INDEX($Z$21:$Z$97,F113))-1 -> 0.63152172 | H113: =(1+INDEX($AA$21:$AA$97,B113))*(1+INDEX($AA$21:$AA$97,C113))*(1+INDEX($AA$21:$AA$97,D113))*(1+INDEX($AA$21:$AA$97,E113))*(1+INDEX($AA$21:$AA$97,F113))-1 -> 0.59020322 | I113: =(1+INDEX($AB$21:$AB$97,B113))*(1+INDEX($AB$21:$AB$97,C113))*(1+INDEX($AB$21:$AB$97,D113))*(1+INDEX($AB$21:$AB$97,E113))*(1+INDEX($AB$21:$AB$97,F113))-1 -> 0.64692008 | J113: =LN((1+G113)/(1+H113)) -> 0.025651326 | K113: =LN((1+I113)/(1+H113)) -> 0.035045105
... A1101: 1000 | B1101: 16 | C1101: 72 | D1101: 22 | E1101: 50 | F1101: 60 | G1101: =(1+INDEX($Z$21:$Z$97,B1101))*(1+INDEX($Z$21:$Z$97,C1101))*(1+INDEX($Z$21:$Z$97,D1101))*(1+INDEX($Z$21:$Z$97,E1101))*(1+INDEX($Z$21:$Z$97,F1101))-1 -> 0.54238812 | H1101: =(1+INDEX($AA$21:$AA$97,B1101))*(1+INDEX($AA$21:$AA$97,C1101))*(1+INDEX($AA$21:$AA$97,D1101))*(1+INDEX($AA$21:$AA$97,E1101))*(1+INDEX($AA$21:$AA$97,F1101))-1 -> 0.52715591 | I1101: =(1+INDEX($AB$21:$AB$97,B1101))*(1+INDEX($AB$21:$AB$97,C1101))*(1+INDEX($AB$21:$AB$97,D1101))*(1+INDEX($AB$21:$AB$97,E1101))*(1+INDEX($AB$21:$AB$97,F1101))-1 -> 0.55658964 | J1101: =LN((1+G1101)/(1+H1101)) -> 0.0099248195 | K1101: =LN((1+I1101)/(1+H1101)) -> 0.019090179

Sheet Stress
A1: Stress
A3: 1. Historical windows
A4: Scenario | B4: Start (quarter end) | C4: End (quarter end)
A5: Global financial crisis | B5: 39447 | C5: 39903
A6: COVID shock | B6: 43921 | C6: 43921
A7: Inflation sell-off (2022) | B7: 44651 | C7: 44925
A9: 2. Asset returns in each scenario
A10: Asset class | B10: Global financial crisis | C10: COVID shock | D10: Inflation sell-off (2022) | E10: US$150 oil (Oil tab)
A11: Australian Equities | B11: =EXP(SUMPRODUCT(LN(1+INDEX('Quarterly returns'!N$6:N$85,MATCH($B$5,'Quarterly returns'!$A$6:$A$85,0)):INDEX('Quarterly returns'!N$6:N$85,MATCH($C$5,'Quarterly returns'!$A$6:$A$85,0)))))-1 -> -0.42395461 | C11: =EXP(SUMPRODUCT(LN(1+INDEX('Quarterly returns'!N$6:N$85,MATCH($B$6,'Quarterly returns'!$A$6:$A$85,0)):INDEX('Quarterly returns'!N$6:N$85,MATCH($C$6,'Quarterly returns'!$A$6:$A$85,0)))))-1 -> -0.23923021 | D11: =EXP(SUMPRODUCT(LN(1+INDEX('Quarterly returns'!N$6:N$85,MATCH($B$7,'Quarterly returns'!$A$6:$A$85,0)):INDEX('Quarterly returns'!N$6:N$85,MATCH($C$7,'Quarterly returns'!$A$6:$A$85,0)))))-1 -> -0.029586588 | E11: =Oil!F28 -> -0.0848026
A12: World Equities | B12: =EXP(SUMPRODUCT(LN(1+INDEX('Quarterly returns'!O$6:O$85,MATCH($B$5,'Quarterly returns'!$A$6:$A$85,0)):INDEX('Quarterly returns'!O$6:O$85,MATCH($C$5,'Quarterly returns'!$A$6:$A$85,0)))))-1 -> -0.31268062 | C12: =EXP(SUMPRODUCT(LN(1+INDEX('Quarterly returns'!O$6:O$85,MATCH($B$6,'Quarterly returns'!$A$6:$A$85,0)):INDEX('Quarterly returns'!O$6:O$85,MATCH($C$6,'Quarterly returns'!$A$6:$A$85,0)))))-1 -> -0.080905967 | D12: =EXP(SUMPRODUCT(LN(1+INDEX('Quarterly returns'!O$6:O$85,MATCH($B$7,'Quarterly returns'!$A$6:$A$85,0)):INDEX('Quarterly returns'!O$6:O$85,MATCH($C$7,'Quarterly returns'!$A$6:$A$85,0)))))-1 -> -0.095374399 | E12: =Oil!F29 -> -0.12992958
A13: Emerging Markets | B13: =EXP(SUMPRODUCT(LN(1+INDEX('Quarterly returns'!P$6:P$85,MATCH($B$5,'Quarterly returns'!$A$6:$A$85,0)):INDEX('Quarterly returns'!P$6:P$85,MATCH($C$5,'Quarterly returns'!$A$6:$A$85,0)))))-1 -> -0.25904312 | C13: =EXP(SUMPRODUCT(LN(1+INDEX('Quarterly returns'!P$6:P$85,MATCH($B$6,'Quarterly returns'!$A$6:$A$85,0)):INDEX('Quarterly returns'!P$6:P$85,MATCH($C$6,'Quarterly returns'!$A$6:$A$85,0)))))-1 -> -0.069947634 | D13: =EXP(SUMPRODUCT(LN(1+INDEX('Quarterly returns'!P$6:P$85,MATCH($B$7,'Quarterly returns'!$A$6:$A$85,0)):INDEX('Quarterly returns'!P$6:P$85,MATCH($C$7,'Quarterly returns'!$A$6:$A$85,0)))))-1 -> -0.090464646 | E13: =Oil!F30 -> -0.13708873
A14: Listed Property | B14: =EXP(SUMPRODUCT(LN(1+INDEX('Quarterly returns'!Q$6:Q$85,MATCH($B$5,'Quarterly returns'!$A$6:$A$85,0)):INDEX('Quarterly returns'!Q$6:Q$85,MATCH($C$5,'Quarterly returns'!$A$6:$A$85,0)))))-1 -> -0.5052704 | C14: =EXP(SUMPRODUCT(LN(1+INDEX('Quarterly returns'!Q$6:Q$85,MATCH($B$6,'Quarterly returns'!$A$6:$A$85,0)):INDEX('Quarterly returns'!Q$6:Q$85,MATCH($C$6,'Quarterly returns'!$A$6:$A$85,0)))))-1 -> -0.16646922 | D14: =EXP(SUMPRODUCT(LN(1+INDEX('Quarterly returns'!Q$6:Q$85,MATCH($B$7,'Quarterly returns'!$A$6:$A$85,0)):INDEX('Quarterly returns'!Q$6:Q$85,MATCH($C$7,'Quarterly returns'!$A$6:$A$85,0)))))-1 -> -0.16027289 | E14: =Oil!F31 -> -0.11553691
A15: Commodities | B15: =EXP(SUMPRODUCT(LN(1+INDEX('Quarterly returns'!R$6:R$85,MATCH($B$5,'Quarterly returns'!$A$6:$A$85,0)):INDEX('Quarterly returns'!R$6:R$85,MATCH($C$5,'Quarterly returns'!$A$6:$A$85,0)))))-1 -> -0.32006394 | C15: =EXP(SUMPRODUCT(LN(1+INDEX('Quarterly returns'!R$6:R$85,MATCH($B$6,'Quarterly returns'!$A$6:$A$85,0)):INDEX('Quarterly returns'!R$6:R$85,MATCH($C$6,'Quarterly returns'!$A$6:$A$85,0)))))-1 -> -0.33781993 | D15: =EXP(SUMPRODUCT(LN(1+INDEX('Quarterly returns'!R$6:R$85,MATCH($B$7,'Quarterly returns'!$A$6:$A$85,0)):INDEX('Quarterly returns'!R$6:R$85,MATCH($C$7,'Quarterly returns'!$A$6:$A$85,0)))))-1 -> 0.35070542 | E15: =Oil!F32 -> 0.29013882
A16: Direct Property | B16: =EXP(SUMPRODUCT(LN(1+INDEX('Quarterly returns'!S$6:S$85,MATCH($B$5,'Quarterly returns'!$A$6:$A$85,0)):INDEX('Quarterly returns'!S$6:S$85,MATCH($C$5,'Quarterly returns'!$A$6:$A$85,0)))))-1 -> -0.059832983 | C16: =EXP(SUMPRODUCT(LN(1+INDEX('Quarterly returns'!S$6:S$85,MATCH($B$6,'Quarterly returns'!$A$6:$A$85,0)):INDEX('Quarterly returns'!S$6:S$85,MATCH($C$6,'Quarterly returns'!$A$6:$A$85,0)))))-1 -> -0.023906178 | D16: =EXP(SUMPRODUCT(LN(1+INDEX('Quarterly returns'!S$6:S$85,MATCH($B$7,'Quarterly returns'!$A$6:$A$85,0)):INDEX('Quarterly returns'!S$6:S$85,MATCH($C$7,'Quarterly returns'!$A$6:$A$85,0)))))-1 -> -0.14837279 | E16: =Oil!F33 -> 0.023268684
A17: Hedge Funds | B17: =EXP(SUMPRODUCT(LN(1+INDEX('Quarterly returns'!T$6:T$85,MATCH($B$5,'Quarterly returns'!$A$6:$A$85,0)):INDEX('Quarterly returns'!T$6:T$85,MATCH($C$5,'Quarterly returns'!$A$6:$A$85,0)))))-1 -> 0.20371951 | C17: =EXP(SUMPRODUCT(LN(1+INDEX('Quarterly returns'!T$6:T$85,MATCH($B$6,'Quarterly returns'!$A$6:$A$85,0)):INDEX('Quarterly returns'!T$6:T$85,MATCH($C$6,'Quarterly returns'!$A$6:$A$85,0)))))-1 -> 0.1267819 | D17: =EXP(SUMPRODUCT(LN(1+INDEX('Quarterly returns'!T$6:T$85,MATCH($B$7,'Quarterly returns'!$A$6:$A$85,0)):INDEX('Quarterly returns'!T$6:T$85,MATCH($C$7,'Quarterly returns'!$A$6:$A$85,0)))))-1 -> 0.023911745 | E17: =Oil!F34 -> -0.041538442
A18: Private Equity | B18: =EXP(SUMPRODUCT(LN(1+INDEX('Quarterly returns'!U$6:U$85,MATCH($B$5,'Quarterly returns'!$A$6:$A$85,0)):INDEX('Quarterly returns'!U$6:U$85,MATCH($C$5,'Quarterly returns'!$A$6:$A$85,0)))))-1 -> -0.15344471 | C18: =EXP(SUMPRODUCT(LN(1+INDEX('Quarterly returns'!U$6:U$85,MATCH($B$6,'Quarterly returns'!$A$6:$A$85,0)):INDEX('Quarterly returns'!U$6:U$85,MATCH($C$6,'Quarterly returns'!$A$6:$A$85,0)))))-1 -> -0.09197953 | D18: =EXP(SUMPRODUCT(LN(1+INDEX('Quarterly returns'!U$6:U$85,MATCH($B$7,'Quarterly returns'!$A$6:$A$85,0)):INDEX('Quarterly returns'!U$6:U$85,MATCH($C$7,'Quarterly returns'!$A$6:$A$85,0)))))-1 -> 0.0094939572 | E18: =Oil!F35 -> -0.09842712
A19: Australian Fixed Income | B19: =EXP(SUMPRODUCT(LN(1+INDEX('Quarterly returns'!V$6:V$85,MATCH($B$5,'Quarterly returns'!$A$6:$A$85,0)):INDEX('Quarterly returns'!V$6:V$85,MATCH($C$5,'Quarterly returns'!$A$6:$A$85,0)))))-1 -> 0.15561261 | C19: =EXP(SUMPRODUCT(LN(1+INDEX('Quarterly returns'!V$6:V$85,MATCH($B$6,'Quarterly returns'!$A$6:$A$85,0)):INDEX('Quarterly returns'!V$6:V$85,MATCH($C$6,'Quarterly returns'!$A$6:$A$85,0)))))-1 -> 0.033109728 | D19: =EXP(SUMPRODUCT(LN(1+INDEX('Quarterly returns'!V$6:V$85,MATCH($B$7,'Quarterly returns'!$A$6:$A$85,0)):INDEX('Quarterly returns'!V$6:V$85,MATCH($C$7,'Quarterly returns'!$A$6:$A$85,0)))))-1 -> -0.1108247 | E19: =Oil!F36 -> -0.04884397
A20: World Fixed Income | B20: =EXP(SUMPRODUCT(LN(1+INDEX('Quarterly returns'!W$6:W$85,MATCH($B$5,'Quarterly returns'!$A$6:$A$85,0)):INDEX('Quarterly returns'!W$6:W$85,MATCH($C$5,'Quarterly returns'!$A$6:$A$85,0)))))-1 -> 0.12829729 | C20: =EXP(SUMPRODUCT(LN(1+INDEX('Quarterly returns'!W$6:W$85,MATCH($B$6,'Quarterly returns'!$A$6:$A$85,0)):INDEX('Quarterly returns'!W$6:W$85,MATCH($C$6,'Quarterly returns'!$A$6:$A$85,0)))))-1 -> 0.030592829 | D20: =EXP(SUMPRODUCT(LN(1+INDEX('Quarterly returns'!W$6:W$85,MATCH($B$7,'Quarterly returns'!$A$6:$A$85,0)):INDEX('Quarterly returns'!W$6:W$85,MATCH($C$7,'Quarterly returns'!$A$6:$A$85,0)))))-1 -> -0.12590993 | E20: =Oil!F37 -> -0.047775824
A21: Cash | B21: =EXP(SUMPRODUCT(LN(1+INDEX('Quarterly returns'!X$6:X$85,MATCH($B$5,'Quarterly returns'!$A$6:$A$85,0)):INDEX('Quarterly returns'!X$6:X$85,MATCH($C$5,'Quarterly returns'!$A$6:$A$85,0)))))-1 -> 0.1052518 | C21: =EXP(SUMPRODUCT(LN(1+INDEX('Quarterly returns'!X$6:X$85,MATCH($B$6,'Quarterly returns'!$A$6:$A$85,0)):INDEX('Quarterly returns'!X$6:X$85,MATCH($C$6,'Quarterly returns'!$A$6:$A$85,0)))))-1 -> 0.0025612734 | D21: =EXP(SUMPRODUCT(LN(1+INDEX('Quarterly returns'!X$6:X$85,MATCH($B$7,'Quarterly returns'!$A$6:$A$85,0)):INDEX('Quarterly returns'!X$6:X$85,MATCH($C$7,'Quarterly returns'!$A$6:$A$85,0)))))-1 -> 0.012555222 | E21: =Oil!F38 -> 0
A24: 3. Portfolio impact
A25: Portfolio | B25: Global financial crisis | C25: COVID shock | D25: Inflation sell-off (2022) | E25: US$150 oil
A26: Current fund | B26: =SUMPRODUCT(B$11:B$21,Portfolio!$C$6:$C$16) -> -0.24167171 | C26: =SUMPRODUCT(C$11:C$21,Portfolio!$C$6:$C$16) -> -0.12092703 | D26: =SUMPRODUCT(D$11:D$21,Portfolio!$C$6:$C$16) -> -0.072754437 | E26: =SUMPRODUCT(E$11:E$21,Portfolio!$C$6:$C$16) -> -0.082609308
A27: Benchmark | B27: =SUMPRODUCT(B$11:B$21,Portfolio!$D$6:$D$16) -> -0.19300089 | C27: =SUMPRODUCT(C$11:C$21,Portfolio!$D$6:$D$16) -> -0.091806485 | D27: =SUMPRODUCT(D$11:D$21,Portfolio!$D$6:$D$16) -> -0.072610798 | E27: =SUMPRODUCT(E$11:E$21,Portfolio!$D$6:$D$16) -> -0.073910247
A28: Recommended | B28: =SUMPRODUCT(B$11:B$21,Portfolio!$E$6:$E$16) -> -0.24131527 | C28: =SUMPRODUCT(C$11:C$21,Portfolio!$E$6:$E$16) -> -0.11048429 | D28: =SUMPRODUCT(D$11:D$21,Portfolio!$E$6:$E$16) -> -0.072174037 | E28: =SUMPRODUCT(E$11:E$21,Portfolio!$E$6:$E$16) -> -0.078202714
A29: Recommended less current | B29: =B28-B26 -> 0.00035643962 | C29: =C28-C26 -> 0.010442735 | D29: =D28-D26 -> 0.00058040016 | E29: =E28-E26 -> 0.004406594
A30: Recommended less benchmark | B30: =B28-B27 -> -0.048314381 | C30: =C28-C27 -> -0.018677806 | D30: =D28-D27 -> 0.00043676061 | E30: =E28-E27 -> -0.004292467

Sheet Oil
A1: Oil
A3: 1. Scenario | N3: Monthly panel, Jan-1968 to Jan-2026 (from Additional data and Data tabs)
A4: Current WTI (US$/bbl) | B4: 96.41 | C4: FRED, 22-Sep-26 | N4: Month end | O4: WTI | P4: ln WTI | Q4: US equity log index | R4: Aus equity ln level | S4: AU 3-month rate (%) | T4: 1m oil (log) | U4: 1m US equity (log) | V4: 1m Aus equity (log) | W4: 1m rate change (pp) | X4: 12m oil (log) | Y4: 12m US equity (log) | Z4: 12m Aus equity (log) | AA4: 12m rate change (pp) | AB4: 60m oil (log) | AC4: 60m US equity (log) | AD4: 60m Aus equity (log) | AE4: 60m rate change (pp)
A5: Scenario WTI (US$/bbl) | B5: 150 | C5: Brief | N5: 24868 | O5: =INDEX('Additional data'!$B$2:$B$965,MATCH(DATE(YEAR(N5),MONTH(N5),1),'Additional data'!$A$2:$A$965,0)) -> 3.07 | P5: =LN(O5) -> 1.1216776 | Q5: =LN(1+INDEX('Additional data'!$H$2:$H$1196,MATCH(N5,'Additional data'!$G$2:$G$1196,1))+INDEX('Additional data'!$I$2:$I$1196,MATCH(N5,'Additional data'!$G$2:$G$1196,1))) -> -0.036975236 | S5: =INDEX('Additional data'!$E$2:$E$699,MATCH(DATE(YEAR(N5),MONTH(N5),1),'Additional data'!$D$2:$D$699,0)) -> 5.1
A6: Oil price change | B6: =B5/B4-1 -> 0.5558552 | N6: 24897 | O6: =INDEX('Additional data'!$B$2:$B$965,MATCH(DATE(YEAR(N6),MONTH(N6),1),'Additional data'!$A$2:$A$965,0)) -> 3.07 | P6: =LN(O6) -> 1.1216776 | Q6: =Q5+LN(1+INDEX('Additional data'!$H$2:$H$1196,MATCH(N6,'Additional data'!$G$2:$G$1196,1))+INDEX('Additional data'!$I$2:$I$1196,MATCH(N6,'Additional data'!$G$2:$G$1196,1))) -> -0.071049216 | S6: =INDEX('Additional data'!$E$2:$E$699,MATCH(DATE(YEAR(N6),MONTH(N6),1),'Additional data'!$D$2:$D$699,0)) -> 5.15 | T6: =P6-P5 -> 0 | U6: =Q6-Q5 -> -0.03407398 | W6: =S6-S5 -> 0.05
A7: Log change | B7: =LN(B5/B4) -> 0.44202536 | N7: 24928 | O7: =INDEX('Additional data'!$B$2:$B$965,MATCH(DATE(YEAR(N7),MONTH(N7),1),'Additional data'!$A$2:$A$965,0)) -> 3.07 | P7: =LN(O7) -> 1.1216776 | Q7: =Q6+LN(1+INDEX('Additional data'!$H$2:$H$1196,MATCH(N7,'Additional data'!$G$2:$G$1196,1))+INDEX('Additional data'!$I$2:$I$1196,MATCH(N7,'Additional data'!$G$2:$G$1196,1))) -> -0.065166553 | S7: =INDEX('Additional data'!$E$2:$E$699,MATCH(DATE(YEAR(N7),MONTH(N7),1),'Additional data'!$D$2:$D$699,0)) -> 5.15 | T7: =P7-P6 -> 0 | U7: =Q7-Q6 -> 0.0058826632 | W7: =S7-S6 -> 0
N8: 24958 | O8: =INDEX('Additional data'!$B$2:$B$965,MATCH(DATE(YEAR(N8),MONTH(N8),1),'Additional data'!$A$2:$A$965,0)) -> 3.07 | P8: =LN(O8) -> 1.1216776 | Q8: =Q7+LN(1+INDEX('Additional data'!$H$2:$H$1196,MATCH(N8,'Additional data'!$G$2:$G$1196,1))+INDEX('Additional data'!$I$2:$I$1196,MATCH(N8,'Additional data'!$G$2:$G$1196,1))) -> 0.025131085 | S8: =INDEX('Additional data'!$E$2:$E$699,MATCH(DATE(YEAR(N8),MONTH(N8),1),'Additional data'!$D$2:$D$699,0)) -> 5.15 | T8: =P8-P7 -> 0 | U8: =Q8-Q7 -> 0.090297638 | W8: =S8-S7 -> 0
A9: 2. Oil and equity returns / interest rates, monthly to 5-year horizons | N9: 24989 | O9: =INDEX('Additional data'!$B$2:$B$965,MATCH(DATE(YEAR(N9),MONTH(N9),1),'Additional data'!$A$2:$A$965,0)) -> 3.07 | P9: =LN(O9) -> 1.1216776 | Q9: =Q8+LN(1+INDEX('Additional data'!$H$2:$H$1196,MATCH(N9,'Additional data'!$G$2:$G$1196,1))+INDEX('Additional data'!$I$2:$I$1196,MATCH(N9,'Additional data'!$G$2:$G$1196,1))) -> 0.052065086 | S9: =INDEX('Additional data'!$E$2:$E$699,MATCH(DATE(YEAR(N9),MONTH(N9),1),'Additional data'!$D$2:$D$699,0)) -> 5.3 | T9: =P9-P8 -> 0 | U9: =Q9-Q8 -> 0.026934001 | W9: =S9-S8 -> 0.15
A10: Series | B10: Horizon (months) | C10: Beta | D10: t-stat | E10: t-stat (overlap-adj.) | F10: R-squared | G10: Obs | H10: Response to scenario | N10: 25019 | O10: =INDEX('Additional data'!$B$2:$B$965,MATCH(DATE(YEAR(N10),MONTH(N10),1),'Additional data'!$A$2:$A$965,0)) -> 3.07 | P10: =LN(O10) -> 1.1216776 | Q10: =Q9+LN(1+INDEX('Additional data'!$H$2:$H$1196,MATCH(N10,'Additional data'!$G$2:$G$1196,1))+INDEX('Additional data'!$I$2:$I$1196,MATCH(N10,'Additional data'!$G$2:$G$1196,1))) -> 0.063301718 | S10: =INDEX('Additional data'!$E$2:$E$699,MATCH(DATE(YEAR(N10),MONTH(N10),1),'Additional data'!$D$2:$D$699,0)) -> 5.5 | T10: =P10-P9 -> 0 | U10: =Q10-Q9 -> 0.011236632 | W10: =S10-S9 -> 0.2
A11: US equities | B11: 1 | C11: =SLOPE($U$6:$U$701,$T$6:$T$701) -> 0.033291576 | D11: =CORREL($U$6:$U$701,$T$6:$T$701)*SQRT((G11-2)/(1-F11)) -> 1.7055863 | E11: =D11/SQRT(B11) -> 1.7055863 | F11: =RSQ($U$6:$U$701,$T$6:$T$701) -> 0.0041741815 | G11: =COUNT($U$6:$U$701) -> 696 | H11: =EXP(C11*$B$7)-1 -> 0.014824531 | N11: 25050 | O11: =INDEX('Additional data'!$B$2:$B$965,MATCH(DATE(YEAR(N11),MONTH(N11),1),'Additional data'!$A$2:$A$965,0)) -> 3.07 | P11: =LN(O11) -> 1.1216776 | Q11: =Q10+LN(1+INDEX('Additional data'!$H$2:$H$1196,MATCH(N11,'Additional data'!$G$2:$G$1196,1))+INDEX('Additional data'!$I$2:$I$1196,MATCH(N11,'Additional data'!$G$2:$G$1196,1))) -> 0.040953854 | S11: =INDEX('Additional data'!$E$2:$E$699,MATCH(DATE(YEAR(N11),MONTH(N11),1),'Additional data'!$D$2:$D$699,0)) -> 5.1 | T11: =P11-P10 -> 0 | U11: =Q11-Q10 -> -0.022347864 | W11: =S11-S10 -> -0.4
A12: US equities | B12: 12 | C12: =SLOPE($Y$17:$Y$701,$X$17:$X$701) -> 0.020301939 | D12: =CORREL($Y$17:$Y$701,$X$17:$X$701)*SQRT((G12-2)/(1-F12)) -> 1.0700093 | E12: =D12/SQRT(B12) -> 0.30888509 | F12: =RSQ($Y$17:$Y$701,$X$17:$X$701) -> 0.001673505 | G12: =COUNT($Y$17:$Y$701) -> 685 | H12: =EXP(C12*$B$7)-1 -> 0.0090143586 | N12: 25081 | O12: =INDEX('Additional data'!$B$2:$B$965,MATCH(DATE(YEAR(N12),MONTH(N12),1),'Additional data'!$A$2:$A$965,0)) -> 3.07 | P12: =LN(O12) -> 1.1216776 | Q12: =Q11+LN(1+INDEX('Additional data'!$H$2:$H$1196,MATCH(N12,'Additional data'!$G$2:$G$1196,1))+INDEX('Additional data'!$I$2:$I$1196,MATCH(N12,'Additional data'!$G$2:$G$1196,1))) -> 0.058499033 | S12: =INDEX('Additional data'!$E$2:$E$699,MATCH(DATE(YEAR(N12),MONTH(N12),1),'Additional data'!$D$2:$D$699,0)) -> 5.1 | T12: =P12-P11 -> 0 | U12: =Q12-Q11 -> 0.017545179 | W12: =S12-S11 -> 0
A13: US equities | B13: 60 | C13: =SLOPE($AC$65:$AC$701,$AB$65:$AB$701) -> -0.22998127 | D13: =CORREL($AC$65:$AC$701,$AB$65:$AB$701)*SQRT((G13-2)/(1-F13)) -> -12.039039 | E13: =D13/SQRT(B13) -> -1.5542333 | F13: =RSQ($AC$65:$AC$701,$AB$65:$AB$701) -> 0.1858332 | G13: =COUNT($AC$65:$AC$701) -> 637 | H13: =EXP(C13*$B$7)-1 -> -0.096661156 | N13: 25111 | O13: =INDEX('Additional data'!$B$2:$B$965,MATCH(DATE(YEAR(N13),MONTH(N13),1),'Additional data'!$A$2:$A$965,0)) -> 3.07 | P13: =LN(O13) -> 1.1216776 | Q13: =Q12+LN(1+INDEX('Additional data'!$H$2:$H$1196,MATCH(N13,'Additional data'!$G$2:$G$1196,1))+INDEX('Additional data'!$I$2:$I$1196,MATCH(N13,'Additional data'!$G$2:$G$1196,1))) -> 0.10232451 | S13: =INDEX('Additional data'!$E$2:$E$699,MATCH(DATE(YEAR(N13),MONTH(N13),1),'Additional data'!$D$2:$D$699,0)) -> 5.05 | T13: =P13-P12 -> 0 | U13: =Q13-Q12 -> 0.04382548 | W13: =S13-S12 -> -0.05
A14: Australian equities | B14: 1 | C14: =SLOPE($V$209:$V$701,$T$209:$T$701) -> 0.067087054 | D14: =CORREL($V$209:$V$701,$T$209:$T$701)*SQRT((G14-2)/(1-F14)) -> 3.0035221 | E14: =D14/SQRT(B14) -> 3.0035221 | F14: =RSQ($V$209:$V$701,$T$209:$T$701) -> 0.018041527 | G14: =COUNT($V$209:$V$701) -> 493 | H14: =EXP(C14*$B$7)-1 -> 0.030098243 | N14: 25142 | O14: =INDEX('Additional data'!$B$2:$B$965,MATCH(DATE(YEAR(N14),MONTH(N14),1),'Additional data'!$A$2:$A$965,0)) -> 3.07 | P14: =LN(O14) -> 1.1216776 | Q14: =Q13+LN(1+INDEX('Additional data'!$H$2:$H$1196,MATCH(N14,'Additional data'!$G$2:$G$1196,1))+INDEX('Additional data'!$I$2:$I$1196,MATCH(N14,'Additional data'!$G$2:$G$1196,1))) -> 0.11098689 | S14: =INDEX('Additional data'!$E$2:$E$699,MATCH(DATE(YEAR(N14),MONTH(N14),1),'Additional data'!$D$2:$D$699,0)) -> 5 | T14: =P14-P13 -> 0 | U14: =Q14-Q13 -> 0.0086623731 | W14: =S14-S13 -> -0.05
A15: Australian equities | B15: 12 | C15: =SLOPE($Z$220:$Z$701,$X$220:$X$701) -> 0.10082179 | D15: =CORREL($Z$220:$Z$701,$X$220:$X$701)*SQRT((G15-2)/(1-F15)) -> 5.1124036 | E15: =D15/SQRT(B15) -> 1.4758238 | F15: =RSQ($Z$220:$Z$701,$X$220:$X$701) -> 0.051639552 | G15: =COUNT($Z$220:$Z$701) -> 482 | H15: =EXP(C15*$B$7)-1 -> 0.045573762 | N15: 25172 | O15: =INDEX('Additional data'!$B$2:$B$965,MATCH(DATE(YEAR(N15),MONTH(N15),1),'Additional data'!$A$2:$A$965,0)) -> 3.07 | P15: =LN(O15) -> 1.1216776 | Q15: =Q14+LN(1+INDEX('Additional data'!$H$2:$H$1196,MATCH(N15,'Additional data'!$G$2:$G$1196,1))+INDEX('Additional data'!$I$2:$I$1196,MATCH(N15,'Additional data'!$G$2:$G$1196,1))) -> 0.1678397 | S15: =INDEX('Additional data'!$E$2:$E$699,MATCH(DATE(YEAR(N15),MONTH(N15),1),'Additional data'!$D$2:$D$699,0)) -> 4.9 | T15: =P15-P14 -> 0 | U15: =Q15-Q14 -> 0.056852812 | W15: =S15-S14 -> -0.1
A16: Australian equities | B16: 60 | C16: =SLOPE($AD$268:$AD$701,$AB$268:$AB$701) -> 0.087571808 | D16: =CORREL($AD$268:$AD$701,$AB$268:$AB$701)*SQRT((G16-2)/(1-F16)) -> 4.4828626 | E16: =D16/SQRT(B16) -> 0.57873507 | F16: =RSQ($AD$268:$AD$701,$AB$268:$AB$701) -> 0.044450857 | G16: =COUNT($AD$268:$AD$701) -> 434 | H16: =EXP(C16*$B$7)-1 -> 0.039467913 | N16: 25203 | O16: =INDEX('Additional data'!$B$2:$B$965,MATCH(DATE(YEAR(N16),MONTH(N16),1),'Additional data'!$A$2:$A$965,0)) -> 3.07 | P16: =LN(O16) -> 1.1216776 | Q16: =Q15+LN(1+INDEX('Additional data'!$H$2:$H$1196,MATCH(N16,'Additional data'!$G$2:$G$1196,1))+INDEX('Additional data'!$I$2:$I$1196,MATCH(N16,'Additional data'!$G$2:$G$1196,1))) -> 0.13221252 | S16: =INDEX('Additional data'!$E$2:$E$699,MATCH(DATE(YEAR(N16),MONTH(N16),1),'Additional data'!$D$2:$D$699,0)) -> 4.9 | T16: =P16-P15 -> 0 | U16: =Q16-Q15 -> -0.035627178 | W16: =S16-S15 -> 0
A17: AU 3-month rate (pp) | B17: 1 | C17: =SLOPE($W$6:$W$701,$T$6:$T$701) -> 0.46261179 | D17: =CORREL($W$6:$W$701,$T$6:$T$701)*SQRT((G17-2)/(1-F17)) -> 1.5243011 | E17: =D17/SQRT(B17) -> 1.5243011 | F17: =RSQ($W$6:$W$701,$T$6:$T$701) -> 0.0033368022 | G17: =COUNT($W$6:$W$701) -> 696 | H17: =C17*$B$7 -> 0.20448614 | N17: 25234 | O17: =INDEX('Additional data'!$B$2:$B$965,MATCH(DATE(YEAR(N17),MONTH(N17),1),'Additional data'!$A$2:$A$965,0)) -> 3.07 | P17: =LN(O17) -> 1.1216776 | Q17: =Q16+LN(1+INDEX('Additional data'!$H$2:$H$1196,MATCH(N17,'Additional data'!$G$2:$G$1196,1))+INDEX('Additional data'!$I$2:$I$1196,MATCH(N17,'Additional data'!$G$2:$G$1196,1))) -> 0.12498647 | S17: =INDEX('Additional data'!$E$2:$E$699,MATCH(DATE(YEAR(N17),MONTH(N17),1),'Additional data'!$D$2:$D$699,0)) -> 5.1 | T17: =P17-P16 -> 0 | U17: =Q17-Q16 -> -0.0072260451 | W17: =S17-S16 -> 0.2 | X17: =P17-P5 -> 0 | Y17: =Q17-Q5 -> 0.16196171 | AA17: =S17-S5 -> 0
A18: AU 3-month rate (pp) | B18: 12 | C18: =SLOPE($AA$17:$AA$701,$X$17:$X$701) -> 2.272911 | D18: =CORREL($AA$17:$AA$701,$X$17:$X$701)*SQRT((G18-2)/(1-F18)) -> 8.4271393 | E18: =D18/SQRT(B18) -> 2.4327056 | F18: =RSQ($AA$17:$AA$701,$X$17:$X$701) -> 0.094184492 | G18: =COUNT($AA$17:$AA$701) -> 685 | H18: =C18*$B$7 -> 1.0046843 | N18: 25262 | O18: =INDEX('Additional data'!$B$2:$B$965,MATCH(DATE(YEAR(N18),MONTH(N18),1),'Additional data'!$A$2:$A$965,0)) -> 3.07 | P18: =LN(O18) -> 1.1216776 | Q18: =Q17+LN(1+INDEX('Additional data'!$H$2:$H$1196,MATCH(N18,'Additional data'!$G$2:$G$1196,1))+INDEX('Additional data'!$I$2:$I$1196,MATCH(N18,'Additional data'!$G$2:$G$1196,1))) -> 0.069473765 | S18: =INDEX('Additional data'!$E$2:$E$699,MATCH(DATE(YEAR(N18),MONTH(N18),1),'Additional data'!$D$2:$D$699,0)) -> 5.1 | T18: =P18-P17 -> 0 | U18: =Q18-Q17 -> -0.05551271 | W18: =S18-S17 -> 0 | X18: =P18-P6 -> 0 | Y18: =Q18-Q6 -> 0.14052298 | AA18: =S18-S6 -> -0.05
A19: AU 3-month rate (pp) | B19: 60 | C19: =SLOPE($AE$65:$AE$701,$AB$65:$AB$701) -> 2.6328845 | D19: =CORREL($AE$65:$AE$701,$AB$65:$AB$701)*SQRT((G19-2)/(1-F19)) -> 11.335291 | E19: =D19/SQRT(B19) -> 1.4633798 | F19: =RSQ($AE$65:$AE$701,$AB$65:$AB$701) -> 0.16829169 | G19: =COUNT($AE$65:$AE$701) -> 637 | H19: =C19*$B$7 -> 1.1638017 | N19: 25293 | O19: =INDEX('Additional data'!$B$2:$B$965,MATCH(DATE(YEAR(N19),MONTH(N19),1),'Additional data'!$A$2:$A$965,0)) -> 3.25 | P19: =LN(O19) -> 1.178655 | Q19: =Q18+LN(1+INDEX('Additional data'!$H$2:$H$1196,MATCH(N19,'Additional data'!$G$2:$G$1196,1))+INDEX('Additional data'!$I$2:$I$1196,MATCH(N19,'Additional data'!$G$2:$G$1196,1))) -> 0.10019694 | S19: =INDEX('Additional data'!$E$2:$E$699,MATCH(DATE(YEAR(N19),MONTH(N19),1),'Additional data'!$D$2:$D$699,0)) -> 5.15 | T19: =P19-P18 -> 0.056977435 | U19: =Q19-Q18 -> 0.030723173 | W19: =S19-S18 -> 0.05 | X19: =P19-P7 -> 0.056977435 | Y19: =Q19-Q7 -> 0.16536349 | AA19: =S19-S7 -> 0
N20: 25323 | O20: =INDEX('Additional data'!$B$2:$B$965,MATCH(DATE(YEAR(N20),MONTH(N20),1),'Additional data'!$A$2:$A$965,0)) -> 3.35 | P20: =LN(O20) -> 1.2089603 | Q20: =Q19+LN(1+INDEX('Additional data'!$H$2:$H$1196,MATCH(N20,'Additional data'!$G$2:$G$1196,1))+INDEX('Additional data'!$I$2:$I$1196,MATCH(N20,'Additional data'!$G$2:$G$1196,1))) -> 0.11990152 | S20: =INDEX('Additional data'!$E$2:$E$699,MATCH(DATE(YEAR(N20),MONTH(N20),1),'Additional data'!$D$2:$D$699,0)) -> 5.4 | T20: =P20-P19 -> 0.030305349 | U20: =Q20-Q19 -> 0.019704583 | W20: =S20-S19 -> 0.25 | X20: =P20-P8 -> 0.087282784 | Y20: =Q20-Q8 -> 0.094770436 | AA20: =S20-S8 -> 0.25
N21: 25354 | O21: =INDEX('Additional data'!$B$2:$B$965,MATCH(DATE(YEAR(N21),MONTH(N21),1),'Additional data'!$A$2:$A$965,0)) -> 3.35 | P21: =LN(O21) -> 1.2089603 | Q21: =Q20+LN(1+INDEX('Additional data'!$H$2:$H$1196,MATCH(N21,'Additional data'!$G$2:$G$1196,1))+INDEX('Additional data'!$I$2:$I$1196,MATCH(N21,'Additional data'!$G$2:$G$1196,1))) -> 0.12379394 | S21: =INDEX('Additional data'!$E$2:$E$699,MATCH(DATE(YEAR(N21),MONTH(N21),1),'Additional data'!$D$2:$D$699,0)) -> 5.5 | T21: =P21-P20 -> 0 | U21: =Q21-Q20 -> 0.0038924147 | W21: =S21-S20 -> 0.1 | X21: =P21-P9 -> 0.087282784 | Y21: =Q21-Q9 -> 0.07172885 | AA21: =S21-S9 -> 0.2
A22: 3. Episode study: supply-driven oil shocks, scaled to US$150 | N22: 25384 | O22: =INDEX('Additional data'!$B$2:$B$965,MATCH(DATE(YEAR(N22),MONTH(N22),1),'Additional data'!$A$2:$A$965,0)) -> 3.35 | P22: =LN(O22) -> 1.2089603 | Q22: =Q21+LN(1+INDEX('Additional data'!$H$2:$H$1196,MATCH(N22,'Additional data'!$G$2:$G$1196,1))+INDEX('Additional data'!$I$2:$I$1196,MATCH(N22,'Additional data'!$G$2:$G$1196,1))) -> 0.054658197 | S22: =INDEX('Additional data'!$E$2:$E$699,MATCH(DATE(YEAR(N22),MONTH(N22),1),'Additional data'!$D$2:$D$699,0)) -> 5.9 | T22: =P22-P21 -> 0 | U22: =Q22-Q21 -> -0.069135739 | W22: =S22-S21 -> 0.4 | X22: =P22-P10 -> 0.087282784 | Y22: =Q22-Q10 -> -0.0086435211 | AA22: =S22-S10 -> 0.4
A23: Episode | B23: Start | C23: End | D23: WTI start | E23: WTI end | F23: WTI change | G23: Scale to scenario | N23: 25415 | O23: =INDEX('Additional data'!$B$2:$B$965,MATCH(DATE(YEAR(N23),MONTH(N23),1),'Additional data'!$A$2:$A$965,0)) -> 3.35 | P23: =LN(O23) -> 1.2089603 | Q23: =Q22+LN(1+INDEX('Additional data'!$H$2:$H$1196,MATCH(N23,'Additional data'!$G$2:$G$1196,1))+INDEX('Additional data'!$I$2:$I$1196,MATCH(N23,'Additional data'!$G$2:$G$1196,1))) -> -0.012229749 | S23: =INDEX('Additional data'!$E$2:$E$699,MATCH(DATE(YEAR(N23),MONTH(N23),1),'Additional data'!$D$2:$D$699,0)) -> 5.8 | T23: =P23-P22 -> 0 | U23: =Q23-Q22 -> -0.066887946 | W23: =S23-S22 -> -0.1 | X23: =P23-P11 -> 0.087282784 | Y23: =Q23-Q11 -> -0.053183603 | AA23: =S23-S11 -> 0.7
A24: Gulf War 1990 | B24: 33085 | C24: 33177 | D24: =INDEX('Additional data'!$B$2:$B$965,MATCH(DATE(YEAR(B24),MONTH(B24),1),'Additional data'!$A$2:$A$965,0)) -> 18.638 | E24: =INDEX('Additional data'!$B$2:$B$965,MATCH(DATE(YEAR(C24),MONTH(C24),1),'Additional data'!$A$2:$A$965,0)) -> 35.922 | F24: =E24/D24-1 -> 0.92735272 | G24: =$B$7/LN(1+F24) -> 0.67366777 | N24: 25446 | O24: =INDEX('Additional data'!$B$2:$B$965,MATCH(DATE(YEAR(N24),MONTH(N24),1),'Additional data'!$A$2:$A$965,0)) -> 3.35 | P24: =LN(O24) -> 1.2089603 | Q24: =Q23+LN(1+INDEX('Additional data'!$H$2:$H$1196,MATCH(N24,'Additional data'!$G$2:$G$1196,1))+INDEX('Additional data'!$I$2:$I$1196,MATCH(N24,'Additional data'!$G$2:$G$1196,1))) -> 0.038368304 | S24: =INDEX('Additional data'!$E$2:$E$699,MATCH(DATE(YEAR(N24),MONTH(N24),1),'Additional data'!$D$2:$D$699,0)) -> 6.1 | T24: =P24-P23 -> 0 | U24: =Q24-Q23 -> 0.050598053 | W24: =S24-S23 -> 0.3 | X24: =P24-P12 -> 0.087282784 | Y24: =Q24-Q12 -> -0.020130729 | AA24: =S24-S12 -> 1
A25: Ukraine invasion 2022 | B25: 44592 | C25: 44742 | D25: =INDEX('Additional data'!$B$2:$B$965,MATCH(DATE(YEAR(B25),MONTH(B25),1),'Additional data'!$A$2:$A$965,0)) -> 83.22 | E25: =INDEX('Additional data'!$B$2:$B$965,MATCH(DATE(YEAR(C25),MONTH(C25),1),'Additional data'!$A$2:$A$965,0)) -> 114.84 | F25: =E25/D25-1 -> 0.37995674 | G25: =$B$7/LN(1+F25) -> 1.3725273 | N25: 25476 | O25: =INDEX('Additional data'!$B$2:$B$965,MATCH(DATE(YEAR(N25),MONTH(N25),1),'Additional data'!$A$2:$A$965,0)) -> 3.35 | P25: =LN(O25) -> 1.2089603 | Q25: =Q24+LN(1+INDEX('Additional data'!$H$2:$H$1196,MATCH(N25,'Additional data'!$G$2:$G$1196,1))+INDEX('Additional data'!$I$2:$I$1196,MATCH(N25,'Additional data'!$G$2:$G$1196,1))) -> 0.014587775 | S25: =INDEX('Additional data'!$E$2:$E$699,MATCH(DATE(YEAR(N25),MONTH(N25),1),'Additional data'!$D$2:$D$699,0)) -> 5.8 | T25: =P25-P24 -> 0 | U25: =Q25-Q24 -> -0.023780529 | W25: =S25-S24 -> -0.3 | X25: =P25-P13 -> 0.087282784 | Y25: =Q25-Q13 -> -0.087736738 | AA25: =S25-S13 -> 0.75
N26: 25507 | O26: =INDEX('Additional data'!$B$2:$B$965,MATCH(DATE(YEAR(N26),MONTH(N26),1),'Additional data'!$A$2:$A$965,0)) -> 3.35 | P26: =LN(O26) -> 1.2089603 | Q26: =Q25+LN(1+INDEX('Additional data'!$H$2:$H$1196,MATCH(N26,'Additional data'!$G$2:$G$1196,1))+INDEX('Additional data'!$I$2:$I$1196,MATCH(N26,'Additional data'!$G$2:$G$1196,1))) -> 0.069643981 | S26: =INDEX('Additional data'!$E$2:$E$699,MATCH(DATE(YEAR(N26),MONTH(N26),1),'Additional data'!$D$2:$D$699,0)) -> 5.6 | T26: =P26-P25 -> 0 | U26: =Q26-Q25 -> 0.055056206 | W26: =S26-S25 -> -0.2 | X26: =P26-P14 -> 0.087282784 | Y26: =Q26-Q14 -> -0.041342905 | AA26: =S26-S14 -> 0.6
A27: Asset class | B27: 1990 as happened | C27: 2022 as happened | D27: 1990 scaled | E27: 2022 scaled | F27: Central case | G27: Note | N27: 25537 | O27: =INDEX('Additional data'!$B$2:$B$965,MATCH(DATE(YEAR(N27),MONTH(N27),1),'Additional data'!$A$2:$A$965,0)) -> 3.35 | P27: =LN(O27) -> 1.2089603 | Q27: =Q26+LN(1+INDEX('Additional data'!$H$2:$H$1196,MATCH(N27,'Additional data'!$G$2:$G$1196,1))+INDEX('Additional data'!$I$2:$I$1196,MATCH(N27,'Additional data'!$G$2:$G$1196,1))) -> 0.036294001 | S27: =INDEX('Additional data'!$E$2:$E$699,MATCH(DATE(YEAR(N27),MONTH(N27),1),'Additional data'!$D$2:$D$699,0)) -> 0 | T27: =P27-P26 -> 0 | U27: =Q27-Q26 -> -0.03334998 | W27: =S27-S26 -> -5.6 | X27: =P27-P15 -> 0.087282784 | Y27: =Q27-Q15 -> -0.1315457 | AA27: =S27-S15 -> -4.9
A28: Australian Equities | B28: =INDEX(Data!B$2:B$497,MATCH($C$24,Data!$A$2:$A$497,0))/INDEX(Data!B$2:B$497,MATCH($B$24,Data!$A$2:$A$497,0))-1 -> -0.14419775 | C28: =INDEX(Data!B$2:B$497,MATCH($C$25,Data!$A$2:$A$497,0))/INDEX(Data!B$2:B$497,MATCH($B$25,Data!$A$2:$A$497,0))-1 -> -0.052795909 | D28: =B28*$G$24 -> -0.097141375 | E28: =C28*$G$25 -> -0.072463825 | F28: =AVERAGE(D28:E28) -> -0.0848026 | N28: 25568 | O28: =INDEX('Additional data'!$B$2:$B$965,MATCH(DATE(YEAR(N28),MONTH(N28),1),'Additional data'!$A$2:$A$965,0)) -> 3.35 | P28: =LN(O28) -> 1.2089603 | Q28: =Q27+LN(1+INDEX('Additional data'!$H$2:$H$1196,MATCH(N28,'Additional data'!$G$2:$G$1196,1))+INDEX('Additional data'!$I$2:$I$1196,MATCH(N28,'Additional data'!$G$2:$G$1196,1))) -> 0.01619333 | S28: =INDEX('Additional data'!$E$2:$E$699,MATCH(DATE(YEAR(N28),MONTH(N28),1),'Additional data'!$D$2:$D$699,0)) -> 5.65 | T28: =P28-P27 -> 0 | U28: =Q28-Q27 -> -0.020100672 | W28: =S28-S27 -> 5.65 | X28: =P28-P16 -> 0.087282784 | Y28: =Q28-Q16 -> -0.11601919 | AA28: =S28-S16 -> 0.75
A29: World Equities | B29: =INDEX(Data!C$2:C$497,MATCH($C$24,Data!$A$2:$A$497,0))/INDEX(Data!C$2:C$497,MATCH($B$24,Data!$A$2:$A$497,0))-1 -> -0.14783853 | C29: =INDEX(Data!C$2:C$497,MATCH($C$25,Data!$A$2:$A$497,0))/INDEX(Data!C$2:C$497,MATCH($B$25,Data!$A$2:$A$497,0))-1 -> -0.11676642 | D29: =B29*$G$24 -> -0.099594054 | E29: =C29*$G$25 -> -0.1602651 | F29: =AVERAGE(D29:E29) -> -0.12992958 | N29: 25599 | O29: =INDEX('Additional data'!$B$2:$B$965,MATCH(DATE(YEAR(N29),MONTH(N29),1),'Additional data'!$A$2:$A$965,0)) -> 3.35 | P29: =LN(O29) -> 1.2089603 | Q29: =Q28+LN(1+INDEX('Additional data'!$H$2:$H$1196,MATCH(N29,'Additional data'!$G$2:$G$1196,1))+INDEX('Additional data'!$I$2:$I$1196,MATCH(N29,'Additional data'!$G$2:$G$1196,1))) -> -0.061768212 | S29: =INDEX('Additional data'!$E$2:$E$699,MATCH(DATE(YEAR(N29),MONTH(N29),1),'Additional data'!$D$2:$D$699,0)) -> 5.8 | T29: =P29-P28 -> 0 | U29: =Q29-Q28 -> -0.077961541 | W29: =S29-S28 -> 0.15 | X29: =P29-P17 -> 0.087282784 | Y29: =Q29-Q17 -> -0.18675469 | AA29: =S29-S17 -> 0.7
A30: Emerging Markets | B30: =INDEX(Data!D$2:D$497,MATCH($C$24,Data!$A$2:$A$497,0))/INDEX(Data!D$2:D$497,MATCH($B$24,Data!$A$2:$A$497,0))-1 -> -0.20748743 | C30: =INDEX(Data!D$2:D$497,MATCH($C$25,Data!$A$2:$A$497,0))/INDEX(Data!D$2:D$497,MATCH($B$25,Data!$A$2:$A$497,0))-1 -> -0.097921451 | D30: =B30*$G$24 -> -0.13977759 | E30: =C30*$G$25 -> -0.13439986 | F30: =AVERAGE(D30:E30) -> -0.13708873 | N30: 25627 | O30: =INDEX('Additional data'!$B$2:$B$965,MATCH(DATE(YEAR(N30),MONTH(N30),1),'Additional data'!$A$2:$A$965,0)) -> 3.35 | P30: =LN(O30) -> 1.2089603 | Q30: =Q29+LN(1+INDEX('Additional data'!$H$2:$H$1196,MATCH(N30,'Additional data'!$G$2:$G$1196,1))+INDEX('Additional data'!$I$2:$I$1196,MATCH(N30,'Additional data'!$G$2:$G$1196,1))) -> -0.0057660217 | S30: =INDEX('Additional data'!$E$2:$E$699,MATCH(DATE(YEAR(N30),MONTH(N30),1),'Additional data'!$D$2:$D$699,0)) -> 6.3 | T30: =P30-P29 -> 0 | U30: =Q30-Q29 -> 0.05600219 | W30: =S30-S29 -> 0.5 | X30: =P30-P18 -> 0.087282784 | Y30: =Q30-Q18 -> -0.075239787 | AA30: =S30-S18 -> 1.2
A31: Listed Property | B31: =INDEX(Data!E$2:E$497,MATCH($C$24,Data!$A$2:$A$497,0))/INDEX(Data!E$2:E$497,MATCH($B$24,Data!$A$2:$A$497,0))-1 -> -0.13561435 | C31: =INDEX(Data!E$2:E$497,MATCH($C$25,Data!$A$2:$A$497,0))/INDEX(Data!E$2:E$497,MATCH($B$25,Data!$A$2:$A$497,0))-1 -> -0.10179383 | D31: =B31*$G$24 -> -0.091359016 | E31: =C31*$G$25 -> -0.13971481 | F31: =AVERAGE(D31:E31) -> -0.11553691 | N31: 25658 | O31: =INDEX('Additional data'!$B$2:$B$965,MATCH(DATE(YEAR(N31),MONTH(N31),1),'Additional data'!$A$2:$A$965,0)) -> 3.35 | P31: =LN(O31) -> 1.2089603 | Q31: =Q30+LN(1+INDEX('Additional data'!$H$2:$H$1196,MATCH(N31,'Additional data'!$G$2:$G$1196,1))+INDEX('Additional data'!$I$2:$I$1196,MATCH(N31,'Additional data'!$G$2:$G$1196,1))) -> -0.010678066 | S31: =INDEX('Additional data'!$E$2:$E$699,MATCH(DATE(YEAR(N31),MONTH(N31),1),'Additional data'!$D$2:$D$699,0)) -> 7.15 | T31: =P31-P30 -> 0 | U31: =Q31-Q30 -> -0.0049120444 | W31: =S31-S30 -> 0.85 | X31: =P31-P19 -> 0.030305349 | Y31: =Q31-Q19 -> -0.110875 | AA31: =S31-S19 -> 2
A32: Commodities | B32: =INDEX(Data!F$2:F$497,MATCH($C$24,Data!$A$2:$A$497,0))/INDEX(Data!F$2:F$497,MATCH($B$24,Data!$A$2:$A$497,0))-1 -> 0.3594477 | C32: =INDEX(Data!F$2:F$497,MATCH($C$25,Data!$A$2:$A$497,0))/INDEX(Data!F$2:F$497,MATCH($B$25,Data!$A$2:$A$497,0))-1 -> 0.24635525 | D32: =B32*$G$24 -> 0.24214833 | E32: =C32*$G$25 -> 0.3381293 | F32: =AVERAGE(D32:E32) -> 0.29013882 | N32: 25688 | O32: =INDEX('Additional data'!$B$2:$B$965,MATCH(DATE(YEAR(N32),MONTH(N32),1),'Additional data'!$A$2:$A$965,0)) -> 3.35 | P32: =LN(O32) -> 1.2089603 | Q32: =Q31+LN(1+INDEX('Additional data'!$H$2:$H$1196,MATCH(N32,'Additional data'!$G$2:$G$1196,1))+INDEX('Additional data'!$I$2:$I$1196,MATCH(N32,'Additional data'!$G$2:$G$1196,1))) -> -0.1214979 | S32: =INDEX('Additional data'!$E$2:$E$699,MATCH(DATE(YEAR(N32),MONTH(N32),1),'Additional data'!$D$2:$D$699,0)) -> 8.6 | T32: =P32-P31 -> 0 | U32: =Q32-Q31 -> -0.11081984 | W32: =S32-S31 -> 1.45 | X32: =P32-P20 -> 0 | Y32: =Q32-Q20 -> -0.24139942 | AA32: =S32-S20 -> 3.2
A33: Direct Property | B33: =INDEX(Data!G$2:G$497,MATCH($C$24,Data!$A$2:$A$497,0))/INDEX(Data!G$2:G$497,MATCH($B$24,Data!$A$2:$A$497,0))-1 -> -0.0059498336 | C33: =INDEX(Data!G$2:G$497,MATCH($C$25,Data!$A$2:$A$497,0))/INDEX(Data!G$2:G$497,MATCH($B$25,Data!$A$2:$A$497,0))-1 -> 0.036826648 | D33: =B33*$G$24 -> -0.0040082111 | E33: =C33*$G$25 -> 0.050545579 | F33: =AVERAGE(D33:E33) -> 0.023268684 | G33: Appraisal-based | N33: 25719 | O33: =INDEX('Additional data'!$B$2:$B$965,MATCH(DATE(YEAR(N33),MONTH(N33),1),'Additional data'!$A$2:$A$965,0)) -> 3.35 | P33: =LN(O33) -> 1.2089603 | Q33: =Q32+LN(1+INDEX('Additional data'!$H$2:$H$1196,MATCH(N33,'Additional data'!$G$2:$G$1196,1))+INDEX('Additional data'!$I$2:$I$1196,MATCH(N33,'Additional data'!$G$2:$G$1196,1))) -> -0.18731724 | S33: =INDEX('Additional data'!$E$2:$E$699,MATCH(DATE(YEAR(N33),MONTH(N33),1),'Additional data'!$D$2:$D$699,0)) -> 9.1 | T33: =P33-P32 -> 0 | U33: =Q33-Q32 -> -0.065819341 | W33: =S33-S32 -> 0.5 | X33: =P33-P21 -> 0 | Y33: =Q33-Q21 -> -0.31111118 | AA33: =S33-S21 -> 3.6
A34: Hedge Funds | B34: =0.5*B29+0.5*B38 -> -0.055620917 | C34: =INDEX(Data!H$2:H$497,MATCH($C$25,Data!$A$2:$A$497,0))/INDEX(Data!H$2:H$497,MATCH($B$25,Data!$A$2:$A$497,0))-1 -> -0.033228386 | D34: =B34*$G$24 -> -0.037470019 | E34: =C34*$G$25 -> -0.045606866 | F34: =AVERAGE(D34:E34) -> -0.041538442 | G34: 1990: 50/50 world eq. / cash | N34: 25749 | O34: =INDEX('Additional data'!$B$2:$B$965,MATCH(DATE(YEAR(N34),MONTH(N34),1),'Additional data'!$A$2:$A$965,0)) -> 3.35 | P34: =LN(O34) -> 1.2089603 | Q34: =Q33+LN(1+INDEX('Additional data'!$H$2:$H$1196,MATCH(N34,'Additional data'!$G$2:$G$1196,1))+INDEX('Additional data'!$I$2:$I$1196,MATCH(N34,'Additional data'!$G$2:$G$1196,1))) -> -0.24092901 | S34: =INDEX('Additional data'!$E$2:$E$699,MATCH(DATE(YEAR(N34),MONTH(N34),1),'Additional data'!$D$2:$D$699,0)) -> 8.7 | T34: =P34-P33 -> 0 | U34: =Q34-Q33 -> -0.053611769 | W34: =S34-S33 -> -0.4 | X34: =P34-P22 -> 0 | Y34: =Q34-Q22 -> -0.29558721 | AA34: =S34-S22 -> 2.8
A35: Private Equity | B35: =B29 -> -0.14783853 | C35: =INDEX(Data!I$2:I$497,MATCH($C$25,Data!$A$2:$A$497,0))/INDEX(Data!I$2:I$497,MATCH($B$25,Data!$A$2:$A$497,0))-1 -> -0.070862114 | D35: =B35*$G$24 -> -0.099594054 | E35: =C35*$G$25 -> -0.097260185 | F35: =AVERAGE(D35:E35) -> -0.09842712 | G35: 1990: world equities | N35: 25780 | O35: =INDEX('Additional data'!$B$2:$B$965,MATCH(DATE(YEAR(N35),MONTH(N35),1),'Additional data'!$A$2:$A$965,0)) -> 3.31 | P35: =LN(O35) -> 1.1969482 | Q35: =Q34+LN(1+INDEX('Additional data'!$H$2:$H$1196,MATCH(N35,'Additional data'!$G$2:$G$1196,1))+INDEX('Additional data'!$I$2:$I$1196,MATCH(N35,'Additional data'!$G$2:$G$1196,1))) -> -0.16916665 | S35: =INDEX('Additional data'!$E$2:$E$699,MATCH(DATE(YEAR(N35),MONTH(N35),1),'Additional data'!$D$2:$D$699,0)) -> 7.4 | T35: =P35-P34 -> -0.012012156 | U35: =Q35-Q34 -> 0.071762366 | W35: =S35-S34 -> -1.3 | X35: =P35-P23 -> -0.012012156 | Y35: =Q35-Q23 -> -0.1569369 | AA35: =S35-S23 -> 1.6
A36: Australian Fixed Income | B36: =INDEX(Data!J$2:J$497,MATCH($C$24,Data!$A$2:$A$497,0))/INDEX(Data!J$2:J$497,MATCH($B$24,Data!$A$2:$A$497,0))-1 -> 0.050321614 | C36: =INDEX(Data!J$2:J$497,MATCH($C$25,Data!$A$2:$A$497,0))/INDEX(Data!J$2:J$497,MATCH($B$25,Data!$A$2:$A$497,0))-1 -> -0.095872768 | D36: =B36*$G$24 -> 0.033900049 | E36: =C36*$G$25 -> -0.13158799 | F36: =AVERAGE(D36:E36) -> -0.04884397 | N36: 25811 | O36: =INDEX('Additional data'!$B$2:$B$965,MATCH(DATE(YEAR(N36),MONTH(N36),1),'Additional data'!$A$2:$A$965,0)) -> 3.31 | P36: =LN(O36) -> 1.1969482 | Q36: =Q35+LN(1+INDEX('Additional data'!$H$2:$H$1196,MATCH(N36,'Additional data'!$G$2:$G$1196,1))+INDEX('Additional data'!$I$2:$I$1196,MATCH(N36,'Additional data'!$G$2:$G$1196,1))) -> -0.12009081 | S36: =INDEX('Additional data'!$E$2:$E$699,MATCH(DATE(YEAR(N36),MONTH(N36),1),'Additional data'!$D$2:$D$699,0)) -> 6.8 | T36: =P36-P35 -> 0 | U36: =Q36-Q35 -> 0.049075838 | W36: =S36-S35 -> -0.6 | X36: =P36-P24 -> -0.012012156 | Y36: =Q36-Q24 -> -0.15845911 | AA36: =S36-S24 -> 0.7
A37: World Fixed Income | B37: =INDEX(Data!K$2:K$497,MATCH($C$24,Data!$A$2:$A$497,0))/INDEX(Data!K$2:K$497,MATCH($B$24,Data!$A$2:$A$497,0))-1 -> 0.023422919 | C37: =INDEX(Data!K$2:K$497,MATCH($C$25,Data!$A$2:$A$497,0))/INDEX(Data!K$2:K$497,MATCH($B$25,Data!$A$2:$A$497,0))-1 -> -0.081113807 | D37: =B37*$G$24 -> 0.015779266 | E37: =C37*$G$25 -> -0.11133091 | F37: =AVERAGE(D37:E37) -> -0.047775824 | N37: 25841 | O37: =INDEX('Additional data'!$B$2:$B$965,MATCH(DATE(YEAR(N37),MONTH(N37),1),'Additional data'!$A$2:$A$965,0)) -> 3.31 | P37: =LN(O37) -> 1.1969482 | Q37: =Q36+LN(1+INDEX('Additional data'!$H$2:$H$1196,MATCH(N37,'Additional data'!$G$2:$G$1196,1))+INDEX('Additional data'!$I$2:$I$1196,MATCH(N37,'Additional data'!$G$2:$G$1196,1))) -> -0.073970872 | S37: =INDEX('Additional data'!$E$2:$E$699,MATCH(DATE(YEAR(N37),MONTH(N37),1),'Additional data'!$D$2:$D$699,0)) -> 6.35 | T37: =P37-P36 -> 0 | U37: =Q37-Q36 -> 0.046119936 | W37: =S37-S36 -> -0.45 | X37: =P37-P25 -> -0.012012156 | Y37: =Q37-Q25 -> -0.088558647 | AA37: =S37-S25 -> 0.55
A38: Cash | B38: =INDEX(Data!L$2:L$497,MATCH($C$24,Data!$A$2:$A$497,0))/INDEX(Data!L$2:L$497,MATCH($B$24,Data!$A$2:$A$497,0))-1 -> 0.0365967 | C38: =INDEX(Data!L$2:L$497,MATCH($C$25,Data!$A$2:$A$497,0))/INDEX(Data!L$2:L$497,MATCH($B$25,Data!$A$2:$A$497,0))-1 -> 0.00077442617 | D38: 0 | E38: 0 | F38: =AVERAGE(D38:E38) -> 0 | G38: Not scaled | N38: 25872 | O38: =INDEX('Additional data'!$B$2:$B$965,MATCH(DATE(YEAR(N38),MONTH(N38),1),'Additional data'!$A$2:$A$965,0)) -> 3.31 | P38: =LN(O38) -> 1.1969482 | Q38: =Q37+LN(1+INDEX('Additional data'!$H$2:$H$1196,MATCH(N38,'Additional data'!$G$2:$G$1196,1))+INDEX('Additional data'!$I$2:$I$1196,MATCH(N38,'Additional data'!$G$2:$G$1196,1))) -> -0.092236681 | S38: =INDEX('Additional data'!$E$2:$E$699,MATCH(DATE(YEAR(N38),MONTH(N38),1),'Additional data'!$D$2:$D$699,0)) -> 6.4 | T38: =P38-P37 -> 0 | U38: =Q38-Q37 -> -0.018265809 | W38: =S38-S37 -> 0.05 | X38: =P38-P26 -> -0.012012156 | Y38: =Q38-Q26 -> -0.16188066 | AA38: =S38-S26 -> 0.8
N39: 25902 | O39: =INDEX('Additional data'!$B$2:$B$965,MATCH(DATE(YEAR(N39),MONTH(N39),1),'Additional data'!$A$2:$A$965,0)) -> 3.31 | P39: =LN(O39) -> 1.1969482 | Q39: =Q38+LN(1+INDEX('Additional data'!$H$2:$H$1196,MATCH(N39,'Additional data'!$G$2:$G$1196,1))+INDEX('Additional data'!$I$2:$I$1196,MATCH(N39,'Additional data'!$G$2:$G$1196,1))) -> -0.042684902 | S39: =INDEX('Additional data'!$E$2:$E$699,MATCH(DATE(YEAR(N39),MONTH(N39),1),'Additional data'!$D$2:$D$699,0)) -> 6.2 | T39: =P39-P38 -> 0 | U39: =Q39-Q38 -> 0.049551779 | W39: =S39-S38 -> -0.2 | X39: =P39-P27 -> -0.012012156 | Y39: =Q39-Q27 -> -0.078978904 | AA39: =S39-S27 -> 6.2
N40: 25933 | O40: =INDEX('Additional data'!$B$2:$B$965,MATCH(DATE(YEAR(N40),MONTH(N40),1),'Additional data'!$A$2:$A$965,0)) -> 3.56 | P40: =LN(O40) -> 1.2697605 | Q40: =Q39+LN(1+INDEX('Additional data'!$H$2:$H$1196,MATCH(N40,'Additional data'!$G$2:$G$1196,1))+INDEX('Additional data'!$I$2:$I$1196,MATCH(N40,'Additional data'!$G$2:$G$1196,1))) -> 0.017092302 | S40: =INDEX('Additional data'!$E$2:$E$699,MATCH(DATE(YEAR(N40),MONTH(N40),1),'Additional data'!$D$2:$D$699,0)) -> 6.5 | T40: =P40-P39 -> 0.072812355 | U40: =Q40-Q39 -> 0.059777204 | W40: =S40-S39 -> 0.3 | X40: =P40-P28 -> 0.060800199 | Y40: =Q40-Q28 -> 0.00089897224 | AA40: =S40-S28 -> 0.85
A41: 4. Portfolio impact | N41: 25964 | O41: =INDEX('Additional data'!$B$2:$B$965,MATCH(DATE(YEAR(N41),MONTH(N41),1),'Additional data'!$A$2:$A$965,0)) -> 3.56 | P41: =LN(O41) -> 1.2697605 | Q41: =Q40+LN(1+INDEX('Additional data'!$H$2:$H$1196,MATCH(N41,'Additional data'!$G$2:$G$1196,1))+INDEX('Additional data'!$I$2:$I$1196,MATCH(N41,'Additional data'!$G$2:$G$1196,1))) -> 0.067880469 | S41: =INDEX('Additional data'!$E$2:$E$699,MATCH(DATE(YEAR(N41),MONTH(N41),1),'Additional data'!$D$2:$D$699,0)) -> 6.6 | T41: =P41-P40 -> 0 | U41: =Q41-Q40 -> 0.050788167 | W41: =S41-S40 -> 0.1 | X41: =P41-P29 -> 0.060800199 | Y41: =Q41-Q29 -> 0.12964868 | AA41: =S41-S29 -> 0.8
A42: Portfolio | B42: 1990 as happened | C42: 2022 as happened | D42: 1990 scaled | E42: 2022 scaled | F42: Central case | N42: 25992 | O42: =INDEX('Additional data'!$B$2:$B$965,MATCH(DATE(YEAR(N42),MONTH(N42),1),'Additional data'!$A$2:$A$965,0)) -> 3.56 | P42: =LN(O42) -> 1.2697605 | Q42: =Q41+LN(1+INDEX('Additional data'!$H$2:$H$1196,MATCH(N42,'Additional data'!$G$2:$G$1196,1))+INDEX('Additional data'!$I$2:$I$1196,MATCH(N42,'Additional data'!$G$2:$G$1196,1))) -> 0.085130822 | S42: =INDEX('Additional data'!$E$2:$E$699,MATCH(DATE(YEAR(N42),MONTH(N42),1),'Additional data'!$D$2:$D$699,0)) -> 7.6 | T42: =P42-P41 -> 0 | U42: =Q42-Q41 -> 0.017250353 | W42: =S42-S41 -> 1 | X42: =P42-P30 -> 0.060800199 | Y42: =Q42-Q30 -> 0.090896844 | AA42: =S42-S30 -> 1.3
A43: Current fund | B43: =SUMPRODUCT(B$28:B$38,Portfolio!$C$6:$C$16) -> -0.088824396 | C43: =SUMPRODUCT(C$28:C$38,Portfolio!$C$6:$C$16) -> -0.075466841 | D43: =SUMPRODUCT(D$28:D$38,Portfolio!$C$6:$C$16) -> -0.061563914 | E43: =SUMPRODUCT(E$28:E$38,Portfolio!$C$6:$C$16) -> -0.1036547 | F43: =SUMPRODUCT(F$28:F$38,Portfolio!$C$6:$C$16) -> -0.082609308 | N43: 26023 | O43: =INDEX('Additional data'!$B$2:$B$965,MATCH(DATE(YEAR(N43),MONTH(N43),1),'Additional data'!$A$2:$A$965,0)) -> 3.56 | P43: =LN(O43) -> 1.2697605 | Q43: =Q42+LN(1+INDEX('Additional data'!$H$2:$H$1196,MATCH(N43,'Additional data'!$G$2:$G$1196,1))+INDEX('Additional data'!$I$2:$I$1196,MATCH(N43,'Additional data'!$G$2:$G$1196,1))) -> 0.12838186 | S43: =INDEX('Additional data'!$E$2:$E$699,MATCH(DATE(YEAR(N43),MONTH(N43),1),'Additional data'!$D$2:$D$699,0)) -> 8 | T43: =P43-P42 -> 0 | U43: =Q43-Q42 -> 0.043251042 | W43: =S43-S42 -> 0.4 | X43: =P43-P31 -> 0.060800199 | Y43: =Q43-Q31 -> 0.13905993 | AA43: =S43-S31 -> 0.85
A44: Benchmark | B44: =SUMPRODUCT(B$28:B$38,Portfolio!$D$6:$D$16) -> -0.075741185 | C44: =SUMPRODUCT(C$28:C$38,Portfolio!$D$6:$D$16) -> -0.069961881 | D44: =SUMPRODUCT(D$28:D$38,Portfolio!$D$6:$D$16) -> -0.051764016 | E44: =SUMPRODUCT(E$28:E$38,Portfolio!$D$6:$D$16) -> -0.096056478 | F44: =SUMPRODUCT(F$28:F$38,Portfolio!$D$6:$D$16) -> -0.073910247 | N44: 26053 | O44: =INDEX('Additional data'!$B$2:$B$965,MATCH(DATE(YEAR(N44),MONTH(N44),1),'Additional data'!$A$2:$A$965,0)) -> 3.56 | P44: =LN(O44) -> 1.2697605 | Q44: =Q43+LN(1+INDEX('Additional data'!$H$2:$H$1196,MATCH(N44,'Additional data'!$G$2:$G$1196,1))+INDEX('Additional data'!$I$2:$I$1196,MATCH(N44,'Additional data'!$G$2:$G$1196,1))) -> 0.16210673 | S44: =INDEX('Additional data'!$E$2:$E$699,MATCH(DATE(YEAR(N44),MONTH(N44),1),'Additional data'!$D$2:$D$699,0)) -> 7.8 | T44: =P44-P43 -> 0 | U44: =Q44-Q43 -> 0.033724869 | W44: =S44-S43 -> -0.2 | X44: =P44-P32 -> 0.060800199 | Y44: =Q44-Q32 -> 0.28360463 | AA44: =S44-S32 -> -0.8
A45: Recommended | B45: =SUMPRODUCT(B$28:B$38,Portfolio!$E$6:$E$16) -> -0.087683595 | C45: =SUMPRODUCT(C$28:C$38,Portfolio!$E$6:$E$16) -> -0.07054248 | D45: =SUMPRODUCT(D$28:D$38,Portfolio!$E$6:$E$16) -> -0.059562692 | E45: =SUMPRODUCT(E$28:E$38,Portfolio!$E$6:$E$16) -> -0.096842736 | F45: =SUMPRODUCT(F$28:F$38,Portfolio!$E$6:$E$16) -> -0.078202714 | N45: 26084 | O45: =INDEX('Additional data'!$B$2:$B$965,MATCH(DATE(YEAR(N45),MONTH(N45),1),'Additional data'!$A$2:$A$965,0)) -> 3.56 | P45: =LN(O45) -> 1.2697605 | Q45: =Q44+LN(1+INDEX('Additional data'!$H$2:$H$1196,MATCH(N45,'Additional data'!$G$2:$G$1196,1))+INDEX('Additional data'!$I$2:$I$1196,MATCH(N45,'Additional data'!$G$2:$G$1196,1))) -> 0.12440487 | S45: =INDEX('Additional data'!$E$2:$E$699,MATCH(DATE(YEAR(N45),MONTH(N45),1),'Additional data'!$D$2:$D$699,0)) -> 7.8 | T45: =P45-P44 -> 0 | U45: =Q45-Q44 -> -0.037701867 | W45: =S45-S44 -> 0 | X45: =P45-P33 -> 0.060800199 | Y45: =Q45-Q33 -> 0.31172211 | AA45: =S45-S33 -> -1.3
A46: Recommended less benchmark | B46: =B45-B44 -> -0.01194241 | C46: =C45-C44 -> -0.00058059813 | D46: =D45-D44 -> -0.0077986765 | E46: =E45-E44 -> -0.00078625756 | F46: =F45-F44 -> -0.004292467 | N46: 26114 | O46: =INDEX('Additional data'!$B$2:$B$965,MATCH(DATE(YEAR(N46),MONTH(N46),1),'Additional data'!$A$2:$A$965,0)) -> 3.56 | P46: =LN(O46) -> 1.2697605 | Q46: =Q45+LN(1+INDEX('Additional data'!$H$2:$H$1196,MATCH(N46,'Additional data'!$G$2:$G$1196,1))+INDEX('Additional data'!$I$2:$I$1196,MATCH(N46,'Additional data'!$G$2:$G$1196,1))) -> 0.12720095 | S46: =INDEX('Additional data'!$E$2:$E$699,MATCH(DATE(YEAR(N46),MONTH(N46),1),'Additional data'!$D$2:$D$699,0)) -> 8.15 | T46: =P46-P45 -> 0 | U46: =Q46-Q45 -> 0.0027960873 | W46: =S46-S45 -> 0.35 | X46: =P46-P34 -> 0.060800199 | Y46: =Q46-Q34 -> 0.36812997 | AA46: =S46-S34 -> -0.55
A47: Recommended less current | B47: =B45-B43 -> 0.0011408007 | C47: =C45-C43 -> 0.0049243614 | D47: =D45-D43 -> 0.0020012215 | E47: =E45-E43 -> 0.0068119664 | F47: =F45-F43 -> 0.004406594 | N47: 26145 | O47: =INDEX('Additional data'!$B$2:$B$965,MATCH(DATE(YEAR(N47),MONTH(N47),1),'Additional data'!$A$2:$A$965,0)) -> 3.56 | P47: =LN(O47) -> 1.2697605 | Q47: =Q46+LN(1+INDEX('Additional data'!$H$2:$H$1196,MATCH(N47,'Additional data'!$G$2:$G$1196,1))+INDEX('Additional data'!$I$2:$I$1196,MATCH(N47,'Additional data'!$G$2:$G$1196,1))) -> 0.085441019 | S47: =INDEX('Additional data'!$E$2:$E$699,MATCH(DATE(YEAR(N47),MONTH(N47),1),'Additional data'!$D$2:$D$699,0)) -> 6.8 | T47: =P47-P46 -> 0 | U47: =Q47-Q46 -> -0.041759934 | W47: =S47-S46 -> -1.35 | X47: =P47-P35 -> 0.072812355 | Y47: =Q47-Q35 -> 0.25460766 | AA47: =S47-S35 -> -0.6
N48: 26176 | O48: =INDEX('Additional data'!$B$2:$B$965,MATCH(DATE(YEAR(N48),MONTH(N48),1),'Additional data'!$A$2:$A$965,0)) -> 3.56 | P48: =LN(O48) -> 1.2697605 | Q48: =Q47+LN(1+INDEX('Additional data'!$H$2:$H$1196,MATCH(N48,'Additional data'!$G$2:$G$1196,1))+INDEX('Additional data'!$I$2:$I$1196,MATCH(N48,'Additional data'!$G$2:$G$1196,1))) -> 0.12715861 | S48: =INDEX('Additional data'!$E$2:$E$699,MATCH(DATE(YEAR(N48),MONTH(N48),1),'Additional data'!$D$2:$D$699,0)) -> 6.7 | T48: =P48-P47 -> 0 | U48: =Q48-Q47 -> 0.041717593 | W48: =S48-S47 -> -0.1 | X48: =P48-P36 -> 0.072812355 | Y48: =Q48-Q36 -> 0.24724942 | AA48: =S48-S36 -> -0.1
N49: 26206 | O49: =INDEX('Additional data'!$B$2:$B$965,MATCH(DATE(YEAR(N49),MONTH(N49),1),'Additional data'!$A$2:$A$965,0)) -> 3.56 | P49: =LN(O49) -> 1.2697605 | Q49: =Q48+LN(1+INDEX('Additional data'!$H$2:$H$1196,MATCH(N49,'Additional data'!$G$2:$G$1196,1))+INDEX('Additional data'!$I$2:$I$1196,MATCH(N49,'Additional data'!$G$2:$G$1196,1))) -> 0.12224657 | S49: =INDEX('Additional data'!$E$2:$E$699,MATCH(DATE(YEAR(N49),MONTH(N49),1),'Additional data'!$D$2:$D$699,0)) -> 6.45 | T49: =P49-P48 -> 0 | U49: =Q49-Q48 -> -0.0049120444 | W49: =S49-S48 -> -0.25 | X49: =P49-P37 -> 0.072812355 | Y49: =Q49-Q37 -> 0.19621744 | AA49: =S49-S37 -> 0.1
A50: 5. Likelihood (1968-2026) | N50: 26237 | O50: =INDEX('Additional data'!$B$2:$B$965,MATCH(DATE(YEAR(N50),MONTH(N50),1),'Additional data'!$A$2:$A$965,0)) -> 3.56 | P50: =LN(O50) -> 1.2697605 | Q50: =Q49+LN(1+INDEX('Additional data'!$H$2:$H$1196,MATCH(N50,'Additional data'!$G$2:$G$1196,1))+INDEX('Additional data'!$I$2:$I$1196,MATCH(N50,'Additional data'!$G$2:$G$1196,1))) -> 0.080903605 | S50: =INDEX('Additional data'!$E$2:$E$699,MATCH(DATE(YEAR(N50),MONTH(N50),1),'Additional data'!$D$2:$D$699,0)) -> 6.3 | T50: =P50-P49 -> 0 | U50: =Q50-Q49 -> -0.041342964 | W50: =S50-S49 -> -0.15 | X50: =P50-P38 -> 0.072812355 | Y50: =Q50-Q38 -> 0.17314029 | AA50: =S50-S38 -> -0.1
A51: 12-month windows with a rise this large | B51: =COUNTIF($X$17:$X$701,">="&$B$7)/COUNT($X$17:$X$701) -> 0.10656934 | N51: 26267 | O51: =INDEX('Additional data'!$B$2:$B$965,MATCH(DATE(YEAR(N51),MONTH(N51),1),'Additional data'!$A$2:$A$965,0)) -> 3.56 | P51: =LN(O51) -> 1.2697605 | Q51: =Q50+LN(1+INDEX('Additional data'!$H$2:$H$1196,MATCH(N51,'Additional data'!$G$2:$G$1196,1))+INDEX('Additional data'!$I$2:$I$1196,MATCH(N51,'Additional data'!$G$2:$G$1196,1))) -> 0.0800032 | S51: =INDEX('Additional data'!$E$2:$E$699,MATCH(DATE(YEAR(N51),MONTH(N51),1),'Additional data'!$D$2:$D$699,0)) -> 6 | T51: =P51-P50 -> 0 | U51: =Q51-Q50 -> -0.00090040524 | W51: =S51-S50 -> -0.3 | X51: =P51-P39 -> 0.072812355 | Y51: =Q51-Q39 -> 0.1226881 | AA51: =S51-S39 -> -0.2
A52: 12-month windows (count) | B52: =COUNT($X$17:$X$701) -> 685 | N52: 26298 | O52: =INDEX('Additional data'!$B$2:$B$965,MATCH(DATE(YEAR(N52),MONTH(N52),1),'Additional data'!$A$2:$A$965,0)) -> 3.56 | P52: =LN(O52) -> 1.2697605 | Q52: =Q51+LN(1+INDEX('Additional data'!$H$2:$H$1196,MATCH(N52,'Additional data'!$G$2:$G$1196,1))+INDEX('Additional data'!$I$2:$I$1196,MATCH(N52,'Additional data'!$G$2:$G$1196,1))) -> 0.16691457 | S52: =INDEX('Additional data'!$E$2:$E$699,MATCH(DATE(YEAR(N52),MONTH(N52),1),'Additional data'!$D$2:$D$699,0)) -> 5.9 | T52: =P52-P51 -> 0 | U52: =Q52-Q51 -> 0.086911372 | W52: =S52-S51 -> -0.1 | X52: =P52-P40 -> 0 | Y52: =Q52-Q40 -> 0.14982227 | AA52: =S52-S40 -> -0.6
A53: 60-month windows with a rise this large | B53: =COUNTIF($AB$65:$AB$701,">="&$B$7)/COUNT($AB$65:$AB$701) -> 0.40345369 | N53: 26329 | O53: =INDEX('Additional data'!$B$2:$B$965,MATCH(DATE(YEAR(N53),MONTH(N53),1),'Additional data'!$A$2:$A$965,0)) -> 3.56 | P53: =LN(O53) -> 1.2697605 | Q53: =Q52+LN(1+INDEX('Additional data'!$H$2:$H$1196,MATCH(N53,'Additional data'!$G$2:$G$1196,1))+INDEX('Additional data'!$I$2:$I$1196,MATCH(N53,'Additional data'!$G$2:$G$1196,1))) -> 0.19414056 | S53: =INDEX('Additional data'!$E$2:$E$699,MATCH(DATE(YEAR(N53),MONTH(N53),1),'Additional data'!$D$2:$D$699,0)) -> 5.6 | T53: =P53-P52 -> 0 | U53: =Q53-Q52 -> 0.027225986 | W53: =S53-S52 -> -0.3 | X53: =P53-P41 -> 0 | Y53: =Q53-Q41 -> 0.12626009 | AA53: =S53-S41 -> -1
